Compiled from "AbstractContraptionEntity.java"
public abstract class com.simibubi.create.content.contraptions.AbstractContraptionEntity extends net.minecraft.world.entity.Entity implements net.minecraftforge.entity.IEntityAdditionalSpawnData {
  private static final net.minecraft.network.syncher.EntityDataAccessor<java.lang.Boolean> STALLED;

  private static final net.minecraft.network.syncher.EntityDataAccessor<java.util.Optional<java.util.UUID>> CONTROLLED_BY;

  public final java.util.Map<net.minecraft.world.entity.Entity, org.apache.commons.lang3.mutable.MutableInt> collidingEntities;

  protected com.simibubi.create.content.contraptions.Contraption contraption;

  protected boolean initialized;

  protected boolean prevPosInvalid;

  private boolean skipActorStop;

  public int staleTicks;

  public com.simibubi.create.content.contraptions.AbstractContraptionEntity(net.minecraft.world.entity.EntityType<?>, net.minecraft.world.level.Level);
    Code:
         0: aload_0
         1: aload_1
         2: aload_2
         3: invokespecial #67                 // Method net/minecraft/world/entity/Entity."<init>":(Lnet/minecraft/world/entity/EntityType;Lnet/minecraft/world/level/Level;)V
         6: aload_0
         7: iconst_3
         8: putfield      #69                 // Field staleTicks:I
        11: aload_0
        12: iconst_1
        13: putfield      #71                 // Field prevPosInvalid:Z
        16: aload_0
        17: new           #73                 // class java/util/IdentityHashMap
        20: dup
        21: invokespecial #76                 // Method java/util/IdentityHashMap."<init>":()V
        24: putfield      #78                 // Field collidingEntities:Ljava/util/Map;
        27: return

  protected void setContraption(com.simibubi.create.content.contraptions.Contraption);
    Code:
         0: aload_0
         1: aload_1
         2: putfield      #89                 // Field contraption:Lcom/simibubi/create/content/contraptions/Contraption;
         5: aload_1
         6: ifnonnull     10
         9: return
        10: aload_0
        11: invokevirtual #93                 // Method level:()Lnet/minecraft/world/level/Level;
        14: getfield      #98                 // Field net/minecraft/world/level/Level.isClientSide:Z
        17: ifeq          21
        20: return
        21: aload_1
        22: aload_0
        23: invokevirtual #104                // Method com/simibubi/create/content/contraptions/Contraption.onEntityCreated:(Lcom/simibubi/create/content/contraptions/AbstractContraptionEntity;)V
        26: return

  public void move(net.minecraft.world.entity.MoverType, net.minecraft.world.phys.Vec3);
    Code:
         0: aload_1
         1: getstatic     #112                // Field net/minecraft/world/entity/MoverType.SHULKER:Lnet/minecraft/world/entity/MoverType;
         4: if_acmpne     8
         7: return
         8: aload_1
         9: getstatic     #115                // Field net/minecraft/world/entity/MoverType.SHULKER_BOX:Lnet/minecraft/world/entity/MoverType;
        12: if_acmpne     16
        15: return
        16: aload_1
        17: getstatic     #118                // Field net/minecraft/world/entity/MoverType.PISTON:Lnet/minecraft/world/entity/MoverType;
        20: if_acmpne     24
        23: return
        24: aload_0
        25: aload_1
        26: aload_2
        27: invokespecial #120                // Method net/minecraft/world/entity/Entity.move:(Lnet/minecraft/world/entity/MoverType;Lnet/minecraft/world/phys/Vec3;)V
        30: return

  public boolean supportsTerrainCollision();
    Code:
         0: aload_0
         1: getfield      #89                 // Field contraption:Lcom/simibubi/create/content/contraptions/Contraption;
         4: instanceof    #127                // class com/simibubi/create/content/contraptions/TranslatingContraption
         7: ifeq          24
        10: aload_0
        11: getfield      #89                 // Field contraption:Lcom/simibubi/create/content/contraptions/Contraption;
        14: instanceof    #129                // class com/simibubi/create/content/contraptions/elevator/ElevatorContraption
        17: ifne          24
        20: iconst_1
        21: goto          25
        24: iconst_0
        25: ireturn

  protected void contraptionInitialize();
    Code:
         0: aload_0
         1: getfield      #89                 // Field contraption:Lcom/simibubi/create/content/contraptions/Contraption;
         4: aload_0
         5: invokevirtual #93                 // Method level:()Lnet/minecraft/world/level/Level;
         8: aload_0
         9: invokevirtual #134                // Method com/simibubi/create/content/contraptions/Contraption.onEntityInitialize:(Lnet/minecraft/world/level/Level;Lcom/simibubi/create/content/contraptions/AbstractContraptionEntity;)V
        12: aload_0
        13: iconst_1
        14: putfield      #136                // Field initialized:Z
        17: return

  public boolean collisionEnabled();
    Code:
         0: iconst_1
         1: ireturn

  public void registerColliding(net.minecraft.world.entity.Entity);
    Code:
         0: aload_0
         1: getfield      #78                 // Field collidingEntities:Ljava/util/Map;
         4: aload_1
         5: new           #141                // class org/apache/commons/lang3/mutable/MutableInt
         8: dup
         9: invokespecial #142                // Method org/apache/commons/lang3/mutable/MutableInt."<init>":()V
        12: invokeinterface #146,  3          // InterfaceMethod java/util/Map.put:(Ljava/lang/Object;Ljava/lang/Object;)Ljava/lang/Object;
        17: pop
        18: return

  public void addSittingPassenger(net.minecraft.world.entity.Entity, int);
    Code:
         0: aload_0
         1: invokevirtual #154                // Method getPassengers:()Ljava/util/List;
         4: invokeinterface #160,  1          // InterfaceMethod java/util/List.iterator:()Ljava/util/Iterator;
         9: astore_3
        10: aload_3
        11: invokeinterface #165,  1          // InterfaceMethod java/util/Iterator.hasNext:()Z
        16: ifeq          95
        19: aload_3
        20: invokeinterface #169,  1          // InterfaceMethod java/util/Iterator.next:()Ljava/lang/Object;
        25: checkcast     #4                  // class net/minecraft/world/entity/Entity
        28: astore        4
        30: aload_0
        31: getfield      #89                 // Field contraption:Lcom/simibubi/create/content/contraptions/Contraption;
        34: aload         4
        36: invokevirtual #173                // Method net/minecraft/world/entity/Entity.getUUID:()Ljava/util/UUID;
        39: invokevirtual #177                // Method com/simibubi/create/content/contraptions/Contraption.getSeatOf:(Ljava/util/UUID;)Lnet/minecraft/core/BlockPos;
        42: astore        5
        44: aload         5
        46: ifnull        92
        49: aload         5
        51: aload_0
        52: getfield      #89                 // Field contraption:Lcom/simibubi/create/content/contraptions/Contraption;
        55: invokevirtual #180                // Method com/simibubi/create/content/contraptions/Contraption.getSeats:()Ljava/util/List;
        58: iload_2
        59: invokeinterface #184,  2          // InterfaceMethod java/util/List.get:(I)Ljava/lang/Object;
        64: invokevirtual #190                // Method net/minecraft/core/BlockPos.equals:(Ljava/lang/Object;)Z
        67: ifeq          92
        70: aload         4
        72: instanceof    #192                // class net/minecraft/world/entity/player/Player
        75: ifeq          79
        78: return
        79: aload_1
        80: instanceof    #192                // class net/minecraft/world/entity/player/Player
        83: ifne          87
        86: return
        87: aload         4
        89: invokevirtual #195                // Method net/minecraft/world/entity/Entity.stopRiding:()V
        92: goto          10
        95: aload_1
        96: aload_0
        97: iconst_1
        98: invokevirtual #199                // Method net/minecraft/world/entity/Entity.startRiding:(Lnet/minecraft/world/entity/Entity;Z)Z
       101: pop
       102: aload_1
       103: instanceof    #201                // class net/minecraft/world/entity/TamableAnimal
       106: ifeq          119
       109: aload_1
       110: checkcast     #201                // class net/minecraft/world/entity/TamableAnimal
       113: astore_3
       114: aload_3
       115: iconst_1
       116: invokevirtual #205                // Method net/minecraft/world/entity/TamableAnimal.setInSittingPose:(Z)V
       119: aload_0
       120: invokevirtual #93                 // Method level:()Lnet/minecraft/world/level/Level;
       123: getfield      #98                 // Field net/minecraft/world/level/Level.isClientSide:Z
       126: ifeq          130
       129: return
       130: aload_0
       131: getfield      #89                 // Field contraption:Lcom/simibubi/create/content/contraptions/Contraption;
       134: invokevirtual #209                // Method com/simibubi/create/content/contraptions/Contraption.getSeatMapping:()Ljava/util/Map;
       137: aload_1
       138: invokevirtual #173                // Method net/minecraft/world/entity/Entity.getUUID:()Ljava/util/UUID;
       141: iload_2
       142: invokestatic  #215                // Method java/lang/Integer.valueOf:(I)Ljava/lang/Integer;
       145: invokeinterface #146,  3          // InterfaceMethod java/util/Map.put:(Ljava/lang/Object;Ljava/lang/Object;)Ljava/lang/Object;
       150: pop
       151: invokestatic  #221                // Method com/simibubi/create/AllPackets.getChannel:()Lnet/minecraftforge/network/simple/SimpleChannel;
       154: getstatic     #225                // Field net/minecraftforge/network/PacketDistributor.TRACKING_ENTITY:Lnet/minecraftforge/network/PacketDistributor;
       157: aload_0
       158: invokedynamic #242,  0            // InvokeDynamic #0:get:(Lcom/simibubi/create/content/contraptions/AbstractContraptionEntity;)Ljava/util/function/Supplier;
       163: invokevirtual #246                // Method net/minecraftforge/network/PacketDistributor.with:(Ljava/util/function/Supplier;)Lnet/minecraftforge/network/PacketDistributor$PacketTarget;
       166: new           #248                // class com/simibubi/create/content/contraptions/sync/ContraptionSeatMappingPacket
       169: dup
       170: aload_0
       171: invokevirtual #252                // Method getId:()I
       174: aload_0
       175: getfield      #89                 // Field contraption:Lcom/simibubi/create/content/contraptions/Contraption;
       178: invokevirtual #209                // Method com/simibubi/create/content/contraptions/Contraption.getSeatMapping:()Ljava/util/Map;
       181: invokespecial #255                // Method com/simibubi/create/content/contraptions/sync/ContraptionSeatMappingPacket."<init>":(ILjava/util/Map;)V
       184: invokevirtual #261                // Method net/minecraftforge/network/simple/SimpleChannel.send:(Lnet/minecraftforge/network/PacketDistributor$PacketTarget;Ljava/lang/Object;)V
       187: return

  protected void removePassenger(net.minecraft.world.entity.Entity);
    Code:
         0: aload_0
         1: aload_1
         2: fconst_1
         3: invokevirtual #273                // Method getPassengerPosition:(Lnet/minecraft/world/entity/Entity;F)Lnet/minecraft/world/phys/Vec3;
         6: astore_2
         7: aload_0
         8: aload_1
         9: invokespecial #275                // Method net/minecraft/world/entity/Entity.removePassenger:(Lnet/minecraft/world/entity/Entity;)V
        12: aload_1
        13: instanceof    #201                // class net/minecraft/world/entity/TamableAnimal
        16: ifeq          29
        19: aload_1
        20: checkcast     #201                // class net/minecraft/world/entity/TamableAnimal
        23: astore_3
        24: aload_3
        25: iconst_0
        26: invokevirtual #205                // Method net/minecraft/world/entity/TamableAnimal.setInSittingPose:(Z)V
        29: aload_0
        30: invokevirtual #93                 // Method level:()Lnet/minecraft/world/level/Level;
        33: getfield      #98                 // Field net/minecraft/world/level/Level.isClientSide:Z
        36: ifeq          40
        39: return
        40: aload_2
        41: ifnull        59
        44: aload_1
        45: invokevirtual #281                // Method net/minecraft/world/entity/Entity.getPersistentData:()Lnet/minecraft/nbt/CompoundTag;
        48: ldc_w         #283                // String ContraptionDismountLocation
        51: aload_2
        52: invokestatic  #289                // Method net/createmod/catnip/math/VecHelper.writeNBT:(Lnet/minecraft/world/phys/Vec3;)Lnet/minecraft/nbt/ListTag;
        55: invokevirtual #294                // Method net/minecraft/nbt/CompoundTag.put:(Ljava/lang/String;Lnet/minecraft/nbt/Tag;)Lnet/minecraft/nbt/Tag;
        58: pop
        59: aload_0
        60: getfield      #89                 // Field contraption:Lcom/simibubi/create/content/contraptions/Contraption;
        63: invokevirtual #209                // Method com/simibubi/create/content/contraptions/Contraption.getSeatMapping:()Ljava/util/Map;
        66: aload_1
        67: invokevirtual #173                // Method net/minecraft/world/entity/Entity.getUUID:()Ljava/util/UUID;
        70: invokeinterface #298,  2          // InterfaceMethod java/util/Map.remove:(Ljava/lang/Object;)Ljava/lang/Object;
        75: pop
        76: invokestatic  #221                // Method com/simibubi/create/AllPackets.getChannel:()Lnet/minecraftforge/network/simple/SimpleChannel;
        79: getstatic     #225                // Field net/minecraftforge/network/PacketDistributor.TRACKING_ENTITY:Lnet/minecraftforge/network/PacketDistributor;
        82: aload_0
        83: invokedynamic #303,  0            // InvokeDynamic #1:get:(Lcom/simibubi/create/content/contraptions/AbstractContraptionEntity;)Ljava/util/function/Supplier;
        88: invokevirtual #246                // Method net/minecraftforge/network/PacketDistributor.with:(Ljava/util/function/Supplier;)Lnet/minecraftforge/network/PacketDistributor$PacketTarget;
        91: new           #248                // class com/simibubi/create/content/contraptions/sync/ContraptionSeatMappingPacket
        94: dup
        95: aload_0
        96: invokevirtual #252                // Method getId:()I
        99: aload_0
       100: getfield      #89                 // Field contraption:Lcom/simibubi/create/content/contraptions/Contraption;
       103: invokevirtual #209                // Method com/simibubi/create/content/contraptions/Contraption.getSeatMapping:()Ljava/util/Map;
       106: aload_1
       107: invokevirtual #304                // Method net/minecraft/world/entity/Entity.getId:()I
       110: invokespecial #307                // Method com/simibubi/create/content/contraptions/sync/ContraptionSeatMappingPacket."<init>":(ILjava/util/Map;I)V
       113: invokevirtual #261                // Method net/minecraftforge/network/simple/SimpleChannel.send:(Lnet/minecraftforge/network/PacketDistributor$PacketTarget;Ljava/lang/Object;)V
       116: return

  public net.minecraft.world.phys.Vec3 getDismountLocationForPassenger(net.minecraft.world.entity.LivingEntity);
    Code:
         0: aload_0
         1: aload_1
         2: invokespecial #312                // Method net/minecraft/world/entity/Entity.getDismountLocationForPassenger:(Lnet/minecraft/world/entity/LivingEntity;)Lnet/minecraft/world/phys/Vec3;
         5: astore_2
         6: aload_1
         7: invokevirtual #315                // Method net/minecraft/world/entity/LivingEntity.getPersistentData:()Lnet/minecraft/nbt/CompoundTag;
        10: astore_3
        11: aload_3
        12: ldc_w         #283                // String ContraptionDismountLocation
        15: invokevirtual #319                // Method net/minecraft/nbt/CompoundTag.contains:(Ljava/lang/String;)Z
        18: ifne          23
        21: aload_2
        22: areturn
        23: aload_3
        24: ldc_w         #283                // String ContraptionDismountLocation
        27: bipush        6
        29: invokevirtual #323                // Method net/minecraft/nbt/CompoundTag.getList:(Ljava/lang/String;I)Lnet/minecraft/nbt/ListTag;
        32: invokestatic  #327                // Method net/createmod/catnip/math/VecHelper.readNBT:(Lnet/minecraft/nbt/ListTag;)Lnet/minecraft/world/phys/Vec3;
        35: astore_2
        36: aload_3
        37: ldc_w         #283                // String ContraptionDismountLocation
        40: invokevirtual #330                // Method net/minecraft/nbt/CompoundTag.remove:(Ljava/lang/String;)V
        43: aload_1
        44: iconst_0
        45: invokevirtual #333                // Method net/minecraft/world/entity/LivingEntity.setOnGround:(Z)V
        48: aload_3
        49: ldc_w         #335                // String ContraptionMountLocation
        52: invokevirtual #319                // Method net/minecraft/nbt/CompoundTag.contains:(Ljava/lang/String;)Z
        55: ifne          60
        58: aload_2
        59: areturn
        60: aload_3
        61: ldc_w         #335                // String ContraptionMountLocation
        64: bipush        6
        66: invokevirtual #323                // Method net/minecraft/nbt/CompoundTag.getList:(Ljava/lang/String;I)Lnet/minecraft/nbt/ListTag;
        69: invokestatic  #327                // Method net/createmod/catnip/math/VecHelper.readNBT:(Lnet/minecraft/nbt/ListTag;)Lnet/minecraft/world/phys/Vec3;
        72: astore        4
        74: aload_3
        75: ldc_w         #335                // String ContraptionMountLocation
        78: invokevirtual #330                // Method net/minecraft/nbt/CompoundTag.remove:(Ljava/lang/String;)V
        81: aload_1
        82: instanceof    #192                // class net/minecraft/world/entity/player/Player
        85: ifeq          114
        88: aload_1
        89: checkcast     #192                // class net/minecraft/world/entity/player/Player
        92: astore        5
        94: aload         4
        96: aload_2
        97: ldc2_w        #336                // double 5000.0d
       100: invokevirtual #341                // Method net/minecraft/world/phys/Vec3.closerThan:(Lnet/minecraft/core/Position;D)Z
       103: ifne          114
       106: getstatic     #347                // Field com/simibubi/create/foundation/advancement/AllAdvancements.LONG_TRAVEL:Lcom/simibubi/create/foundation/advancement/CreateAdvancement;
       109: aload         5
       111: invokevirtual #353                // Method com/simibubi/create/foundation/advancement/CreateAdvancement.awardTo:(Lnet/minecraft/world/entity/player/Player;)V
       114: aload_2
       115: areturn

  public void positionRider(net.minecraft.world.entity.Entity, net.minecraft.world.entity.Entity$MoveFunction);
    Code:
         0: aload_0
         1: aload_1
         2: invokevirtual #367                // Method hasPassenger:(Lnet/minecraft/world/entity/Entity;)Z
         5: ifne          9
         8: return
         9: aload_0
        10: aload_1
        11: fconst_1
        12: invokevirtual #273                // Method getPassengerPosition:(Lnet/minecraft/world/entity/Entity;F)Lnet/minecraft/world/phys/Vec3;
        15: astore_3
        16: aload_3
        17: ifnonnull     21
        20: return
        21: ldc_w         #368                // float -0.125f
        24: fstore        4
        26: aload_1
        27: instanceof    #2                  // class com/simibubi/create/content/contraptions/AbstractContraptionEntity
        30: ifeq          36
        33: fconst_0
        34: fstore        4
        36: aload_2
        37: aload_1
        38: aload_3
        39: getfield      #372                // Field net/minecraft/world/phys/Vec3.x:D
        42: aload_3
        43: getfield      #375                // Field net/minecraft/world/phys/Vec3.y:D
        46: aload_1
        47: invokestatic  #381                // Method com/simibubi/create/content/contraptions/actors/seat/SeatEntity.getCustomEntitySeatOffset:(Lnet/minecraft/world/entity/Entity;)D
        50: dadd
        51: fload         4
        53: f2d
        54: dadd
        55: aload_3
        56: getfield      #384                // Field net/minecraft/world/phys/Vec3.z:D
        59: invokeinterface #388,  8          // InterfaceMethod net/minecraft/world/entity/Entity$MoveFunction.accept:(Lnet/minecraft/world/entity/Entity;DDD)V
        64: return

  public net.minecraft.world.phys.Vec3 getPassengerPosition(net.minecraft.world.entity.Entity, float);
    Code:
         0: aload_0
         1: getfield      #89                 // Field contraption:Lcom/simibubi/create/content/contraptions/Contraption;
         4: ifnonnull     9
         7: aconst_null
         8: areturn
         9: aload_1
        10: invokevirtual #173                // Method net/minecraft/world/entity/Entity.getUUID:()Ljava/util/UUID;
        13: astore_3
        14: aload_1
        15: instanceof    #394                // class com/simibubi/create/content/contraptions/OrientedContraptionEntity
        18: ifeq          66
        21: aload_0
        22: getfield      #89                 // Field contraption:Lcom/simibubi/create/content/contraptions/Contraption;
        25: aload_3
        26: invokevirtual #397                // Method com/simibubi/create/content/contraptions/Contraption.getBearingPosOf:(Ljava/util/UUID;)Lnet/minecraft/core/BlockPos;
        29: astore        4
        31: aload         4
        33: ifnull        66
        36: aload_0
        37: aload         4
        39: invokestatic  #401                // Method net/createmod/catnip/math/VecHelper.getCenterOf:(Lnet/minecraft/core/Vec3i;)Lnet/minecraft/world/phys/Vec3;
        42: fload_2
        43: invokevirtual #405                // Method toGlobalVector:(Lnet/minecraft/world/phys/Vec3;F)Lnet/minecraft/world/phys/Vec3;
        46: getstatic     #408                // Field net/minecraft/core/BlockPos.ZERO:Lnet/minecraft/core/BlockPos;
        49: invokestatic  #401                // Method net/createmod/catnip/math/VecHelper.getCenterOf:(Lnet/minecraft/core/Vec3i;)Lnet/minecraft/world/phys/Vec3;
        52: invokevirtual #412                // Method net/minecraft/world/phys/Vec3.add:(Lnet/minecraft/world/phys/Vec3;)Lnet/minecraft/world/phys/Vec3;
        55: ldc2_w        #413                // double 0.5d
        58: dconst_1
        59: ldc2_w        #413                // double 0.5d
        62: invokevirtual #418                // Method net/minecraft/world/phys/Vec3.subtract:(DDD)Lnet/minecraft/world/phys/Vec3;
        65: areturn
        66: aload_1
        67: invokevirtual #424                // Method net/minecraft/world/entity/Entity.getBoundingBox:()Lnet/minecraft/world/phys/AABB;
        70: astore        4
        72: aload         4
        74: invokevirtual #430                // Method net/minecraft/world/phys/AABB.getYsize:()D
        77: dstore        5
        79: aload_0
        80: getfield      #89                 // Field contraption:Lcom/simibubi/create/content/contraptions/Contraption;
        83: aload_3
        84: invokevirtual #177                // Method com/simibubi/create/content/contraptions/Contraption.getSeatOf:(Ljava/util/UUID;)Lnet/minecraft/core/BlockPos;
        87: astore        7
        89: aload         7
        91: ifnonnull     96
        94: aconst_null
        95: areturn
        96: aload_0
        97: aload         7
        99: invokestatic  #433                // Method net/minecraft/world/phys/Vec3.atLowerCornerOf:(Lnet/minecraft/core/Vec3i;)Lnet/minecraft/world/phys/Vec3;
       102: ldc2_w        #413                // double 0.5d
       105: aload_1
       106: invokevirtual #436                // Method net/minecraft/world/entity/Entity.getMyRidingOffset:()D
       109: dload         5
       111: dadd
       112: ldc2_w        #437                // double 0.15000000596046448d
       115: dsub
       116: ldc2_w        #413                // double 0.5d
       119: invokevirtual #440                // Method net/minecraft/world/phys/Vec3.add:(DDD)Lnet/minecraft/world/phys/Vec3;
       122: fload_2
       123: invokevirtual #405                // Method toGlobalVector:(Lnet/minecraft/world/phys/Vec3;F)Lnet/minecraft/world/phys/Vec3;
       126: getstatic     #408                // Field net/minecraft/core/BlockPos.ZERO:Lnet/minecraft/core/BlockPos;
       129: invokestatic  #401                // Method net/createmod/catnip/math/VecHelper.getCenterOf:(Lnet/minecraft/core/Vec3i;)Lnet/minecraft/world/phys/Vec3;
       132: invokevirtual #412                // Method net/minecraft/world/phys/Vec3.add:(Lnet/minecraft/world/phys/Vec3;)Lnet/minecraft/world/phys/Vec3;
       135: ldc2_w        #413                // double 0.5d
       138: dload         5
       140: ldc2_w        #413                // double 0.5d
       143: invokevirtual #418                // Method net/minecraft/world/phys/Vec3.subtract:(DDD)Lnet/minecraft/world/phys/Vec3;
       146: astore        8
       148: aload         8
       150: areturn

  protected boolean canAddPassenger(net.minecraft.world.entity.Entity);
    Code:
         0: aload_1
         1: instanceof    #394                // class com/simibubi/create/content/contraptions/OrientedContraptionEntity
         4: ifeq          9
         7: iconst_1
         8: ireturn
         9: aload_0
        10: getfield      #89                 // Field contraption:Lcom/simibubi/create/content/contraptions/Contraption;
        13: invokevirtual #209                // Method com/simibubi/create/content/contraptions/Contraption.getSeatMapping:()Ljava/util/Map;
        16: invokeinterface #452,  1          // InterfaceMethod java/util/Map.size:()I
        21: aload_0
        22: getfield      #89                 // Field contraption:Lcom/simibubi/create/content/contraptions/Contraption;
        25: invokevirtual #180                // Method com/simibubi/create/content/contraptions/Contraption.getSeats:()Ljava/util/List;
        28: invokeinterface #453,  1          // InterfaceMethod java/util/List.size:()I
        33: if_icmpge     40
        36: iconst_1
        37: goto          41
        40: iconst_0
        41: ireturn

  public net.minecraft.network.chat.Component getContraptionName();
    Code:
         0: aload_0
         1: invokevirtual #459                // Method getName:()Lnet/minecraft/network/chat/Component;
         4: areturn

  public java.util.Optional<java.util.UUID> getControllingPlayer();
    Code:
         0: aload_0
         1: getfield      #466                // Field entityData:Lnet/minecraft/network/syncher/SynchedEntityData;
         4: getstatic     #468                // Field CONTROLLED_BY:Lnet/minecraft/network/syncher/EntityDataAccessor;
         7: invokevirtual #473                // Method net/minecraft/network/syncher/SynchedEntityData.get:(Lnet/minecraft/network/syncher/EntityDataAccessor;)Ljava/lang/Object;
        10: checkcast     #475                // class java/util/Optional
        13: areturn

  public void setControllingPlayer(java.util.UUID);
    Code:
         0: aload_0
         1: getfield      #466                // Field entityData:Lnet/minecraft/network/syncher/SynchedEntityData;
         4: getstatic     #468                // Field CONTROLLED_BY:Lnet/minecraft/network/syncher/EntityDataAccessor;
         7: aload_1
         8: invokestatic  #482                // Method java/util/Optional.ofNullable:(Ljava/lang/Object;)Ljava/util/Optional;
        11: invokevirtual #486                // Method net/minecraft/network/syncher/SynchedEntityData.set:(Lnet/minecraft/network/syncher/EntityDataAccessor;Ljava/lang/Object;)V
        14: return

  public boolean startControlling(net.minecraft.core.BlockPos, net.minecraft.world.entity.player.Player);
    Code:
         0: iconst_0
         1: ireturn

  public boolean control(net.minecraft.core.BlockPos, java.util.Collection<java.lang.Integer>, net.minecraft.world.entity.player.Player);
    Code:
         0: iconst_1
         1: ireturn

  public void stopControlling(net.minecraft.core.BlockPos);
    Code:
         0: aload_0
         1: invokevirtual #500                // Method getControllingPlayer:()Ljava/util/Optional;
         4: aload_0
         5: invokevirtual #93                 // Method level:()Lnet/minecraft/world/level/Level;
         8: dup
         9: invokestatic  #505                // Method java/util/Objects.requireNonNull:(Ljava/lang/Object;)Ljava/lang/Object;
        12: pop
        13: invokedynamic #518,  0            // InvokeDynamic #2:apply:(Lnet/minecraft/world/level/Level;)Ljava/util/function/Function;
        18: invokevirtual #522                // Method java/util/Optional.map:(Ljava/util/function/Function;)Ljava/util/Optional;
        21: invokedynamic #531,  0            // InvokeDynamic #3:apply:()Ljava/util/function/Function;
        26: invokevirtual #522                // Method java/util/Optional.map:(Ljava/util/function/Function;)Ljava/util/Optional;
        29: invokedynamic #542,  0            // InvokeDynamic #4:accept:()Ljava/util/function/Consumer;
        34: invokevirtual #546                // Method java/util/Optional.ifPresent:(Ljava/util/function/Consumer;)V
        37: aload_0
        38: aconst_null
        39: invokevirtual #548                // Method setControllingPlayer:(Ljava/util/UUID;)V
        42: return

  public boolean handlePlayerInteraction(net.minecraft.world.entity.player.Player, net.minecraft.core.BlockPos, net.minecraft.core.Direction, net.minecraft.world.InteractionHand);
    Code:
         0: aload_0
         1: getfield      #89                 // Field contraption:Lcom/simibubi/create/content/contraptions/Contraption;
         4: invokevirtual #180                // Method com/simibubi/create/content/contraptions/Contraption.getSeats:()Ljava/util/List;
         7: aload_2
         8: invokeinterface #554,  2          // InterfaceMethod java/util/List.indexOf:(Ljava/lang/Object;)I
        13: istore        5
        15: iload         5
        17: iconst_m1
        18: if_icmpeq     36
        21: getstatic     #560                // Field com/simibubi/create/AllItems.WRENCH:Lcom/tterrag/registrate/util/entry/ItemEntry;
        24: aload_1
        25: aload         4
        27: invokevirtual #564                // Method net/minecraft/world/entity/player/Player.getItemInHand:(Lnet/minecraft/world/InteractionHand;)Lnet/minecraft/world/item/ItemStack;
        30: invokevirtual #570                // Method com/tterrag/registrate/util/entry/ItemEntry.isIn:(Lnet/minecraft/world/item/ItemStack;)Z
        33: ifeq          94
        36: aload_0
        37: getfield      #89                 // Field contraption:Lcom/simibubi/create/content/contraptions/Contraption;
        40: getfield      #573                // Field com/simibubi/create/content/contraptions/Contraption.interactors:Ljava/util/Map;
        43: aload_2
        44: invokeinterface #576,  2          // InterfaceMethod java/util/Map.containsKey:(Ljava/lang/Object;)Z
        49: ifeq          77
        52: aload_0
        53: getfield      #89                 // Field contraption:Lcom/simibubi/create/content/contraptions/Contraption;
        56: getfield      #573                // Field com/simibubi/create/content/contraptions/Contraption.interactors:Ljava/util/Map;
        59: aload_2
        60: invokeinterface #578,  2          // InterfaceMethod java/util/Map.get:(Ljava/lang/Object;)Ljava/lang/Object;
        65: checkcast     #580                // class com/simibubi/create/api/behaviour/interaction/MovingInteractionBehaviour
        68: aload_1
        69: aload         4
        71: aload_2
        72: aload_0
        73: invokevirtual #583                // Method com/simibubi/create/api/behaviour/interaction/MovingInteractionBehaviour.handlePlayerInteraction:(Lnet/minecraft/world/entity/player/Player;Lnet/minecraft/world/InteractionHand;Lnet/minecraft/core/BlockPos;Lcom/simibubi/create/content/contraptions/AbstractContraptionEntity;)Z
        76: ireturn
        77: aload_0
        78: getfield      #89                 // Field contraption:Lcom/simibubi/create/content/contraptions/Contraption;
        81: getfield      #587                // Field com/simibubi/create/content/contraptions/Contraption.storage:Lcom/simibubi/create/content/contraptions/MountedStorageManager;
        84: aload_0
        85: getfield      #89                 // Field contraption:Lcom/simibubi/create/content/contraptions/Contraption;
        88: aload_1
        89: aload_2
        90: invokevirtual #593                // Method com/simibubi/create/content/contraptions/MountedStorageManager.handlePlayerStorageInteraction:(Lcom/simibubi/create/content/contraptions/Contraption;Lnet/minecraft/world/entity/player/Player;Lnet/minecraft/core/BlockPos;)Z
        93: ireturn
        94: aload_1
        95: invokevirtual #596                // Method net/minecraft/world/entity/player/Player.isPassenger:()Z
        98: ifeq          103
       101: iconst_0
       102: ireturn
       103: aconst_null
       104: astore        6
       106: aload_0
       107: getfield      #89                 // Field contraption:Lcom/simibubi/create/content/contraptions/Contraption;
       110: invokevirtual #209                // Method com/simibubi/create/content/contraptions/Contraption.getSeatMapping:()Ljava/util/Map;
       113: invokeinterface #600,  1          // InterfaceMethod java/util/Map.entrySet:()Ljava/util/Set;
       118: invokeinterface #603,  1          // InterfaceMethod java/util/Set.iterator:()Ljava/util/Iterator;
       123: astore        7
       125: aload         7
       127: invokeinterface #165,  1          // InterfaceMethod java/util/Iterator.hasNext:()Z
       132: ifeq          245
       135: aload         7
       137: invokeinterface #169,  1          // InterfaceMethod java/util/Iterator.next:()Ljava/lang/Object;
       142: checkcast     #19                 // class java/util/Map$Entry
       145: astore        8
       147: aload         8
       149: invokeinterface #606,  1          // InterfaceMethod java/util/Map$Entry.getValue:()Ljava/lang/Object;
       154: checkcast     #211                // class java/lang/Integer
       157: invokevirtual #609                // Method java/lang/Integer.intValue:()I
       160: iload         5
       162: if_icmpeq     168
       165: goto          125
       168: aload_0
       169: invokevirtual #154                // Method getPassengers:()Ljava/util/List;
       172: invokeinterface #160,  1          // InterfaceMethod java/util/List.iterator:()Ljava/util/Iterator;
       177: astore        9
       179: aload         9
       181: invokeinterface #165,  1          // InterfaceMethod java/util/Iterator.hasNext:()Z
       186: ifeq          242
       189: aload         9
       191: invokeinterface #169,  1          // InterfaceMethod java/util/Iterator.next:()Ljava/lang/Object;
       196: checkcast     #4                  // class net/minecraft/world/entity/Entity
       199: astore        10
       201: aload         8
       203: invokeinterface #612,  1          // InterfaceMethod java/util/Map$Entry.getKey:()Ljava/lang/Object;
       208: checkcast     #420                // class java/util/UUID
       211: aload         10
       213: invokevirtual #173                // Method net/minecraft/world/entity/Entity.getUUID:()Ljava/util/UUID;
       216: invokevirtual #613                // Method java/util/UUID.equals:(Ljava/lang/Object;)Z
       219: ifne          225
       222: goto          179
       225: aload         10
       227: instanceof    #192                // class net/minecraft/world/entity/player/Player
       230: ifeq          235
       233: iconst_0
       234: ireturn
       235: aload         10
       237: astore        6
       239: goto          179
       242: goto          125
       245: aload         6
       247: ifnull        299
       250: aload_0
       251: invokevirtual #93                 // Method level:()Lnet/minecraft/world/level/Level;
       254: getfield      #98                 // Field net/minecraft/world/level/Level.isClientSide:Z
       257: ifne          299
       260: aload_0
       261: aload         6
       263: fconst_1
       264: invokevirtual #273                // Method getPassengerPosition:(Lnet/minecraft/world/entity/Entity;F)Lnet/minecraft/world/phys/Vec3;
       267: astore        7
       269: aload         6
       271: invokevirtual #195                // Method net/minecraft/world/entity/Entity.stopRiding:()V
       274: aload         7
       276: ifnull        299
       279: aload         6
       281: aload         7
       283: getfield      #372                // Field net/minecraft/world/phys/Vec3.x:D
       286: aload         7
       288: getfield      #375                // Field net/minecraft/world/phys/Vec3.y:D
       291: aload         7
       293: getfield      #384                // Field net/minecraft/world/phys/Vec3.z:D
       296: invokevirtual #617                // Method net/minecraft/world/entity/Entity.teleportTo:(DDD)V
       299: aload_0
       300: invokevirtual #93                 // Method level:()Lnet/minecraft/world/level/Level;
       303: getfield      #98                 // Field net/minecraft/world/level/Level.isClientSide:Z
       306: ifeq          311
       309: iconst_1
       310: ireturn
       311: aload_0
       312: aload_0
       313: invokevirtual #93                 // Method level:()Lnet/minecraft/world/level/Level;
       316: aload_1
       317: invokestatic  #623                // Method com/simibubi/create/content/contraptions/actors/seat/SeatBlock.getLeashed:(Lnet/minecraft/world/level/Level;Lnet/minecraft/world/entity/player/Player;)Lcom/google/common/base/Optional;
       320: aload_1
       321: invokevirtual #628                // Method com/google/common/base/Optional.or:(Ljava/lang/Object;)Ljava/lang/Object;
       324: checkcast     #4                  // class net/minecraft/world/entity/Entity
       327: iload         5
       329: invokevirtual #630                // Method addSittingPassenger:(Lnet/minecraft/world/entity/Entity;I)V
       332: iconst_1
       333: ireturn

  public net.minecraft.world.phys.Vec3 toGlobalVector(net.minecraft.world.phys.Vec3, float);
    Code:
         0: aload_0
         1: aload_1
         2: fload_2
         3: iconst_0
         4: invokevirtual #642                // Method toGlobalVector:(Lnet/minecraft/world/phys/Vec3;FZ)Lnet/minecraft/world/phys/Vec3;
         7: areturn

  public net.minecraft.world.phys.Vec3 toGlobalVector(net.minecraft.world.phys.Vec3, float, boolean);
    Code:
         0: iload_3
         1: ifeq          11
         4: aload_0
         5: invokevirtual #647                // Method getPrevAnchorVec:()Lnet/minecraft/world/phys/Vec3;
         8: goto          15
        11: aload_0
        12: invokevirtual #650                // Method getAnchorVec:()Lnet/minecraft/world/phys/Vec3;
        15: astore        4
        17: getstatic     #408                // Field net/minecraft/core/BlockPos.ZERO:Lnet/minecraft/core/BlockPos;
        20: invokestatic  #401                // Method net/createmod/catnip/math/VecHelper.getCenterOf:(Lnet/minecraft/core/Vec3i;)Lnet/minecraft/world/phys/Vec3;
        23: astore        5
        25: aload_1
        26: aload         5
        28: invokevirtual #652                // Method net/minecraft/world/phys/Vec3.subtract:(Lnet/minecraft/world/phys/Vec3;)Lnet/minecraft/world/phys/Vec3;
        31: astore_1
        32: aload_0
        33: aload_1
        34: fload_2
        35: invokevirtual #655                // Method applyRotation:(Lnet/minecraft/world/phys/Vec3;F)Lnet/minecraft/world/phys/Vec3;
        38: astore_1
        39: aload_1
        40: aload         5
        42: invokevirtual #412                // Method net/minecraft/world/phys/Vec3.add:(Lnet/minecraft/world/phys/Vec3;)Lnet/minecraft/world/phys/Vec3;
        45: aload         4
        47: invokevirtual #412                // Method net/minecraft/world/phys/Vec3.add:(Lnet/minecraft/world/phys/Vec3;)Lnet/minecraft/world/phys/Vec3;
        50: astore_1
        51: aload_1
        52: areturn

  public net.minecraft.world.phys.Vec3 toLocalVector(net.minecraft.world.phys.Vec3, float);
    Code:
         0: aload_0
         1: aload_1
         2: fload_2
         3: iconst_0
         4: invokevirtual #661                // Method toLocalVector:(Lnet/minecraft/world/phys/Vec3;FZ)Lnet/minecraft/world/phys/Vec3;
         7: areturn

  public net.minecraft.world.phys.Vec3 toLocalVector(net.minecraft.world.phys.Vec3, float, boolean);
    Code:
         0: iload_3
         1: ifeq          11
         4: aload_0
         5: invokevirtual #647                // Method getPrevAnchorVec:()Lnet/minecraft/world/phys/Vec3;
         8: goto          15
        11: aload_0
        12: invokevirtual #650                // Method getAnchorVec:()Lnet/minecraft/world/phys/Vec3;
        15: astore        4
        17: getstatic     #408                // Field net/minecraft/core/BlockPos.ZERO:Lnet/minecraft/core/BlockPos;
        20: invokestatic  #401                // Method net/createmod/catnip/math/VecHelper.getCenterOf:(Lnet/minecraft/core/Vec3i;)Lnet/minecraft/world/phys/Vec3;
        23: astore        5
        25: aload_1
        26: aload         4
        28: invokevirtual #652                // Method net/minecraft/world/phys/Vec3.subtract:(Lnet/minecraft/world/phys/Vec3;)Lnet/minecraft/world/phys/Vec3;
        31: aload         5
        33: invokevirtual #652                // Method net/minecraft/world/phys/Vec3.subtract:(Lnet/minecraft/world/phys/Vec3;)Lnet/minecraft/world/phys/Vec3;
        36: astore_1
        37: aload_0
        38: aload_1
        39: fload_2
        40: invokevirtual #664                // Method reverseRotation:(Lnet/minecraft/world/phys/Vec3;F)Lnet/minecraft/world/phys/Vec3;
        43: astore_1
        44: aload_1
        45: aload         5
        47: invokevirtual #412                // Method net/minecraft/world/phys/Vec3.add:(Lnet/minecraft/world/phys/Vec3;)Lnet/minecraft/world/phys/Vec3;
        50: astore_1
        51: aload_1
        52: areturn

  public void tick();
    Code:
         0: aload_0
         1: getfield      #89                 // Field contraption:Lcom/simibubi/create/content/contraptions/Contraption;
         4: ifnonnull     12
         7: aload_0
         8: invokevirtual #669                // Method discard:()V
        11: return
        12: aload_0
        13: getfield      #78                 // Field collidingEntities:Ljava/util/Map;
        16: invokeinterface #600,  1          // InterfaceMethod java/util/Map.entrySet:()Ljava/util/Set;
        21: invokedynamic #680,  0            // InvokeDynamic #5:test:()Ljava/util/function/Predicate;
        26: invokeinterface #684,  2          // InterfaceMethod java/util/Set.removeIf:(Ljava/util/function/Predicate;)Z
        31: pop
        32: aload_0
        33: aload_0
        34: invokevirtual #687                // Method getX:()D
        37: putfield      #690                // Field xo:D
        40: aload_0
        41: aload_0
        42: invokevirtual #693                // Method getY:()D
        45: putfield      #696                // Field yo:D
        48: aload_0
        49: aload_0
        50: invokevirtual #699                // Method getZ:()D
        53: putfield      #702                // Field zo:D
        56: aload_0
        57: iconst_0
        58: putfield      #71                 // Field prevPosInvalid:Z
        61: aload_0
        62: getfield      #136                // Field initialized:Z
        65: ifne          72
        68: aload_0
        69: invokevirtual #704                // Method contraptionInitialize:()V
        72: aload_0
        73: getfield      #89                 // Field contraption:Lcom/simibubi/create/content/contraptions/Contraption;
        76: aload_0
        77: invokevirtual #707                // Method com/simibubi/create/content/contraptions/Contraption.tickStorage:(Lcom/simibubi/create/content/contraptions/AbstractContraptionEntity;)V
        80: aload_0
        81: invokevirtual #710                // Method tickContraption:()V
        84: aload_0
        85: invokespecial #712                // Method net/minecraft/world/entity/Entity.tick:()V
        88: aload_0
        89: invokevirtual #93                 // Method level:()Lnet/minecraft/world/level/Level;
        92: astore_2
        93: aload_2
        94: instanceof    #714                // class com/simibubi/create/foundation/mixin/accessor/ServerLevelAccessor
        97: ifeq          108
       100: aload_2
       101: checkcast     #714                // class com/simibubi/create/foundation/mixin/accessor/ServerLevelAccessor
       104: astore_1
       105: goto          109
       108: return
       109: aload_0
       110: invokevirtual #154                // Method getPassengers:()Ljava/util/List;
       113: invokeinterface #160,  1          // InterfaceMethod java/util/List.iterator:()Ljava/util/Iterator;
       118: astore_2
       119: aload_2
       120: invokeinterface #165,  1          // InterfaceMethod java/util/Iterator.hasNext:()Z
       125: ifeq          182
       128: aload_2
       129: invokeinterface #169,  1          // InterfaceMethod java/util/Iterator.next:()Ljava/lang/Object;
       134: checkcast     #4                  // class net/minecraft/world/entity/Entity
       137: astore_3
       138: aload_3
       139: instanceof    #192                // class net/minecraft/world/entity/player/Player
       142: ifeq          148
       145: goto          119
       148: aload_3
       149: invokevirtual #717                // Method net/minecraft/world/entity/Entity.isAlwaysTicking:()Z
       152: ifeq          158
       155: goto          119
       158: aload_1
       159: invokeinterface #721,  1          // InterfaceMethod com/simibubi/create/foundation/mixin/accessor/ServerLevelAccessor.create$getEntityTickList:()Lnet/minecraft/world/level/entity/EntityTickList;
       164: aload_3
       165: invokevirtual #725                // Method net/minecraft/world/level/entity/EntityTickList.contains:(Lnet/minecraft/world/entity/Entity;)Z
       168: ifeq          174
       171: goto          119
       174: aload_0
       175: aload_3
       176: invokevirtual #727                // Method positionRider:(Lnet/minecraft/world/entity/Entity;)V
       179: goto          119
       182: return

  public void alignPassenger(net.minecraft.world.entity.Entity);
    Code:
         0: aload_0
         1: aload_1
         2: invokevirtual #733                // Method net/minecraft/world/entity/Entity.getEyePosition:()Lnet/minecraft/world/phys/Vec3;
         5: invokevirtual #736                // Method getContactPointMotion:(Lnet/minecraft/world/phys/Vec3;)Lnet/minecraft/world/phys/Vec3;
         8: astore_2
         9: aload_2
        10: invokevirtual #739                // Method net/minecraft/world/phys/Vec3.length:()D
        13: dconst_0
        14: invokestatic  #745                // Method net/minecraft/util/Mth.equal:(DD)Z
        17: ifeq          21
        20: return
        21: aload_1
        22: instanceof    #747                // class net/minecraft/world/entity/decoration/ArmorStand
        25: ifeq          29
        28: return
        29: aload_1
        30: instanceof    #314                // class net/minecraft/world/entity/LivingEntity
        33: ifeq          44
        36: aload_1
        37: checkcast     #314                // class net/minecraft/world/entity/LivingEntity
        40: astore_3
        41: goto          45
        44: return
        45: aload_3
        46: invokevirtual #751                // Method net/minecraft/world/entity/LivingEntity.getYRot:()F
        49: fstore        4
        51: aload_2
        52: getfield      #372                // Field net/minecraft/world/phys/Vec3.x:D
        55: aload_2
        56: getfield      #384                // Field net/minecraft/world/phys/Vec3.z:D
        59: invokestatic  #755                // Method net/minecraft/util/Mth.atan2:(DD)D
        62: dneg
        63: invokestatic  #761                // Method net/createmod/catnip/math/AngleHelper.deg:(D)F
        66: fstore        5
        68: ldc2_w        #762                // double 0.4000000059604645d
        71: fload         4
        73: f2d
        74: fload         5
        76: f2d
        77: invokestatic  #767                // Method net/createmod/catnip/math/AngleHelper.angleLerp:(DDD)F
        80: fstore        5
        82: aload_0
        83: invokevirtual #93                 // Method level:()Lnet/minecraft/world/level/Level;
        86: getfield      #98                 // Field net/minecraft/world/level/Level.isClientSide:Z
        89: ifeq          135
        92: aload_3
        93: dconst_0
        94: dconst_0
        95: dconst_0
        96: fconst_0
        97: fconst_0
        98: iconst_0
        99: iconst_0
       100: invokevirtual #771                // Method net/minecraft/world/entity/LivingEntity.lerpTo:(DDDFFIZ)V
       103: aload_3
       104: fconst_0
       105: iconst_0
       106: invokevirtual #775                // Method net/minecraft/world/entity/LivingEntity.lerpHeadTo:(FI)V
       109: aload_3
       110: fload         5
       112: invokevirtual #779                // Method net/minecraft/world/entity/LivingEntity.setYRot:(F)V
       115: aload_3
       116: fconst_0
       117: invokevirtual #782                // Method net/minecraft/world/entity/LivingEntity.setXRot:(F)V
       120: aload_3
       121: fload         5
       123: putfield      #785                // Field net/minecraft/world/entity/LivingEntity.yBodyRot:F
       126: aload_3
       127: fload         5
       129: putfield      #788                // Field net/minecraft/world/entity/LivingEntity.yHeadRot:F
       132: goto          141
       135: aload_3
       136: fload         5
       138: invokevirtual #779                // Method net/minecraft/world/entity/LivingEntity.setYRot:(F)V
       141: return

  public void setBlock(net.minecraft.core.BlockPos, net.minecraft.world.level.levelgen.structure.templatesystem.StructureTemplate$StructureBlockInfo);
    Code:
         0: aload_0
         1: getfield      #89                 // Field contraption:Lcom/simibubi/create/content/contraptions/Contraption;
         4: getfield      #797                // Field com/simibubi/create/content/contraptions/Contraption.blocks:Ljava/util/Map;
         7: aload_1
         8: aload_2
         9: invokeinterface #146,  3          // InterfaceMethod java/util/Map.put:(Ljava/lang/Object;Ljava/lang/Object;)Ljava/lang/Object;
        14: pop
        15: invokestatic  #221                // Method com/simibubi/create/AllPackets.getChannel:()Lnet/minecraftforge/network/simple/SimpleChannel;
        18: getstatic     #225                // Field net/minecraftforge/network/PacketDistributor.TRACKING_ENTITY:Lnet/minecraftforge/network/PacketDistributor;
        21: aload_0
        22: invokedynamic #802,  0            // InvokeDynamic #6:get:(Lcom/simibubi/create/content/contraptions/AbstractContraptionEntity;)Ljava/util/function/Supplier;
        27: invokevirtual #246                // Method net/minecraftforge/network/PacketDistributor.with:(Ljava/util/function/Supplier;)Lnet/minecraftforge/network/PacketDistributor$PacketTarget;
        30: new           #804                // class com/simibubi/create/content/contraptions/ContraptionBlockChangedPacket
        33: dup
        34: aload_0
        35: invokevirtual #252                // Method getId:()I
        38: aload_1
        39: aload_2
        40: invokevirtual #808                // Method net/minecraft/world/level/levelgen/structure/templatesystem/StructureTemplate$StructureBlockInfo.state:()Lnet/minecraft/world/level/block/state/BlockState;
        43: invokespecial #811                // Method com/simibubi/create/content/contraptions/ContraptionBlockChangedPacket."<init>":(ILnet/minecraft/core/BlockPos;Lnet/minecraft/world/level/block/state/BlockState;)V
        46: invokevirtual #261                // Method net/minecraftforge/network/simple/SimpleChannel.send:(Lnet/minecraftforge/network/PacketDistributor$PacketTarget;Ljava/lang/Object;)V
        49: return

  protected abstract void tickContraption();

  public abstract net.minecraft.world.phys.Vec3 applyRotation(net.minecraft.world.phys.Vec3, float);

  public abstract net.minecraft.world.phys.Vec3 reverseRotation(net.minecraft.world.phys.Vec3, float);

  public void tickActors();
    Code:
         0: aload_0
         1: getfield      #89                 // Field contraption:Lcom/simibubi/create/content/contraptions/Contraption;
         4: getfield      #817                // Field com/simibubi/create/content/contraptions/Contraption.stalled:Z
         7: istore_1
         8: aload_0
         9: invokevirtual #93                 // Method level:()Lnet/minecraft/world/level/Level;
        12: getfield      #98                 // Field net/minecraft/world/level/Level.isClientSide:Z
        15: ifne          26
        18: aload_0
        19: getfield      #89                 // Field contraption:Lcom/simibubi/create/content/contraptions/Contraption;
        22: iconst_0
        23: putfield      #817                // Field com/simibubi/create/content/contraptions/Contraption.stalled:Z
        26: aload_0
        27: iconst_1
        28: putfield      #819                // Field skipActorStop:Z
        31: aload_0
        32: getfield      #89                 // Field contraption:Lcom/simibubi/create/content/contraptions/Contraption;
        35: invokevirtual #822                // Method com/simibubi/create/content/contraptions/Contraption.getActors:()Ljava/util/List;
        38: invokeinterface #160,  1          // InterfaceMethod java/util/List.iterator:()Ljava/util/Iterator;
        43: astore_2
        44: aload_2
        45: invokeinterface #165,  1          // InterfaceMethod java/util/Iterator.hasNext:()Z
        50: ifeq          340
        53: aload_2
        54: invokeinterface #169,  1          // InterfaceMethod java/util/Iterator.next:()Ljava/lang/Object;
        59: checkcast     #824                // class org/apache/commons/lang3/tuple/MutablePair
        62: astore_3
        63: aload_3
        64: getfield      #828                // Field org/apache/commons/lang3/tuple/MutablePair.right:Ljava/lang/Object;
        67: checkcast     #830                // class com/simibubi/create/content/contraptions/behaviour/MovementContext
        70: astore        4
        72: aload_3
        73: getfield      #833                // Field org/apache/commons/lang3/tuple/MutablePair.left:Ljava/lang/Object;
        76: checkcast     #24                 // class net/minecraft/world/level/levelgen/structure/templatesystem/StructureTemplate$StructureBlockInfo
        79: astore        5
        81: getstatic     #839                // Field com/simibubi/create/api/behaviour/movement/MovementBehaviour.REGISTRY:Lcom/simibubi/create/api/registry/SimpleRegistry;
        84: aload         5
        86: invokevirtual #808                // Method net/minecraft/world/level/levelgen/structure/templatesystem/StructureTemplate$StructureBlockInfo.state:()Lnet/minecraft/world/level/block/state/BlockState;
        89: invokeinterface #844,  2          // InterfaceMethod com/simibubi/create/api/registry/SimpleRegistry.get:(Lnet/minecraft/world/level/block/state/StateHolder;)Ljava/lang/Object;
        94: checkcast     #835                // class com/simibubi/create/api/behaviour/movement/MovementBehaviour
        97: astore        6
        99: aload         6
       101: ifnonnull     107
       104: goto          44
       107: aload         4
       109: getfield      #846                // Field com/simibubi/create/content/contraptions/behaviour/MovementContext.motion:Lnet/minecraft/world/phys/Vec3;
       112: astore        7
       114: aload_0
       115: aload         5
       117: invokevirtual #850                // Method net/minecraft/world/level/levelgen/structure/templatesystem/StructureTemplate$StructureBlockInfo.pos:()Lnet/minecraft/core/BlockPos;
       120: invokestatic  #401                // Method net/createmod/catnip/math/VecHelper.getCenterOf:(Lnet/minecraft/core/Vec3i;)Lnet/minecraft/world/phys/Vec3;
       123: aload         6
       125: aload         4
       127: invokeinterface #854,  2          // InterfaceMethod com/simibubi/create/api/behaviour/movement/MovementBehaviour.getActiveAreaOffset:(Lcom/simibubi/create/content/contraptions/behaviour/MovementContext;)Lnet/minecraft/world/phys/Vec3;
       132: invokevirtual #412                // Method net/minecraft/world/phys/Vec3.add:(Lnet/minecraft/world/phys/Vec3;)Lnet/minecraft/world/phys/Vec3;
       135: fconst_1
       136: invokevirtual #405                // Method toGlobalVector:(Lnet/minecraft/world/phys/Vec3;F)Lnet/minecraft/world/phys/Vec3;
       139: astore        8
       141: aload         8
       143: invokestatic  #858                // Method net/minecraft/core/BlockPos.containing:(Lnet/minecraft/core/Position;)Lnet/minecraft/core/BlockPos;
       146: astore        9
       148: aload         4
       150: getfield      #861                // Field com/simibubi/create/content/contraptions/behaviour/MovementContext.stall:Z
       153: ifne          177
       156: aload_0
       157: aload         4
       159: aload         5
       161: aload         6
       163: aload         8
       165: aload         9
       167: invokevirtual #865                // Method shouldActorTrigger:(Lcom/simibubi/create/content/contraptions/behaviour/MovementContext;Lnet/minecraft/world/level/levelgen/structure/templatesystem/StructureTemplate$StructureBlockInfo;Lcom/simibubi/create/api/behaviour/movement/MovementBehaviour;Lnet/minecraft/world/phys/Vec3;Lnet/minecraft/core/BlockPos;)Z
       170: ifeq          177
       173: iconst_1
       174: goto          178
       177: iconst_0
       178: istore        10
       180: aload         4
       182: aload_0
       183: invokedynamic #873,  0            // InvokeDynamic #7:apply:(Lcom/simibubi/create/content/contraptions/AbstractContraptionEntity;)Ljava/util/function/UnaryOperator;
       188: putfield      #877                // Field com/simibubi/create/content/contraptions/behaviour/MovementContext.rotation:Ljava/util/function/UnaryOperator;
       191: aload         4
       193: aload         8
       195: putfield      #879                // Field com/simibubi/create/content/contraptions/behaviour/MovementContext.position:Lnet/minecraft/world/phys/Vec3;
       198: aload_0
       199: aload         4
       201: aload         6
       203: invokevirtual #883                // Method isActorActive:(Lcom/simibubi/create/content/contraptions/behaviour/MovementContext;Lcom/simibubi/create/api/behaviour/movement/MovementBehaviour;)Z
       206: ifne          222
       209: aload         6
       211: invokeinterface #886,  1          // InterfaceMethod com/simibubi/create/api/behaviour/movement/MovementBehaviour.mustTickWhileDisabled:()Z
       216: ifne          222
       219: goto          44
       222: iload         10
       224: ifeq          262
       227: aload         4
       229: getfield      #861                // Field com/simibubi/create/content/contraptions/behaviour/MovementContext.stall:Z
       232: ifne          262
       235: aload         6
       237: aload         4
       239: aload         9
       241: invokeinterface #890,  3          // InterfaceMethod com/simibubi/create/api/behaviour/movement/MovementBehaviour.visitNewPosition:(Lcom/simibubi/create/content/contraptions/behaviour/MovementContext;Lnet/minecraft/core/BlockPos;)V
       246: aload_0
       247: invokevirtual #893                // Method isAlive:()Z
       250: ifne          256
       253: goto          340
       256: aload         4
       258: iconst_0
       259: putfield      #896                // Field com/simibubi/create/content/contraptions/behaviour/MovementContext.firstMovement:Z
       262: aload         7
       264: aload         4
       266: getfield      #846                // Field com/simibubi/create/content/contraptions/behaviour/MovementContext.motion:Lnet/minecraft/world/phys/Vec3;
       269: invokevirtual #897                // Method net/minecraft/world/phys/Vec3.equals:(Ljava/lang/Object;)Z
       272: ifne          301
       275: aload         6
       277: aload         4
       279: aload         7
       281: aload         4
       283: getfield      #846                // Field com/simibubi/create/content/contraptions/behaviour/MovementContext.motion:Lnet/minecraft/world/phys/Vec3;
       286: invokeinterface #901,  4          // InterfaceMethod com/simibubi/create/api/behaviour/movement/MovementBehaviour.onSpeedChanged:(Lcom/simibubi/create/content/contraptions/behaviour/MovementContext;Lnet/minecraft/world/phys/Vec3;Lnet/minecraft/world/phys/Vec3;)V
       291: aload_0
       292: invokevirtual #893                // Method isAlive:()Z
       295: ifne          301
       298: goto          340
       301: aload         6
       303: aload         4
       305: invokeinterface #904,  2          // InterfaceMethod com/simibubi/create/api/behaviour/movement/MovementBehaviour.tick:(Lcom/simibubi/create/content/contraptions/behaviour/MovementContext;)V
       310: aload_0
       311: invokevirtual #893                // Method isAlive:()Z
       314: ifne          320
       317: goto          340
       320: aload_0
       321: getfield      #89                 // Field contraption:Lcom/simibubi/create/content/contraptions/Contraption;
       324: dup
       325: getfield      #817                // Field com/simibubi/create/content/contraptions/Contraption.stalled:Z
       328: aload         4
       330: getfield      #861                // Field com/simibubi/create/content/contraptions/behaviour/MovementContext.stall:Z
       333: ior
       334: putfield      #817                // Field com/simibubi/create/content/contraptions/Contraption.stalled:Z
       337: goto          44
       340: aload_0
       341: invokevirtual #893                // Method isAlive:()Z
       344: ifne          359
       347: aload_0
       348: getfield      #89                 // Field contraption:Lcom/simibubi/create/content/contraptions/Contraption;
       351: aload_0
       352: invokevirtual #93                 // Method level:()Lnet/minecraft/world/level/Level;
       355: invokevirtual #908                // Method com/simibubi/create/content/contraptions/Contraption.stop:(Lnet/minecraft/world/level/Level;)V
       358: return
       359: aload_0
       360: iconst_0
       361: putfield      #819                // Field skipActorStop:Z
       364: aload_0
       365: invokevirtual #154                // Method getPassengers:()Ljava/util/List;
       368: invokeinterface #160,  1          // InterfaceMethod java/util/List.iterator:()Ljava/util/Iterator;
       373: astore_2
       374: aload_2
       375: invokeinterface #165,  1          // InterfaceMethod java/util/Iterator.hasNext:()Z
       380: ifeq          461
       383: aload_2
       384: invokeinterface #169,  1          // InterfaceMethod java/util/Iterator.next:()Ljava/lang/Object;
       389: checkcast     #4                  // class net/minecraft/world/entity/Entity
       392: astore_3
       393: aload_3
       394: instanceof    #394                // class com/simibubi/create/content/contraptions/OrientedContraptionEntity
       397: ifeq          374
       400: aload_3
       401: checkcast     #394                // class com/simibubi/create/content/contraptions/OrientedContraptionEntity
       404: astore        4
       406: aload_0
       407: getfield      #89                 // Field contraption:Lcom/simibubi/create/content/contraptions/Contraption;
       410: getfield      #911                // Field com/simibubi/create/content/contraptions/Contraption.stabilizedSubContraptions:Ljava/util/Map;
       413: aload_3
       414: invokevirtual #173                // Method net/minecraft/world/entity/Entity.getUUID:()Ljava/util/UUID;
       417: invokeinterface #576,  2          // InterfaceMethod java/util/Map.containsKey:(Ljava/lang/Object;)Z
       422: ifne          428
       425: goto          374
       428: aload         4
       430: getfield      #912                // Field com/simibubi/create/content/contraptions/OrientedContraptionEntity.contraption:Lcom/simibubi/create/content/contraptions/Contraption;
       433: ifnull        458
       436: aload         4
       438: getfield      #912                // Field com/simibubi/create/content/contraptions/OrientedContraptionEntity.contraption:Lcom/simibubi/create/content/contraptions/Contraption;
       441: getfield      #817                // Field com/simibubi/create/content/contraptions/Contraption.stalled:Z
       444: ifeq          458
       447: aload_0
       448: getfield      #89                 // Field contraption:Lcom/simibubi/create/content/contraptions/Contraption;
       451: iconst_1
       452: putfield      #817                // Field com/simibubi/create/content/contraptions/Contraption.stalled:Z
       455: goto          461
       458: goto          374
       461: aload_0
       462: invokevirtual #93                 // Method level:()Lnet/minecraft/world/level/Level;
       465: getfield      #98                 // Field net/minecraft/world/level/Level.isClientSide:Z
       468: ifne          510
       471: iload_1
       472: ifne          489
       475: aload_0
       476: getfield      #89                 // Field contraption:Lcom/simibubi/create/content/contraptions/Contraption;
       479: getfield      #817                // Field com/simibubi/create/content/contraptions/Contraption.stalled:Z
       482: ifeq          489
       485: aload_0
       486: invokevirtual #915                // Method onContraptionStalled:()V
       489: aload_0
       490: getfield      #466                // Field entityData:Lnet/minecraft/network/syncher/SynchedEntityData;
       493: getstatic     #917                // Field STALLED:Lnet/minecraft/network/syncher/EntityDataAccessor;
       496: aload_0
       497: getfield      #89                 // Field contraption:Lcom/simibubi/create/content/contraptions/Contraption;
       500: getfield      #817                // Field com/simibubi/create/content/contraptions/Contraption.stalled:Z
       503: invokestatic  #922                // Method java/lang/Boolean.valueOf:(Z)Ljava/lang/Boolean;
       506: invokevirtual #486                // Method net/minecraft/network/syncher/SynchedEntityData.set:(Lnet/minecraft/network/syncher/EntityDataAccessor;Ljava/lang/Object;)V
       509: return
       510: aload_0
       511: getfield      #89                 // Field contraption:Lcom/simibubi/create/content/contraptions/Contraption;
       514: aload_0
       515: invokevirtual #925                // Method isStalled:()Z
       518: putfield      #817                // Field com/simibubi/create/content/contraptions/Contraption.stalled:Z
       521: return

  public void refreshPSIs();
    Code:
         0: aload_0
         1: getfield      #89                 // Field contraption:Lcom/simibubi/create/content/contraptions/Contraption;
         4: invokevirtual #822                // Method com/simibubi/create/content/contraptions/Contraption.getActors:()Ljava/util/List;
         7: invokeinterface #160,  1          // InterfaceMethod java/util/List.iterator:()Ljava/util/Iterator;
        12: astore_1
        13: aload_1
        14: invokeinterface #165,  1          // InterfaceMethod java/util/Iterator.hasNext:()Z
        19: ifeq          110
        22: aload_1
        23: invokeinterface #169,  1          // InterfaceMethod java/util/Iterator.next:()Ljava/lang/Object;
        28: checkcast     #824                // class org/apache/commons/lang3/tuple/MutablePair
        31: astore_2
        32: aload_2
        33: getfield      #828                // Field org/apache/commons/lang3/tuple/MutablePair.right:Ljava/lang/Object;
        36: checkcast     #830                // class com/simibubi/create/content/contraptions/behaviour/MovementContext
        39: astore_3
        40: aload_2
        41: getfield      #833                // Field org/apache/commons/lang3/tuple/MutablePair.left:Ljava/lang/Object;
        44: checkcast     #24                 // class net/minecraft/world/level/levelgen/structure/templatesystem/StructureTemplate$StructureBlockInfo
        47: astore        4
        49: getstatic     #839                // Field com/simibubi/create/api/behaviour/movement/MovementBehaviour.REGISTRY:Lcom/simibubi/create/api/registry/SimpleRegistry;
        52: aload         4
        54: invokevirtual #808                // Method net/minecraft/world/level/levelgen/structure/templatesystem/StructureTemplate$StructureBlockInfo.state:()Lnet/minecraft/world/level/block/state/BlockState;
        57: invokeinterface #844,  2          // InterfaceMethod com/simibubi/create/api/registry/SimpleRegistry.get:(Lnet/minecraft/world/level/block/state/StateHolder;)Ljava/lang/Object;
        62: checkcast     #835                // class com/simibubi/create/api/behaviour/movement/MovementBehaviour
        65: astore        5
        67: aload         5
        69: instanceof    #943                // class com/simibubi/create/content/contraptions/actors/psi/PortableStorageInterfaceMovement
        72: ifeq          107
        75: aload_0
        76: aload_3
        77: aload         5
        79: invokevirtual #883                // Method isActorActive:(Lcom/simibubi/create/content/contraptions/behaviour/MovementContext;Lcom/simibubi/create/api/behaviour/movement/MovementBehaviour;)Z
        82: ifeq          107
        85: aload_3
        86: getfield      #879                // Field com/simibubi/create/content/contraptions/behaviour/MovementContext.position:Lnet/minecraft/world/phys/Vec3;
        89: ifnull        107
        92: aload         5
        94: aload_3
        95: aload_3
        96: getfield      #879                // Field com/simibubi/create/content/contraptions/behaviour/MovementContext.position:Lnet/minecraft/world/phys/Vec3;
        99: invokestatic  #858                // Method net/minecraft/core/BlockPos.containing:(Lnet/minecraft/core/Position;)Lnet/minecraft/core/BlockPos;
       102: invokeinterface #890,  3          // InterfaceMethod com/simibubi/create/api/behaviour/movement/MovementBehaviour.visitNewPosition:(Lcom/simibubi/create/content/contraptions/behaviour/MovementContext;Lnet/minecraft/core/BlockPos;)V
       107: goto          13
       110: return

  protected boolean isActorActive(com.simibubi.create.content.contraptions.behaviour.MovementContext, com.simibubi.create.api.behaviour.movement.MovementBehaviour);
    Code:
         0: aload_2
         1: aload_1
         2: invokeinterface #947,  2          // InterfaceMethod com/simibubi/create/api/behaviour/movement/MovementBehaviour.isActive:(Lcom/simibubi/create/content/contraptions/behaviour/MovementContext;)Z
         7: ireturn

  protected void onContraptionStalled();
    Code:
         0: invokestatic  #221                // Method com/simibubi/create/AllPackets.getChannel:()Lnet/minecraftforge/network/simple/SimpleChannel;
         3: getstatic     #225                // Field net/minecraftforge/network/PacketDistributor.TRACKING_ENTITY:Lnet/minecraftforge/network/PacketDistributor;
         6: aload_0
         7: invokedynamic #952,  0            // InvokeDynamic #8:get:(Lcom/simibubi/create/content/contraptions/AbstractContraptionEntity;)Ljava/util/function/Supplier;
        12: invokevirtual #246                // Method net/minecraftforge/network/PacketDistributor.with:(Ljava/util/function/Supplier;)Lnet/minecraftforge/network/PacketDistributor$PacketTarget;
        15: new           #954                // class com/simibubi/create/content/contraptions/ContraptionStallPacket
        18: dup
        19: aload_0
        20: invokevirtual #252                // Method getId:()I
        23: aload_0
        24: invokevirtual #687                // Method getX:()D
        27: aload_0
        28: invokevirtual #693                // Method getY:()D
        31: aload_0
        32: invokevirtual #699                // Method getZ:()D
        35: aload_0
        36: invokevirtual #957                // Method getStalledAngle:()F
        39: invokespecial #960                // Method com/simibubi/create/content/contraptions/ContraptionStallPacket."<init>":(IDDDF)V
        42: invokevirtual #261                // Method net/minecraftforge/network/simple/SimpleChannel.send:(Lnet/minecraftforge/network/PacketDistributor$PacketTarget;Ljava/lang/Object;)V
        45: return

  protected boolean shouldActorTrigger(com.simibubi.create.content.contraptions.behaviour.MovementContext, net.minecraft.world.level.levelgen.structure.templatesystem.StructureTemplate$StructureBlockInfo, com.simibubi.create.api.behaviour.movement.MovementBehaviour, net.minecraft.world.phys.Vec3, net.minecraft.core.BlockPos);
    Code:
         0: aload_1
         1: getfield      #879                // Field com/simibubi/create/content/contraptions/behaviour/MovementContext.position:Lnet/minecraft/world/phys/Vec3;
         4: astore        6
         6: aload         6
         8: ifnonnull     13
        11: iconst_0
        12: ireturn
        13: aload_1
        14: aload         4
        16: aload         6
        18: invokevirtual #652                // Method net/minecraft/world/phys/Vec3.subtract:(Lnet/minecraft/world/phys/Vec3;)Lnet/minecraft/world/phys/Vec3;
        21: putfield      #846                // Field com/simibubi/create/content/contraptions/behaviour/MovementContext.motion:Lnet/minecraft/world/phys/Vec3;
        24: aload_0
        25: invokevirtual #93                 // Method level:()Lnet/minecraft/world/level/Level;
        28: invokevirtual #962                // Method net/minecraft/world/level/Level.isClientSide:()Z
        31: ifne          121
        34: aload_1
        35: getfield      #963                // Field com/simibubi/create/content/contraptions/behaviour/MovementContext.contraption:Lcom/simibubi/create/content/contraptions/Contraption;
        38: getfield      #965                // Field com/simibubi/create/content/contraptions/Contraption.entity:Lcom/simibubi/create/content/contraptions/AbstractContraptionEntity;
        41: astore        8
        43: aload         8
        45: instanceof    #967                // class com/simibubi/create/content/trains/entity/CarriageContraptionEntity
        48: ifeq          121
        51: aload         8
        53: checkcast     #967                // class com/simibubi/create/content/trains/entity/CarriageContraptionEntity
        56: astore        7
        58: aload         7
        60: invokevirtual #971                // Method com/simibubi/create/content/trains/entity/CarriageContraptionEntity.getCarriage:()Lcom/simibubi/create/content/trains/entity/Carriage;
        63: ifnull        121
        66: aload         7
        68: invokevirtual #971                // Method com/simibubi/create/content/trains/entity/CarriageContraptionEntity.getCarriage:()Lcom/simibubi/create/content/trains/entity/Carriage;
        71: getfield      #977                // Field com/simibubi/create/content/trains/entity/Carriage.train:Lcom/simibubi/create/content/trains/entity/Train;
        74: astore        8
        76: aload         8
        78: getfield      #983                // Field com/simibubi/create/content/trains/entity/Train.speedBeforeStall:Ljava/lang/Double;
        81: ifnull        95
        84: aload         8
        86: getfield      #983                // Field com/simibubi/create/content/trains/entity/Train.speedBeforeStall:Ljava/lang/Double;
        89: invokevirtual #988                // Method java/lang/Double.doubleValue:()D
        92: goto          100
        95: aload         8
        97: getfield      #991                // Field com/simibubi/create/content/trains/entity/Train.speed:D
       100: dstore        9
       102: aload_1
       103: aload_1
       104: getfield      #846                // Field com/simibubi/create/content/contraptions/behaviour/MovementContext.motion:Lnet/minecraft/world/phys/Vec3;
       107: invokevirtual #994                // Method net/minecraft/world/phys/Vec3.normalize:()Lnet/minecraft/world/phys/Vec3;
       110: dload         9
       112: invokestatic  #1000               // Method java/lang/Math.abs:(D)D
       115: invokevirtual #1004               // Method net/minecraft/world/phys/Vec3.scale:(D)Lnet/minecraft/world/phys/Vec3;
       118: putfield      #846                // Field com/simibubi/create/content/contraptions/behaviour/MovementContext.motion:Lnet/minecraft/world/phys/Vec3;
       121: aload_1
       122: getfield      #846                // Field com/simibubi/create/content/contraptions/behaviour/MovementContext.motion:Lnet/minecraft/world/phys/Vec3;
       125: astore        7
       127: aload_0
       128: aload         7
       130: fconst_1
       131: invokevirtual #664                // Method reverseRotation:(Lnet/minecraft/world/phys/Vec3;F)Lnet/minecraft/world/phys/Vec3;
       134: astore        7
       136: aload_1
       137: aload         7
       139: putfield      #1007               // Field com/simibubi/create/content/contraptions/behaviour/MovementContext.relativeMotion:Lnet/minecraft/world/phys/Vec3;
       142: aload_1
       143: getfield      #963                // Field com/simibubi/create/content/contraptions/behaviour/MovementContext.contraption:Lcom/simibubi/create/content/contraptions/Contraption;
       146: instanceof    #1009               // class com/simibubi/create/content/trains/entity/CarriageContraption
       149: ifne          159
       152: aload_3
       153: instanceof    #943                // class com/simibubi/create/content/contraptions/actors/psi/PortableStorageInterfaceMovement
       156: ifeq          163
       159: iconst_1
       160: goto          164
       163: iconst_0
       164: istore        8
       166: aload         6
       168: invokestatic  #858                // Method net/minecraft/core/BlockPos.containing:(Lnet/minecraft/core/Position;)Lnet/minecraft/core/BlockPos;
       171: aload         5
       173: invokevirtual #190                // Method net/minecraft/core/BlockPos.equals:(Ljava/lang/Object;)Z
       176: ifeq          203
       179: aload_1
       180: getfield      #1007               // Field com/simibubi/create/content/contraptions/behaviour/MovementContext.relativeMotion:Lnet/minecraft/world/phys/Vec3;
       183: invokevirtual #739                // Method net/minecraft/world/phys/Vec3.length:()D
       186: dconst_0
       187: dcmpl
       188: ifgt          196
       191: iload         8
       193: ifeq          207
       196: aload_1
       197: getfield      #896                // Field com/simibubi/create/content/contraptions/behaviour/MovementContext.firstMovement:Z
       200: ifeq          207
       203: iconst_1
       204: goto          208
       207: iconst_0
       208: ireturn

  public void move(double, double, double);
    Code:
         0: aload_0
         1: aload_0
         2: invokevirtual #687                // Method getX:()D
         5: dload_1
         6: dadd
         7: aload_0
         8: invokevirtual #693                // Method getY:()D
        11: dload_3
        12: dadd
        13: aload_0
        14: invokevirtual #699                // Method getZ:()D
        17: dload         5
        19: dadd
        20: invokevirtual #1017               // Method setPos:(DDD)V
        23: return

  public net.minecraft.world.phys.Vec3 getAnchorVec();
    Code:
         0: aload_0
         1: invokevirtual #1019               // Method position:()Lnet/minecraft/world/phys/Vec3;
         4: areturn

  public net.minecraft.world.phys.Vec3 getPrevAnchorVec();
    Code:
         0: aload_0
         1: invokevirtual #1022               // Method getPrevPositionVec:()Lnet/minecraft/world/phys/Vec3;
         4: areturn

  public float getYawOffset();
    Code:
         0: fconst_0
         1: freturn

  public void setPos(double, double, double);
    Code:
         0: aload_0
         1: dload_1
         2: dload_3
         3: dload         5
         5: invokespecial #1024               // Method net/minecraft/world/entity/Entity.setPos:(DDD)V
         8: aload_0
         9: getfield      #89                 // Field contraption:Lcom/simibubi/create/content/contraptions/Contraption;
        12: ifnonnull     16
        15: return
        16: aload_0
        17: getfield      #89                 // Field contraption:Lcom/simibubi/create/content/contraptions/Contraption;
        20: getfield      #1027               // Field com/simibubi/create/content/contraptions/Contraption.bounds:Lnet/minecraft/world/phys/AABB;
        23: astore        7
        25: aload         7
        27: ifnonnull     31
        30: return
        31: aload_0
        32: invokevirtual #650                // Method getAnchorVec:()Lnet/minecraft/world/phys/Vec3;
        35: astore        8
        37: aload_0
        38: aload         7
        40: aload         8
        42: invokevirtual #1030               // Method net/minecraft/world/phys/AABB.move:(Lnet/minecraft/world/phys/Vec3;)Lnet/minecraft/world/phys/AABB;
        45: invokevirtual #1034               // Method setBoundingBox:(Lnet/minecraft/world/phys/AABB;)V
        48: return

  public static float yawFromVector(net.minecraft.world.phys.Vec3);
    Code:
         0: ldc2_w        #1039               // double 4.71238898038469d
         3: aload_0
         4: getfield      #384                // Field net/minecraft/world/phys/Vec3.z:D
         7: aload_0
         8: getfield      #372                // Field net/minecraft/world/phys/Vec3.x:D
        11: invokestatic  #1041               // Method java/lang/Math.atan2:(DD)D
        14: dadd
        15: ldc2_w        #1042               // double 3.141592653589793d
        18: ddiv
        19: ldc2_w        #1044               // double 180.0d
        22: dmul
        23: d2f
        24: freturn

  public static float pitchFromVector(net.minecraft.world.phys.Vec3);
    Code:
         0: aload_0
         1: getfield      #375                // Field net/minecraft/world/phys/Vec3.y:D
         4: invokestatic  #1050               // Method java/lang/Math.acos:(D)D
         7: ldc2_w        #1042               // double 3.141592653589793d
        10: ddiv
        11: ldc2_w        #1044               // double 180.0d
        14: dmul
        15: d2f
        16: freturn

  public static net.minecraft.world.entity.EntityType$Builder<?> build(net.minecraft.world.entity.EntityType$Builder<?>);
    Code:
         0: aload_0
         1: astore_1
         2: aload_1
         3: fconst_1
         4: fconst_1
         5: invokevirtual #1057               // Method net/minecraft/world/entity/EntityType$Builder.sized:(FF)Lnet/minecraft/world/entity/EntityType$Builder;
         8: areturn

  protected void defineSynchedData();
    Code:
         0: aload_0
         1: getfield      #466                // Field entityData:Lnet/minecraft/network/syncher/SynchedEntityData;
         4: getstatic     #917                // Field STALLED:Lnet/minecraft/network/syncher/EntityDataAccessor;
         7: iconst_0
         8: invokestatic  #922                // Method java/lang/Boolean.valueOf:(Z)Ljava/lang/Boolean;
        11: invokevirtual #1066               // Method net/minecraft/network/syncher/SynchedEntityData.define:(Lnet/minecraft/network/syncher/EntityDataAccessor;Ljava/lang/Object;)V
        14: aload_0
        15: getfield      #466                // Field entityData:Lnet/minecraft/network/syncher/SynchedEntityData;
        18: getstatic     #468                // Field CONTROLLED_BY:Lnet/minecraft/network/syncher/EntityDataAccessor;
        21: invokestatic  #1069               // Method java/util/Optional.empty:()Ljava/util/Optional;
        24: invokevirtual #1066               // Method net/minecraft/network/syncher/SynchedEntityData.define:(Lnet/minecraft/network/syncher/EntityDataAccessor;Ljava/lang/Object;)V
        27: return

  public net.minecraft.network.protocol.Packet<net.minecraft.network.protocol.game.ClientGamePacketListener> getAddEntityPacket();
    Code:
         0: aload_0
         1: invokestatic  #1078               // Method net/minecraftforge/network/NetworkHooks.getEntitySpawningPacket:(Lnet/minecraft/world/entity/Entity;)Lnet/minecraft/network/protocol/Packet;
         4: areturn

  public void writeSpawnData(net.minecraft.network.FriendlyByteBuf);
    Code:
         0: new           #291                // class net/minecraft/nbt/CompoundTag
         3: dup
         4: invokespecial #1081               // Method net/minecraft/nbt/CompoundTag."<init>":()V
         7: astore_2
         8: aload_0
         9: aload_2
        10: iconst_1
        11: invokevirtual #1085               // Method writeAdditional:(Lnet/minecraft/nbt/CompoundTag;Z)V
        14: aload_2
        15: aload_1
        16: invokestatic  #1091               // Method com/simibubi/create/content/contraptions/data/ContraptionSyncLimiting.writeSafe:(Lnet/minecraft/nbt/CompoundTag;Lnet/minecraft/network/FriendlyByteBuf;)V
        19: return

  protected final void addAdditionalSaveData(net.minecraft.nbt.CompoundTag);
    Code:
         0: aload_0
         1: aload_1
         2: iconst_0
         3: invokevirtual #1085               // Method writeAdditional:(Lnet/minecraft/nbt/CompoundTag;Z)V
         6: return

  protected void writeAdditional(net.minecraft.nbt.CompoundTag, boolean);
    Code:
         0: aload_0
         1: getfield      #89                 // Field contraption:Lcom/simibubi/create/content/contraptions/Contraption;
         4: ifnull        23
         7: aload_1
         8: ldc_w         #1098               // String Contraption
        11: aload_0
        12: getfield      #89                 // Field contraption:Lcom/simibubi/create/content/contraptions/Contraption;
        15: iload_2
        16: invokevirtual #1101               // Method com/simibubi/create/content/contraptions/Contraption.writeNBT:(Z)Lnet/minecraft/nbt/CompoundTag;
        19: invokevirtual #294                // Method net/minecraft/nbt/CompoundTag.put:(Ljava/lang/String;Lnet/minecraft/nbt/Tag;)Lnet/minecraft/nbt/Tag;
        22: pop
        23: aload_1
        24: ldc_w         #1103               // String Stalled
        27: aload_0
        28: invokevirtual #925                // Method isStalled:()Z
        31: invokevirtual #1107               // Method net/minecraft/nbt/CompoundTag.putBoolean:(Ljava/lang/String;Z)V
        34: aload_1
        35: ldc_w         #1109               // String Initialized
        38: aload_0
        39: getfield      #136                // Field initialized:Z
        42: invokevirtual #1107               // Method net/minecraft/nbt/CompoundTag.putBoolean:(Ljava/lang/String;Z)V
        45: return

  public void readSpawnData(net.minecraft.network.FriendlyByteBuf);
    Code:
         0: aload_1
         1: invokevirtual #1116               // Method net/minecraft/network/FriendlyByteBuf.readAnySizeNbt:()Lnet/minecraft/nbt/CompoundTag;
         4: astore_2
         5: aload_2
         6: ifnull        15
         9: aload_0
        10: aload_2
        11: iconst_1
        12: invokevirtual #1119               // Method readAdditional:(Lnet/minecraft/nbt/CompoundTag;Z)V
        15: return

  protected final void readAdditionalSaveData(net.minecraft.nbt.CompoundTag);
    Code:
         0: aload_0
         1: aload_1
         2: iconst_0
         3: invokevirtual #1119               // Method readAdditional:(Lnet/minecraft/nbt/CompoundTag;Z)V
         6: return

  protected void readAdditional(net.minecraft.nbt.CompoundTag, boolean);
    Code:
         0: aload_1
         1: invokevirtual #1125               // Method net/minecraft/nbt/CompoundTag.isEmpty:()Z
         4: ifeq          8
         7: return
         8: aload_0
         9: aload_1
        10: ldc_w         #1109               // String Initialized
        13: invokevirtual #1128               // Method net/minecraft/nbt/CompoundTag.getBoolean:(Ljava/lang/String;)Z
        16: putfield      #136                // Field initialized:Z
        19: aload_0
        20: aload_0
        21: invokevirtual #93                 // Method level:()Lnet/minecraft/world/level/Level;
        24: aload_1
        25: ldc_w         #1098               // String Contraption
        28: invokevirtual #1132               // Method net/minecraft/nbt/CompoundTag.getCompound:(Ljava/lang/String;)Lnet/minecraft/nbt/CompoundTag;
        31: iload_2
        32: invokestatic  #1136               // Method com/simibubi/create/content/contraptions/Contraption.fromNBT:(Lnet/minecraft/world/level/Level;Lnet/minecraft/nbt/CompoundTag;Z)Lcom/simibubi/create/content/contraptions/Contraption;
        35: putfield      #89                 // Field contraption:Lcom/simibubi/create/content/contraptions/Contraption;
        38: aload_0
        39: getfield      #89                 // Field contraption:Lcom/simibubi/create/content/contraptions/Contraption;
        42: aload_0
        43: putfield      #965                // Field com/simibubi/create/content/contraptions/Contraption.entity:Lcom/simibubi/create/content/contraptions/AbstractContraptionEntity;
        46: aload_0
        47: getfield      #466                // Field entityData:Lnet/minecraft/network/syncher/SynchedEntityData;
        50: getstatic     #917                // Field STALLED:Lnet/minecraft/network/syncher/EntityDataAccessor;
        53: aload_1
        54: ldc_w         #1103               // String Stalled
        57: invokevirtual #1128               // Method net/minecraft/nbt/CompoundTag.getBoolean:(Ljava/lang/String;)Z
        60: invokestatic  #922                // Method java/lang/Boolean.valueOf:(Z)Ljava/lang/Boolean;
        63: invokevirtual #486                // Method net/minecraft/network/syncher/SynchedEntityData.set:(Lnet/minecraft/network/syncher/EntityDataAccessor;Ljava/lang/Object;)V
        66: return

  public void disassemble();
    Code:
         0: aload_0
         1: invokevirtual #893                // Method isAlive:()Z
         4: ifne          8
         7: return
         8: aload_0
         9: getfield      #89                 // Field contraption:Lcom/simibubi/create/content/contraptions/Contraption;
        12: ifnonnull     16
        15: return
        16: aload_0
        17: invokevirtual #1142               // Method makeStructureTransform:()Lcom/simibubi/create/content/contraptions/StructureTransform;
        20: astore_1
        21: aload_0
        22: getfield      #89                 // Field contraption:Lcom/simibubi/create/content/contraptions/Contraption;
        25: aload_0
        26: invokevirtual #93                 // Method level:()Lnet/minecraft/world/level/Level;
        29: invokevirtual #908                // Method com/simibubi/create/content/contraptions/Contraption.stop:(Lnet/minecraft/world/level/Level;)V
        32: invokestatic  #221                // Method com/simibubi/create/AllPackets.getChannel:()Lnet/minecraftforge/network/simple/SimpleChannel;
        35: getstatic     #225                // Field net/minecraftforge/network/PacketDistributor.TRACKING_ENTITY:Lnet/minecraftforge/network/PacketDistributor;
        38: aload_0
        39: invokedynamic #1147,  0           // InvokeDynamic #9:get:(Lcom/simibubi/create/content/contraptions/AbstractContraptionEntity;)Ljava/util/function/Supplier;
        44: invokevirtual #246                // Method net/minecraftforge/network/PacketDistributor.with:(Ljava/util/function/Supplier;)Lnet/minecraftforge/network/PacketDistributor$PacketTarget;
        47: new           #1149               // class com/simibubi/create/content/contraptions/ContraptionDisassemblyPacket
        50: dup
        51: aload_0
        52: invokevirtual #252                // Method getId:()I
        55: aload_1
        56: invokespecial #1152               // Method com/simibubi/create/content/contraptions/ContraptionDisassemblyPacket."<init>":(ILcom/simibubi/create/content/contraptions/StructureTransform;)V
        59: invokevirtual #261                // Method net/minecraftforge/network/simple/SimpleChannel.send:(Lnet/minecraftforge/network/PacketDistributor$PacketTarget;Ljava/lang/Object;)V
        62: aload_0
        63: getfield      #89                 // Field contraption:Lcom/simibubi/create/content/contraptions/Contraption;
        66: aload_0
        67: invokevirtual #93                 // Method level:()Lnet/minecraft/world/level/Level;
        70: aload_1
        71: invokevirtual #1156               // Method com/simibubi/create/content/contraptions/Contraption.addBlocksToWorld:(Lnet/minecraft/world/level/Level;Lcom/simibubi/create/content/contraptions/StructureTransform;)V
        74: aload_0
        75: getfield      #89                 // Field contraption:Lcom/simibubi/create/content/contraptions/Contraption;
        78: aload_0
        79: invokevirtual #93                 // Method level:()Lnet/minecraft/world/level/Level;
        82: aload_1
        83: aload_0
        84: invokevirtual #154                // Method getPassengers:()Ljava/util/List;
        87: invokevirtual #1160               // Method com/simibubi/create/content/contraptions/Contraption.addPassengersToWorld:(Lnet/minecraft/world/level/Level;Lcom/simibubi/create/content/contraptions/StructureTransform;Ljava/util/List;)V
        90: aload_0
        91: invokevirtual #154                // Method getPassengers:()Ljava/util/List;
        94: invokeinterface #160,  1          // InterfaceMethod java/util/List.iterator:()Ljava/util/Iterator;
        99: astore_2
       100: aload_2
       101: invokeinterface #165,  1          // InterfaceMethod java/util/Iterator.hasNext:()Z
       106: ifeq          213
       109: aload_2
       110: invokeinterface #169,  1          // InterfaceMethod java/util/Iterator.next:()Ljava/lang/Object;
       115: checkcast     #4                  // class net/minecraft/world/entity/Entity
       118: astore_3
       119: aload_3
       120: instanceof    #394                // class com/simibubi/create/content/contraptions/OrientedContraptionEntity
       123: ifne          129
       126: goto          100
       129: aload_3
       130: invokevirtual #173                // Method net/minecraft/world/entity/Entity.getUUID:()Ljava/util/UUID;
       133: astore        4
       135: aload_0
       136: getfield      #89                 // Field contraption:Lcom/simibubi/create/content/contraptions/Contraption;
       139: getfield      #911                // Field com/simibubi/create/content/contraptions/Contraption.stabilizedSubContraptions:Ljava/util/Map;
       142: aload         4
       144: invokeinterface #576,  2          // InterfaceMethod java/util/Map.containsKey:(Ljava/lang/Object;)Z
       149: ifne          155
       152: goto          100
       155: aload_1
       156: aload_0
       157: getfield      #89                 // Field contraption:Lcom/simibubi/create/content/contraptions/Contraption;
       160: getfield      #911                // Field com/simibubi/create/content/contraptions/Contraption.stabilizedSubContraptions:Ljava/util/Map;
       163: aload         4
       165: invokeinterface #578,  2          // InterfaceMethod java/util/Map.get:(Ljava/lang/Object;)Ljava/lang/Object;
       170: checkcast     #1164               // class net/createmod/catnip/math/BlockFace
       173: invokevirtual #1167               // Method net/createmod/catnip/math/BlockFace.getConnectedPos:()Lnet/minecraft/core/BlockPos;
       176: invokevirtual #1170               // Method com/simibubi/create/content/contraptions/StructureTransform.apply:(Lnet/minecraft/core/BlockPos;)Lnet/minecraft/core/BlockPos;
       179: astore        5
       181: aload_3
       182: aload         5
       184: invokevirtual #1172               // Method net/minecraft/core/BlockPos.getX:()I
       187: i2d
       188: aload         5
       190: invokevirtual #1174               // Method net/minecraft/core/BlockPos.getY:()I
       193: i2d
       194: aload         5
       196: invokevirtual #1176               // Method net/minecraft/core/BlockPos.getZ:()I
       199: i2d
       200: invokevirtual #1024               // Method net/minecraft/world/entity/Entity.setPos:(DDD)V
       203: aload_3
       204: checkcast     #2                  // class com/simibubi/create/content/contraptions/AbstractContraptionEntity
       207: invokevirtual #1178               // Method disassemble:()V
       210: goto          100
       213: aload_0
       214: iconst_1
       215: putfield      #819                // Field skipActorStop:Z
       218: aload_0
       219: invokevirtual #669                // Method discard:()V
       222: aload_0
       223: invokevirtual #1181               // Method ejectPassengers:()V
       226: aload_0
       227: aload_1
       228: invokevirtual #1185               // Method moveCollidedEntitiesOnDisassembly:(Lcom/simibubi/create/content/contraptions/StructureTransform;)V
       231: getstatic     #1189               // Field com/simibubi/create/AllSoundEvents.CONTRAPTION_DISASSEMBLE:Lcom/simibubi/create/AllSoundEvents$SoundEntry;
       234: aload_0
       235: invokevirtual #93                 // Method level:()Lnet/minecraft/world/level/Level;
       238: aload_0
       239: invokevirtual #1192               // Method blockPosition:()Lnet/minecraft/core/BlockPos;
       242: invokevirtual #1196               // Method com/simibubi/create/AllSoundEvents$SoundEntry.playOnServer:(Lnet/minecraft/world/level/Level;Lnet/minecraft/core/Vec3i;)V
       245: return

  private void moveCollidedEntitiesOnDisassembly(com.simibubi.create.content.contraptions.StructureTransform);
    Code:
         0: aload_0
         1: getfield      #78                 // Field collidingEntities:Ljava/util/Map;
         4: invokeinterface #1202,  1         // InterfaceMethod java/util/Map.keySet:()Ljava/util/Set;
         9: invokeinterface #603,  1          // InterfaceMethod java/util/Set.iterator:()Ljava/util/Iterator;
        14: astore_2
        15: aload_2
        16: invokeinterface #165,  1          // InterfaceMethod java/util/Iterator.hasNext:()Z
        21: ifeq          115
        24: aload_2
        25: invokeinterface #169,  1          // InterfaceMethod java/util/Iterator.next:()Ljava/lang/Object;
        30: checkcast     #4                  // class net/minecraft/world/entity/Entity
        33: astore_3
        34: aload_0
        35: aload_3
        36: invokevirtual #1203               // Method net/minecraft/world/entity/Entity.position:()Lnet/minecraft/world/phys/Vec3;
        39: fconst_0
        40: invokevirtual #1205               // Method toLocalVector:(Lnet/minecraft/world/phys/Vec3;F)Lnet/minecraft/world/phys/Vec3;
        43: astore        4
        45: aload_1
        46: aload         4
        48: invokevirtual #1207               // Method com/simibubi/create/content/contraptions/StructureTransform.apply:(Lnet/minecraft/world/phys/Vec3;)Lnet/minecraft/world/phys/Vec3;
        51: astore        5
        53: aload_0
        54: invokevirtual #93                 // Method level:()Lnet/minecraft/world/level/Level;
        57: getfield      #98                 // Field net/minecraft/world/level/Level.isClientSide:Z
        60: ifeq          89
        63: aload_3
        64: aload         5
        66: getfield      #372                // Field net/minecraft/world/phys/Vec3.x:D
        69: aload         5
        71: getfield      #375                // Field net/minecraft/world/phys/Vec3.y:D
        74: ldc2_w        #1208               // double 0.0625d
        77: dadd
        78: aload         5
        80: getfield      #384                // Field net/minecraft/world/phys/Vec3.z:D
        83: invokevirtual #1024               // Method net/minecraft/world/entity/Entity.setPos:(DDD)V
        86: goto          112
        89: aload_3
        90: aload         5
        92: getfield      #372                // Field net/minecraft/world/phys/Vec3.x:D
        95: aload         5
        97: getfield      #375                // Field net/minecraft/world/phys/Vec3.y:D
       100: ldc2_w        #1208               // double 0.0625d
       103: dadd
       104: aload         5
       106: getfield      #384                // Field net/minecraft/world/phys/Vec3.z:D
       109: invokevirtual #617                // Method net/minecraft/world/entity/Entity.teleportTo:(DDD)V
       112: goto          15
       115: return

  public void remove(net.minecraft.world.entity.Entity$RemovalReason);
    Code:
         0: aload_0
         1: invokevirtual #93                 // Method level:()Lnet/minecraft/world/level/Level;
         4: getfield      #98                 // Field net/minecraft/world/level/Level.isClientSide:Z
         7: ifne          42
        10: aload_0
        11: invokevirtual #1213               // Method isRemoved:()Z
        14: ifne          42
        17: aload_0
        18: getfield      #89                 // Field contraption:Lcom/simibubi/create/content/contraptions/Contraption;
        21: ifnull        42
        24: aload_0
        25: getfield      #819                // Field skipActorStop:Z
        28: ifne          42
        31: aload_0
        32: getfield      #89                 // Field contraption:Lcom/simibubi/create/content/contraptions/Contraption;
        35: aload_0
        36: invokevirtual #93                 // Method level:()Lnet/minecraft/world/level/Level;
        39: invokevirtual #908                // Method com/simibubi/create/content/contraptions/Contraption.stop:(Lnet/minecraft/world/level/Level;)V
        42: aload_0
        43: getfield      #89                 // Field contraption:Lcom/simibubi/create/content/contraptions/Contraption;
        46: ifnull        57
        49: aload_0
        50: getfield      #89                 // Field contraption:Lcom/simibubi/create/content/contraptions/Contraption;
        53: aload_0
        54: invokevirtual #1216               // Method com/simibubi/create/content/contraptions/Contraption.onEntityRemoved:(Lcom/simibubi/create/content/contraptions/AbstractContraptionEntity;)V
        57: aload_0
        58: aload_1
        59: invokespecial #1218               // Method net/minecraft/world/entity/Entity.remove:(Lnet/minecraft/world/entity/Entity$RemovalReason;)V
        62: return

  protected abstract com.simibubi.create.content.contraptions.StructureTransform makeStructureTransform();

  public void kill();
    Code:
         0: aload_0
         1: invokevirtual #1181               // Method ejectPassengers:()V
         4: aload_0
         5: invokespecial #1223               // Method net/minecraft/world/entity/Entity.kill:()V
         8: return

  protected void onBelowWorld();
    Code:
         0: aload_0
         1: invokevirtual #1181               // Method ejectPassengers:()V
         4: aload_0
         5: invokespecial #1226               // Method net/minecraft/world/entity/Entity.onBelowWorld:()V
         8: return

  public void onRemovedFromWorld();
    Code:
         0: aload_0
         1: invokespecial #1229               // Method net/minecraft/world/entity/Entity.onRemovedFromWorld:()V
         4: return

  protected void doWaterSplashEffect();
    Code:
         0: return

  public com.simibubi.create.content.contraptions.Contraption getContraption();
    Code:
         0: aload_0
         1: getfield      #89                 // Field contraption:Lcom/simibubi/create/content/contraptions/Contraption;
         4: areturn

  public boolean isStalled();
    Code:
         0: aload_0
         1: getfield      #466                // Field entityData:Lnet/minecraft/network/syncher/SynchedEntityData;
         4: getstatic     #917                // Field STALLED:Lnet/minecraft/network/syncher/EntityDataAccessor;
         7: invokevirtual #473                // Method net/minecraft/network/syncher/SynchedEntityData.get:(Lnet/minecraft/network/syncher/EntityDataAccessor;)Ljava/lang/Object;
        10: checkcast     #919                // class java/lang/Boolean
        13: invokevirtual #1235               // Method java/lang/Boolean.booleanValue:()Z
        16: ireturn

  static void handleStallPacket(com.simibubi.create.content.contraptions.ContraptionStallPacket);
    Code:
         0: invokestatic  #1247               // Method net/minecraft/client/Minecraft.getInstance:()Lnet/minecraft/client/Minecraft;
         3: getfield      #1250               // Field net/minecraft/client/Minecraft.level:Lnet/minecraft/client/multiplayer/ClientLevel;
         6: aload_0
         7: getfield      #1253               // Field com/simibubi/create/content/contraptions/ContraptionStallPacket.entityID:I
        10: invokevirtual #1259               // Method net/minecraft/client/multiplayer/ClientLevel.getEntity:(I)Lnet/minecraft/world/entity/Entity;
        13: astore_2
        14: aload_2
        15: instanceof    #2                  // class com/simibubi/create/content/contraptions/AbstractContraptionEntity
        18: ifeq          46
        21: aload_2
        22: checkcast     #2                  // class com/simibubi/create/content/contraptions/AbstractContraptionEntity
        25: astore_1
        26: aload_1
        27: aload_0
        28: getfield      #1260               // Field com/simibubi/create/content/contraptions/ContraptionStallPacket.x:D
        31: aload_0
        32: getfield      #1261               // Field com/simibubi/create/content/contraptions/ContraptionStallPacket.y:D
        35: aload_0
        36: getfield      #1262               // Field com/simibubi/create/content/contraptions/ContraptionStallPacket.z:D
        39: aload_0
        40: getfield      #1264               // Field com/simibubi/create/content/contraptions/ContraptionStallPacket.angle:F
        43: invokevirtual #1268               // Method handleStallInformation:(DDDF)V
        46: return

  static void handleBlockChangedPacket(com.simibubi.create.content.contraptions.ContraptionBlockChangedPacket);
    Code:
         0: invokestatic  #1247               // Method net/minecraft/client/Minecraft.getInstance:()Lnet/minecraft/client/Minecraft;
         3: getfield      #1250               // Field net/minecraft/client/Minecraft.level:Lnet/minecraft/client/multiplayer/ClientLevel;
         6: aload_0
         7: getfield      #1274               // Field com/simibubi/create/content/contraptions/ContraptionBlockChangedPacket.entityID:I
        10: invokevirtual #1259               // Method net/minecraft/client/multiplayer/ClientLevel.getEntity:(I)Lnet/minecraft/world/entity/Entity;
        13: astore_2
        14: aload_2
        15: instanceof    #2                  // class com/simibubi/create/content/contraptions/AbstractContraptionEntity
        18: ifeq          38
        21: aload_2
        22: checkcast     #2                  // class com/simibubi/create/content/contraptions/AbstractContraptionEntity
        25: astore_1
        26: aload_1
        27: aload_0
        28: getfield      #1276               // Field com/simibubi/create/content/contraptions/ContraptionBlockChangedPacket.localPos:Lnet/minecraft/core/BlockPos;
        31: aload_0
        32: getfield      #1280               // Field com/simibubi/create/content/contraptions/ContraptionBlockChangedPacket.newState:Lnet/minecraft/world/level/block/state/BlockState;
        35: invokevirtual #1284               // Method handleBlockChange:(Lnet/minecraft/core/BlockPos;Lnet/minecraft/world/level/block/state/BlockState;)V
        38: return

  static void handleDisassemblyPacket(com.simibubi.create.content.contraptions.ContraptionDisassemblyPacket);
    Code:
         0: invokestatic  #1247               // Method net/minecraft/client/Minecraft.getInstance:()Lnet/minecraft/client/Minecraft;
         3: getfield      #1250               // Field net/minecraft/client/Minecraft.level:Lnet/minecraft/client/multiplayer/ClientLevel;
         6: aload_0
         7: getfield      #1288               // Field com/simibubi/create/content/contraptions/ContraptionDisassemblyPacket.entityID:I
        10: invokevirtual #1259               // Method net/minecraft/client/multiplayer/ClientLevel.getEntity:(I)Lnet/minecraft/world/entity/Entity;
        13: astore_2
        14: aload_2
        15: instanceof    #2                  // class com/simibubi/create/content/contraptions/AbstractContraptionEntity
        18: ifeq          34
        21: aload_2
        22: checkcast     #2                  // class com/simibubi/create/content/contraptions/AbstractContraptionEntity
        25: astore_1
        26: aload_1
        27: aload_0
        28: getfield      #1290               // Field com/simibubi/create/content/contraptions/ContraptionDisassemblyPacket.transform:Lcom/simibubi/create/content/contraptions/StructureTransform;
        31: invokevirtual #1185               // Method moveCollidedEntitiesOnDisassembly:(Lcom/simibubi/create/content/contraptions/StructureTransform;)V
        34: return

  protected abstract float getStalledAngle();

  protected abstract void handleStallInformation(double, double, double, float);

  protected void handleBlockChange(net.minecraft.core.BlockPos, net.minecraft.world.level.block.state.BlockState);
    Code:
         0: aload_0
         1: getfield      #89                 // Field contraption:Lcom/simibubi/create/content/contraptions/Contraption;
         4: ifnull        23
         7: aload_0
         8: getfield      #89                 // Field contraption:Lcom/simibubi/create/content/contraptions/Contraption;
        11: getfield      #797                // Field com/simibubi/create/content/contraptions/Contraption.blocks:Ljava/util/Map;
        14: aload_1
        15: invokeinterface #576,  2          // InterfaceMethod java/util/Map.containsKey:(Ljava/lang/Object;)Z
        20: ifne          24
        23: return
        24: aload_0
        25: getfield      #89                 // Field contraption:Lcom/simibubi/create/content/contraptions/Contraption;
        28: getfield      #797                // Field com/simibubi/create/content/contraptions/Contraption.blocks:Ljava/util/Map;
        31: aload_1
        32: invokeinterface #578,  2          // InterfaceMethod java/util/Map.get:(Ljava/lang/Object;)Ljava/lang/Object;
        37: checkcast     #24                 // class net/minecraft/world/level/levelgen/structure/templatesystem/StructureTemplate$StructureBlockInfo
        40: astore_3
        41: aload_0
        42: getfield      #89                 // Field contraption:Lcom/simibubi/create/content/contraptions/Contraption;
        45: getfield      #797                // Field com/simibubi/create/content/contraptions/Contraption.blocks:Ljava/util/Map;
        48: aload_1
        49: new           #24                 // class net/minecraft/world/level/levelgen/structure/templatesystem/StructureTemplate$StructureBlockInfo
        52: dup
        53: aload_3
        54: invokevirtual #850                // Method net/minecraft/world/level/levelgen/structure/templatesystem/StructureTemplate$StructureBlockInfo.pos:()Lnet/minecraft/core/BlockPos;
        57: aload_2
        58: aload_3
        59: invokevirtual #1293               // Method net/minecraft/world/level/levelgen/structure/templatesystem/StructureTemplate$StructureBlockInfo.nbt:()Lnet/minecraft/nbt/CompoundTag;
        62: invokespecial #1296               // Method net/minecraft/world/level/levelgen/structure/templatesystem/StructureTemplate$StructureBlockInfo."<init>":(Lnet/minecraft/core/BlockPos;Lnet/minecraft/world/level/block/state/BlockState;Lnet/minecraft/nbt/CompoundTag;)V
        65: invokeinterface #146,  3          // InterfaceMethod java/util/Map.put:(Ljava/lang/Object;Ljava/lang/Object;)Ljava/lang/Object;
        70: pop
        71: aload_3
        72: invokevirtual #808                // Method net/minecraft/world/level/levelgen/structure/templatesystem/StructureTemplate$StructureBlockInfo.state:()Lnet/minecraft/world/level/block/state/BlockState;
        75: aload_2
        76: if_acmpeq     96
        79: aload_2
        80: invokevirtual #1302               // Method net/minecraft/world/level/block/state/BlockState.getBlock:()Lnet/minecraft/world/level/block/Block;
        83: instanceof    #1304               // class com/simibubi/create/content/decoration/slidingDoor/SlidingDoorBlock
        86: ifne          96
        89: aload_0
        90: getfield      #89                 // Field contraption:Lcom/simibubi/create/content/contraptions/Contraption;
        93: invokevirtual #1307               // Method com/simibubi/create/content/contraptions/Contraption.resetClientContraption:()V
        96: aload_0
        97: getfield      #89                 // Field contraption:Lcom/simibubi/create/content/contraptions/Contraption;
       100: invokevirtual #1310               // Method com/simibubi/create/content/contraptions/Contraption.invalidateColliders:()V
       103: return

  public net.minecraft.nbt.CompoundTag saveWithoutId(net.minecraft.nbt.CompoundTag);
    Code:
         0: aload_0
         1: invokevirtual #1019               // Method position:()Lnet/minecraft/world/phys/Vec3;
         4: astore_2
         5: aload_0
         6: invokevirtual #154                // Method getPassengers:()Ljava/util/List;
         9: astore_3
        10: aload_3
        11: invokeinterface #160,  1          // InterfaceMethod java/util/List.iterator:()Ljava/util/Iterator;
        16: astore        4
        18: aload         4
        20: invokeinterface #165,  1          // InterfaceMethod java/util/Iterator.hasNext:()Z
        25: ifeq          82
        28: aload         4
        30: invokeinterface #169,  1          // InterfaceMethod java/util/Iterator.next:()Ljava/lang/Object;
        35: checkcast     #4                  // class net/minecraft/world/entity/Entity
        38: astore        5
        40: aload         5
        42: getstatic     #1316               // Field net/minecraft/world/entity/Entity$RemovalReason.UNLOADED_TO_CHUNK:Lnet/minecraft/world/entity/Entity$RemovalReason;
        45: putfield      #1319               // Field net/minecraft/world/entity/Entity.removalReason:Lnet/minecraft/world/entity/Entity$RemovalReason;
        48: aload         5
        50: invokevirtual #1203               // Method net/minecraft/world/entity/Entity.position:()Lnet/minecraft/world/phys/Vec3;
        53: astore        6
        55: aload         5
        57: aload_2
        58: getfield      #372                // Field net/minecraft/world/phys/Vec3.x:D
        61: aload         6
        63: getfield      #375                // Field net/minecraft/world/phys/Vec3.y:D
        66: aload_2
        67: getfield      #384                // Field net/minecraft/world/phys/Vec3.z:D
        70: invokevirtual #1322               // Method net/minecraft/world/entity/Entity.setPosRaw:(DDD)V
        73: aload         5
        75: aconst_null
        76: putfield      #1319               // Field net/minecraft/world/entity/Entity.removalReason:Lnet/minecraft/world/entity/Entity$RemovalReason;
        79: goto          18
        82: aload_0
        83: aload_1
        84: invokespecial #1324               // Method net/minecraft/world/entity/Entity.saveWithoutId:(Lnet/minecraft/nbt/CompoundTag;)Lnet/minecraft/nbt/CompoundTag;
        87: astore        4
        89: aload         4
        91: areturn

  public void setDeltaMovement(net.minecraft.world.phys.Vec3);
    Code:
         0: return

  public net.minecraft.world.level.material.PushReaction getPistonPushReaction();
    Code:
         0: getstatic     #1340               // Field net/minecraft/world/level/material/PushReaction.IGNORE:Lnet/minecraft/world/level/material/PushReaction;
         3: areturn

  public void setContraptionMotion(net.minecraft.world.phys.Vec3);
    Code:
         0: aload_0
         1: aload_1
         2: invokespecial #1343               // Method net/minecraft/world/entity/Entity.setDeltaMovement:(Lnet/minecraft/world/phys/Vec3;)V
         5: return

  public boolean isPickable();
    Code:
         0: iconst_0
         1: ireturn

  public boolean hurt(net.minecraft.world.damagesource.DamageSource, float);
    Code:
         0: iconst_0
         1: ireturn

  public net.minecraft.world.phys.Vec3 getPrevPositionVec();
    Code:
         0: aload_0
         1: getfield      #71                 // Field prevPosInvalid:Z
         4: ifeq          14
         7: aload_0
         8: invokevirtual #1019               // Method position:()Lnet/minecraft/world/phys/Vec3;
        11: goto          33
        14: new           #277                // class net/minecraft/world/phys/Vec3
        17: dup
        18: aload_0
        19: getfield      #690                // Field xo:D
        22: aload_0
        23: getfield      #696                // Field yo:D
        26: aload_0
        27: getfield      #702                // Field zo:D
        30: invokespecial #1351               // Method net/minecraft/world/phys/Vec3."<init>":(DDD)V
        33: areturn

  public abstract com.simibubi.create.content.contraptions.AbstractContraptionEntity$ContraptionRotationState getRotationState();

  public net.minecraft.world.phys.Vec3 getContactPointMotion(net.minecraft.world.phys.Vec3);
    Code:
         0: aload_0
         1: getfield      #71                 // Field prevPosInvalid:Z
         4: ifeq          11
         7: getstatic     #1355               // Field net/minecraft/world/phys/Vec3.ZERO:Lnet/minecraft/world/phys/Vec3;
        10: areturn
        11: aload_0
        12: aload_0
        13: aload_1
        14: fconst_0
        15: iconst_1
        16: invokevirtual #661                // Method toLocalVector:(Lnet/minecraft/world/phys/Vec3;FZ)Lnet/minecraft/world/phys/Vec3;
        19: fconst_1
        20: iconst_1
        21: invokevirtual #642                // Method toGlobalVector:(Lnet/minecraft/world/phys/Vec3;FZ)Lnet/minecraft/world/phys/Vec3;
        24: astore_2
        25: aload_2
        26: aload_1
        27: invokevirtual #652                // Method net/minecraft/world/phys/Vec3.subtract:(Lnet/minecraft/world/phys/Vec3;)Lnet/minecraft/world/phys/Vec3;
        30: astore_3
        31: aload_0
        32: invokevirtual #1019               // Method position:()Lnet/minecraft/world/phys/Vec3;
        35: aload_0
        36: invokevirtual #1022               // Method getPrevPositionVec:()Lnet/minecraft/world/phys/Vec3;
        39: invokevirtual #652                // Method net/minecraft/world/phys/Vec3.subtract:(Lnet/minecraft/world/phys/Vec3;)Lnet/minecraft/world/phys/Vec3;
        42: astore        4
        44: aload_3
        45: aload         4
        47: invokevirtual #412                // Method net/minecraft/world/phys/Vec3.add:(Lnet/minecraft/world/phys/Vec3;)Lnet/minecraft/world/phys/Vec3;
        50: areturn

  public boolean canCollideWith(net.minecraft.world.entity.Entity);
    Code:
         0: aload_1
         1: instanceof    #192                // class net/minecraft/world/entity/player/Player
         4: ifeq          16
         7: aload_1
         8: invokevirtual #1363               // Method net/minecraft/world/entity/Entity.isSpectator:()Z
        11: ifeq          16
        14: iconst_0
        15: ireturn
        16: aload_1
        17: getfield      #1366               // Field net/minecraft/world/entity/Entity.noPhysics:Z
        20: ifeq          25
        23: iconst_0
        24: ireturn
        25: aload_1
        26: instanceof    #1368               // class net/minecraft/world/entity/decoration/HangingEntity
        29: ifeq          34
        32: iconst_0
        33: ireturn
        34: aload_1
        35: instanceof    #1370               // class net/minecraft/world/entity/vehicle/AbstractMinecart
        38: ifeq          57
        41: aload_0
        42: getfield      #89                 // Field contraption:Lcom/simibubi/create/content/contraptions/Contraption;
        45: instanceof    #1372               // class com/simibubi/create/content/contraptions/mounted/MountedContraption
        48: ifne          55
        51: iconst_1
        52: goto          56
        55: iconst_0
        56: ireturn
        57: aload_1
        58: instanceof    #1374               // class com/simibubi/create/content/contraptions/glue/SuperGlueEntity
        61: ifeq          66
        64: iconst_0
        65: ireturn
        66: aload_1
        67: instanceof    #377                // class com/simibubi/create/content/contraptions/actors/seat/SeatEntity
        70: ifeq          75
        73: iconst_0
        74: ireturn
        75: aload_1
        76: instanceof    #1376               // class net/minecraft/world/entity/projectile/Projectile
        79: ifeq          84
        82: iconst_0
        83: ireturn
        84: aload_1
        85: invokevirtual #1379               // Method net/minecraft/world/entity/Entity.getVehicle:()Lnet/minecraft/world/entity/Entity;
        88: ifnull        93
        91: iconst_0
        92: ireturn
        93: aload_0
        94: invokevirtual #1380               // Method getVehicle:()Lnet/minecraft/world/entity/Entity;
        97: astore_2
        98: aload_2
        99: ifnull        117
       102: aload_2
       103: aload_1
       104: if_acmpne     109
       107: iconst_0
       108: ireturn
       109: aload_2
       110: invokevirtual #1379               // Method net/minecraft/world/entity/Entity.getVehicle:()Lnet/minecraft/world/entity/Entity;
       113: astore_2
       114: goto          98
       117: aload_1
       118: invokevirtual #1382               // Method net/minecraft/world/entity/Entity.getPistonPushReaction:()Lnet/minecraft/world/level/material/PushReaction;
       121: getstatic     #1385               // Field net/minecraft/world/level/material/PushReaction.NORMAL:Lnet/minecraft/world/level/material/PushReaction;
       124: if_acmpne     131
       127: iconst_1
       128: goto          132
       131: iconst_0
       132: ireturn

  public boolean hasExactlyOnePlayerPassenger();
    Code:
         0: iconst_0
         1: ireturn

  public abstract void applyLocalTransforms(com.mojang.blaze3d.vertex.PoseStack, float);

  protected boolean updateInWaterStateAndDoFluidPushing();
    Code:
         0: iconst_0
         1: ireturn

  public void setSecondsOnFire(int);
    Code:
         0: return

  public boolean isIgnoringBlockTriggers();
    Code:
         0: iconst_1
         1: ireturn

  public boolean isReadyForRender();
    Code:
         0: aload_0
         1: getfield      #136                // Field initialized:Z
         4: ireturn

  public boolean isAliveOrStale();
    Code:
         0: aload_0
         1: invokevirtual #893                // Method isAlive:()Z
         4: ifne          17
         7: aload_0
         8: invokevirtual #93                 // Method level:()Lnet/minecraft/world/level/Level;
        11: invokevirtual #962                // Method net/minecraft/world/level/Level.isClientSide:()Z
        14: ifeq          32
        17: aload_0
        18: getfield      #69                 // Field staleTicks:I
        21: ifle          28
        24: iconst_1
        25: goto          33
        28: iconst_0
        29: goto          33
        32: iconst_0
        33: ireturn

  public boolean isPrevPosInvalid();
    Code:
         0: aload_0
         1: getfield      #71                 // Field prevPosInvalid:Z
         4: ireturn

  private net.minecraft.world.entity.Entity lambda$disassemble$9();
    Code:
         0: aload_0
         1: areturn

  private net.minecraft.world.entity.Entity lambda$onContraptionStalled$8();
    Code:
         0: aload_0
         1: areturn

  private net.minecraft.world.phys.Vec3 lambda$tickActors$7(net.minecraft.world.phys.Vec3);
    Code:
         0: aload_0
         1: aload_1
         2: fconst_1
         3: invokevirtual #655                // Method applyRotation:(Lnet/minecraft/world/phys/Vec3;F)Lnet/minecraft/world/phys/Vec3;
         6: areturn

  private net.minecraft.world.entity.Entity lambda$setBlock$6();
    Code:
         0: aload_0
         1: areturn

  private static boolean lambda$tick$5(java.util.Map$Entry);
    Code:
         0: aload_0
         1: invokeinterface #606,  1          // InterfaceMethod java/util/Map$Entry.getValue:()Ljava/lang/Object;
         6: checkcast     #141                // class org/apache/commons/lang3/mutable/MutableInt
         9: invokevirtual #1402               // Method org/apache/commons/lang3/mutable/MutableInt.incrementAndGet:()I
        12: iconst_3
        13: if_icmple     20
        16: iconst_1
        17: goto          21
        20: iconst_0
        21: ireturn

  private static void lambda$stopControlling$4(net.minecraft.server.level.ServerPlayer);
    Code:
         0: invokestatic  #221                // Method com/simibubi/create/AllPackets.getChannel:()Lnet/minecraftforge/network/simple/SimpleChannel;
         3: getstatic     #1405               // Field net/minecraftforge/network/PacketDistributor.PLAYER:Lnet/minecraftforge/network/PacketDistributor;
         6: aload_0
         7: invokedynamic #1415,  0           // InvokeDynamic #10:get:(Lnet/minecraft/server/level/ServerPlayer;)Ljava/util/function/Supplier;
        12: invokevirtual #246                // Method net/minecraftforge/network/PacketDistributor.with:(Ljava/util/function/Supplier;)Lnet/minecraftforge/network/PacketDistributor$PacketTarget;
        15: new           #1417               // class com/simibubi/create/content/contraptions/actors/trainControls/ControlsStopControllingPacket
        18: dup
        19: invokespecial #1418               // Method com/simibubi/create/content/contraptions/actors/trainControls/ControlsStopControllingPacket."<init>":()V
        22: invokevirtual #261                // Method net/minecraftforge/network/simple/SimpleChannel.send:(Lnet/minecraftforge/network/PacketDistributor$PacketTarget;Ljava/lang/Object;)V
        25: return

  private static net.minecraft.server.level.ServerPlayer lambda$stopControlling$3(net.minecraft.server.level.ServerPlayer);
    Code:
         0: aload_0
         1: areturn

  private static net.minecraft.server.level.ServerPlayer lambda$stopControlling$2(net.minecraft.world.entity.player.Player);
    Code:
         0: aload_0
         1: instanceof    #1422               // class net/minecraft/server/level/ServerPlayer
         4: ifeq          14
         7: aload_0
         8: checkcast     #1422               // class net/minecraft/server/level/ServerPlayer
        11: goto          15
        14: aconst_null
        15: areturn

  private net.minecraft.world.entity.Entity lambda$removePassenger$1();
    Code:
         0: aload_0
         1: areturn

  private net.minecraft.world.entity.Entity lambda$addSittingPassenger$0();
    Code:
         0: aload_0
         1: areturn

  static {};
    Code:
         0: ldc           #2                  // class com/simibubi/create/content/contraptions/AbstractContraptionEntity
         2: getstatic     #1429               // Field net/minecraft/network/syncher/EntityDataSerializers.BOOLEAN:Lnet/minecraft/network/syncher/EntityDataSerializer;
         5: invokestatic  #1433               // Method net/minecraft/network/syncher/SynchedEntityData.defineId:(Ljava/lang/Class;Lnet/minecraft/network/syncher/EntityDataSerializer;)Lnet/minecraft/network/syncher/EntityDataAccessor;
         8: putstatic     #917                // Field STALLED:Lnet/minecraft/network/syncher/EntityDataAccessor;
        11: ldc           #2                  // class com/simibubi/create/content/contraptions/AbstractContraptionEntity
        13: getstatic     #1436               // Field net/minecraft/network/syncher/EntityDataSerializers.OPTIONAL_UUID:Lnet/minecraft/network/syncher/EntityDataSerializer;
        16: invokestatic  #1433               // Method net/minecraft/network/syncher/SynchedEntityData.defineId:(Ljava/lang/Class;Lnet/minecraft/network/syncher/EntityDataSerializer;)Lnet/minecraft/network/syncher/EntityDataAccessor;
        19: putstatic     #468                // Field CONTROLLED_BY:Lnet/minecraft/network/syncher/EntityDataAccessor;
        22: return
}
