Compiled from "CarriageContraptionEntityRenderer.java"
public class com.simibubi.create.content.trains.entity.CarriageContraptionEntityRenderer extends com.simibubi.create.content.contraptions.render.ContraptionEntityRenderer<com.simibubi.create.content.trains.entity.CarriageContraptionEntity> {
  public com.simibubi.create.content.trains.entity.CarriageContraptionEntityRenderer(net.minecraft.client.renderer.entity.EntityRendererProvider$Context);
    Code:
         0: aload_0
         1: aload_1
         2: invokespecial #25                 // Method com/simibubi/create/content/contraptions/render/ContraptionEntityRenderer."<init>":(Lnet/minecraft/client/renderer/entity/EntityRendererProvider$Context;)V
         5: return

  public boolean shouldRender(com.simibubi.create.content.trains.entity.CarriageContraptionEntity, net.minecraft.client.renderer.culling.Frustum, double, double, double);
    Code:
         0: aload_1
         1: invokevirtual #37                 // Method com/simibubi/create/content/trains/entity/CarriageContraptionEntity.getCarriage:()Lcom/simibubi/create/content/trains/entity/Carriage;
         4: astore        9
         6: aload         9
         8: ifnull        64
        11: aload         9
        13: getfield      #43                 // Field com/simibubi/create/content/trains/entity/Carriage.bogeys:Lnet/createmod/catnip/data/Couple;
        16: invokevirtual #49                 // Method net/createmod/catnip/data/Couple.iterator:()Ljava/util/Iterator;
        19: astore        10
        21: aload         10
        23: invokeinterface #55,  1           // InterfaceMethod java/util/Iterator.hasNext:()Z
        28: ifeq          64
        31: aload         10
        33: invokeinterface #59,  1           // InterfaceMethod java/util/Iterator.next:()Ljava/lang/Object;
        38: checkcast     #61                 // class com/simibubi/create/content/trains/entity/CarriageBogey
        41: astore        11
        43: aload         11
        45: ifnull        61
        48: aload         11
        50: getfield      #64                 // Field com/simibubi/create/content/trains/entity/CarriageBogey.couplingAnchors:Lnet/createmod/catnip/data/Couple;
        53: invokedynamic #83,  0             // InvokeDynamic #0:apply:()Ljava/util/function/Function;
        58: invokevirtual #87                 // Method net/createmod/catnip/data/Couple.replace:(Ljava/util/function/Function;)V
        61: goto          21
        64: aload_0
        65: aload_1
        66: aload_2
        67: dload_3
        68: dload         5
        70: dload         7
        72: invokespecial #90                 // Method com/simibubi/create/content/contraptions/render/ContraptionEntityRenderer.shouldRender:(Lcom/simibubi/create/content/contraptions/AbstractContraptionEntity;Lnet/minecraft/client/renderer/culling/Frustum;DDD)Z
        75: ireturn

  public void render(com.simibubi.create.content.trains.entity.CarriageContraptionEntity, float, float, com.mojang.blaze3d.vertex.PoseStack, net.minecraft.client.renderer.MultiBufferSource, int);
    Code:
         0: aload_1
         1: getfield      #108                // Field com/simibubi/create/content/trains/entity/CarriageContraptionEntity.validForRender:Z
         4: ifeq          14
         7: aload_1
         8: getfield      #111                // Field com/simibubi/create/content/trains/entity/CarriageContraptionEntity.firstPositionUpdate:Z
        11: ifeq          15
        14: return
        15: aload_0
        16: aload_1
        17: fload_2
        18: fload_3
        19: aload         4
        21: aload         5
        23: iload         6
        25: invokespecial #114                // Method com/simibubi/create/content/contraptions/render/ContraptionEntityRenderer.render:(Lcom/simibubi/create/content/contraptions/AbstractContraptionEntity;FFLcom/mojang/blaze3d/vertex/PoseStack;Lnet/minecraft/client/renderer/MultiBufferSource;I)V
        28: aload_1
        29: invokevirtual #37                 // Method com/simibubi/create/content/trains/entity/CarriageContraptionEntity.getCarriage:()Lcom/simibubi/create/content/trains/entity/Carriage;
        32: astore        7
        34: aload         7
        36: ifnonnull     40
        39: return
        40: aload_1
        41: fload_3
        42: invokevirtual #118                // Method com/simibubi/create/content/trains/entity/CarriageContraptionEntity.getPosition:(F)Lnet/minecraft/world/phys/Vec3;
        45: astore        8
        47: aload_1
        48: fload_3
        49: invokevirtual #122                // Method com/simibubi/create/content/trains/entity/CarriageContraptionEntity.getViewYRot:(F)F
        52: fstore        9
        54: aload_1
        55: fload_3
        56: invokevirtual #125                // Method com/simibubi/create/content/trains/entity/CarriageContraptionEntity.getViewXRot:(F)F
        59: fstore        10
        61: aload         7
        63: getfield      #129                // Field com/simibubi/create/content/trains/entity/Carriage.bogeySpacing:I
        66: istore        11
        68: aload         7
        70: getfield      #43                 // Field com/simibubi/create/content/trains/entity/Carriage.bogeys:Lnet/createmod/catnip/data/Couple;
        73: aload_1
        74: iload         11
        76: aload         4
        78: fload         9
        80: fload         10
        82: fload_3
        83: aload         5
        85: iload         6
        87: aload         8
        89: aload         7
        91: invokedynamic #142,  0            // InvokeDynamic #1:accept:(Lcom/simibubi/create/content/trains/entity/CarriageContraptionEntity;ILcom/mojang/blaze3d/vertex/PoseStack;FFFLnet/minecraft/client/renderer/MultiBufferSource;ILnet/minecraft/world/phys/Vec3;Lcom/simibubi/create/content/trains/entity/Carriage;)Ljava/util/function/Consumer;
        96: invokevirtual #146                // Method net/createmod/catnip/data/Couple.forEach:(Ljava/util/function/Consumer;)V
        99: return

  public static void translateBogey(com.mojang.blaze3d.vertex.PoseStack, com.simibubi.create.content.trains.entity.CarriageBogey, int, float, float, float);
    Code:
         0: aload_1
         1: invokevirtual #163                // Method com/simibubi/create/content/trains/entity/CarriageBogey.isUpsideDown:()Z
         4: istore        6
         6: aload_1
         7: getfield      #165                // Field com/simibubi/create/content/trains/entity/CarriageBogey.carriage:Lcom/simibubi/create/content/trains/entity/Carriage;
        10: invokevirtual #169                // Method com/simibubi/create/content/trains/entity/Carriage.leadingBogey:()Lcom/simibubi/create/content/trains/entity/CarriageBogey;
        13: invokevirtual #163                // Method com/simibubi/create/content/trains/entity/CarriageBogey.isUpsideDown:()Z
        16: istore        7
        18: aload_0
        19: invokestatic  #175                // InterfaceMethod dev/engine_room/flywheel/lib/transform/TransformStack.of:(Lcom/mojang/blaze3d/vertex/PoseStack;)Ldev/engine_room/flywheel/lib/transform/PoseTransformStack;
        22: fload_3
        23: ldc           #176                // float 90.0f
        25: fadd
        26: invokevirtual #182                // Method dev/engine_room/flywheel/lib/transform/PoseTransformStack.rotateYDegrees:(F)Ldev/engine_room/flywheel/lib/transform/Rotate;
        29: checkcast     #178                // class dev/engine_room/flywheel/lib/transform/PoseTransformStack
        32: fload         4
        34: fneg
        35: invokevirtual #185                // Method dev/engine_room/flywheel/lib/transform/PoseTransformStack.rotateXDegrees:(F)Ldev/engine_room/flywheel/lib/transform/Rotate;
        38: checkcast     #178                // class dev/engine_room/flywheel/lib/transform/PoseTransformStack
        41: ldc           #186                // float 180.0f
        43: invokevirtual #182                // Method dev/engine_room/flywheel/lib/transform/PoseTransformStack.rotateYDegrees:(F)Ldev/engine_room/flywheel/lib/transform/Rotate;
        46: checkcast     #178                // class dev/engine_room/flywheel/lib/transform/PoseTransformStack
        49: fconst_0
        50: fconst_0
        51: aload_1
        52: getfield      #189                // Field com/simibubi/create/content/trains/entity/CarriageBogey.isLeading:Z
        55: ifeq          62
        58: fconst_0
        59: goto          65
        62: iload_2
        63: ineg
        64: i2f
        65: invokevirtual #195                // Method dev/engine_room/flywheel/lib/transform/PoseTransformStack.translate:(FFF)Ldev/engine_room/flywheel/lib/transform/PoseTransformStack;
        68: ldc           #196                // float -180.0f
        70: invokevirtual #182                // Method dev/engine_room/flywheel/lib/transform/PoseTransformStack.rotateYDegrees:(F)Ldev/engine_room/flywheel/lib/transform/Rotate;
        73: checkcast     #178                // class dev/engine_room/flywheel/lib/transform/PoseTransformStack
        76: fload         4
        78: invokevirtual #185                // Method dev/engine_room/flywheel/lib/transform/PoseTransformStack.rotateXDegrees:(F)Ldev/engine_room/flywheel/lib/transform/Rotate;
        81: checkcast     #178                // class dev/engine_room/flywheel/lib/transform/PoseTransformStack
        84: fload_3
        85: fneg
        86: ldc           #176                // float 90.0f
        88: fsub
        89: invokevirtual #182                // Method dev/engine_room/flywheel/lib/transform/PoseTransformStack.rotateYDegrees:(F)Ldev/engine_room/flywheel/lib/transform/Rotate;
        92: checkcast     #178                // class dev/engine_room/flywheel/lib/transform/PoseTransformStack
        95: aload_1
        96: getfield      #199                // Field com/simibubi/create/content/trains/entity/CarriageBogey.yaw:Lnet/createmod/catnip/animation/LerpedFloat;
        99: fload         5
       101: invokevirtual #204                // Method net/createmod/catnip/animation/LerpedFloat.getValue:(F)F
       104: invokevirtual #182                // Method dev/engine_room/flywheel/lib/transform/PoseTransformStack.rotateYDegrees:(F)Ldev/engine_room/flywheel/lib/transform/Rotate;
       107: checkcast     #178                // class dev/engine_room/flywheel/lib/transform/PoseTransformStack
       110: aload_1
       111: getfield      #207                // Field com/simibubi/create/content/trains/entity/CarriageBogey.pitch:Lnet/createmod/catnip/animation/LerpedFloat;
       114: fload         5
       116: invokevirtual #204                // Method net/createmod/catnip/animation/LerpedFloat.getValue:(F)F
       119: invokevirtual #185                // Method dev/engine_room/flywheel/lib/transform/PoseTransformStack.rotateXDegrees:(F)Ldev/engine_room/flywheel/lib/transform/Rotate;
       122: checkcast     #178                // class dev/engine_room/flywheel/lib/transform/PoseTransformStack
       125: fconst_0
       126: ldc           #208                // float 0.5f
       128: fconst_0
       129: invokevirtual #195                // Method dev/engine_room/flywheel/lib/transform/PoseTransformStack.translate:(FFF)Ldev/engine_room/flywheel/lib/transform/PoseTransformStack;
       132: iload         6
       134: ifeq          142
       137: ldc           #186                // float 180.0f
       139: goto          143
       142: fconst_0
       143: invokevirtual #211                // Method dev/engine_room/flywheel/lib/transform/PoseTransformStack.rotateZDegrees:(F)Ldev/engine_room/flywheel/lib/transform/Rotate;
       146: checkcast     #178                // class dev/engine_room/flywheel/lib/transform/PoseTransformStack
       149: iload         6
       151: iload         7
       153: if_icmpeq     160
       156: fconst_2
       157: goto          161
       160: fconst_0
       161: invokevirtual #215                // Method dev/engine_room/flywheel/lib/transform/PoseTransformStack.translateY:(F)Ldev/engine_room/flywheel/lib/transform/Translate;
       164: pop
       165: return

  public static int getBogeyLightCoords(com.simibubi.create.content.trains.entity.CarriageContraptionEntity, com.simibubi.create.content.trains.entity.CarriageBogey, float);
    Code:
         0: aload_1
         1: invokevirtual #223                // Method com/simibubi/create/content/trains/entity/CarriageBogey.getAnchorPosition:()Lnet/minecraft/world/phys/Vec3;
         4: astore_3
         5: aload_3
         6: ifnonnull     17
         9: aload_0
        10: fload_2
        11: invokevirtual #226                // Method com/simibubi/create/content/trains/entity/CarriageContraptionEntity.getLightProbePosition:(F)Lnet/minecraft/world/phys/Vec3;
        14: goto          18
        17: aload_3
        18: invokestatic  #236                // Method net/minecraft/core/BlockPos.containing:(Lnet/minecraft/core/Position;)Lnet/minecraft/core/BlockPos;
        21: astore        4
        23: aload_0
        24: invokevirtual #240                // Method com/simibubi/create/content/trains/entity/CarriageContraptionEntity.level:()Lnet/minecraft/world/level/Level;
        27: getstatic     #246                // Field net/minecraft/world/level/LightLayer.BLOCK:Lnet/minecraft/world/level/LightLayer;
        30: aload         4
        32: invokevirtual #252                // Method net/minecraft/world/level/Level.getBrightness:(Lnet/minecraft/world/level/LightLayer;Lnet/minecraft/core/BlockPos;)I
        35: aload_0
        36: invokevirtual #240                // Method com/simibubi/create/content/trains/entity/CarriageContraptionEntity.level:()Lnet/minecraft/world/level/Level;
        39: getstatic     #255                // Field net/minecraft/world/level/LightLayer.SKY:Lnet/minecraft/world/level/LightLayer;
        42: aload         4
        44: invokevirtual #252                // Method net/minecraft/world/level/Level.getBrightness:(Lnet/minecraft/world/level/LightLayer;Lnet/minecraft/core/BlockPos;)I
        47: invokestatic  #261                // Method net/minecraft/client/renderer/LightTexture.pack:(II)I
        50: ireturn

  public void render(com.simibubi.create.content.contraptions.AbstractContraptionEntity, float, float, com.mojang.blaze3d.vertex.PoseStack, net.minecraft.client.renderer.MultiBufferSource, int);
    Code:
         0: aload_0
         1: aload_1
         2: checkcast     #33                 // class com/simibubi/create/content/trains/entity/CarriageContraptionEntity
         5: fload_2
         6: fload_3
         7: aload         4
         9: aload         5
        11: iload         6
        13: invokevirtual #266                // Method render:(Lcom/simibubi/create/content/trains/entity/CarriageContraptionEntity;FFLcom/mojang/blaze3d/vertex/PoseStack;Lnet/minecraft/client/renderer/MultiBufferSource;I)V
        16: return

  public boolean shouldRender(com.simibubi.create.content.contraptions.AbstractContraptionEntity, net.minecraft.client.renderer.culling.Frustum, double, double, double);
    Code:
         0: aload_0
         1: aload_1
         2: checkcast     #33                 // class com/simibubi/create/content/trains/entity/CarriageContraptionEntity
         5: aload_2
         6: dload_3
         7: dload         5
         9: dload         7
        11: invokevirtual #268                // Method shouldRender:(Lcom/simibubi/create/content/trains/entity/CarriageContraptionEntity;Lnet/minecraft/client/renderer/culling/Frustum;DDD)Z
        14: ireturn

  public void render(net.minecraft.world.entity.Entity, float, float, com.mojang.blaze3d.vertex.PoseStack, net.minecraft.client.renderer.MultiBufferSource, int);
    Code:
         0: aload_0
         1: aload_1
         2: checkcast     #33                 // class com/simibubi/create/content/trains/entity/CarriageContraptionEntity
         5: fload_2
         6: fload_3
         7: aload         4
         9: aload         5
        11: iload         6
        13: invokevirtual #266                // Method render:(Lcom/simibubi/create/content/trains/entity/CarriageContraptionEntity;FFLcom/mojang/blaze3d/vertex/PoseStack;Lnet/minecraft/client/renderer/MultiBufferSource;I)V
        16: return

  public boolean shouldRender(net.minecraft.world.entity.Entity, net.minecraft.client.renderer.culling.Frustum, double, double, double);
    Code:
         0: aload_0
         1: aload_1
         2: checkcast     #33                 // class com/simibubi/create/content/trains/entity/CarriageContraptionEntity
         5: aload_2
         6: dload_3
         7: dload         5
         9: dload         7
        11: invokevirtual #268                // Method shouldRender:(Lcom/simibubi/create/content/trains/entity/CarriageContraptionEntity;Lnet/minecraft/client/renderer/culling/Frustum;DDD)Z
        14: ireturn

  private static void lambda$render$1(com.simibubi.create.content.trains.entity.CarriageContraptionEntity, int, com.mojang.blaze3d.vertex.PoseStack, float, float, float, net.minecraft.client.renderer.MultiBufferSource, int, net.minecraft.world.phys.Vec3, com.simibubi.create.content.trains.entity.Carriage, com.simibubi.create.content.trains.entity.CarriageBogey);
    Code:
         0: aload         10
         2: ifnonnull     6
         5: return
         6: aload         10
         8: getfield      #189                // Field com/simibubi/create/content/trains/entity/CarriageBogey.isLeading:Z
        11: ifeq          20
        14: getstatic     #273                // Field net/minecraft/core/BlockPos.ZERO:Lnet/minecraft/core/BlockPos;
        17: goto          34
        20: getstatic     #273                // Field net/minecraft/core/BlockPos.ZERO:Lnet/minecraft/core/BlockPos;
        23: aload_0
        24: invokevirtual #277                // Method com/simibubi/create/content/trains/entity/CarriageContraptionEntity.getInitialOrientation:()Lnet/minecraft/core/Direction;
        27: invokevirtual #282                // Method net/minecraft/core/Direction.getCounterClockWise:()Lnet/minecraft/core/Direction;
        30: iload_1
        31: invokevirtual #286                // Method net/minecraft/core/BlockPos.relative:(Lnet/minecraft/core/Direction;I)Lnet/minecraft/core/BlockPos;
        34: astore        11
        36: aload_0
        37: invokevirtual #240                // Method com/simibubi/create/content/trains/entity/CarriageContraptionEntity.level:()Lnet/minecraft/world/level/Level;
        40: invokestatic  #292                // InterfaceMethod dev/engine_room/flywheel/api/visualization/VisualizationManager.supportsVisualization:(Lnet/minecraft/world/level/LevelAccessor;)Z
        43: ifne          126
        46: aload_0
        47: invokevirtual #296                // Method com/simibubi/create/content/trains/entity/CarriageContraptionEntity.getContraption:()Lcom/simibubi/create/content/contraptions/Contraption;
        50: aload         11
        52: invokevirtual #302                // Method com/simibubi/create/content/contraptions/Contraption.isHiddenInPortal:(Lnet/minecraft/core/BlockPos;)Z
        55: ifne          126
        58: aload_2
        59: invokevirtual #306                // Method com/mojang/blaze3d/vertex/PoseStack.pushPose:()V
        62: aload_2
        63: aload         10
        65: iload_1
        66: fload_3
        67: fload         4
        69: fload         5
        71: invokestatic  #308                // Method translateBogey:(Lcom/mojang/blaze3d/vertex/PoseStack;Lcom/simibubi/create/content/trains/entity/CarriageBogey;IFFF)V
        74: aload_0
        75: aload         10
        77: fload         5
        79: invokestatic  #310                // Method getBogeyLightCoords:(Lcom/simibubi/create/content/trains/entity/CarriageContraptionEntity;Lcom/simibubi/create/content/trains/entity/CarriageBogey;F)I
        82: istore        12
        84: aload         10
        86: invokevirtual #314                // Method com/simibubi/create/content/trains/entity/CarriageBogey.getStyle:()Lcom/simibubi/create/content/trains/bogey/BogeyStyle;
        89: aload         10
        91: invokevirtual #318                // Method com/simibubi/create/content/trains/entity/CarriageBogey.getSize:()Lcom/simibubi/create/content/trains/bogey/BogeySizes$BogeySize;
        94: fload         5
        96: aload_2
        97: aload         6
        99: iload         12
       101: iload         7
       103: aload         10
       105: getfield      #321                // Field com/simibubi/create/content/trains/entity/CarriageBogey.wheelAngle:Lnet/createmod/catnip/animation/LerpedFloat;
       108: fload         5
       110: invokevirtual #204                // Method net/createmod/catnip/animation/LerpedFloat.getValue:(F)F
       113: aload         10
       115: getfield      #325                // Field com/simibubi/create/content/trains/entity/CarriageBogey.bogeyData:Lnet/minecraft/nbt/CompoundTag;
       118: iconst_1
       119: invokevirtual #330                // Method com/simibubi/create/content/trains/bogey/BogeyStyle.render:(Lcom/simibubi/create/content/trains/bogey/BogeySizes$BogeySize;FLcom/mojang/blaze3d/vertex/PoseStack;Lnet/minecraft/client/renderer/MultiBufferSource;IIFLnet/minecraft/nbt/CompoundTag;Z)V
       122: aload_2
       123: invokevirtual #333                // Method com/mojang/blaze3d/vertex/PoseStack.popPose:()V
       126: aload         10
       128: aload         8
       130: fload         4
       132: fload_3
       133: iload_1
       134: fload         5
       136: aload         10
       138: getfield      #189                // Field com/simibubi/create/content/trains/entity/CarriageBogey.isLeading:Z
       141: invokevirtual #337                // Method com/simibubi/create/content/trains/entity/CarriageBogey.updateCouplingAnchor:(Lnet/minecraft/world/phys/Vec3;FFIFZ)V
       144: aload         9
       146: invokevirtual #340                // Method com/simibubi/create/content/trains/entity/Carriage.isOnTwoBogeys:()Z
       149: ifne          178
       152: aload         10
       154: aload         8
       156: fload         4
       158: fload_3
       159: iload_1
       160: fload         5
       162: aload         10
       164: getfield      #189                // Field com/simibubi/create/content/trains/entity/CarriageBogey.isLeading:Z
       167: ifne          174
       170: iconst_1
       171: goto          175
       174: iconst_0
       175: invokevirtual #337                // Method com/simibubi/create/content/trains/entity/CarriageBogey.updateCouplingAnchor:(Lnet/minecraft/world/phys/Vec3;FFIFZ)V
       178: return

  private static net.minecraft.world.phys.Vec3 lambda$shouldRender$0(net.minecraft.world.phys.Vec3);
    Code:
         0: aconst_null
         1: areturn
}
