Compiled from "ContraptionVisual.java"
public class com.simibubi.create.content.contraptions.render.ContraptionVisual<E extends com.simibubi.create.content.contraptions.AbstractContraptionEntity> extends dev.engine_room.flywheel.lib.visual.AbstractEntityVisual<E> implements dev.engine_room.flywheel.api.visual.DynamicVisual, dev.engine_room.flywheel.api.visual.TickableVisual, dev.engine_room.flywheel.api.visual.ShaderLightVisual {
  protected static final int DEFAULT_LIGHT_PADDING;

  protected final dev.engine_room.flywheel.api.visualization.VisualEmbedding embedding;

  protected final java.util.List<dev.engine_room.flywheel.api.visual.BlockEntityVisual<?>> children;

  protected final java.util.List<com.simibubi.create.content.contraptions.render.ActorVisual> actors;

  protected final dev.engine_room.flywheel.lib.task.PlanMap<dev.engine_room.flywheel.api.visual.DynamicVisual, dev.engine_room.flywheel.api.visual.DynamicVisual$Context> dynamicVisuals;

  protected final dev.engine_room.flywheel.lib.task.PlanMap<dev.engine_room.flywheel.api.visual.TickableVisual, dev.engine_room.flywheel.api.visual.TickableVisual$Context> tickableVisuals;

  protected dev.engine_room.flywheel.lib.instance.TransformedInstance structure;

  protected dev.engine_room.flywheel.api.visual.SectionTrackedVisual$SectionCollector sectionCollector;

  protected long minSection;

  protected long maxSection;

  protected int lightPaddingBlocks;

  protected int lastStructureVersion;

  protected int lastVersionChildren;

  private final com.mojang.blaze3d.vertex.PoseStack contraptionMatrix;

  public com.simibubi.create.content.contraptions.render.ContraptionVisual(dev.engine_room.flywheel.api.visualization.VisualizationContext, E, float);
    Code:
         0: aload_0
         1: aload_1
         2: aload_2
         3: fload_3
         4: invokespecial #91                 // Method dev/engine_room/flywheel/lib/visual/AbstractEntityVisual."<init>":(Ldev/engine_room/flywheel/api/visualization/VisualizationContext;Lnet/minecraft/world/entity/Entity;F)V
         7: aload_0
         8: new           #93                 // class java/util/ArrayList
        11: dup
        12: invokespecial #96                 // Method java/util/ArrayList."<init>":()V
        15: putfield      #98                 // Field children:Ljava/util/List;
        18: aload_0
        19: new           #93                 // class java/util/ArrayList
        22: dup
        23: invokespecial #96                 // Method java/util/ArrayList."<init>":()V
        26: putfield      #100                // Field actors:Ljava/util/List;
        29: aload_0
        30: new           #102                // class dev/engine_room/flywheel/lib/task/PlanMap
        33: dup
        34: invokespecial #103                // Method dev/engine_room/flywheel/lib/task/PlanMap."<init>":()V
        37: putfield      #105                // Field dynamicVisuals:Ldev/engine_room/flywheel/lib/task/PlanMap;
        40: aload_0
        41: new           #102                // class dev/engine_room/flywheel/lib/task/PlanMap
        44: dup
        45: invokespecial #103                // Method dev/engine_room/flywheel/lib/task/PlanMap."<init>":()V
        48: putfield      #107                // Field tickableVisuals:Ldev/engine_room/flywheel/lib/task/PlanMap;
        51: aload_0
        52: iconst_1
        53: putfield      #109                // Field lightPaddingBlocks:I
        56: aload_0
        57: new           #40                 // class com/mojang/blaze3d/vertex/PoseStack
        60: dup
        61: invokespecial #110                // Method com/mojang/blaze3d/vertex/PoseStack."<init>":()V
        64: putfield      #112                // Field contraptionMatrix:Lcom/mojang/blaze3d/vertex/PoseStack;
        67: aload_0
        68: aload_1
        69: getstatic     #118                // Field net/minecraft/core/Vec3i.ZERO:Lnet/minecraft/core/Vec3i;
        72: invokeinterface #124,  2          // InterfaceMethod dev/engine_room/flywheel/api/visualization/VisualizationContext.createEmbedding:(Lnet/minecraft/core/Vec3i;)Ldev/engine_room/flywheel/api/visualization/VisualEmbedding;
        77: putfield      #126                // Field embedding:Ldev/engine_room/flywheel/api/visualization/VisualEmbedding;
        80: aload_0
        81: fload_3
        82: invokevirtual #130                // Method setEmbeddingMatrices:(F)V
        85: aload_2
        86: invokevirtual #136                // Method com/simibubi/create/content/contraptions/AbstractContraptionEntity.getContraption:()Lcom/simibubi/create/content/contraptions/Contraption;
        89: astore        4
        91: aload         4
        93: ifnonnull     97
        96: return
        97: aload         4
        99: invokevirtual #142                // Method com/simibubi/create/content/contraptions/Contraption.getOrCreateClientContraptionLazy:()Lcom/simibubi/create/content/contraptions/render/ClientContraption;
       102: astore        5
       104: aload_0
       105: aload         5
       107: invokevirtual #146                // Method setupStructure:(Lcom/simibubi/create/content/contraptions/render/ClientContraption;)V
       110: aload_0
       111: aload         4
       113: aload         5
       115: fload_3
       116: invokevirtual #150                // Method setupChildren:(Lcom/simibubi/create/content/contraptions/Contraption;Lcom/simibubi/create/content/contraptions/render/ClientContraption;F)V
       119: return

  private void setupStructure(com.simibubi.create.content.contraptions.render.ClientContraption);
    Code:
         0: aload_1
         1: invokevirtual #168                // Method com/simibubi/create/content/contraptions/render/ClientContraption.getRenderLevel:()Lcom/simibubi/create/foundation/virtualWorld/VirtualRenderWorld;
         4: astore_2
         5: aload_1
         6: invokevirtual #172                // Method com/simibubi/create/content/contraptions/render/ClientContraption.getRenderedBlocks:()Lcom/simibubi/create/content/contraptions/render/ClientContraption$RenderedBlocks;
         9: astore_3
        10: new           #14                 // class com/simibubi/create/content/contraptions/render/ContraptionVisual$1
        13: dup
        14: aload_0
        15: aload_2
        16: aload_3
        17: invokespecial #175                // Method com/simibubi/create/content/contraptions/render/ContraptionVisual$1."<init>":(Lcom/simibubi/create/content/contraptions/render/ContraptionVisual;Lnet/minecraft/world/level/BlockAndTintGetter;Lcom/simibubi/create/content/contraptions/render/ClientContraption$RenderedBlocks;)V
        20: astore        4
        22: new           #177                // class dev/engine_room/flywheel/lib/model/baked/ForgeBlockModelBuilder
        25: dup
        26: aload         4
        28: aload_3
        29: invokevirtual #181                // Method com/simibubi/create/content/contraptions/render/ClientContraption$RenderedBlocks.positions:()Ljava/lang/Iterable;
        32: invokespecial #184                // Method dev/engine_room/flywheel/lib/model/baked/ForgeBlockModelBuilder."<init>":(Lnet/minecraft/world/level/BlockAndTintGetter;Ljava/lang/Iterable;)V
        35: aload_1
        36: dup
        37: invokestatic  #190                // Method java/util/Objects.requireNonNull:(Ljava/lang/Object;)Ljava/lang/Object;
        40: pop
        41: invokedynamic #208,  0            // InvokeDynamic #0:apply:(Lcom/simibubi/create/content/contraptions/render/ClientContraption;)Ljava/util/function/Function;
        46: invokevirtual #212                // Method dev/engine_room/flywheel/lib/model/baked/ForgeBlockModelBuilder.modelDataLookup:(Ljava/util/function/Function;)Ldev/engine_room/flywheel/lib/model/baked/ForgeBlockModelBuilder;
        49: invokedynamic #223,  0            // InvokeDynamic #1:apply:()Ljava/util/function/BiFunction;
        54: invokevirtual #227                // Method dev/engine_room/flywheel/lib/model/baked/ForgeBlockModelBuilder.materialFunc:(Ljava/util/function/BiFunction;)Ldev/engine_room/flywheel/lib/model/baked/ForgeBlockModelBuilder;
        57: invokevirtual #231                // Method dev/engine_room/flywheel/lib/model/baked/ForgeBlockModelBuilder.build:()Ldev/engine_room/flywheel/lib/model/SimpleModel;
        60: astore        5
        62: aload_0
        63: getfield      #126                // Field embedding:Ldev/engine_room/flywheel/api/visualization/VisualEmbedding;
        66: invokeinterface #237,  1          // InterfaceMethod dev/engine_room/flywheel/api/visualization/VisualEmbedding.instancerProvider:()Ldev/engine_room/flywheel/api/instance/InstancerProvider;
        71: getstatic     #243                // Field dev/engine_room/flywheel/lib/instance/InstanceTypes.TRANSFORMED:Ldev/engine_room/flywheel/api/instance/InstanceType;
        74: aload         5
        76: invokeinterface #249,  3          // InterfaceMethod dev/engine_room/flywheel/api/instance/InstancerProvider.instancer:(Ldev/engine_room/flywheel/api/instance/InstanceType;Ldev/engine_room/flywheel/api/model/Model;)Ldev/engine_room/flywheel/api/instance/Instancer;
        81: astore        6
        83: aload_0
        84: getfield      #251                // Field structure:Ldev/engine_room/flywheel/lib/instance/TransformedInstance;
        87: ifnonnull     107
        90: aload_0
        91: aload         6
        93: invokeinterface #257,  1          // InterfaceMethod dev/engine_room/flywheel/api/instance/Instancer.createInstance:()Ldev/engine_room/flywheel/api/instance/Instance;
        98: checkcast     #259                // class dev/engine_room/flywheel/lib/instance/TransformedInstance
       101: putfield      #251                // Field structure:Ldev/engine_room/flywheel/lib/instance/TransformedInstance;
       104: goto          118
       107: aload         6
       109: aload_0
       110: getfield      #251                // Field structure:Ldev/engine_room/flywheel/lib/instance/TransformedInstance;
       113: invokeinterface #269,  2          // InterfaceMethod dev/engine_room/flywheel/api/instance/Instancer.stealInstance:(Ldev/engine_room/flywheel/api/instance/Instance;)V
       118: aload_0
       119: getfield      #251                // Field structure:Ldev/engine_room/flywheel/lib/instance/TransformedInstance;
       122: invokevirtual #272                // Method dev/engine_room/flywheel/lib/instance/TransformedInstance.setChanged:()V
       125: aload_0
       126: aload_1
       127: invokevirtual #276                // Method com/simibubi/create/content/contraptions/render/ClientContraption.structureVersion:()I
       130: putfield      #278                // Field lastStructureVersion:I
       133: return

  private void setupChildren(com.simibubi.create.content.contraptions.Contraption, com.simibubi.create.content.contraptions.render.ClientContraption, float);
    Code:
         0: aload_0
         1: getfield      #98                 // Field children:Ljava/util/List;
         4: invokedynamic #302,  0            // InvokeDynamic #2:accept:()Ljava/util/function/Consumer;
         9: invokeinterface #308,  2          // InterfaceMethod java/util/List.forEach:(Ljava/util/function/Consumer;)V
        14: aload_0
        15: getfield      #98                 // Field children:Ljava/util/List;
        18: invokeinterface #311,  1          // InterfaceMethod java/util/List.clear:()V
        23: aload_0
        24: getfield      #105                // Field dynamicVisuals:Ldev/engine_room/flywheel/lib/task/PlanMap;
        27: invokevirtual #312                // Method dev/engine_room/flywheel/lib/task/PlanMap.clear:()V
        30: aload_0
        31: getfield      #107                // Field tickableVisuals:Ldev/engine_room/flywheel/lib/task/PlanMap;
        34: invokevirtual #312                // Method dev/engine_room/flywheel/lib/task/PlanMap.clear:()V
        37: aload_2
        38: getfield      #315                // Field com/simibubi/create/content/contraptions/render/ClientContraption.renderedBlockEntityView:Ljava/util/List;
        41: invokeinterface #319,  1          // InterfaceMethod java/util/List.iterator:()Ljava/util/Iterator;
        46: astore        4
        48: aload         4
        50: invokeinterface #325,  1          // InterfaceMethod java/util/Iterator.hasNext:()Z
        55: ifeq          80
        58: aload         4
        60: invokeinterface #329,  1          // InterfaceMethod java/util/Iterator.next:()Ljava/lang/Object;
        65: checkcast     #331                // class net/minecraft/world/level/block/entity/BlockEntity
        68: astore        5
        70: aload_0
        71: aload         5
        73: fload_3
        74: invokevirtual #335                // Method setupVisualizer:(Lnet/minecraft/world/level/block/entity/BlockEntity;F)V
        77: goto          48
        80: aload_2
        81: invokevirtual #168                // Method com/simibubi/create/content/contraptions/render/ClientContraption.getRenderLevel:()Lcom/simibubi/create/foundation/virtualWorld/VirtualRenderWorld;
        84: astore        4
        86: aload_0
        87: getfield      #100                // Field actors:Ljava/util/List;
        90: invokedynamic #342,  0            // InvokeDynamic #3:accept:()Ljava/util/function/Consumer;
        95: invokeinterface #308,  2          // InterfaceMethod java/util/List.forEach:(Ljava/util/function/Consumer;)V
       100: aload_0
       101: getfield      #100                // Field actors:Ljava/util/List;
       104: invokeinterface #311,  1          // InterfaceMethod java/util/List.clear:()V
       109: aload_1
       110: invokevirtual #346                // Method com/simibubi/create/content/contraptions/Contraption.getActors:()Ljava/util/List;
       113: invokeinterface #319,  1          // InterfaceMethod java/util/List.iterator:()Ljava/util/Iterator;
       118: astore        5
       120: aload         5
       122: invokeinterface #325,  1          // InterfaceMethod java/util/Iterator.hasNext:()Z
       127: ifeq          153
       130: aload         5
       132: invokeinterface #329,  1          // InterfaceMethod java/util/Iterator.next:()Ljava/lang/Object;
       137: checkcast     #348                // class org/apache/commons/lang3/tuple/MutablePair
       140: astore        6
       142: aload_0
       143: aload         6
       145: aload         4
       147: invokevirtual #352                // Method setupActor:(Lorg/apache/commons/lang3/tuple/MutablePair;Lcom/simibubi/create/foundation/virtualWorld/VirtualRenderWorld;)V
       150: goto          120
       153: aload_0
       154: aload_2
       155: invokevirtual #355                // Method com/simibubi/create/content/contraptions/render/ClientContraption.childrenVersion:()I
       158: putfield      #357                // Field lastVersionChildren:I
       161: return

  protected <T extends net.minecraft.world.level.block.entity.BlockEntity> void setupVisualizer(T, float);
    Code:
         0: aload_1
         1: invokevirtual #367                // Method net/minecraft/world/level/block/entity/BlockEntity.getType:()Lnet/minecraft/world/level/block/entity/BlockEntityType;
         4: invokestatic  #373                // Method dev/engine_room/flywheel/api/visualization/VisualizerRegistry.getVisualizer:(Lnet/minecraft/world/level/block/entity/BlockEntityType;)Ldev/engine_room/flywheel/api/visualization/BlockEntityVisualizer;
         7: astore_3
         8: aload_3
         9: ifnonnull     13
        12: return
        13: aload_3
        14: aload_0
        15: getfield      #126                // Field embedding:Ldev/engine_room/flywheel/api/visualization/VisualEmbedding;
        18: aload_1
        19: fload_2
        20: invokeinterface #379,  4          // InterfaceMethod dev/engine_room/flywheel/api/visualization/BlockEntityVisualizer.createVisual:(Ldev/engine_room/flywheel/api/visualization/VisualizationContext;Lnet/minecraft/world/level/block/entity/BlockEntity;F)Ldev/engine_room/flywheel/api/visual/BlockEntityVisual;
        25: astore        4
        27: aload_0
        28: getfield      #98                 // Field children:Ljava/util/List;
        31: aload         4
        33: invokeinterface #383,  2          // InterfaceMethod java/util/List.add:(Ljava/lang/Object;)Z
        38: pop
        39: aload         4
        41: instanceof    #7                  // class dev/engine_room/flywheel/api/visual/DynamicVisual
        44: ifeq          70
        47: aload         4
        49: checkcast     #7                  // class dev/engine_room/flywheel/api/visual/DynamicVisual
        52: astore        5
        54: aload_0
        55: getfield      #105                // Field dynamicVisuals:Ldev/engine_room/flywheel/lib/task/PlanMap;
        58: aload         5
        60: aload         5
        62: invokeinterface #387,  1          // InterfaceMethod dev/engine_room/flywheel/api/visual/DynamicVisual.planFrame:()Ldev/engine_room/flywheel/api/task/Plan;
        67: invokevirtual #390                // Method dev/engine_room/flywheel/lib/task/PlanMap.add:(Ljava/lang/Object;Ldev/engine_room/flywheel/api/task/Plan;)V
        70: aload         4
        72: instanceof    #9                  // class dev/engine_room/flywheel/api/visual/TickableVisual
        75: ifeq          101
        78: aload         4
        80: checkcast     #9                  // class dev/engine_room/flywheel/api/visual/TickableVisual
        83: astore        5
        85: aload_0
        86: getfield      #107                // Field tickableVisuals:Ldev/engine_room/flywheel/lib/task/PlanMap;
        89: aload         5
        91: aload         5
        93: invokeinterface #395,  1          // InterfaceMethod dev/engine_room/flywheel/api/visual/TickableVisual.planTick:()Ldev/engine_room/flywheel/api/task/Plan;
        98: invokevirtual #390                // Method dev/engine_room/flywheel/lib/task/PlanMap.add:(Ljava/lang/Object;Ldev/engine_room/flywheel/api/task/Plan;)V
       101: return

  protected void setupActor(org.apache.commons.lang3.tuple.MutablePair<net.minecraft.world.level.levelgen.structure.templatesystem.StructureTemplate$StructureBlockInfo, com.simibubi.create.content.contraptions.behaviour.MovementContext>, com.simibubi.create.foundation.virtualWorld.VirtualRenderWorld);
    Code:
         0: aload_1
         1: invokevirtual #411                // Method org/apache/commons/lang3/tuple/MutablePair.getRight:()Ljava/lang/Object;
         4: checkcast     #413                // class com/simibubi/create/content/contraptions/behaviour/MovementContext
         7: astore_3
         8: aload_3
         9: ifnonnull     13
        12: return
        13: aload_3
        14: getfield      #417                // Field com/simibubi/create/content/contraptions/behaviour/MovementContext.world:Lnet/minecraft/world/level/Level;
        17: ifnonnull     28
        20: aload_3
        21: aload_0
        22: getfield      #420                // Field level:Lnet/minecraft/world/level/Level;
        25: putfield      #417                // Field com/simibubi/create/content/contraptions/behaviour/MovementContext.world:Lnet/minecraft/world/level/Level;
        28: aload_1
        29: invokevirtual #423                // Method org/apache/commons/lang3/tuple/MutablePair.getLeft:()Ljava/lang/Object;
        32: checkcast     #21                 // class net/minecraft/world/level/levelgen/structure/templatesystem/StructureTemplate$StructureBlockInfo
        35: astore        4
        37: getstatic     #429                // Field com/simibubi/create/api/behaviour/movement/MovementBehaviour.REGISTRY:Lcom/simibubi/create/api/registry/SimpleRegistry;
        40: aload         4
        42: invokevirtual #433                // Method net/minecraft/world/level/levelgen/structure/templatesystem/StructureTemplate$StructureBlockInfo.state:()Lnet/minecraft/world/level/block/state/BlockState;
        45: invokeinterface #439,  2          // InterfaceMethod com/simibubi/create/api/registry/SimpleRegistry.get:(Lnet/minecraft/world/level/block/state/StateHolder;)Ljava/lang/Object;
        50: checkcast     #425                // class com/simibubi/create/api/behaviour/movement/MovementBehaviour
        53: astore        5
        55: aload         5
        57: ifnonnull     61
        60: return
        61: aload         5
        63: aload_0
        64: getfield      #126                // Field embedding:Ldev/engine_room/flywheel/api/visualization/VisualEmbedding;
        67: aload_2
        68: aload_3
        69: invokeinterface #442,  4          // InterfaceMethod com/simibubi/create/api/behaviour/movement/MovementBehaviour.createVisual:(Ldev/engine_room/flywheel/api/visualization/VisualizationContext;Lcom/simibubi/create/foundation/virtualWorld/VirtualRenderWorld;Lcom/simibubi/create/content/contraptions/behaviour/MovementContext;)Lcom/simibubi/create/content/contraptions/render/ActorVisual;
        74: astore        6
        76: aload         6
        78: ifnonnull     82
        81: return
        82: aload_0
        83: getfield      #100                // Field actors:Ljava/util/List;
        86: aload         6
        88: invokeinterface #383,  2          // InterfaceMethod java/util/List.add:(Ljava/lang/Object;)Z
        93: pop
        94: return

  public dev.engine_room.flywheel.api.task.Plan<dev.engine_room.flywheel.api.visual.TickableVisual$Context> planTick();
    Code:
         0: iconst_2
         1: anewarray     #452                // class dev/engine_room/flywheel/api/task/Plan
         4: dup
         5: iconst_0
         6: aload_0
         7: invokedynamic #461,  0            // InvokeDynamic #4:get:(Lcom/simibubi/create/content/contraptions/render/ContraptionVisual;)Ldev/engine_room/flywheel/lib/task/functional/SupplierWithContext$Ignored;
        12: invokedynamic #468,  0            // InvokeDynamic #5:accept:()Ldev/engine_room/flywheel/lib/task/functional/ConsumerWithContext$Ignored;
        17: invokestatic  #474                // Method dev/engine_room/flywheel/lib/task/ForEachPlan.of:(Ldev/engine_room/flywheel/lib/task/functional/SupplierWithContext$Ignored;Ldev/engine_room/flywheel/lib/task/functional/ConsumerWithContext$Ignored;)Ldev/engine_room/flywheel/lib/task/ForEachPlan;
        20: aastore
        21: dup
        22: iconst_1
        23: aload_0
        24: getfield      #107                // Field tickableVisuals:Ldev/engine_room/flywheel/lib/task/PlanMap;
        27: aastore
        28: invokestatic  #479                // Method dev/engine_room/flywheel/lib/task/NestedPlan.of:([Ldev/engine_room/flywheel/api/task/Plan;)Ldev/engine_room/flywheel/lib/task/NestedPlan;
        31: areturn

  public dev.engine_room.flywheel.api.task.Plan<dev.engine_room.flywheel.api.visual.DynamicVisual$Context> planFrame();
    Code:
         0: aload_0
         1: invokedynamic #490,  0            // InvokeDynamic #6:run:(Lcom/simibubi/create/content/contraptions/render/ContraptionVisual;)Ldev/engine_room/flywheel/lib/task/functional/RunnableWithContext;
         6: invokestatic  #495                // Method dev/engine_room/flywheel/lib/task/RunnablePlan.of:(Ldev/engine_room/flywheel/lib/task/functional/RunnableWithContext;)Ldev/engine_room/flywheel/lib/task/RunnablePlan;
         9: iconst_2
        10: anewarray     #452                // class dev/engine_room/flywheel/api/task/Plan
        13: dup
        14: iconst_0
        15: aload_0
        16: invokedynamic #500,  0            // InvokeDynamic #7:get:(Lcom/simibubi/create/content/contraptions/render/ContraptionVisual;)Ldev/engine_room/flywheel/lib/task/functional/SupplierWithContext$Ignored;
        21: invokedynamic #504,  0            // InvokeDynamic #8:accept:()Ldev/engine_room/flywheel/lib/task/functional/ConsumerWithContext$Ignored;
        26: invokestatic  #474                // Method dev/engine_room/flywheel/lib/task/ForEachPlan.of:(Ldev/engine_room/flywheel/lib/task/functional/SupplierWithContext$Ignored;Ldev/engine_room/flywheel/lib/task/functional/ConsumerWithContext$Ignored;)Ldev/engine_room/flywheel/lib/task/ForEachPlan;
        29: aastore
        30: dup
        31: iconst_1
        32: aload_0
        33: getfield      #105                // Field dynamicVisuals:Ldev/engine_room/flywheel/lib/task/PlanMap;
        36: aastore
        37: invokestatic  #479                // Method dev/engine_room/flywheel/lib/task/NestedPlan.of:([Ldev/engine_room/flywheel/api/task/Plan;)Ldev/engine_room/flywheel/lib/task/NestedPlan;
        40: invokevirtual #508                // Method dev/engine_room/flywheel/lib/task/RunnablePlan.then:(Ldev/engine_room/flywheel/api/task/Plan;)Ldev/engine_room/flywheel/api/task/Plan;
        43: areturn

  protected void beginFrame(dev.engine_room.flywheel.api.visual.DynamicVisual$Context);
    Code:
         0: aload_1
         1: invokeinterface #511,  1          // InterfaceMethod dev/engine_room/flywheel/api/visual/DynamicVisual$Context.partialTick:()F
         6: fstore_2
         7: aload_0
         8: fload_2
         9: invokevirtual #130                // Method setEmbeddingMatrices:(F)V
        12: aload_0
        13: invokevirtual #514                // Method checkAndUpdateLightSections:()V
        16: aload_0
        17: getfield      #517                // Field entity:Lnet/minecraft/world/entity/Entity;
        20: checkcast     #132                // class com/simibubi/create/content/contraptions/AbstractContraptionEntity
        23: invokevirtual #136                // Method com/simibubi/create/content/contraptions/AbstractContraptionEntity.getContraption:()Lcom/simibubi/create/content/contraptions/Contraption;
        26: astore_3
        27: aload_3
        28: invokevirtual #142                // Method com/simibubi/create/content/contraptions/Contraption.getOrCreateClientContraptionLazy:()Lcom/simibubi/create/content/contraptions/render/ClientContraption;
        31: astore        4
        33: aload_0
        34: getfield      #278                // Field lastStructureVersion:I
        37: aload         4
        39: invokevirtual #276                // Method com/simibubi/create/content/contraptions/render/ClientContraption.structureVersion:()I
        42: if_icmpeq     51
        45: aload_0
        46: aload         4
        48: invokevirtual #146                // Method setupStructure:(Lcom/simibubi/create/content/contraptions/render/ClientContraption;)V
        51: aload_0
        52: getfield      #357                // Field lastVersionChildren:I
        55: aload         4
        57: invokevirtual #355                // Method com/simibubi/create/content/contraptions/render/ClientContraption.childrenVersion:()I
        60: if_icmpeq     71
        63: aload_0
        64: aload_3
        65: aload         4
        67: fload_2
        68: invokevirtual #150                // Method setupChildren:(Lcom/simibubi/create/content/contraptions/Contraption;Lcom/simibubi/create/content/contraptions/render/ClientContraption;F)V
        71: return

  private void setEmbeddingMatrices(float);
    Code:
         0: aload_0
         1: invokevirtual #522                // Method renderOrigin:()Lnet/minecraft/core/Vec3i;
         4: astore_2
         5: aload_0
         6: getfield      #517                // Field entity:Lnet/minecraft/world/entity/Entity;
         9: checkcast     #132                // class com/simibubi/create/content/contraptions/AbstractContraptionEntity
        12: invokevirtual #525                // Method com/simibubi/create/content/contraptions/AbstractContraptionEntity.isPrevPosInvalid:()Z
        15: ifeq          74
        18: aload_0
        19: getfield      #517                // Field entity:Lnet/minecraft/world/entity/Entity;
        22: checkcast     #132                // class com/simibubi/create/content/contraptions/AbstractContraptionEntity
        25: invokevirtual #529                // Method com/simibubi/create/content/contraptions/AbstractContraptionEntity.getX:()D
        28: aload_2
        29: invokevirtual #531                // Method net/minecraft/core/Vec3i.getX:()I
        32: i2d
        33: dsub
        34: dstore_3
        35: aload_0
        36: getfield      #517                // Field entity:Lnet/minecraft/world/entity/Entity;
        39: checkcast     #132                // class com/simibubi/create/content/contraptions/AbstractContraptionEntity
        42: invokevirtual #534                // Method com/simibubi/create/content/contraptions/AbstractContraptionEntity.getY:()D
        45: aload_2
        46: invokevirtual #536                // Method net/minecraft/core/Vec3i.getY:()I
        49: i2d
        50: dsub
        51: dstore        5
        53: aload_0
        54: getfield      #517                // Field entity:Lnet/minecraft/world/entity/Entity;
        57: checkcast     #132                // class com/simibubi/create/content/contraptions/AbstractContraptionEntity
        60: invokevirtual #539                // Method com/simibubi/create/content/contraptions/AbstractContraptionEntity.getZ:()D
        63: aload_2
        64: invokevirtual #541                // Method net/minecraft/core/Vec3i.getZ:()I
        67: i2d
        68: dsub
        69: dstore        7
        71: goto          172
        74: fload_1
        75: f2d
        76: aload_0
        77: getfield      #517                // Field entity:Lnet/minecraft/world/entity/Entity;
        80: checkcast     #132                // class com/simibubi/create/content/contraptions/AbstractContraptionEntity
        83: getfield      #545                // Field com/simibubi/create/content/contraptions/AbstractContraptionEntity.xo:D
        86: aload_0
        87: getfield      #517                // Field entity:Lnet/minecraft/world/entity/Entity;
        90: checkcast     #132                // class com/simibubi/create/content/contraptions/AbstractContraptionEntity
        93: invokevirtual #529                // Method com/simibubi/create/content/contraptions/AbstractContraptionEntity.getX:()D
        96: invokestatic  #551                // Method net/minecraft/util/Mth.lerp:(DDD)D
        99: aload_2
       100: invokevirtual #531                // Method net/minecraft/core/Vec3i.getX:()I
       103: i2d
       104: dsub
       105: dstore_3
       106: fload_1
       107: f2d
       108: aload_0
       109: getfield      #517                // Field entity:Lnet/minecraft/world/entity/Entity;
       112: checkcast     #132                // class com/simibubi/create/content/contraptions/AbstractContraptionEntity
       115: getfield      #554                // Field com/simibubi/create/content/contraptions/AbstractContraptionEntity.yo:D
       118: aload_0
       119: getfield      #517                // Field entity:Lnet/minecraft/world/entity/Entity;
       122: checkcast     #132                // class com/simibubi/create/content/contraptions/AbstractContraptionEntity
       125: invokevirtual #534                // Method com/simibubi/create/content/contraptions/AbstractContraptionEntity.getY:()D
       128: invokestatic  #551                // Method net/minecraft/util/Mth.lerp:(DDD)D
       131: aload_2
       132: invokevirtual #536                // Method net/minecraft/core/Vec3i.getY:()I
       135: i2d
       136: dsub
       137: dstore        5
       139: fload_1
       140: f2d
       141: aload_0
       142: getfield      #517                // Field entity:Lnet/minecraft/world/entity/Entity;
       145: checkcast     #132                // class com/simibubi/create/content/contraptions/AbstractContraptionEntity
       148: getfield      #557                // Field com/simibubi/create/content/contraptions/AbstractContraptionEntity.zo:D
       151: aload_0
       152: getfield      #517                // Field entity:Lnet/minecraft/world/entity/Entity;
       155: checkcast     #132                // class com/simibubi/create/content/contraptions/AbstractContraptionEntity
       158: invokevirtual #539                // Method com/simibubi/create/content/contraptions/AbstractContraptionEntity.getZ:()D
       161: invokestatic  #551                // Method net/minecraft/util/Mth.lerp:(DDD)D
       164: aload_2
       165: invokevirtual #541                // Method net/minecraft/core/Vec3i.getZ:()I
       168: i2d
       169: dsub
       170: dstore        7
       172: aload_0
       173: getfield      #112                // Field contraptionMatrix:Lcom/mojang/blaze3d/vertex/PoseStack;
       176: invokevirtual #560                // Method com/mojang/blaze3d/vertex/PoseStack.setIdentity:()V
       179: aload_0
       180: getfield      #112                // Field contraptionMatrix:Lcom/mojang/blaze3d/vertex/PoseStack;
       183: dload_3
       184: dload         5
       186: dload         7
       188: invokevirtual #564                // Method com/mojang/blaze3d/vertex/PoseStack.translate:(DDD)V
       191: aload_0
       192: getfield      #517                // Field entity:Lnet/minecraft/world/entity/Entity;
       195: checkcast     #132                // class com/simibubi/create/content/contraptions/AbstractContraptionEntity
       198: aload_0
       199: getfield      #112                // Field contraptionMatrix:Lcom/mojang/blaze3d/vertex/PoseStack;
       202: fload_1
       203: invokevirtual #568                // Method com/simibubi/create/content/contraptions/AbstractContraptionEntity.applyLocalTransforms:(Lcom/mojang/blaze3d/vertex/PoseStack;F)V
       206: aload_0
       207: getfield      #126                // Field embedding:Ldev/engine_room/flywheel/api/visualization/VisualEmbedding;
       210: aload_0
       211: getfield      #112                // Field contraptionMatrix:Lcom/mojang/blaze3d/vertex/PoseStack;
       214: invokevirtual #572                // Method com/mojang/blaze3d/vertex/PoseStack.last:()Lcom/mojang/blaze3d/vertex/PoseStack$Pose;
       217: invokevirtual #576                // Method com/mojang/blaze3d/vertex/PoseStack$Pose.pose:()Lorg/joml/Matrix4f;
       220: aload_0
       221: getfield      #112                // Field contraptionMatrix:Lcom/mojang/blaze3d/vertex/PoseStack;
       224: invokevirtual #572                // Method com/mojang/blaze3d/vertex/PoseStack.last:()Lcom/mojang/blaze3d/vertex/PoseStack$Pose;
       227: invokevirtual #580                // Method com/mojang/blaze3d/vertex/PoseStack$Pose.normal:()Lorg/joml/Matrix3f;
       230: invokeinterface #584,  3          // InterfaceMethod dev/engine_room/flywheel/api/visualization/VisualEmbedding.transforms:(Lorg/joml/Matrix4fc;Lorg/joml/Matrix3fc;)V
       235: return

  public void setSectionCollector(dev.engine_room.flywheel.api.visual.SectionTrackedVisual$SectionCollector);
    Code:
         0: aload_0
         1: aload_1
         2: putfield      #592                // Field sectionCollector:Ldev/engine_room/flywheel/api/visual/SectionTrackedVisual$SectionCollector;
         5: aload_0
         6: invokevirtual #514                // Method checkAndUpdateLightSections:()V
         9: return

  private void checkAndUpdateLightSections();
    Code:
         0: aload_0
         1: getfield      #517                // Field entity:Lnet/minecraft/world/entity/Entity;
         4: checkcast     #132                // class com/simibubi/create/content/contraptions/AbstractContraptionEntity
         7: invokevirtual #597                // Method com/simibubi/create/content/contraptions/AbstractContraptionEntity.getBoundingBox:()Lnet/minecraft/world/phys/AABB;
        10: astore_1
        11: aload_1
        12: getfield      #602                // Field net/minecraft/world/phys/AABB.minX:D
        15: invokestatic  #606                // Method net/minecraft/util/Mth.floor:(D)I
        18: aload_0
        19: getfield      #109                // Field lightPaddingBlocks:I
        22: isub
        23: invokestatic  #612                // Method net/minecraft/core/SectionPos.blockToSectionCoord:(I)I
        26: istore_2
        27: aload_1
        28: getfield      #615                // Field net/minecraft/world/phys/AABB.minY:D
        31: invokestatic  #606                // Method net/minecraft/util/Mth.floor:(D)I
        34: aload_0
        35: getfield      #109                // Field lightPaddingBlocks:I
        38: isub
        39: invokestatic  #612                // Method net/minecraft/core/SectionPos.blockToSectionCoord:(I)I
        42: istore_3
        43: aload_1
        44: getfield      #618                // Field net/minecraft/world/phys/AABB.minZ:D
        47: invokestatic  #606                // Method net/minecraft/util/Mth.floor:(D)I
        50: aload_0
        51: getfield      #109                // Field lightPaddingBlocks:I
        54: isub
        55: invokestatic  #612                // Method net/minecraft/core/SectionPos.blockToSectionCoord:(I)I
        58: istore        4
        60: aload_1
        61: getfield      #621                // Field net/minecraft/world/phys/AABB.maxX:D
        64: invokestatic  #624                // Method net/minecraft/util/Mth.ceil:(D)I
        67: aload_0
        68: getfield      #109                // Field lightPaddingBlocks:I
        71: iadd
        72: invokestatic  #612                // Method net/minecraft/core/SectionPos.blockToSectionCoord:(I)I
        75: istore        5
        77: aload_1
        78: getfield      #627                // Field net/minecraft/world/phys/AABB.maxY:D
        81: invokestatic  #624                // Method net/minecraft/util/Mth.ceil:(D)I
        84: aload_0
        85: getfield      #109                // Field lightPaddingBlocks:I
        88: iadd
        89: invokestatic  #612                // Method net/minecraft/core/SectionPos.blockToSectionCoord:(I)I
        92: istore        6
        94: aload_1
        95: getfield      #630                // Field net/minecraft/world/phys/AABB.maxZ:D
        98: invokestatic  #624                // Method net/minecraft/util/Mth.ceil:(D)I
       101: aload_0
       102: getfield      #109                // Field lightPaddingBlocks:I
       105: iadd
       106: invokestatic  #612                // Method net/minecraft/core/SectionPos.blockToSectionCoord:(I)I
       109: istore        7
       111: aload_0
       112: getfield      #632                // Field minSection:J
       115: iload_2
       116: iload_3
       117: iload         4
       119: invokestatic  #636                // Method net/minecraft/core/SectionPos.asLong:(III)J
       122: lcmp
       123: ifne          144
       126: aload_0
       127: getfield      #638                // Field maxSection:J
       130: iload         5
       132: iload         6
       134: iload         7
       136: invokestatic  #636                // Method net/minecraft/core/SectionPos.asLong:(III)J
       139: lcmp
       140: ifne          144
       143: return
       144: aload_0
       145: iload_2
       146: iload_3
       147: iload         4
       149: invokestatic  #636                // Method net/minecraft/core/SectionPos.asLong:(III)J
       152: putfield      #632                // Field minSection:J
       155: aload_0
       156: iload         5
       158: iload         6
       160: iload         7
       162: invokestatic  #636                // Method net/minecraft/core/SectionPos.asLong:(III)J
       165: putfield      #638                // Field maxSection:J
       168: new           #640                // class it/unimi/dsi/fastutil/longs/LongArraySet
       171: dup
       172: invokespecial #641                // Method it/unimi/dsi/fastutil/longs/LongArraySet."<init>":()V
       175: astore        8
       177: iload_2
       178: istore        9
       180: iload         9
       182: iload         5
       184: if_icmpgt     243
       187: iload_3
       188: istore        10
       190: iload         10
       192: iload         6
       194: if_icmpgt     237
       197: iload         4
       199: istore        11
       201: iload         11
       203: iload         7
       205: if_icmpgt     231
       208: aload         8
       210: iload         9
       212: iload         10
       214: iload         11
       216: invokestatic  #636                // Method net/minecraft/core/SectionPos.asLong:(III)J
       219: invokeinterface #646,  3          // InterfaceMethod it/unimi/dsi/fastutil/longs/LongSet.add:(J)Z
       224: pop
       225: iinc          11, 1
       228: goto          201
       231: iinc          10, 1
       234: goto          190
       237: iinc          9, 1
       240: goto          180
       243: aload_0
       244: getfield      #592                // Field sectionCollector:Ldev/engine_room/flywheel/api/visual/SectionTrackedVisual$SectionCollector;
       247: aload         8
       249: invokeinterface #650,  2          // InterfaceMethod dev/engine_room/flywheel/api/visual/SectionTrackedVisual$SectionCollector.sections:(Lit/unimi/dsi/fastutil/longs/LongSet;)V
       254: return

  protected void _delete();
    Code:
         0: aload_0
         1: getfield      #98                 // Field children:Ljava/util/List;
         4: invokedynamic #302,  0            // InvokeDynamic #2:accept:()Ljava/util/function/Consumer;
         9: invokeinterface #308,  2          // InterfaceMethod java/util/List.forEach:(Ljava/util/function/Consumer;)V
        14: aload_0
        15: getfield      #100                // Field actors:Ljava/util/List;
        18: invokedynamic #342,  0            // InvokeDynamic #3:accept:()Ljava/util/function/Consumer;
        23: invokeinterface #308,  2          // InterfaceMethod java/util/List.forEach:(Ljava/util/function/Consumer;)V
        28: aload_0
        29: getfield      #251                // Field structure:Ldev/engine_room/flywheel/lib/instance/TransformedInstance;
        32: ifnull        42
        35: aload_0
        36: getfield      #251                // Field structure:Ldev/engine_room/flywheel/lib/instance/TransformedInstance;
        39: invokevirtual #662                // Method dev/engine_room/flywheel/lib/instance/TransformedInstance.delete:()V
        42: aload_0
        43: getfield      #126                // Field embedding:Ldev/engine_room/flywheel/api/visualization/VisualEmbedding;
        46: invokeinterface #663,  1          // InterfaceMethod dev/engine_room/flywheel/api/visualization/VisualEmbedding.delete:()V
        51: return

  private java.util.List lambda$planFrame$2();
    Code:
         0: aload_0
         1: getfield      #100                // Field actors:Ljava/util/List;
         4: areturn

  private java.util.List lambda$planTick$1();
    Code:
         0: aload_0
         1: getfield      #100                // Field actors:Ljava/util/List;
         4: areturn

  private static dev.engine_room.flywheel.api.material.Material lambda$setupStructure$0(net.minecraft.client.renderer.RenderType, java.lang.Boolean);
    Code:
         0: aload_0
         1: aload_1
         2: invokevirtual #668                // Method java/lang/Boolean.booleanValue:()Z
         5: invokestatic  #674                // Method dev/engine_room/flywheel/lib/model/ModelUtil.getMaterial:(Lnet/minecraft/client/renderer/RenderType;Z)Ldev/engine_room/flywheel/api/material/Material;
         8: astore_2
         9: aload_2
        10: ifnull        39
        13: aload_2
        14: invokeinterface #680,  1          // InterfaceMethod dev/engine_room/flywheel/api/material/Material.cardinalLightingMode:()Ldev/engine_room/flywheel/api/material/CardinalLightingMode;
        19: getstatic     #686                // Field dev/engine_room/flywheel/api/material/CardinalLightingMode.ENTITY:Ldev/engine_room/flywheel/api/material/CardinalLightingMode;
        22: if_acmpne     39
        25: aload_2
        26: invokestatic  #690                // Method dev/engine_room/flywheel/lib/material/SimpleMaterial.builderOf:(Ldev/engine_room/flywheel/api/material/Material;)Ldev/engine_room/flywheel/lib/material/SimpleMaterial$Builder;
        29: getstatic     #693                // Field dev/engine_room/flywheel/api/material/CardinalLightingMode.CHUNK:Ldev/engine_room/flywheel/api/material/CardinalLightingMode;
        32: invokevirtual #696                // Method dev/engine_room/flywheel/lib/material/SimpleMaterial$Builder.cardinalLightingMode:(Ldev/engine_room/flywheel/api/material/CardinalLightingMode;)Ldev/engine_room/flywheel/lib/material/SimpleMaterial$Builder;
        35: invokevirtual #699                // Method dev/engine_room/flywheel/lib/material/SimpleMaterial$Builder.build:()Ldev/engine_room/flywheel/lib/material/SimpleMaterial;
        38: areturn
        39: aload_2
        40: areturn
}
