Compiled from "Carriage.java"
public class com.simibubi.create.content.trains.entity.Carriage$DimensionalCarriageEntity {
  public net.minecraft.world.phys.Vec3 positionAnchor;

  public net.createmod.catnip.data.Couple<net.minecraft.world.phys.Vec3> rotationAnchors;

  public java.lang.ref.WeakReference<com.simibubi.create.content.trains.entity.CarriageContraptionEntity> entity;

  public com.simibubi.create.content.trains.graph.TrackNodeLocation pivot;

  int discardTicks;

  public float cutoff;

  public boolean pointsInitialised;

  final com.simibubi.create.content.trains.entity.Carriage this$0;

  public com.simibubi.create.content.trains.entity.Carriage$DimensionalCarriageEntity(com.simibubi.create.content.trains.entity.Carriage);
    Code:
         0: aload_0
         1: aload_1
         2: putfield      #54                 // Field this$0:Lcom/simibubi/create/content/trains/entity/Carriage;
         5: aload_0
         6: invokespecial #57                 // Method java/lang/Object."<init>":()V
         9: aload_0
        10: new           #59                 // class java/lang/ref/WeakReference
        13: dup
        14: aconst_null
        15: invokespecial #62                 // Method java/lang/ref/WeakReference."<init>":(Ljava/lang/Object;)V
        18: putfield      #64                 // Field entity:Ljava/lang/ref/WeakReference;
        21: aload_0
        22: aconst_null
        23: aconst_null
        24: invokestatic  #70                 // Method net/createmod/catnip/data/Couple.create:(Ljava/lang/Object;Ljava/lang/Object;)Lnet/createmod/catnip/data/Couple;
        27: putfield      #72                 // Field rotationAnchors:Lnet/createmod/catnip/data/Couple;
        30: aload_0
        31: iconst_0
        32: putfield      #74                 // Field pointsInitialised:Z
        35: return

  public void discardPivot();
    Code:
         0: aload_0
         1: invokevirtual #81                 // Method minAllowedLocalCoord:()I
         4: istore_1
         5: aload_0
         6: invokevirtual #84                 // Method maxAllowedLocalCoord:()I
         9: istore_2
        10: aload_0
        11: fconst_0
        12: putfield      #86                 // Field cutoff:F
        15: aload_0
        16: aconst_null
        17: putfield      #88                 // Field pivot:Lcom/simibubi/create/content/trains/graph/TrackNodeLocation;
        20: aload_0
        21: getfield      #54                 // Field this$0:Lcom/simibubi/create/content/trains/entity/Carriage;
        24: getfield      #92                 // Field com/simibubi/create/content/trains/entity/Carriage.serialisedPassengers:Ljava/util/Map;
        27: invokeinterface #96,  1           // InterfaceMethod java/util/Map.isEmpty:()Z
        32: ifne          45
        35: aload_0
        36: getfield      #64                 // Field entity:Ljava/lang/ref/WeakReference;
        39: invokevirtual #100                // Method java/lang/ref/WeakReference.get:()Ljava/lang/Object;
        42: ifnonnull     61
        45: iload_1
        46: aload_0
        47: invokevirtual #81                 // Method minAllowedLocalCoord:()I
        50: if_icmpne     61
        53: iload_2
        54: aload_0
        55: invokevirtual #84                 // Method maxAllowedLocalCoord:()I
        58: if_icmpeq     69
        61: aload_0
        62: invokevirtual #103                // Method updatePassengerLoadout:()V
        65: aload_0
        66: invokevirtual #106                // Method updateRenderedCutoff:()V
        69: return

  public void updateCutoff(boolean);
    Code:
         0: aload_0
         1: getfield      #72                 // Field rotationAnchors:Lnet/createmod/catnip/data/Couple;
         4: invokevirtual #113                // Method net/createmod/catnip/data/Couple.getFirst:()Ljava/lang/Object;
         7: checkcast     #115                // class net/minecraft/world/phys/Vec3
        10: astore_2
        11: aload_0
        12: getfield      #72                 // Field rotationAnchors:Lnet/createmod/catnip/data/Couple;
        15: invokevirtual #118                // Method net/createmod/catnip/data/Couple.getSecond:()Ljava/lang/Object;
        18: checkcast     #115                // class net/minecraft/world/phys/Vec3
        21: astore_3
        22: aload_2
        23: ifnull        30
        26: aload_3
        27: ifnonnull     31
        30: return
        31: aload_0
        32: getfield      #88                 // Field pivot:Lcom/simibubi/create/content/trains/graph/TrackNodeLocation;
        35: ifnonnull     44
        38: aload_0
        39: fconst_0
        40: putfield      #86                 // Field cutoff:F
        43: return
        44: aload_0
        45: getfield      #88                 // Field pivot:Lcom/simibubi/create/content/trains/graph/TrackNodeLocation;
        48: invokevirtual #124                // Method com/simibubi/create/content/trains/graph/TrackNodeLocation.getLocation:()Lnet/minecraft/world/phys/Vec3;
        51: dconst_0
        52: dconst_1
        53: dconst_0
        54: invokevirtual #128                // Method net/minecraft/world/phys/Vec3.add:(DDD)Lnet/minecraft/world/phys/Vec3;
        57: astore        4
        59: aload_0
        60: getfield      #54                 // Field this$0:Lcom/simibubi/create/content/trains/entity/Carriage;
        63: invokevirtual #132                // Method com/simibubi/create/content/trains/entity/Carriage.leadingBogey:()Lcom/simibubi/create/content/trains/entity/CarriageBogey;
        66: getfield      #138                // Field com/simibubi/create/content/trains/entity/CarriageBogey.type:Lcom/simibubi/create/content/trains/bogey/AbstractBogeyBlock;
        69: invokevirtual #144                // Method com/simibubi/create/content/trains/bogey/AbstractBogeyBlock.getWheelPointSpacing:()D
        72: ldc2_w        #145                // double 2.0d
        75: ddiv
        76: dstore        5
        78: aload_0
        79: getfield      #54                 // Field this$0:Lcom/simibubi/create/content/trains/entity/Carriage;
        82: invokevirtual #149                // Method com/simibubi/create/content/trains/entity/Carriage.trailingBogey:()Lcom/simibubi/create/content/trains/entity/CarriageBogey;
        85: getfield      #138                // Field com/simibubi/create/content/trains/entity/CarriageBogey.type:Lcom/simibubi/create/content/trains/bogey/AbstractBogeyBlock;
        88: invokevirtual #144                // Method com/simibubi/create/content/trains/bogey/AbstractBogeyBlock.getWheelPointSpacing:()D
        91: ldc2_w        #145                // double 2.0d
        94: ddiv
        95: dstore        7
        97: dload         5
        99: aload_0
       100: getfield      #54                 // Field this$0:Lcom/simibubi/create/content/trains/entity/Carriage;
       103: getfield      #152                // Field com/simibubi/create/content/trains/entity/Carriage.bogeySpacing:I
       106: i2d
       107: dadd
       108: dload         7
       110: dadd
       111: dstore        9
       113: aload_0
       114: getfield      #54                 // Field this$0:Lcom/simibubi/create/content/trains/entity/Carriage;
       117: invokevirtual #155                // Method com/simibubi/create/content/trains/entity/Carriage.isOnTwoBogeys:()Z
       120: ifeq          158
       123: aload_3
       124: aload_2
       125: invokevirtual #159                // Method net/minecraft/world/phys/Vec3.subtract:(Lnet/minecraft/world/phys/Vec3;)Lnet/minecraft/world/phys/Vec3;
       128: invokevirtual #162                // Method net/minecraft/world/phys/Vec3.normalize:()Lnet/minecraft/world/phys/Vec3;
       131: astore        11
       133: aload_3
       134: aload         11
       136: dload         7
       138: invokevirtual #166                // Method net/minecraft/world/phys/Vec3.scale:(D)Lnet/minecraft/world/phys/Vec3;
       141: invokevirtual #168                // Method net/minecraft/world/phys/Vec3.add:(Lnet/minecraft/world/phys/Vec3;)Lnet/minecraft/world/phys/Vec3;
       144: astore_3
       145: aload_2
       146: aload         11
       148: dload         5
       150: dneg
       151: invokevirtual #166                // Method net/minecraft/world/phys/Vec3.scale:(D)Lnet/minecraft/world/phys/Vec3;
       154: invokevirtual #168                // Method net/minecraft/world/phys/Vec3.add:(Lnet/minecraft/world/phys/Vec3;)Lnet/minecraft/world/phys/Vec3;
       157: astore_2
       158: aload_2
       159: aload         4
       161: invokevirtual #172                // Method net/minecraft/world/phys/Vec3.distanceTo:(Lnet/minecraft/world/phys/Vec3;)D
       164: dstore        11
       166: aload_3
       167: aload         4
       169: invokevirtual #172                // Method net/minecraft/world/phys/Vec3.distanceTo:(Lnet/minecraft/world/phys/Vec3;)D
       172: dstore        13
       174: dload         11
       176: dload         9
       178: ddiv
       179: dstore        11
       181: dload         13
       183: dload         9
       185: ddiv
       186: dstore        13
       188: iload_1
       189: ifeq          215
       192: dload         11
       194: dload         13
       196: dcmpl
       197: ifle          215
       200: dload         11
       202: dconst_1
       203: dcmpl
       204: ifle          215
       207: aload_0
       208: fconst_0
       209: putfield      #86                 // Field cutoff:F
       212: goto          331
       215: iload_1
       216: ifeq          242
       219: dload         11
       221: dload         13
       223: dcmpg
       224: ifge          242
       227: dload         13
       229: dconst_1
       230: dcmpl
       231: ifle          242
       234: aload_0
       235: fconst_1
       236: putfield      #86                 // Field cutoff:F
       239: goto          331
       242: iload_1
       243: ifne          270
       246: dload         11
       248: dload         13
       250: dcmpl
       251: ifle          270
       254: dload         11
       256: dconst_1
       257: dcmpl
       258: ifle          270
       261: aload_0
       262: ldc           #173                // float -1.0f
       264: putfield      #86                 // Field cutoff:F
       267: goto          331
       270: iload_1
       271: ifne          297
       274: dload         11
       276: dload         13
       278: dcmpg
       279: ifge          297
       282: dload         13
       284: dconst_1
       285: dcmpl
       286: ifle          297
       289: aload_0
       290: fconst_0
       291: putfield      #86                 // Field cutoff:F
       294: goto          331
       297: aload_0
       298: dconst_1
       299: iload_1
       300: ifeq          308
       303: dload         11
       305: goto          310
       308: dload         13
       310: dsub
       311: dconst_0
       312: dconst_1
       313: invokestatic  #179                // Method net/minecraft/util/Mth.clamp:(DDD)D
       316: d2f
       317: iload_1
       318: ifeq          325
       321: iconst_1
       322: goto          326
       325: iconst_m1
       326: i2f
       327: fmul
       328: putfield      #86                 // Field cutoff:F
       331: return

  public com.simibubi.create.content.trains.graph.TrackNodeLocation findPivot(net.minecraft.resources.ResourceKey<net.minecraft.world.level.Level>, boolean);
    Code:
         0: aload_0
         1: getfield      #88                 // Field pivot:Lcom/simibubi/create/content/trains/graph/TrackNodeLocation;
         4: ifnull        12
         7: aload_0
         8: getfield      #88                 // Field pivot:Lcom/simibubi/create/content/trains/graph/TrackNodeLocation;
        11: areturn
        12: iload_2
        13: ifeq          26
        16: aload_0
        17: getfield      #54                 // Field this$0:Lcom/simibubi/create/content/trains/entity/Carriage;
        20: invokevirtual #197                // Method com/simibubi/create/content/trains/entity/Carriage.getLeadingPoint:()Lcom/simibubi/create/content/trains/entity/TravellingPoint;
        23: goto          33
        26: aload_0
        27: getfield      #54                 // Field this$0:Lcom/simibubi/create/content/trains/entity/Carriage;
        30: invokevirtual #200                // Method com/simibubi/create/content/trains/entity/Carriage.getTrailingPoint:()Lcom/simibubi/create/content/trains/entity/TravellingPoint;
        33: astore_3
        34: iload_2
        35: ifne          48
        38: aload_0
        39: getfield      #54                 // Field this$0:Lcom/simibubi/create/content/trains/entity/Carriage;
        42: invokevirtual #197                // Method com/simibubi/create/content/trains/entity/Carriage.getLeadingPoint:()Lcom/simibubi/create/content/trains/entity/TravellingPoint;
        45: goto          55
        48: aload_0
        49: getfield      #54                 // Field this$0:Lcom/simibubi/create/content/trains/entity/Carriage;
        52: invokevirtual #200                // Method com/simibubi/create/content/trains/entity/Carriage.getTrailingPoint:()Lcom/simibubi/create/content/trains/entity/TravellingPoint;
        55: astore        4
        57: aload_0
        58: getfield      #54                 // Field this$0:Lcom/simibubi/create/content/trains/entity/Carriage;
        61: getfield      #204                // Field com/simibubi/create/content/trains/entity/Carriage.portalScout:Lcom/simibubi/create/content/trains/entity/TravellingPoint;
        64: aload_3
        65: getfield      #208                // Field com/simibubi/create/content/trains/entity/TravellingPoint.node1:Lcom/simibubi/create/content/trains/graph/TrackNode;
        68: putfield      #208                // Field com/simibubi/create/content/trains/entity/TravellingPoint.node1:Lcom/simibubi/create/content/trains/graph/TrackNode;
        71: aload_0
        72: getfield      #54                 // Field this$0:Lcom/simibubi/create/content/trains/entity/Carriage;
        75: getfield      #204                // Field com/simibubi/create/content/trains/entity/Carriage.portalScout:Lcom/simibubi/create/content/trains/entity/TravellingPoint;
        78: aload_3
        79: getfield      #211                // Field com/simibubi/create/content/trains/entity/TravellingPoint.node2:Lcom/simibubi/create/content/trains/graph/TrackNode;
        82: putfield      #211                // Field com/simibubi/create/content/trains/entity/TravellingPoint.node2:Lcom/simibubi/create/content/trains/graph/TrackNode;
        85: aload_0
        86: getfield      #54                 // Field this$0:Lcom/simibubi/create/content/trains/entity/Carriage;
        89: getfield      #204                // Field com/simibubi/create/content/trains/entity/Carriage.portalScout:Lcom/simibubi/create/content/trains/entity/TravellingPoint;
        92: aload_3
        93: getfield      #215                // Field com/simibubi/create/content/trains/entity/TravellingPoint.edge:Lcom/simibubi/create/content/trains/graph/TrackEdge;
        96: putfield      #215                // Field com/simibubi/create/content/trains/entity/TravellingPoint.edge:Lcom/simibubi/create/content/trains/graph/TrackEdge;
        99: aload_0
       100: getfield      #54                 // Field this$0:Lcom/simibubi/create/content/trains/entity/Carriage;
       103: getfield      #204                // Field com/simibubi/create/content/trains/entity/Carriage.portalScout:Lcom/simibubi/create/content/trains/entity/TravellingPoint;
       106: aload_3
       107: getfield      #218                // Field com/simibubi/create/content/trains/entity/TravellingPoint.position:D
       110: putfield      #218                // Field com/simibubi/create/content/trains/entity/TravellingPoint.position:D
       113: aload_0
       114: getfield      #54                 // Field this$0:Lcom/simibubi/create/content/trains/entity/Carriage;
       117: getfield      #204                // Field com/simibubi/create/content/trains/entity/Carriage.portalScout:Lcom/simibubi/create/content/trains/entity/TravellingPoint;
       120: aload         4
       122: invokevirtual #222                // Method com/simibubi/create/content/trains/entity/TravellingPoint.follow:(Lcom/simibubi/create/content/trains/entity/TravellingPoint;)Lcom/simibubi/create/content/trains/entity/TravellingPoint$ITrackSelector;
       125: astore        5
       127: aload_0
       128: getfield      #54                 // Field this$0:Lcom/simibubi/create/content/trains/entity/Carriage;
       131: getfield      #152                // Field com/simibubi/create/content/trains/entity/Carriage.bogeySpacing:I
       134: bipush        10
       136: iadd
       137: istore        6
       139: iload_2
       140: ifeq          147
       143: iconst_m1
       144: goto          148
       147: iconst_1
       148: istore        7
       150: aload_0
       151: getfield      #54                 // Field this$0:Lcom/simibubi/create/content/trains/entity/Carriage;
       154: getfield      #204                // Field com/simibubi/create/content/trains/entity/Carriage.portalScout:Lcom/simibubi/create/content/trains/entity/TravellingPoint;
       157: aload_0
       158: getfield      #54                 // Field this$0:Lcom/simibubi/create/content/trains/entity/Carriage;
       161: getfield      #226                // Field com/simibubi/create/content/trains/entity/Carriage.train:Lcom/simibubi/create/content/trains/entity/Train;
       164: getfield      #232                // Field com/simibubi/create/content/trains/entity/Train.graph:Lcom/simibubi/create/content/trains/graph/TrackGraph;
       167: iload         7
       169: iload         6
       171: imul
       172: i2d
       173: aload         5
       175: aload_0
       176: getfield      #54                 // Field this$0:Lcom/simibubi/create/content/trains/entity/Carriage;
       179: getfield      #204                // Field com/simibubi/create/content/trains/entity/Carriage.portalScout:Lcom/simibubi/create/content/trains/entity/TravellingPoint;
       182: invokevirtual #236                // Method com/simibubi/create/content/trains/entity/TravellingPoint.ignoreEdgePoints:()Lcom/simibubi/create/content/trains/entity/TravellingPoint$IEdgePointListener;
       185: aload_0
       186: getfield      #54                 // Field this$0:Lcom/simibubi/create/content/trains/entity/Carriage;
       189: getfield      #204                // Field com/simibubi/create/content/trains/entity/Carriage.portalScout:Lcom/simibubi/create/content/trains/entity/TravellingPoint;
       192: invokevirtual #240                // Method com/simibubi/create/content/trains/entity/TravellingPoint.ignoreTurns:()Lcom/simibubi/create/content/trains/entity/TravellingPoint$ITurnListener;
       195: aload_0
       196: aload_1
       197: invokedynamic #260,  0            // InvokeDynamic #0:test:(Lcom/simibubi/create/content/trains/entity/Carriage$DimensionalCarriageEntity;Lnet/minecraft/resources/ResourceKey;)Lcom/simibubi/create/content/trains/entity/TravellingPoint$IPortalListener;
       202: invokevirtual #264                // Method com/simibubi/create/content/trains/entity/TravellingPoint.travel:(Lcom/simibubi/create/content/trains/graph/TrackGraph;DLcom/simibubi/create/content/trains/entity/TravellingPoint$ITrackSelector;Lcom/simibubi/create/content/trains/entity/TravellingPoint$IEdgePointListener;Lcom/simibubi/create/content/trains/entity/TravellingPoint$ITurnListener;Lcom/simibubi/create/content/trains/entity/TravellingPoint$IPortalListener;)D
       205: pop2
       206: aload_0
       207: getfield      #88                 // Field pivot:Lcom/simibubi/create/content/trains/graph/TrackNodeLocation;
       210: areturn

  public net.minecraft.nbt.CompoundTag write();
    Code:
         0: new           #278                // class net/minecraft/nbt/CompoundTag
         3: dup
         4: invokespecial #279                // Method net/minecraft/nbt/CompoundTag."<init>":()V
         7: astore_1
         8: aload_1
         9: ldc_w         #281                // String Cutoff
        12: aload_0
        13: getfield      #86                 // Field cutoff:F
        16: invokevirtual #285                // Method net/minecraft/nbt/CompoundTag.putFloat:(Ljava/lang/String;F)V
        19: aload_1
        20: ldc_w         #287                // String DiscardTicks
        23: aload_0
        24: getfield      #289                // Field discardTicks:I
        27: invokevirtual #293                // Method net/minecraft/nbt/CompoundTag.putInt:(Ljava/lang/String;I)V
        30: aload_0
        31: getfield      #54                 // Field this$0:Lcom/simibubi/create/content/trains/entity/Carriage;
        34: getfield      #297                // Field com/simibubi/create/content/trains/entity/Carriage.storage:Lcom/simibubi/create/content/contraptions/minecart/TrainCargoManager;
        37: aload_1
        38: iconst_0
        39: invokevirtual #302                // Method com/simibubi/create/content/contraptions/minecart/TrainCargoManager.write:(Lnet/minecraft/nbt/CompoundTag;Z)V
        42: aload_0
        43: getfield      #88                 // Field pivot:Lcom/simibubi/create/content/trains/graph/TrackNodeLocation;
        46: ifnull        65
        49: aload_1
        50: ldc_w         #304                // String Pivot
        53: aload_0
        54: getfield      #88                 // Field pivot:Lcom/simibubi/create/content/trains/graph/TrackNodeLocation;
        57: aconst_null
        58: invokevirtual #307                // Method com/simibubi/create/content/trains/graph/TrackNodeLocation.write:(Lcom/simibubi/create/content/trains/graph/DimensionPalette;)Lnet/minecraft/nbt/CompoundTag;
        61: invokevirtual #311                // Method net/minecraft/nbt/CompoundTag.put:(Ljava/lang/String;Lnet/minecraft/nbt/Tag;)Lnet/minecraft/nbt/Tag;
        64: pop
        65: aload_0
        66: getfield      #313                // Field positionAnchor:Lnet/minecraft/world/phys/Vec3;
        69: ifnull        87
        72: aload_1
        73: ldc_w         #315                // String PositionAnchor
        76: aload_0
        77: getfield      #313                // Field positionAnchor:Lnet/minecraft/world/phys/Vec3;
        80: invokestatic  #321                // Method net/createmod/catnip/math/VecHelper.writeNBT:(Lnet/minecraft/world/phys/Vec3;)Lnet/minecraft/nbt/ListTag;
        83: invokevirtual #311                // Method net/minecraft/nbt/CompoundTag.put:(Ljava/lang/String;Lnet/minecraft/nbt/Tag;)Lnet/minecraft/nbt/Tag;
        86: pop
        87: aload_0
        88: getfield      #72                 // Field rotationAnchors:Lnet/createmod/catnip/data/Couple;
        91: invokedynamic #332,  0            // InvokeDynamic #1:test:()Ljava/util/function/Predicate;
        96: invokevirtual #336                // Method net/createmod/catnip/data/Couple.both:(Ljava/util/function/Predicate;)Z
        99: ifeq          122
       102: aload_1
       103: ldc_w         #338                // String RotationAnchors
       106: aload_0
       107: getfield      #72                 // Field rotationAnchors:Lnet/createmod/catnip/data/Couple;
       110: invokedynamic #350,  0            // InvokeDynamic #2:apply:()Ljava/util/function/Function;
       115: invokevirtual #354                // Method net/createmod/catnip/data/Couple.serializeEach:(Ljava/util/function/Function;)Lnet/minecraft/nbt/ListTag;
       118: invokevirtual #311                // Method net/minecraft/nbt/CompoundTag.put:(Ljava/lang/String;Lnet/minecraft/nbt/Tag;)Lnet/minecraft/nbt/Tag;
       121: pop
       122: aload_1
       123: areturn

  public void read(net.minecraft.nbt.CompoundTag);
    Code:
         0: aload_0
         1: aload_1
         2: ldc_w         #281                // String Cutoff
         5: invokevirtual #362                // Method net/minecraft/nbt/CompoundTag.getFloat:(Ljava/lang/String;)F
         8: putfield      #86                 // Field cutoff:F
        11: aload_0
        12: aload_1
        13: ldc_w         #287                // String DiscardTicks
        16: invokevirtual #366                // Method net/minecraft/nbt/CompoundTag.getInt:(Ljava/lang/String;)I
        19: putfield      #289                // Field discardTicks:I
        22: aload_0
        23: getfield      #54                 // Field this$0:Lcom/simibubi/create/content/trains/entity/Carriage;
        26: getfield      #297                // Field com/simibubi/create/content/trains/entity/Carriage.storage:Lcom/simibubi/create/content/contraptions/minecart/TrainCargoManager;
        29: aload_1
        30: iconst_0
        31: aconst_null
        32: invokevirtual #369                // Method com/simibubi/create/content/contraptions/minecart/TrainCargoManager.read:(Lnet/minecraft/nbt/CompoundTag;ZLcom/simibubi/create/content/contraptions/Contraption;)V
        35: aload_1
        36: ldc_w         #304                // String Pivot
        39: invokevirtual #373                // Method net/minecraft/nbt/CompoundTag.contains:(Ljava/lang/String;)Z
        42: ifeq          60
        45: aload_0
        46: aload_1
        47: ldc_w         #304                // String Pivot
        50: invokevirtual #377                // Method net/minecraft/nbt/CompoundTag.getCompound:(Ljava/lang/String;)Lnet/minecraft/nbt/CompoundTag;
        53: aconst_null
        54: invokestatic  #380                // Method com/simibubi/create/content/trains/graph/TrackNodeLocation.read:(Lnet/minecraft/nbt/CompoundTag;Lcom/simibubi/create/content/trains/graph/DimensionPalette;)Lcom/simibubi/create/content/trains/graph/TrackNodeLocation;
        57: putfield      #88                 // Field pivot:Lcom/simibubi/create/content/trains/graph/TrackNodeLocation;
        60: aload_0
        61: getfield      #313                // Field positionAnchor:Lnet/minecraft/world/phys/Vec3;
        64: ifnull        68
        67: return
        68: aload_1
        69: ldc_w         #315                // String PositionAnchor
        72: invokevirtual #373                // Method net/minecraft/nbt/CompoundTag.contains:(Ljava/lang/String;)Z
        75: ifeq          94
        78: aload_0
        79: aload_1
        80: ldc_w         #315                // String PositionAnchor
        83: bipush        6
        85: invokevirtual #384                // Method net/minecraft/nbt/CompoundTag.getList:(Ljava/lang/String;I)Lnet/minecraft/nbt/ListTag;
        88: invokestatic  #388                // Method net/createmod/catnip/math/VecHelper.readNBT:(Lnet/minecraft/nbt/ListTag;)Lnet/minecraft/world/phys/Vec3;
        91: putfield      #313                // Field positionAnchor:Lnet/minecraft/world/phys/Vec3;
        94: aload_1
        95: ldc_w         #338                // String RotationAnchors
        98: invokevirtual #373                // Method net/minecraft/nbt/CompoundTag.contains:(Ljava/lang/String;)Z
       101: ifeq          125
       104: aload_0
       105: aload_1
       106: ldc_w         #338                // String RotationAnchors
       109: bipush        10
       111: invokevirtual #384                // Method net/minecraft/nbt/CompoundTag.getList:(Ljava/lang/String;I)Lnet/minecraft/nbt/ListTag;
       114: invokedynamic #395,  0            // InvokeDynamic #3:apply:()Ljava/util/function/Function;
       119: invokestatic  #399                // Method net/createmod/catnip/data/Couple.deserializeEach:(Lnet/minecraft/nbt/ListTag;Ljava/util/function/Function;)Lnet/createmod/catnip/data/Couple;
       122: putfield      #72                 // Field rotationAnchors:Lnet/createmod/catnip/data/Couple;
       125: return

  public net.minecraft.world.phys.Vec3 leadingAnchor();
    Code:
         0: aload_0
         1: getfield      #54                 // Field this$0:Lcom/simibubi/create/content/trains/entity/Carriage;
         4: invokevirtual #155                // Method com/simibubi/create/content/trains/entity/Carriage.isOnTwoBogeys:()Z
         7: ifeq          23
        10: aload_0
        11: getfield      #72                 // Field rotationAnchors:Lnet/createmod/catnip/data/Couple;
        14: invokevirtual #113                // Method net/createmod/catnip/data/Couple.getFirst:()Ljava/lang/Object;
        17: checkcast     #115                // class net/minecraft/world/phys/Vec3
        20: goto          27
        23: aload_0
        24: getfield      #313                // Field positionAnchor:Lnet/minecraft/world/phys/Vec3;
        27: areturn

  public net.minecraft.world.phys.Vec3 trailingAnchor();
    Code:
         0: aload_0
         1: getfield      #54                 // Field this$0:Lcom/simibubi/create/content/trains/entity/Carriage;
         4: invokevirtual #155                // Method com/simibubi/create/content/trains/entity/Carriage.isOnTwoBogeys:()Z
         7: ifeq          23
        10: aload_0
        11: getfield      #72                 // Field rotationAnchors:Lnet/createmod/catnip/data/Couple;
        14: invokevirtual #118                // Method net/createmod/catnip/data/Couple.getSecond:()Ljava/lang/Object;
        17: checkcast     #115                // class net/minecraft/world/phys/Vec3
        20: goto          27
        23: aload_0
        24: getfield      #313                // Field positionAnchor:Lnet/minecraft/world/phys/Vec3;
        27: areturn

  public int minAllowedLocalCoord();
    Code:
         0: aload_0
         1: getfield      #86                 // Field cutoff:F
         4: fconst_0
         5: fcmpg
         6: ifgt          13
         9: ldc_w         #400                // int -2147483648
        12: ireturn
        13: aload_0
        14: getfield      #86                 // Field cutoff:F
        17: fconst_1
        18: fcmpl
        19: iflt          26
        22: ldc_w         #401                // int 2147483647
        25: ireturn
        26: aload_0
        27: getfield      #54                 // Field this$0:Lcom/simibubi/create/content/trains/entity/Carriage;
        30: getfield      #152                // Field com/simibubi/create/content/trains/entity/Carriage.bogeySpacing:I
        33: ineg
        34: iconst_m1
        35: iadd
        36: i2f
        37: iconst_2
        38: aload_0
        39: getfield      #54                 // Field this$0:Lcom/simibubi/create/content/trains/entity/Carriage;
        42: getfield      #152                // Field com/simibubi/create/content/trains/entity/Carriage.bogeySpacing:I
        45: iadd
        46: i2f
        47: aload_0
        48: getfield      #86                 // Field cutoff:F
        51: fmul
        52: fadd
        53: invokestatic  #405                // Method net/minecraft/util/Mth.floor:(F)I
        56: ireturn

  public int maxAllowedLocalCoord();
    Code:
         0: aload_0
         1: getfield      #86                 // Field cutoff:F
         4: fconst_0
         5: fcmpl
         6: iflt          13
         9: ldc_w         #401                // int 2147483647
        12: ireturn
        13: aload_0
        14: getfield      #86                 // Field cutoff:F
        17: ldc           #173                // float -1.0f
        19: fcmpg
        20: ifgt          27
        23: ldc_w         #400                // int -2147483648
        26: ireturn
        27: aload_0
        28: getfield      #54                 // Field this$0:Lcom/simibubi/create/content/trains/entity/Carriage;
        31: getfield      #152                // Field com/simibubi/create/content/trains/entity/Carriage.bogeySpacing:I
        34: ineg
        35: iconst_m1
        36: iadd
        37: i2f
        38: iconst_2
        39: aload_0
        40: getfield      #54                 // Field this$0:Lcom/simibubi/create/content/trains/entity/Carriage;
        43: getfield      #152                // Field com/simibubi/create/content/trains/entity/Carriage.bogeySpacing:I
        46: iadd
        47: i2f
        48: aload_0
        49: getfield      #86                 // Field cutoff:F
        52: fconst_1
        53: fadd
        54: fmul
        55: fadd
        56: invokestatic  #408                // Method net/minecraft/util/Mth.ceil:(F)I
        59: ireturn

  public void updatePassengerLoadout();
    Code:
         0: aload_0
         1: getfield      #64                 // Field entity:Ljava/lang/ref/WeakReference;
         4: invokevirtual #100                // Method java/lang/ref/WeakReference.get:()Ljava/lang/Object;
         7: checkcast     #410                // class net/minecraft/world/entity/Entity
        10: astore_1
        11: aload_1
        12: instanceof    #412                // class com/simibubi/create/content/trains/entity/CarriageContraptionEntity
        15: ifeq          26
        18: aload_1
        19: checkcast     #412                // class com/simibubi/create/content/trains/entity/CarriageContraptionEntity
        22: astore_2
        23: goto          27
        26: return
        27: aload_1
        28: invokevirtual #416                // Method net/minecraft/world/entity/Entity.level:()Lnet/minecraft/world/level/Level;
        31: astore        4
        33: aload         4
        35: instanceof    #418                // class net/minecraft/server/level/ServerLevel
        38: ifeq          50
        41: aload         4
        43: checkcast     #418                // class net/minecraft/server/level/ServerLevel
        46: astore_3
        47: goto          51
        50: return
        51: new           #420                // class java/util/HashSet
        54: dup
        55: invokespecial #421                // Method java/util/HashSet."<init>":()V
        58: astore        4
        60: aload_0
        61: invokevirtual #81                 // Method minAllowedLocalCoord:()I
        64: istore        5
        66: aload_0
        67: invokevirtual #84                 // Method maxAllowedLocalCoord:()I
        70: istore        6
        72: aload_0
        73: getfield      #54                 // Field this$0:Lcom/simibubi/create/content/trains/entity/Carriage;
        76: getfield      #92                 // Field com/simibubi/create/content/trains/entity/Carriage.serialisedPassengers:Ljava/util/Map;
        79: invokeinterface #425,  1          // InterfaceMethod java/util/Map.entrySet:()Ljava/util/Set;
        84: invokeinterface #431,  1          // InterfaceMethod java/util/Set.iterator:()Ljava/util/Iterator;
        89: astore        7
        91: aload         7
        93: invokeinterface #436,  1          // InterfaceMethod java/util/Iterator.hasNext:()Z
        98: ifeq          332
       101: aload         7
       103: invokeinterface #439,  1          // InterfaceMethod java/util/Iterator.next:()Ljava/lang/Object;
       108: checkcast     #24                 // class java/util/Map$Entry
       111: astore        8
       113: aload         8
       115: invokeinterface #442,  1          // InterfaceMethod java/util/Map$Entry.getKey:()Ljava/lang/Object;
       120: checkcast     #444                // class java/lang/Integer
       123: astore        9
       125: aload_2
       126: invokevirtual #448                // Method com/simibubi/create/content/trains/entity/CarriageContraptionEntity.getContraption:()Lcom/simibubi/create/content/contraptions/Contraption;
       129: invokevirtual #454                // Method com/simibubi/create/content/contraptions/Contraption.getSeats:()Ljava/util/List;
       132: astore        10
       134: aload         9
       136: invokevirtual #457                // Method java/lang/Integer.intValue:()I
       139: aload         10
       141: invokeinterface #462,  1          // InterfaceMethod java/util/List.size:()I
       146: if_icmplt     152
       149: goto          91
       152: aload         10
       154: aload         9
       156: invokevirtual #457                // Method java/lang/Integer.intValue:()I
       159: invokeinterface #465,  2          // InterfaceMethod java/util/List.get:(I)Ljava/lang/Object;
       164: checkcast     #467                // class net/minecraft/core/BlockPos
       167: astore        11
       169: aload_2
       170: aload         11
       172: iload         5
       174: iload         6
       176: invokevirtual #471                // Method com/simibubi/create/content/trains/entity/CarriageContraptionEntity.isLocalCoordWithin:(Lnet/minecraft/core/BlockPos;II)Z
       179: ifne          185
       182: goto          91
       185: aload         8
       187: invokeinterface #474,  1          // InterfaceMethod java/util/Map$Entry.getValue:()Ljava/lang/Object;
       192: checkcast     #278                // class net/minecraft/nbt/CompoundTag
       195: astore        12
       197: aconst_null
       198: astore        13
       200: aload         12
       202: ldc_w         #476                // String PlayerPassenger
       205: invokevirtual #373                // Method net/minecraft/nbt/CompoundTag.contains:(Ljava/lang/String;)Z
       208: ifeq          234
       211: aload_3
       212: invokevirtual #480                // Method net/minecraft/server/level/ServerLevel.getServer:()Lnet/minecraft/server/MinecraftServer;
       215: invokevirtual #486                // Method net/minecraft/server/MinecraftServer.getPlayerList:()Lnet/minecraft/server/players/PlayerList;
       218: aload         12
       220: ldc_w         #476                // String PlayerPassenger
       223: invokevirtual #490                // Method net/minecraft/nbt/CompoundTag.getUUID:(Ljava/lang/String;)Ljava/util/UUID;
       226: invokevirtual #496                // Method net/minecraft/server/players/PlayerList.getPlayer:(Ljava/util/UUID;)Lnet/minecraft/server/level/ServerPlayer;
       229: astore        13
       231: goto          263
       234: aload         12
       236: aload_1
       237: invokevirtual #416                // Method net/minecraft/world/entity/Entity.level:()Lnet/minecraft/world/level/Level;
       240: aload_0
       241: invokedynamic #505,  0            // InvokeDynamic #4:apply:(Lcom/simibubi/create/content/trains/entity/Carriage$DimensionalCarriageEntity;)Ljava/util/function/Function;
       246: invokestatic  #511                // Method net/minecraft/world/entity/EntityType.loadEntityRecursive:(Lnet/minecraft/nbt/CompoundTag;Lnet/minecraft/world/level/Level;Ljava/util/function/Function;)Lnet/minecraft/world/entity/Entity;
       249: astore        13
       251: aload         13
       253: ifnull        263
       256: aload_3
       257: aload         13
       259: invokevirtual #515                // Method net/minecraft/server/level/ServerLevel.tryAddFreshEntityWithPassengers:(Lnet/minecraft/world/entity/Entity;)Z
       262: pop
       263: aload         13
       265: ifnull        319
       268: aload         13
       270: invokevirtual #416                // Method net/minecraft/world/entity/Entity.level:()Lnet/minecraft/world/level/Level;
       273: invokevirtual #520                // Method net/minecraft/world/level/Level.dimension:()Lnet/minecraft/resources/ResourceKey;
       276: astore        14
       278: aload         14
       280: aload_3
       281: invokevirtual #521                // Method net/minecraft/server/level/ServerLevel.dimension:()Lnet/minecraft/resources/ResourceKey;
       284: invokevirtual #526                // Method net/minecraft/resources/ResourceKey.equals:(Ljava/lang/Object;)Z
       287: ifne          308
       290: aload         13
       292: instanceof    #528                // class net/minecraft/server/level/ServerPlayer
       295: ifeq          308
       298: aload         13
       300: checkcast     #528                // class net/minecraft/server/level/ServerPlayer
       303: astore        15
       305: goto          91
       308: aload_2
       309: aload         13
       311: aload         9
       313: invokevirtual #457                // Method java/lang/Integer.intValue:()I
       316: invokevirtual #532                // Method com/simibubi/create/content/trains/entity/CarriageContraptionEntity.addSittingPassenger:(Lnet/minecraft/world/entity/Entity;I)V
       319: aload         4
       321: aload         9
       323: invokeinterface #534,  2          // InterfaceMethod java/util/Set.add:(Ljava/lang/Object;)Z
       328: pop
       329: goto          91
       332: aload         4
       334: aload_0
       335: getfield      #54                 // Field this$0:Lcom/simibubi/create/content/trains/entity/Carriage;
       338: getfield      #92                 // Field com/simibubi/create/content/trains/entity/Carriage.serialisedPassengers:Ljava/util/Map;
       341: dup
       342: invokestatic  #537                // Method java/util/Objects.requireNonNull:(Ljava/lang/Object;)Ljava/lang/Object;
       345: pop
       346: invokedynamic #548,  0            // InvokeDynamic #5:accept:(Ljava/util/Map;)Ljava/util/function/Consumer;
       351: invokeinterface #552,  2          // InterfaceMethod java/util/Set.forEach:(Ljava/util/function/Consumer;)V
       356: aload_2
       357: invokevirtual #448                // Method com/simibubi/create/content/trains/entity/CarriageContraptionEntity.getContraption:()Lcom/simibubi/create/content/contraptions/Contraption;
       360: invokevirtual #556                // Method com/simibubi/create/content/contraptions/Contraption.getSeatMapping:()Ljava/util/Map;
       363: astore        7
       365: aload_1
       366: invokevirtual #559                // Method net/minecraft/world/entity/Entity.getPassengers:()Ljava/util/List;
       369: invokeinterface #560,  1          // InterfaceMethod java/util/List.iterator:()Ljava/util/Iterator;
       374: astore        8
       376: aload         8
       378: invokeinterface #436,  1          // InterfaceMethod java/util/Iterator.hasNext:()Z
       383: ifeq          519
       386: aload         8
       388: invokeinterface #439,  1          // InterfaceMethod java/util/Iterator.next:()Ljava/lang/Object;
       393: checkcast     #410                // class net/minecraft/world/entity/Entity
       396: astore        9
       398: aload_2
       399: invokevirtual #448                // Method com/simibubi/create/content/trains/entity/CarriageContraptionEntity.getContraption:()Lcom/simibubi/create/content/contraptions/Contraption;
       402: aload         9
       404: invokevirtual #563                // Method net/minecraft/world/entity/Entity.getUUID:()Ljava/util/UUID;
       407: invokevirtual #567                // Method com/simibubi/create/content/contraptions/Contraption.getSeatOf:(Ljava/util/UUID;)Lnet/minecraft/core/BlockPos;
       410: astore        10
       412: aload_2
       413: aload         10
       415: iload         5
       417: iload         6
       419: invokevirtual #471                // Method com/simibubi/create/content/trains/entity/CarriageContraptionEntity.isLocalCoordWithin:(Lnet/minecraft/core/BlockPos;II)Z
       422: ifeq          428
       425: goto          376
       428: aload         7
       430: aload         9
       432: invokevirtual #563                // Method net/minecraft/world/entity/Entity.getUUID:()Ljava/util/UUID;
       435: invokeinterface #570,  2          // InterfaceMethod java/util/Map.containsKey:(Ljava/lang/Object;)Z
       440: ifne          446
       443: goto          376
       446: aload         7
       448: aload         9
       450: invokevirtual #563                // Method net/minecraft/world/entity/Entity.getUUID:()Ljava/util/UUID;
       453: invokeinterface #572,  2          // InterfaceMethod java/util/Map.get:(Ljava/lang/Object;)Ljava/lang/Object;
       458: checkcast     #444                // class java/lang/Integer
       461: astore        11
       463: aload         9
       465: instanceof    #528                // class net/minecraft/server/level/ServerPlayer
       468: ifeq          491
       471: aload         9
       473: checkcast     #528                // class net/minecraft/server/level/ServerPlayer
       476: astore        12
       478: aload_0
       479: aload_3
       480: aload         12
       482: aload         11
       484: iconst_1
       485: invokevirtual #576                // Method dismountPlayer:(Lnet/minecraft/server/level/ServerLevel;Lnet/minecraft/server/level/ServerPlayer;Ljava/lang/Integer;Z)V
       488: goto          376
       491: aload_0
       492: getfield      #54                 // Field this$0:Lcom/simibubi/create/content/trains/entity/Carriage;
       495: getfield      #92                 // Field com/simibubi/create/content/trains/entity/Carriage.serialisedPassengers:Ljava/util/Map;
       498: aload         11
       500: aload         9
       502: invokevirtual #579                // Method net/minecraft/world/entity/Entity.serializeNBT:()Lnet/minecraft/nbt/CompoundTag;
       505: invokeinterface #582,  3          // InterfaceMethod java/util/Map.put:(Ljava/lang/Object;Ljava/lang/Object;)Ljava/lang/Object;
       510: pop
       511: aload         9
       513: invokevirtual #585                // Method net/minecraft/world/entity/Entity.discard:()V
       516: goto          376
       519: return

  private void dismountPlayer(net.minecraft.server.level.ServerLevel, net.minecraft.server.level.ServerPlayer, java.lang.Integer, boolean);
    Code:
         0: iload         4
         2: ifne          10
         5: aload_2
         6: invokevirtual #615                // Method net/minecraft/server/level/ServerPlayer.stopRiding:()V
         9: return
        10: new           #278                // class net/minecraft/nbt/CompoundTag
        13: dup
        14: invokespecial #279                // Method net/minecraft/nbt/CompoundTag."<init>":()V
        17: astore        5
        19: aload         5
        21: ldc_w         #476                // String PlayerPassenger
        24: aload_2
        25: invokevirtual #616                // Method net/minecraft/server/level/ServerPlayer.getUUID:()Ljava/util/UUID;
        28: invokevirtual #620                // Method net/minecraft/nbt/CompoundTag.putUUID:(Ljava/lang/String;Ljava/util/UUID;)V
        31: aload_0
        32: getfield      #54                 // Field this$0:Lcom/simibubi/create/content/trains/entity/Carriage;
        35: getfield      #92                 // Field com/simibubi/create/content/trains/entity/Carriage.serialisedPassengers:Ljava/util/Map;
        38: aload_3
        39: aload         5
        41: invokeinterface #582,  3          // InterfaceMethod java/util/Map.put:(Ljava/lang/Object;Ljava/lang/Object;)Ljava/lang/Object;
        46: pop
        47: aload_2
        48: invokevirtual #615                // Method net/minecraft/server/level/ServerPlayer.stopRiding:()V
        51: aload_2
        52: invokevirtual #623                // Method net/minecraft/server/level/ServerPlayer.getPersistentData:()Lnet/minecraft/nbt/CompoundTag;
        55: ldc_w         #625                // String ContraptionDismountLocation
        58: invokevirtual #628                // Method net/minecraft/nbt/CompoundTag.remove:(Ljava/lang/String;)V
        61: aload_0
        62: getfield      #54                 // Field this$0:Lcom/simibubi/create/content/trains/entity/Carriage;
        65: getfield      #631                // Field com/simibubi/create/content/trains/entity/Carriage.entities:Ljava/util/Map;
        68: invokeinterface #425,  1          // InterfaceMethod java/util/Map.entrySet:()Ljava/util/Set;
        73: invokeinterface #431,  1          // InterfaceMethod java/util/Set.iterator:()Ljava/util/Iterator;
        78: astore        6
        80: aload         6
        82: invokeinterface #436,  1          // InterfaceMethod java/util/Iterator.hasNext:()Z
        87: ifeq          242
        90: aload         6
        92: invokeinterface #439,  1          // InterfaceMethod java/util/Iterator.next:()Ljava/lang/Object;
        97: checkcast     #24                 // class java/util/Map$Entry
       100: astore        7
       102: aload         7
       104: invokeinterface #474,  1          // InterfaceMethod java/util/Map$Entry.getValue:()Ljava/lang/Object;
       109: checkcast     #2                  // class com/simibubi/create/content/trains/entity/Carriage$DimensionalCarriageEntity
       112: astore        8
       114: aload         8
       116: aload_0
       117: if_acmpne     123
       120: goto          80
       123: aload_2
       124: invokevirtual #632                // Method net/minecraft/server/level/ServerPlayer.level:()Lnet/minecraft/world/level/Level;
       127: invokevirtual #520                // Method net/minecraft/world/level/Level.dimension:()Lnet/minecraft/resources/ResourceKey;
       130: aload         7
       132: invokeinterface #442,  1          // InterfaceMethod java/util/Map$Entry.getKey:()Ljava/lang/Object;
       137: invokevirtual #526                // Method net/minecraft/resources/ResourceKey.equals:(Ljava/lang/Object;)Z
       140: ifeq          146
       143: goto          80
       146: aload         8
       148: getfield      #88                 // Field pivot:Lcom/simibubi/create/content/trains/graph/TrackNodeLocation;
       151: ifnonnull     162
       154: aload         8
       156: getfield      #313                // Field positionAnchor:Lnet/minecraft/world/phys/Vec3;
       159: goto          170
       162: aload         8
       164: getfield      #88                 // Field pivot:Lcom/simibubi/create/content/trains/graph/TrackNodeLocation;
       167: invokevirtual #124                // Method com/simibubi/create/content/trains/graph/TrackNodeLocation.getLocation:()Lnet/minecraft/world/phys/Vec3;
       170: astore        9
       172: aload         9
       174: ifnonnull     180
       177: goto          80
       180: aload_1
       181: invokevirtual #480                // Method net/minecraft/server/level/ServerLevel.getServer:()Lnet/minecraft/server/MinecraftServer;
       184: aload         7
       186: invokeinterface #442,  1          // InterfaceMethod java/util/Map$Entry.getKey:()Ljava/lang/Object;
       191: checkcast     #523                // class net/minecraft/resources/ResourceKey
       194: invokevirtual #636                // Method net/minecraft/server/MinecraftServer.getLevel:(Lnet/minecraft/resources/ResourceKey;)Lnet/minecraft/server/level/ServerLevel;
       197: astore        10
       199: aload_2
       200: aload         10
       202: aload         9
       204: getfield      #639                // Field net/minecraft/world/phys/Vec3.x:D
       207: aload         9
       209: getfield      #642                // Field net/minecraft/world/phys/Vec3.y:D
       212: aload         9
       214: getfield      #645                // Field net/minecraft/world/phys/Vec3.z:D
       217: aload_2
       218: invokevirtual #649                // Method net/minecraft/server/level/ServerPlayer.getYRot:()F
       221: aload_2
       222: invokevirtual #652                // Method net/minecraft/server/level/ServerPlayer.getXRot:()F
       225: invokevirtual #656                // Method net/minecraft/server/level/ServerPlayer.teleportTo:(Lnet/minecraft/server/level/ServerLevel;DDDFF)V
       228: aload_2
       229: invokevirtual #659                // Method net/minecraft/server/level/ServerPlayer.setPortalCooldown:()V
       232: getstatic     #665                // Field com/simibubi/create/foundation/advancement/AllAdvancements.TRAIN_PORTAL:Lcom/simibubi/create/foundation/advancement/CreateAdvancement;
       235: aload_2
       236: invokevirtual #671                // Method com/simibubi/create/foundation/advancement/CreateAdvancement.awardTo:(Lnet/minecraft/world/entity/player/Player;)V
       239: goto          80
       242: return

  public void updateRenderedCutoff();
    Code:
         0: aload_0
         1: getfield      #64                 // Field entity:Ljava/lang/ref/WeakReference;
         4: invokevirtual #100                // Method java/lang/ref/WeakReference.get:()Ljava/lang/Object;
         7: checkcast     #410                // class net/minecraft/world/entity/Entity
        10: astore_1
        11: aload_1
        12: instanceof    #412                // class com/simibubi/create/content/trains/entity/CarriageContraptionEntity
        15: ifeq          26
        18: aload_1
        19: checkcast     #412                // class com/simibubi/create/content/trains/entity/CarriageContraptionEntity
        22: astore_2
        23: goto          27
        26: return
        27: aload_2
        28: invokevirtual #448                // Method com/simibubi/create/content/trains/entity/CarriageContraptionEntity.getContraption:()Lcom/simibubi/create/content/contraptions/Contraption;
        31: astore_3
        32: aload_3
        33: instanceof    #678                // class com/simibubi/create/content/trains/entity/CarriageContraption
        36: ifeq          48
        39: aload_3
        40: checkcast     #678                // class com/simibubi/create/content/trains/entity/CarriageContraption
        43: astore        4
        45: goto          49
        48: return
        49: aload         4
        51: aload_0
        52: invokevirtual #81                 // Method minAllowedLocalCoord:()I
        55: putfield      #681                // Field com/simibubi/create/content/trains/entity/CarriageContraption.portalCutoffMin:I
        58: aload         4
        60: aload_0
        61: invokevirtual #84                 // Method maxAllowedLocalCoord:()I
        64: putfield      #684                // Field com/simibubi/create/content/trains/entity/CarriageContraption.portalCutoffMax:I
        67: aload_1
        68: invokevirtual #416                // Method net/minecraft/world/entity/Entity.level:()Lnet/minecraft/world/level/Level;
        71: invokevirtual #687                // Method net/minecraft/world/level/Level.isClientSide:()Z
        74: ifne          78
        77: return
        78: getstatic     #693                // Field net/minecraftforge/api/distmarker/Dist.CLIENT:Lnet/minecraftforge/api/distmarker/Dist;
        81: aload_0
        82: aload_2
        83: invokedynamic #704,  0            // InvokeDynamic #6:get:(Lcom/simibubi/create/content/trains/entity/Carriage$DimensionalCarriageEntity;Lcom/simibubi/create/content/trains/entity/CarriageContraptionEntity;)Ljava/util/function/Supplier;
        88: invokestatic  #710                // Method net/minecraftforge/fml/DistExecutor.unsafeRunWhenOn:(Lnet/minecraftforge/api/distmarker/Dist;Ljava/util/function/Supplier;)V
        91: return

  private void invalidate(com.simibubi.create.content.trains.entity.CarriageContraptionEntity);
    Code:
         0: aload_1
         1: invokevirtual #721                // Method com/simibubi/create/content/trains/entity/CarriageContraptionEntity.updateRenderedPortalCutoff:()V
         4: aload_1
         5: invokevirtual #448                // Method com/simibubi/create/content/trains/entity/CarriageContraptionEntity.getContraption:()Lcom/simibubi/create/content/contraptions/Contraption;
         8: invokevirtual #724                // Method com/simibubi/create/content/contraptions/Contraption.invalidateClientContraptionStructure:()V
        11: aload_1
        12: invokevirtual #448                // Method com/simibubi/create/content/trains/entity/CarriageContraptionEntity.getContraption:()Lcom/simibubi/create/content/contraptions/Contraption;
        15: invokevirtual #727                // Method com/simibubi/create/content/contraptions/Contraption.invalidateClientContraptionChildren:()V
        18: return

  private void createEntity(net.minecraft.world.level.Level, boolean);
    Code:
         0: aload_0
         1: getfield      #313                // Field positionAnchor:Lnet/minecraft/world/phys/Vec3;
         4: ifnull        28
         7: aload_0
         8: getfield      #54                 // Field this$0:Lcom/simibubi/create/content/trains/entity/Carriage;
        11: getfield      #732                // Field com/simibubi/create/content/trains/entity/Carriage.serialisedEntity:Lnet/minecraft/nbt/CompoundTag;
        14: ldc_w         #734                // String Pos
        17: aload_0
        18: getfield      #313                // Field positionAnchor:Lnet/minecraft/world/phys/Vec3;
        21: invokestatic  #321                // Method net/createmod/catnip/math/VecHelper.writeNBT:(Lnet/minecraft/world/phys/Vec3;)Lnet/minecraft/nbt/ListTag;
        24: invokevirtual #311                // Method net/minecraft/nbt/CompoundTag.put:(Ljava/lang/String;Lnet/minecraft/nbt/Tag;)Lnet/minecraft/nbt/Tag;
        27: pop
        28: aload_0
        29: getfield      #54                 // Field this$0:Lcom/simibubi/create/content/trains/entity/Carriage;
        32: getfield      #732                // Field com/simibubi/create/content/trains/entity/Carriage.serialisedEntity:Lnet/minecraft/nbt/CompoundTag;
        35: aload_1
        36: invokestatic  #737                // Method net/minecraft/world/entity/EntityType.create:(Lnet/minecraft/nbt/CompoundTag;Lnet/minecraft/world/level/Level;)Ljava/util/Optional;
        39: aconst_null
        40: invokevirtual #742                // Method java/util/Optional.orElse:(Ljava/lang/Object;)Ljava/lang/Object;
        43: checkcast     #410                // class net/minecraft/world/entity/Entity
        46: astore_3
        47: aload_3
        48: instanceof    #412                // class com/simibubi/create/content/trains/entity/CarriageContraptionEntity
        51: ifeq          63
        54: aload_3
        55: checkcast     #412                // class com/simibubi/create/content/trains/entity/CarriageContraptionEntity
        58: astore        4
        60: goto          75
        63: aload_0
        64: getfield      #54                 // Field this$0:Lcom/simibubi/create/content/trains/entity/Carriage;
        67: getfield      #226                // Field com/simibubi/create/content/trains/entity/Carriage.train:Lcom/simibubi/create/content/trains/entity/Train;
        70: iconst_1
        71: putfield      #745                // Field com/simibubi/create/content/trains/entity/Train.invalid:Z
        74: return
        75: aload_3
        76: aload_0
        77: getfield      #313                // Field positionAnchor:Lnet/minecraft/world/phys/Vec3;
        80: invokevirtual #749                // Method net/minecraft/world/entity/Entity.moveTo:(Lnet/minecraft/world/phys/Vec3;)V
        83: aload_0
        84: new           #59                 // class java/lang/ref/WeakReference
        87: dup
        88: aload         4
        90: invokespecial #62                 // Method java/lang/ref/WeakReference."<init>":(Ljava/lang/Object;)V
        93: putfield      #64                 // Field entity:Ljava/lang/ref/WeakReference;
        96: aload         4
        98: aload_0
        99: getfield      #54                 // Field this$0:Lcom/simibubi/create/content/trains/entity/Carriage;
       102: invokevirtual #752                // Method com/simibubi/create/content/trains/entity/CarriageContraptionEntity.setCarriage:(Lcom/simibubi/create/content/trains/entity/Carriage;)V
       105: aload         4
       107: invokevirtual #755                // Method com/simibubi/create/content/trains/entity/CarriageContraptionEntity.syncCarriage:()V
       110: aload_1
       111: instanceof    #418                // class net/minecraft/server/level/ServerLevel
       114: ifeq          130
       117: aload_1
       118: checkcast     #418                // class net/minecraft/server/level/ServerLevel
       121: astore        5
       123: aload         5
       125: aload_3
       126: invokevirtual #758                // Method net/minecraft/server/level/ServerLevel.addFreshEntity:(Lnet/minecraft/world/entity/Entity;)Z
       129: pop
       130: aload_0
       131: invokevirtual #103                // Method updatePassengerLoadout:()V
       134: return

  private void removeAndSaveEntity(com.simibubi.create.content.trains.entity.CarriageContraptionEntity, boolean);
    Code:
         0: aload_1
         1: invokevirtual #448                // Method com/simibubi/create/content/trains/entity/CarriageContraptionEntity.getContraption:()Lcom/simibubi/create/content/contraptions/Contraption;
         4: astore_3
         5: aload_3
         6: ifnull        138
         9: aload_3
        10: invokevirtual #556                // Method com/simibubi/create/content/contraptions/Contraption.getSeatMapping:()Ljava/util/Map;
        13: astore        4
        15: aload_1
        16: invokevirtual #764                // Method com/simibubi/create/content/trains/entity/CarriageContraptionEntity.getPassengers:()Ljava/util/List;
        19: invokeinterface #560,  1          // InterfaceMethod java/util/List.iterator:()Ljava/util/Iterator;
        24: astore        5
        26: aload         5
        28: invokeinterface #436,  1          // InterfaceMethod java/util/Iterator.hasNext:()Z
        33: ifeq          138
        36: aload         5
        38: invokeinterface #439,  1          // InterfaceMethod java/util/Iterator.next:()Ljava/lang/Object;
        43: checkcast     #410                // class net/minecraft/world/entity/Entity
        46: astore        6
        48: aload         4
        50: aload         6
        52: invokevirtual #563                // Method net/minecraft/world/entity/Entity.getUUID:()Ljava/util/UUID;
        55: invokeinterface #570,  2          // InterfaceMethod java/util/Map.containsKey:(Ljava/lang/Object;)Z
        60: ifne          66
        63: goto          26
        66: aload         4
        68: aload         6
        70: invokevirtual #563                // Method net/minecraft/world/entity/Entity.getUUID:()Ljava/util/UUID;
        73: invokeinterface #572,  2          // InterfaceMethod java/util/Map.get:(Ljava/lang/Object;)Ljava/lang/Object;
        78: checkcast     #444                // class java/lang/Integer
        81: astore        7
        83: aload         6
        85: instanceof    #528                // class net/minecraft/server/level/ServerPlayer
        88: ifeq          115
        91: aload         6
        93: checkcast     #528                // class net/minecraft/server/level/ServerPlayer
        96: astore        8
        98: aload_0
        99: aload         8
       101: invokevirtual #768                // Method net/minecraft/server/level/ServerPlayer.serverLevel:()Lnet/minecraft/server/level/ServerLevel;
       104: aload         8
       106: aload         7
       108: iload_2
       109: invokevirtual #576                // Method dismountPlayer:(Lnet/minecraft/server/level/ServerLevel;Lnet/minecraft/server/level/ServerPlayer;Ljava/lang/Integer;Z)V
       112: goto          26
       115: aload_0
       116: getfield      #54                 // Field this$0:Lcom/simibubi/create/content/trains/entity/Carriage;
       119: getfield      #92                 // Field com/simibubi/create/content/trains/entity/Carriage.serialisedPassengers:Ljava/util/Map;
       122: aload         7
       124: aload         6
       126: invokevirtual #579                // Method net/minecraft/world/entity/Entity.serializeNBT:()Lnet/minecraft/nbt/CompoundTag;
       129: invokeinterface #582,  3          // InterfaceMethod java/util/Map.put:(Ljava/lang/Object;Ljava/lang/Object;)Ljava/lang/Object;
       134: pop
       135: goto          26
       138: aload_1
       139: invokevirtual #764                // Method com/simibubi/create/content/trains/entity/CarriageContraptionEntity.getPassengers:()Ljava/util/List;
       142: invokeinterface #560,  1          // InterfaceMethod java/util/List.iterator:()Ljava/util/Iterator;
       147: astore        4
       149: aload         4
       151: invokeinterface #436,  1          // InterfaceMethod java/util/Iterator.hasNext:()Z
       156: ifeq          187
       159: aload         4
       161: invokeinterface #439,  1          // InterfaceMethod java/util/Iterator.next:()Ljava/lang/Object;
       166: checkcast     #410                // class net/minecraft/world/entity/Entity
       169: astore        5
       171: aload         5
       173: instanceof    #770                // class net/minecraft/world/entity/player/Player
       176: ifne          184
       179: aload         5
       181: invokevirtual #585                // Method net/minecraft/world/entity/Entity.discard:()V
       184: goto          149
       187: aload_0
       188: getfield      #54                 // Field this$0:Lcom/simibubi/create/content/trains/entity/Carriage;
       191: aload_1
       192: invokevirtual #774                // Method com/simibubi/create/content/trains/entity/Carriage.serialize:(Lnet/minecraft/world/entity/Entity;)V
       195: aload_1
       196: invokevirtual #775                // Method com/simibubi/create/content/trains/entity/CarriageContraptionEntity.discard:()V
       199: aload_0
       200: getfield      #64                 // Field entity:Ljava/lang/ref/WeakReference;
       203: invokevirtual #778                // Method java/lang/ref/WeakReference.clear:()V
       206: return

  public void alignEntity(com.simibubi.create.content.trains.entity.CarriageContraptionEntity);
    Code:
         0: aload_0
         1: getfield      #72                 // Field rotationAnchors:Lnet/createmod/catnip/data/Couple;
         4: invokedynamic #785,  0            // InvokeDynamic #7:test:()Ljava/util/function/Predicate;
         9: invokevirtual #788                // Method net/createmod/catnip/data/Couple.either:(Ljava/util/function/Predicate;)Z
        12: ifeq          16
        15: return
        16: aload_0
        17: getfield      #72                 // Field rotationAnchors:Lnet/createmod/catnip/data/Couple;
        20: invokevirtual #113                // Method net/createmod/catnip/data/Couple.getFirst:()Ljava/lang/Object;
        23: checkcast     #115                // class net/minecraft/world/phys/Vec3
        26: astore_2
        27: aload_0
        28: getfield      #72                 // Field rotationAnchors:Lnet/createmod/catnip/data/Couple;
        31: invokevirtual #118                // Method net/createmod/catnip/data/Couple.getSecond:()Ljava/lang/Object;
        34: checkcast     #115                // class net/minecraft/world/phys/Vec3
        37: astore_3
        38: aload_2
        39: getfield      #639                // Field net/minecraft/world/phys/Vec3.x:D
        42: aload_3
        43: getfield      #639                // Field net/minecraft/world/phys/Vec3.x:D
        46: dsub
        47: dstore        4
        49: aload_2
        50: getfield      #642                // Field net/minecraft/world/phys/Vec3.y:D
        53: aload_3
        54: getfield      #642                // Field net/minecraft/world/phys/Vec3.y:D
        57: dsub
        58: dstore        6
        60: aload_2
        61: getfield      #645                // Field net/minecraft/world/phys/Vec3.z:D
        64: aload_3
        65: getfield      #645                // Field net/minecraft/world/phys/Vec3.z:D
        68: dsub
        69: dstore        8
        71: aload_1
        72: aload_1
        73: getfield      #791                // Field com/simibubi/create/content/trains/entity/CarriageContraptionEntity.yaw:F
        76: putfield      #794                // Field com/simibubi/create/content/trains/entity/CarriageContraptionEntity.prevYaw:F
        79: aload_1
        80: aload_1
        81: getfield      #797                // Field com/simibubi/create/content/trains/entity/CarriageContraptionEntity.pitch:F
        84: putfield      #800                // Field com/simibubi/create/content/trains/entity/CarriageContraptionEntity.prevPitch:F
        87: aload_1
        88: invokevirtual #801                // Method com/simibubi/create/content/trains/entity/CarriageContraptionEntity.level:()Lnet/minecraft/world/level/Level;
        91: invokevirtual #687                // Method net/minecraft/world/level/Level.isClientSide:()Z
        94: ifne          279
        97: aload_0
        98: getfield      #313                // Field positionAnchor:Lnet/minecraft/world/phys/Vec3;
       101: aload_0
       102: getfield      #313                // Field positionAnchor:Lnet/minecraft/world/phys/Vec3;
       105: aload_1
       106: invokevirtual #803                // Method com/simibubi/create/content/trains/entity/CarriageContraptionEntity.position:()Lnet/minecraft/world/phys/Vec3;
       109: invokevirtual #159                // Method net/minecraft/world/phys/Vec3.subtract:(Lnet/minecraft/world/phys/Vec3;)Lnet/minecraft/world/phys/Vec3;
       112: invokevirtual #162                // Method net/minecraft/world/phys/Vec3.normalize:()Lnet/minecraft/world/phys/Vec3;
       115: ldc2_w        #804                // double 16.0d
       118: invokevirtual #166                // Method net/minecraft/world/phys/Vec3.scale:(D)Lnet/minecraft/world/phys/Vec3;
       121: invokevirtual #168                // Method net/minecraft/world/phys/Vec3.add:(Lnet/minecraft/world/phys/Vec3;)Lnet/minecraft/world/phys/Vec3;
       124: astore        10
       126: aload_1
       127: invokevirtual #764                // Method com/simibubi/create/content/trains/entity/CarriageContraptionEntity.getPassengers:()Ljava/util/List;
       130: invokeinterface #560,  1          // InterfaceMethod java/util/List.iterator:()Ljava/util/Iterator;
       135: astore        11
       137: aload         11
       139: invokeinterface #436,  1          // InterfaceMethod java/util/Iterator.hasNext:()Z
       144: ifeq          222
       147: aload         11
       149: invokeinterface #439,  1          // InterfaceMethod java/util/Iterator.next:()Ljava/lang/Object;
       154: checkcast     #410                // class net/minecraft/world/entity/Entity
       157: astore        12
       159: aload         12
       161: instanceof    #770                // class net/minecraft/world/entity/player/Player
       164: ifne          170
       167: goto          137
       170: aload         12
       172: aload_1
       173: invokevirtual #809                // Method net/minecraft/world/entity/Entity.distanceToSqr:(Lnet/minecraft/world/entity/Entity;)D
       176: ldc2_w        #810                // double 1024.0d
       179: dcmpl
       180: ifle          186
       183: goto          137
       186: aload_1
       187: invokevirtual #801                // Method com/simibubi/create/content/trains/entity/CarriageContraptionEntity.level:()Lnet/minecraft/world/level/Level;
       190: aload         10
       192: invokestatic  #815                // Method net/minecraft/core/BlockPos.containing:(Lnet/minecraft/core/Position;)Lnet/minecraft/core/BlockPos;
       195: invokestatic  #821                // Method com/simibubi/create/content/trains/entity/CarriageEntityHandler.isActiveChunk:(Lnet/minecraft/world/level/Level;Lnet/minecraft/core/BlockPos;)Z
       198: ifeq          204
       201: goto          222
       204: aload_0
       205: getfield      #54                 // Field this$0:Lcom/simibubi/create/content/trains/entity/Carriage;
       208: getfield      #226                // Field com/simibubi/create/content/trains/entity/Carriage.train:Lcom/simibubi/create/content/trains/entity/Train;
       211: aload_0
       212: getfield      #54                 // Field this$0:Lcom/simibubi/create/content/trains/entity/Carriage;
       215: getfield      #824                // Field com/simibubi/create/content/trains/entity/Carriage.id:I
       218: putfield      #827                // Field com/simibubi/create/content/trains/entity/Train.carriageWaitingForChunks:I
       221: return
       222: aload_1
       223: invokevirtual #764                // Method com/simibubi/create/content/trains/entity/CarriageContraptionEntity.getPassengers:()Ljava/util/List;
       226: invokeinterface #831,  1          // InterfaceMethod java/util/List.stream:()Ljava/util/stream/Stream;
       231: invokedynamic #837,  0            // InvokeDynamic #8:test:()Ljava/util/function/Predicate;
       236: invokeinterface #842,  2          // InterfaceMethod java/util/stream/Stream.anyMatch:(Ljava/util/function/Predicate;)Z
       241: ifeq          244
       244: aload_0
       245: getfield      #54                 // Field this$0:Lcom/simibubi/create/content/trains/entity/Carriage;
       248: getfield      #226                // Field com/simibubi/create/content/trains/entity/Carriage.train:Lcom/simibubi/create/content/trains/entity/Train;
       251: getfield      #827                // Field com/simibubi/create/content/trains/entity/Train.carriageWaitingForChunks:I
       254: aload_0
       255: getfield      #54                 // Field this$0:Lcom/simibubi/create/content/trains/entity/Carriage;
       258: getfield      #824                // Field com/simibubi/create/content/trains/entity/Carriage.id:I
       261: if_icmpne     275
       264: aload_0
       265: getfield      #54                 // Field this$0:Lcom/simibubi/create/content/trains/entity/Carriage;
       268: getfield      #226                // Field com/simibubi/create/content/trains/entity/Carriage.train:Lcom/simibubi/create/content/trains/entity/Train;
       271: iconst_m1
       272: putfield      #827                // Field com/simibubi/create/content/trains/entity/Train.carriageWaitingForChunks:I
       275: aload_1
       276: invokevirtual #845                // Method com/simibubi/create/content/trains/entity/CarriageContraptionEntity.setServerSidePrevPosition:()V
       279: aload_1
       280: aload_0
       281: getfield      #313                // Field positionAnchor:Lnet/minecraft/world/phys/Vec3;
       284: invokevirtual #848                // Method com/simibubi/create/content/trains/entity/CarriageContraptionEntity.setPos:(Lnet/minecraft/world/phys/Vec3;)V
       287: aload_1
       288: dload         8
       290: dload         4
       292: invokestatic  #852                // Method net/minecraft/util/Mth.atan2:(DD)D
       295: ldc2_w        #853                // double 180.0d
       298: dmul
       299: ldc2_w        #855                // double 3.141592653589793d
       302: ddiv
       303: d2f
       304: ldc_w         #857                // float 180.0f
       307: fadd
       308: putfield      #791                // Field com/simibubi/create/content/trains/entity/CarriageContraptionEntity.yaw:F
       311: aload_1
       312: dload         6
       314: dload         4
       316: dload         4
       318: dmul
       319: dload         8
       321: dload         8
       323: dmul
       324: dadd
       325: invokestatic  #863                // Method java/lang/Math.sqrt:(D)D
       328: invokestatic  #864                // Method java/lang/Math.atan2:(DD)D
       331: ldc2_w        #853                // double 180.0d
       334: dmul
       335: ldc2_w        #855                // double 3.141592653589793d
       338: ddiv
       339: d2f
       340: ldc           #173                // float -1.0f
       342: fmul
       343: putfield      #797                // Field com/simibubi/create/content/trains/entity/CarriageContraptionEntity.pitch:F
       346: aload_1
       347: getfield      #867                // Field com/simibubi/create/content/trains/entity/CarriageContraptionEntity.firstPositionUpdate:Z
       350: ifne          354
       353: return
       354: aload_1
       355: aload_1
       356: invokevirtual #870                // Method com/simibubi/create/content/trains/entity/CarriageContraptionEntity.getX:()D
       359: putfield      #873                // Field com/simibubi/create/content/trains/entity/CarriageContraptionEntity.xo:D
       362: aload_1
       363: aload_1
       364: invokevirtual #876                // Method com/simibubi/create/content/trains/entity/CarriageContraptionEntity.getY:()D
       367: putfield      #879                // Field com/simibubi/create/content/trains/entity/CarriageContraptionEntity.yo:D
       370: aload_1
       371: aload_1
       372: invokevirtual #882                // Method com/simibubi/create/content/trains/entity/CarriageContraptionEntity.getZ:()D
       375: putfield      #885                // Field com/simibubi/create/content/trains/entity/CarriageContraptionEntity.zo:D
       378: aload_1
       379: aload_1
       380: getfield      #791                // Field com/simibubi/create/content/trains/entity/CarriageContraptionEntity.yaw:F
       383: putfield      #794                // Field com/simibubi/create/content/trains/entity/CarriageContraptionEntity.prevYaw:F
       386: aload_1
       387: aload_1
       388: getfield      #797                // Field com/simibubi/create/content/trains/entity/CarriageContraptionEntity.pitch:F
       391: putfield      #800                // Field com/simibubi/create/content/trains/entity/CarriageContraptionEntity.prevPitch:F
       394: return

  private static boolean lambda$alignEntity$4(net.minecraft.world.entity.Entity);
    Code:
         0: aload_0
         1: instanceof    #770                // class net/minecraft/world/entity/player/Player
         4: ireturn

  private java.lang.Runnable lambda$updateRenderedCutoff$3(com.simibubi.create.content.trains.entity.CarriageContraptionEntity);
    Code:
         0: aload_0
         1: aload_1
         2: invokedynamic #902,  0            // InvokeDynamic #9:run:(Lcom/simibubi/create/content/trains/entity/Carriage$DimensionalCarriageEntity;Lcom/simibubi/create/content/trains/entity/CarriageContraptionEntity;)Ljava/lang/Runnable;
         7: areturn

  private void lambda$updateRenderedCutoff$2(com.simibubi.create.content.trains.entity.CarriageContraptionEntity);
    Code:
         0: aload_0
         1: aload_1
         2: invokevirtual #904                // Method invalidate:(Lcom/simibubi/create/content/trains/entity/CarriageContraptionEntity;)V
         5: return

  private net.minecraft.world.entity.Entity lambda$updatePassengerLoadout$1(net.minecraft.world.entity.Entity);
    Code:
         0: aload_1
         1: aload_0
         2: getfield      #313                // Field positionAnchor:Lnet/minecraft/world/phys/Vec3;
         5: invokevirtual #749                // Method net/minecraft/world/entity/Entity.moveTo:(Lnet/minecraft/world/phys/Vec3;)V
         8: aload_1
         9: areturn

  private boolean lambda$findPivot$0(net.minecraft.resources.ResourceKey, net.createmod.catnip.data.Couple);
    Code:
         0: getstatic     #910                // Field net/createmod/catnip/data/Iterate.trueAndFalse:[Z
         3: astore_3
         4: aload_3
         5: arraylength
         6: istore        4
         8: iconst_0
         9: istore        5
        11: iload         5
        13: iload         4
        15: if_icmpge     62
        18: aload_3
        19: iload         5
        21: baload
        22: istore        6
        24: aload_2
        25: iload         6
        27: invokevirtual #914                // Method net/createmod/catnip/data/Couple.get:(Z)Ljava/lang/Object;
        30: checkcast     #120                // class com/simibubi/create/content/trains/graph/TrackNodeLocation
        33: getfield      #916                // Field com/simibubi/create/content/trains/graph/TrackNodeLocation.dimension:Lnet/minecraft/resources/ResourceKey;
        36: aload_1
        37: invokevirtual #526                // Method net/minecraft/resources/ResourceKey.equals:(Ljava/lang/Object;)Z
        40: ifeq          56
        43: aload_0
        44: aload_2
        45: iload         6
        47: invokevirtual #914                // Method net/createmod/catnip/data/Couple.get:(Z)Ljava/lang/Object;
        50: checkcast     #120                // class com/simibubi/create/content/trains/graph/TrackNodeLocation
        53: putfield      #88                 // Field pivot:Lcom/simibubi/create/content/trains/graph/TrackNodeLocation;
        56: iinc          5, 1
        59: goto          11
        62: iconst_1
        63: ireturn
}
