Compiled from "Train.java"
public class com.simibubi.create.content.trains.entity.Train {
  public double speed;

  public double targetSpeed;

  public java.lang.Double speedBeforeStall;

  public int carriageWaitingForChunks;

  public double throttle;

  public boolean honk;

  public java.util.UUID id;

  public java.util.UUID owner;

  public com.simibubi.create.content.trains.graph.TrackGraph graph;

  public com.simibubi.create.content.trains.entity.Navigation navigation;

  public com.simibubi.create.content.trains.schedule.ScheduleRuntime runtime;

  public com.simibubi.create.content.trains.entity.TrainIconType icon;

  public int mapColorIndex;

  public net.minecraft.network.chat.Component name;

  public com.simibubi.create.content.trains.entity.TrainStatus status;

  public boolean invalid;

  public com.simibubi.create.content.trains.entity.TravellingPoint$SteerDirection manualSteer;

  public boolean manualTick;

  public java.util.UUID currentStation;

  public boolean currentlyBackwards;

  public boolean doubleEnded;

  public java.util.List<com.simibubi.create.content.trains.entity.Carriage> carriages;

  public java.util.List<java.lang.Integer> carriageSpacing;

  public boolean updateSignalBlocks;

  public java.util.Map<java.util.UUID, java.util.UUID> occupiedSignalBlocks;

  public java.util.Set<java.util.UUID> reservedSignalBlocks;

  public java.util.Set<java.util.UUID> occupiedObservers;

  public java.util.Map<java.util.UUID, net.createmod.catnip.data.Pair<java.lang.Integer, java.lang.Boolean>> cachedObserverFiltering;

  java.util.List<com.simibubi.create.content.trains.entity.TrainMigration> migratingPoints;

  public int migrationCooldown;

  public boolean derailed;

  public int fuelTicks;

  public int honkTicks;

  public java.lang.Boolean lowHonk;

  public int honkPitch;

  public float accumulatedSteamRelease;

  int tickOffset;

  int ticksSinceLastMailTransfer;

  double[] stress;

  public net.minecraft.world.entity.player.Player backwardsDriver;

  public com.simibubi.create.content.trains.entity.Train(java.util.UUID, java.util.UUID, com.simibubi.create.content.trains.graph.TrackGraph, java.util.List<com.simibubi.create.content.trains.entity.Carriage>, java.util.List<java.lang.Integer>, boolean);
    Code:
         0: aload_0
         1: invokespecial #157                // Method java/lang/Object."<init>":()V
         4: aload_0
         5: dconst_0
         6: putfield      #159                // Field speed:D
         9: aload_0
        10: dconst_0
        11: putfield      #161                // Field targetSpeed:D
        14: aload_0
        15: aconst_null
        16: putfield      #163                // Field speedBeforeStall:Ljava/lang/Double;
        19: aload_0
        20: iconst_m1
        21: putfield      #165                // Field carriageWaitingForChunks:I
        24: aload_0
        25: dconst_1
        26: putfield      #167                // Field throttle:D
        29: aload_0
        30: iconst_0
        31: putfield      #169                // Field honk:Z
        34: aload_0
        35: aload_1
        36: putfield      #171                // Field id:Ljava/util/UUID;
        39: aload_0
        40: aload_2
        41: putfield      #173                // Field owner:Ljava/util/UUID;
        44: aload_0
        45: aload_3
        46: putfield      #175                // Field graph:Lcom/simibubi/create/content/trains/graph/TrackGraph;
        49: aload_0
        50: aload         4
        52: putfield      #177                // Field carriages:Ljava/util/List;
        55: aload_0
        56: aload         5
        58: putfield      #179                // Field carriageSpacing:Ljava/util/List;
        61: aload_0
        62: invokestatic  #185                // Method com/simibubi/create/content/trains/entity/TrainIconType.getDefault:()Lcom/simibubi/create/content/trains/entity/TrainIconType;
        65: putfield      #187                // Field icon:Lcom/simibubi/create/content/trains/entity/TrainIconType;
        68: aload_0
        69: aload         5
        71: invokeinterface #193,  1          // InterfaceMethod java/util/List.size:()I
        76: newarray       double
        78: putfield      #195                // Field stress:[D
        81: aload_0
        82: ldc           #197                // String train.unnamed
        84: iconst_0
        85: anewarray     #4                  // class java/lang/Object
        88: invokestatic  #203                // Method com/simibubi/create/foundation/utility/CreateLang.translateDirect:(Ljava/lang/String;[Ljava/lang/Object;)Lnet/minecraft/network/chat/MutableComponent;
        91: putfield      #205                // Field name:Lnet/minecraft/network/chat/Component;
        94: aload_0
        95: new           #207                // class com/simibubi/create/content/trains/entity/TrainStatus
        98: dup
        99: aload_0
       100: invokespecial #210                // Method com/simibubi/create/content/trains/entity/TrainStatus."<init>":(Lcom/simibubi/create/content/trains/entity/Train;)V
       103: putfield      #212                // Field status:Lcom/simibubi/create/content/trains/entity/TrainStatus;
       106: aload_0
       107: iload         6
       109: putfield      #214                // Field doubleEnded:Z
       112: aload         4
       114: aload_0
       115: invokedynamic #233,  0            // InvokeDynamic #0:accept:(Lcom/simibubi/create/content/trains/entity/Train;)Ljava/util/function/Consumer;
       120: invokeinterface #237,  2          // InterfaceMethod java/util/List.forEach:(Ljava/util/function/Consumer;)V
       125: aload_0
       126: new           #239                // class com/simibubi/create/content/trains/entity/Navigation
       129: dup
       130: aload_0
       131: invokespecial #240                // Method com/simibubi/create/content/trains/entity/Navigation."<init>":(Lcom/simibubi/create/content/trains/entity/Train;)V
       134: putfield      #242                // Field navigation:Lcom/simibubi/create/content/trains/entity/Navigation;
       137: aload_0
       138: new           #59                 // class com/simibubi/create/content/trains/schedule/ScheduleRuntime
       141: dup
       142: aload_0
       143: invokespecial #243                // Method com/simibubi/create/content/trains/schedule/ScheduleRuntime."<init>":(Lcom/simibubi/create/content/trains/entity/Train;)V
       146: putfield      #245                // Field runtime:Lcom/simibubi/create/content/trains/schedule/ScheduleRuntime;
       149: aload_0
       150: new           #247                // class java/util/ArrayList
       153: dup
       154: invokespecial #248                // Method java/util/ArrayList."<init>":()V
       157: putfield      #250                // Field migratingPoints:Ljava/util/List;
       160: aload_0
       161: aconst_null
       162: putfield      #252                // Field currentStation:Ljava/util/UUID;
       165: aload_0
       166: getstatic     #255                // Field com/simibubi/create/content/trains/entity/TravellingPoint$SteerDirection.NONE:Lcom/simibubi/create/content/trains/entity/TravellingPoint$SteerDirection;
       169: putfield      #257                // Field manualSteer:Lcom/simibubi/create/content/trains/entity/TravellingPoint$SteerDirection;
       172: aload_0
       173: new           #259                // class java/util/HashMap
       176: dup
       177: invokespecial #260                // Method java/util/HashMap."<init>":()V
       180: putfield      #262                // Field occupiedSignalBlocks:Ljava/util/Map;
       183: aload_0
       184: new           #264                // class java/util/HashSet
       187: dup
       188: invokespecial #265                // Method java/util/HashSet."<init>":()V
       191: putfield      #267                // Field reservedSignalBlocks:Ljava/util/Set;
       194: aload_0
       195: new           #264                // class java/util/HashSet
       198: dup
       199: invokespecial #265                // Method java/util/HashSet."<init>":()V
       202: putfield      #269                // Field occupiedObservers:Ljava/util/Set;
       205: aload_0
       206: new           #259                // class java/util/HashMap
       209: dup
       210: invokespecial #260                // Method java/util/HashMap."<init>":()V
       213: putfield      #271                // Field cachedObserverFiltering:Ljava/util/Map;
       216: aload_0
       217: getstatic     #277                // Field com/simibubi/create/Create.RANDOM:Ljava/util/Random;
       220: bipush        100
       222: invokevirtual #283                // Method java/util/Random.nextInt:(I)I
       225: putfield      #285                // Field tickOffset:I
       228: return

  public void earlyTick(net.minecraft.world.level.Level);
    Code:
         0: aload_0
         1: getfield      #212                // Field status:Lcom/simibubi/create/content/trains/entity/TrainStatus;
         4: aload_1
         5: invokevirtual #292                // Method com/simibubi/create/content/trains/entity/TrainStatus.tick:(Lnet/minecraft/world/level/Level;)V
         8: aload_0
         9: getfield      #175                // Field graph:Lcom/simibubi/create/content/trains/graph/TrackGraph;
        12: ifnonnull     32
        15: aload_0
        16: getfield      #250                // Field migratingPoints:Ljava/util/List;
        19: invokeinterface #296,  1          // InterfaceMethod java/util/List.isEmpty:()Z
        24: ifne          32
        27: aload_0
        28: aload_1
        29: invokevirtual #299                // Method reattachToTracks:(Lnet/minecraft/world/level/Level;)V
        32: aload_0
        33: getfield      #175                // Field graph:Lcom/simibubi/create/content/trains/graph/TrackGraph;
        36: ifnonnull     53
        39: aload_0
        40: aload_0
        41: getfield      #262                // Field occupiedSignalBlocks:Ljava/util/Map;
        44: invokeinterface #303,  1          // InterfaceMethod java/util/Map.keySet:()Ljava/util/Set;
        49: invokevirtual #307                // Method addToSignalGroups:(Ljava/util/Collection;)V
        52: return
        53: aload_0
        54: getfield      #309                // Field updateSignalBlocks:Z
        57: ifeq          69
        60: aload_0
        61: iconst_0
        62: putfield      #309                // Field updateSignalBlocks:Z
        65: aload_0
        66: invokevirtual #312                // Method collectInitiallyOccupiedSignalBlocks:()V
        69: aload_0
        70: aload_0
        71: getfield      #262                // Field occupiedSignalBlocks:Ljava/util/Map;
        74: invokeinterface #303,  1          // InterfaceMethod java/util/Map.keySet:()Ljava/util/Set;
        79: invokevirtual #307                // Method addToSignalGroups:(Ljava/util/Collection;)V
        82: aload_0
        83: aload_0
        84: getfield      #267                // Field reservedSignalBlocks:Ljava/util/Set;
        87: invokevirtual #307                // Method addToSignalGroups:(Ljava/util/Collection;)V
        90: aload_0
        91: getfield      #269                // Field occupiedObservers:Ljava/util/Set;
        94: invokeinterface #315,  1          // InterfaceMethod java/util/Set.isEmpty:()Z
        99: ifeq          103
       102: return
       103: aload_0
       104: aload_1
       105: invokevirtual #318                // Method tickOccupiedObservers:(Lnet/minecraft/world/level/Level;)V
       108: return

  private void tickOccupiedObservers(net.minecraft.world.level.Level);
    Code:
         0: iconst_0
         1: istore_2
         2: aload_0
         3: getfield      #177                // Field carriages:Ljava/util/List;
         6: invokeinterface #324,  1          // InterfaceMethod java/util/List.iterator:()Ljava/util/Iterator;
        11: astore_3
        12: aload_3
        13: invokeinterface #329,  1          // InterfaceMethod java/util/Iterator.hasNext:()Z
        18: ifeq          46
        21: aload_3
        22: invokeinterface #333,  1          // InterfaceMethod java/util/Iterator.next:()Ljava/lang/Object;
        27: checkcast     #21                 // class com/simibubi/create/content/trains/entity/Carriage
        30: astore        4
        32: iload_2
        33: aload         4
        35: getfield      #337                // Field com/simibubi/create/content/trains/entity/Carriage.storage:Lcom/simibubi/create/content/contraptions/minecart/TrainCargoManager;
        38: invokevirtual #342                // Method com/simibubi/create/content/contraptions/minecart/TrainCargoManager.getVersion:()I
        41: iadd
        42: istore_2
        43: goto          12
        46: aload_0
        47: getfield      #269                // Field occupiedObservers:Ljava/util/Set;
        50: invokeinterface #343,  1          // InterfaceMethod java/util/Set.iterator:()Ljava/util/Iterator;
        55: astore_3
        56: aload_3
        57: invokeinterface #329,  1          // InterfaceMethod java/util/Iterator.hasNext:()Z
        62: ifeq          435
        65: aload_3
        66: invokeinterface #333,  1          // InterfaceMethod java/util/Iterator.next:()Ljava/lang/Object;
        71: checkcast     #345                // class java/util/UUID
        74: astore        4
        76: aload_0
        77: getfield      #175                // Field graph:Lcom/simibubi/create/content/trains/graph/TrackGraph;
        80: getstatic     #351                // Field com/simibubi/create/content/trains/graph/EdgePointType.OBSERVER:Lcom/simibubi/create/content/trains/graph/EdgePointType;
        83: aload         4
        85: invokevirtual #357                // Method com/simibubi/create/content/trains/graph/TrackGraph.getPoint:(Lcom/simibubi/create/content/trains/graph/EdgePointType;Ljava/util/UUID;)Lcom/simibubi/create/content/trains/signal/TrackEdgePoint;
        88: checkcast     #359                // class com/simibubi/create/content/trains/observer/TrackObserver
        91: astore        5
        93: aload         5
        95: ifnonnull     101
        98: goto          56
       101: aload         5
       103: invokevirtual #363                // Method com/simibubi/create/content/trains/observer/TrackObserver.getFilter:()Lcom/simibubi/create/content/logistics/filter/FilterItemStack;
       106: astore        6
       108: aload         6
       110: invokevirtual #366                // Method com/simibubi/create/content/logistics/filter/FilterItemStack.isEmpty:()Z
       113: ifeq          125
       116: aload         5
       118: aload_0
       119: invokevirtual #369                // Method com/simibubi/create/content/trains/observer/TrackObserver.keepAlive:(Lcom/simibubi/create/content/trains/entity/Train;)V
       122: goto          56
       125: aload_0
       126: getfield      #271                // Field cachedObserverFiltering:Ljava/util/Map;
       129: aload         4
       131: invokedynamic #381,  0            // InvokeDynamic #1:apply:()Ljava/util/function/Function;
       136: invokeinterface #385,  3          // InterfaceMethod java/util/Map.computeIfAbsent:(Ljava/lang/Object;Ljava/util/function/Function;)Ljava/lang/Object;
       141: checkcast     #387                // class net/createmod/catnip/data/Pair
       144: astore        7
       146: aload         7
       148: invokevirtual #390                // Method net/createmod/catnip/data/Pair.getSecond:()Ljava/lang/Object;
       151: checkcast     #392                // class java/lang/Boolean
       154: invokevirtual #395                // Method java/lang/Boolean.booleanValue:()Z
       157: istore        8
       159: aload         7
       161: invokevirtual #398                // Method net/createmod/catnip/data/Pair.getFirst:()Ljava/lang/Object;
       164: checkcast     #400                // class java/lang/Integer
       167: invokevirtual #403                // Method java/lang/Integer.intValue:()I
       170: iload_2
       171: if_icmpne     188
       174: iload         8
       176: ifeq          56
       179: aload         5
       181: aload_0
       182: invokevirtual #369                // Method com/simibubi/create/content/trains/observer/TrackObserver.keepAlive:(Lcom/simibubi/create/content/trains/entity/Train;)V
       185: goto          56
       188: iconst_0
       189: istore        8
       191: aload_0
       192: getfield      #177                // Field carriages:Ljava/util/List;
       195: invokeinterface #324,  1          // InterfaceMethod java/util/List.iterator:()Ljava/util/Iterator;
       200: astore        9
       202: aload         9
       204: invokeinterface #329,  1          // InterfaceMethod java/util/Iterator.hasNext:()Z
       209: ifeq          397
       212: aload         9
       214: invokeinterface #333,  1          // InterfaceMethod java/util/Iterator.next:()Ljava/lang/Object;
       219: checkcast     #21                 // class com/simibubi/create/content/trains/entity/Carriage
       222: astore        10
       224: iload         8
       226: ifeq          232
       229: goto          397
       232: aload         10
       234: getfield      #337                // Field com/simibubi/create/content/trains/entity/Carriage.storage:Lcom/simibubi/create/content/contraptions/minecart/TrainCargoManager;
       237: invokevirtual #407                // Method com/simibubi/create/content/contraptions/minecart/TrainCargoManager.getAllItems:()Lnet/minecraftforge/items/wrapper/CombinedInvWrapper;
       240: astore        11
       242: aload         11
       244: ifnull        313
       247: iconst_0
       248: istore        12
       250: iload         12
       252: aload         11
       254: invokeinterface #412,  1          // InterfaceMethod net/minecraftforge/items/IItemHandlerModifiable.getSlots:()I
       259: if_icmpge     313
       262: iload         8
       264: ifeq          270
       267: goto          313
       270: aload         11
       272: iload         12
       274: iconst_1
       275: iconst_1
       276: invokeinterface #416,  4          // InterfaceMethod net/minecraftforge/items/IItemHandlerModifiable.extractItem:(IIZ)Lnet/minecraft/world/item/ItemStack;
       281: astore        13
       283: aload         13
       285: invokevirtual #419                // Method net/minecraft/world/item/ItemStack.isEmpty:()Z
       288: ifeq          294
       291: goto          307
       294: iload         8
       296: aload         6
       298: aload_1
       299: aload         13
       301: invokevirtual #423                // Method com/simibubi/create/content/logistics/filter/FilterItemStack.test:(Lnet/minecraft/world/level/Level;Lnet/minecraft/world/item/ItemStack;)Z
       304: ior
       305: istore        8
       307: iinc          12, 1
       310: goto          250
       313: aload         10
       315: getfield      #337                // Field com/simibubi/create/content/trains/entity/Carriage.storage:Lcom/simibubi/create/content/contraptions/minecart/TrainCargoManager;
       318: invokevirtual #427                // Method com/simibubi/create/content/contraptions/minecart/TrainCargoManager.getFluids:()Lcom/simibubi/create/api/contraption/storage/fluid/MountedFluidStorageWrapper;
       321: astore        12
       323: aload         12
       325: ifnull        394
       328: iconst_0
       329: istore        13
       331: iload         13
       333: aload         12
       335: invokeinterface #430,  1          // InterfaceMethod net/minecraftforge/fluids/capability/IFluidHandler.getTanks:()I
       340: if_icmpge     394
       343: iload         8
       345: ifeq          351
       348: goto          394
       351: aload         12
       353: iconst_1
       354: getstatic     #434                // Field net/minecraftforge/fluids/capability/IFluidHandler$FluidAction.SIMULATE:Lnet/minecraftforge/fluids/capability/IFluidHandler$FluidAction;
       357: invokeinterface #438,  3          // InterfaceMethod net/minecraftforge/fluids/capability/IFluidHandler.drain:(ILnet/minecraftforge/fluids/capability/IFluidHandler$FluidAction;)Lnet/minecraftforge/fluids/FluidStack;
       362: astore        14
       364: aload         14
       366: invokevirtual #441                // Method net/minecraftforge/fluids/FluidStack.isEmpty:()Z
       369: ifeq          375
       372: goto          388
       375: iload         8
       377: aload         6
       379: aload_1
       380: aload         14
       382: invokevirtual #444                // Method com/simibubi/create/content/logistics/filter/FilterItemStack.test:(Lnet/minecraft/world/level/Level;Lnet/minecraftforge/fluids/FluidStack;)Z
       385: ior
       386: istore        8
       388: iinc          13, 1
       391: goto          331
       394: goto          202
       397: aload_0
       398: getfield      #271                // Field cachedObserverFiltering:Ljava/util/Map;
       401: aload         4
       403: iload_2
       404: invokestatic  #448                // Method java/lang/Integer.valueOf:(I)Ljava/lang/Integer;
       407: iload         8
       409: invokestatic  #451                // Method java/lang/Boolean.valueOf:(Z)Ljava/lang/Boolean;
       412: invokestatic  #455                // Method net/createmod/catnip/data/Pair.of:(Ljava/lang/Object;Ljava/lang/Object;)Lnet/createmod/catnip/data/Pair;
       415: invokeinterface #459,  3          // InterfaceMethod java/util/Map.put:(Ljava/lang/Object;Ljava/lang/Object;)Ljava/lang/Object;
       420: pop
       421: iload         8
       423: ifeq          432
       426: aload         5
       428: aload_0
       429: invokevirtual #369                // Method com/simibubi/create/content/trains/observer/TrackObserver.keepAlive:(Lcom/simibubi/create/content/trains/entity/Train;)V
       432: goto          56
       435: return

  private void addToSignalGroups(java.util.Collection<java.util.UUID>);
    Code:
         0: getstatic     #483                // Field com/simibubi/create/Create.RAILWAYS:Lcom/simibubi/create/content/trains/GlobalRailwayManager;
         3: getfield      #488                // Field com/simibubi/create/content/trains/GlobalRailwayManager.signalEdgeGroups:Ljava/util/Map;
         6: astore_2
         7: aload_1
         8: invokeinterface #491,  1          // InterfaceMethod java/util/Collection.iterator:()Ljava/util/Iterator;
        13: astore_3
        14: aload_3
        15: invokeinterface #329,  1          // InterfaceMethod java/util/Iterator.hasNext:()Z
        20: ifeq          69
        23: aload_2
        24: aload_3
        25: invokeinterface #333,  1          // InterfaceMethod java/util/Iterator.next:()Ljava/lang/Object;
        30: invokeinterface #494,  2          // InterfaceMethod java/util/Map.get:(Ljava/lang/Object;)Ljava/lang/Object;
        35: checkcast     #496                // class com/simibubi/create/content/trains/signal/SignalEdgeGroup
        38: astore        4
        40: aload         4
        42: ifnonnull     54
        45: aload_3
        46: invokeinterface #499,  1          // InterfaceMethod java/util/Iterator.remove:()V
        51: goto          66
        54: aload         4
        56: getfield      #502                // Field com/simibubi/create/content/trains/signal/SignalEdgeGroup.trains:Ljava/util/Set;
        59: aload_0
        60: invokeinterface #506,  2          // InterfaceMethod java/util/Set.add:(Ljava/lang/Object;)Z
        65: pop
        66: goto          14
        69: return

  public void tick(net.minecraft.world.level.Level);
    Code:
         0: getstatic     #483                // Field com/simibubi/create/Create.RAILWAYS:Lcom/simibubi/create/content/trains/GlobalRailwayManager;
         3: invokevirtual #518                // Method com/simibubi/create/content/trains/GlobalRailwayManager.markTracksDirty:()V
         6: aload_0
         7: getfield      #175                // Field graph:Lcom/simibubi/create/content/trains/graph/TrackGraph;
        10: ifnonnull     33
        13: aload_0
        14: getfield      #177                // Field carriages:Ljava/util/List;
        17: aload_1
        18: invokedynamic #526,  0            // InvokeDynamic #2:accept:(Lnet/minecraft/world/level/Level;)Ljava/util/function/Consumer;
        23: invokeinterface #237,  2          // InterfaceMethod java/util/List.forEach:(Ljava/util/function/Consumer;)V
        28: aload_0
        29: invokevirtual #529                // Method updateConductors:()V
        32: return
        33: aload_0
        34: invokevirtual #533                // Method getCurrentStation:()Lcom/simibubi/create/content/trains/station/GlobalStation;
        37: astore_2
        38: aload_2
        39: ifnull        70
        42: aload_0
        43: dup
        44: getfield      #535                // Field ticksSinceLastMailTransfer:I
        47: iconst_1
        48: iadd
        49: putfield      #535                // Field ticksSinceLastMailTransfer:I
        52: aload_0
        53: getfield      #535                // Field ticksSinceLastMailTransfer:I
        56: bipush        20
        58: if_icmple     70
        61: aload_2
        62: invokevirtual #540                // Method com/simibubi/create/content/trains/station/GlobalStation.runMailTransfer:()V
        65: aload_0
        66: iconst_0
        67: putfield      #535                // Field ticksSinceLastMailTransfer:I
        70: aload_0
        71: invokevirtual #529                // Method updateConductors:()V
        74: aload_0
        75: getfield      #245                // Field runtime:Lcom/simibubi/create/content/trains/schedule/ScheduleRuntime;
        78: aload_1
        79: invokevirtual #541                // Method com/simibubi/create/content/trains/schedule/ScheduleRuntime.tick:(Lnet/minecraft/world/level/Level;)V
        82: aload_0
        83: getfield      #242                // Field navigation:Lcom/simibubi/create/content/trains/entity/Navigation;
        86: aload_1
        87: invokevirtual #542                // Method com/simibubi/create/content/trains/entity/Navigation.tick:(Lnet/minecraft/world/level/Level;)V
        90: aload_0
        91: invokevirtual #545                // Method tickPassiveSlowdown:()V
        94: aload_0
        95: getfield      #547                // Field derailed:Z
        98: ifeq          105
       101: aload_0
       102: invokevirtual #550                // Method tickDerailedSlowdown:()V
       105: aload_0
       106: getfield      #159                // Field speed:D
       109: dstore_3
       110: aconst_null
       111: astore        5
       113: aload_0
       114: getfield      #177                // Field carriages:Ljava/util/List;
       117: invokeinterface #193,  1          // InterfaceMethod java/util/List.size:()I
       122: istore        6
       124: iconst_0
       125: istore        7
       127: dconst_0
       128: dstore        8
       130: aload_0
       131: getfield      #165                // Field carriageWaitingForChunks:I
       134: iconst_m1
       135: if_icmpeq     140
       138: dconst_0
       139: dstore_3
       140: iconst_0
       141: istore        10
       143: iload         10
       145: iload         6
       147: if_icmpge     544
       150: aload_0
       151: getfield      #177                // Field carriages:Ljava/util/List;
       154: iload         10
       156: invokeinterface #553,  2          // InterfaceMethod java/util/List.get:(I)Ljava/lang/Object;
       161: checkcast     #21                 // class com/simibubi/create/content/trains/entity/Carriage
       164: astore        11
       166: aload         5
       168: ifnull        498
       171: aload_0
       172: getfield      #179                // Field carriageSpacing:Ljava/util/List;
       175: iload         10
       177: iconst_1
       178: isub
       179: invokeinterface #553,  2          // InterfaceMethod java/util/List.get:(I)Ljava/lang/Object;
       184: checkcast     #400                // class java/lang/Integer
       187: invokevirtual #403                // Method java/lang/Integer.intValue:()I
       190: istore        12
       192: iload         12
       194: i2d
       195: dstore        13
       197: aload         11
       199: invokevirtual #557                // Method com/simibubi/create/content/trains/entity/Carriage.getLeadingPoint:()Lcom/simibubi/create/content/trains/entity/TravellingPoint;
       202: astore        15
       204: aload         5
       206: invokevirtual #560                // Method com/simibubi/create/content/trains/entity/Carriage.getTrailingPoint:()Lcom/simibubi/create/content/trains/entity/TravellingPoint;
       209: astore        16
       211: iconst_0
       212: istore        17
       214: dconst_0
       215: dstore        18
       217: aload         15
       219: getfield      #564                // Field com/simibubi/create/content/trains/entity/TravellingPoint.node1:Lcom/simibubi/create/content/trains/graph/TrackNode;
       222: ifnull        454
       225: aload         16
       227: getfield      #564                // Field com/simibubi/create/content/trains/entity/TravellingPoint.node1:Lcom/simibubi/create/content/trains/graph/TrackNode;
       230: ifnull        454
       233: aload         15
       235: getfield      #564                // Field com/simibubi/create/content/trains/entity/TravellingPoint.node1:Lcom/simibubi/create/content/trains/graph/TrackNode;
       238: invokevirtual #570                // Method com/simibubi/create/content/trains/graph/TrackNode.getLocation:()Lcom/simibubi/create/content/trains/graph/TrackNodeLocation;
       241: getfield      #576                // Field com/simibubi/create/content/trains/graph/TrackNodeLocation.dimension:Lnet/minecraft/resources/ResourceKey;
       244: astore        20
       246: aload         16
       248: getfield      #564                // Field com/simibubi/create/content/trains/entity/TravellingPoint.node1:Lcom/simibubi/create/content/trains/graph/TrackNode;
       251: invokevirtual #570                // Method com/simibubi/create/content/trains/graph/TrackNode.getLocation:()Lcom/simibubi/create/content/trains/graph/TrackNodeLocation;
       254: getfield      #576                // Field com/simibubi/create/content/trains/graph/TrackNodeLocation.dimension:Lnet/minecraft/resources/ResourceKey;
       257: astore        21
       259: getstatic     #582                // Field net/createmod/catnip/data/Iterate.trueAndFalse:[Z
       262: astore        22
       264: aload         22
       266: arraylength
       267: istore        23
       269: iconst_0
       270: istore        24
       272: iload         24
       274: iload         23
       276: if_icmpge     454
       279: aload         22
       281: iload         24
       283: baload
       284: istore        25
       286: iload         25
       288: ifeq          296
       291: aload         20
       293: goto          298
       296: aload         21
       298: astore        26
       300: iload         25
       302: ifne          318
       305: aload         20
       307: aload         21
       309: invokevirtual #588                // Method net/minecraft/resources/ResourceKey.equals:(Ljava/lang/Object;)Z
       312: ifeq          318
       315: goto          448
       318: aload         20
       320: aload         21
       322: invokevirtual #588                // Method net/minecraft/resources/ResourceKey.equals:(Ljava/lang/Object;)Z
       325: ifne          331
       328: goto          448
       331: aload         11
       333: aload         26
       335: invokevirtual #592                // Method com/simibubi/create/content/trains/entity/Carriage.getDimensionalIfPresent:(Lnet/minecraft/resources/ResourceKey;)Lcom/simibubi/create/content/trains/entity/Carriage$DimensionalCarriageEntity;
       338: astore        27
       340: aload         5
       342: aload         26
       344: invokevirtual #592                // Method com/simibubi/create/content/trains/entity/Carriage.getDimensionalIfPresent:(Lnet/minecraft/resources/ResourceKey;)Lcom/simibubi/create/content/trains/entity/Carriage$DimensionalCarriageEntity;
       347: astore        28
       349: aload         27
       351: ifnull        448
       354: aload         28
       356: ifnonnull     362
       359: goto          448
       362: aload         27
       364: invokevirtual #596                // Method com/simibubi/create/content/trains/entity/Carriage$DimensionalCarriageEntity.leadingAnchor:()Lnet/minecraft/world/phys/Vec3;
       367: astore        29
       369: aload         28
       371: invokevirtual #599                // Method com/simibubi/create/content/trains/entity/Carriage$DimensionalCarriageEntity.trailingAnchor:()Lnet/minecraft/world/phys/Vec3;
       374: astore        30
       376: aload         29
       378: ifnull        448
       381: aload         30
       383: ifnonnull     389
       386: goto          448
       389: aload         29
       391: aload         30
       393: invokevirtual #605                // Method net/minecraft/world/phys/Vec3.distanceToSqr:(Lnet/minecraft/world/phys/Vec3;)D
       396: dstore        31
       398: aload         11
       400: invokevirtual #609                // Method com/simibubi/create/content/trains/entity/Carriage.leadingBogey:()Lcom/simibubi/create/content/trains/entity/CarriageBogey;
       403: invokevirtual #614                // Method com/simibubi/create/content/trains/entity/CarriageBogey.isUpsideDown:()Z
       406: aload         5
       408: invokevirtual #617                // Method com/simibubi/create/content/trains/entity/Carriage.trailingBogey:()Lcom/simibubi/create/content/trains/entity/CarriageBogey;
       411: invokevirtual #614                // Method com/simibubi/create/content/trains/entity/CarriageBogey.isUpsideDown:()Z
       414: if_icmpeq     431
       417: dload         31
       419: ldc2_w        #618                // double 4.0d
       422: dsub
       423: invokestatic  #625                // Method java/lang/Math.sqrt:(D)D
       426: dstore        31
       428: goto          438
       431: dload         31
       433: invokestatic  #625                // Method java/lang/Math.sqrt:(D)D
       436: dstore        31
       438: dload         18
       440: dload         31
       442: dadd
       443: dstore        18
       445: iinc          17, 1
       448: iinc          24, 1
       451: goto          272
       454: iload         17
       456: ifle          467
       459: dload         18
       461: iload         17
       463: i2d
       464: ddiv
       465: dstore        13
       467: aload_0
       468: getfield      #195                // Field stress:[D
       471: iload         10
       473: iconst_1
       474: isub
       475: iload         12
       477: i2d
       478: dload         13
       480: dsub
       481: dastore
       482: dload         8
       484: iload         12
       486: i2d
       487: dload         13
       489: dsub
       490: invokestatic  #628                // Method java/lang/Math.abs:(D)D
       493: invokestatic  #632                // Method java/lang/Math.max:(DD)D
       496: dstore        8
       498: aload         11
       500: astore        5
       502: aload         11
       504: getfield      #635                // Field com/simibubi/create/content/trains/entity/Carriage.stalled:Z
       507: ifeq          538
       510: aload_0
       511: getfield      #163                // Field speedBeforeStall:Ljava/lang/Double;
       514: ifnonnull     528
       517: aload_0
       518: aload_0
       519: getfield      #159                // Field speed:D
       522: invokestatic  #640                // Method java/lang/Double.valueOf:(D)Ljava/lang/Double;
       525: putfield      #163                // Field speedBeforeStall:Ljava/lang/Double;
       528: dconst_0
       529: dstore_3
       530: aload_0
       531: dconst_0
       532: putfield      #159                // Field speed:D
       535: iconst_1
       536: istore        7
       538: iinc          10, 1
       541: goto          143
       544: iload         7
       546: ifne          579
       549: aload_0
       550: getfield      #163                // Field speedBeforeStall:Ljava/lang/Double;
       553: ifnull        579
       556: aload_0
       557: aload_0
       558: getfield      #163                // Field speedBeforeStall:Ljava/lang/Double;
       561: invokevirtual #644                // Method java/lang/Double.doubleValue:()D
       564: ldc2_w        #645                // double -1.0d
       567: dconst_1
       568: invokestatic  #652                // Method net/minecraft/util/Mth.clamp:(DDD)D
       571: putfield      #159                // Field speed:D
       574: aload_0
       575: aconst_null
       576: putfield      #163                // Field speedBeforeStall:Ljava/lang/Double;
       579: aload_0
       580: getfield      #242                // Field navigation:Lcom/simibubi/create/content/trains/entity/Navigation;
       583: getfield      #655                // Field com/simibubi/create/content/trains/entity/Navigation.distanceToDestination:D
       586: ldc2_w        #656                // double 5.0d
       589: dcmpg
       590: ifge          597
       593: iconst_1
       594: goto          598
       597: iconst_0
       598: istore        10
       600: iload         10
       602: ifeq          611
       605: ldc2_w        #658                // double 0.75d
       608: goto          614
       611: ldc2_w        #660                // double 0.5d
       614: dstore        11
       616: iload         10
       618: ifeq          625
       621: dconst_0
       622: goto          628
       625: ldc2_w        #662                // double 0.125d
       628: dstore        13
       630: iconst_0
       631: istore        15
       633: aload_0
       634: getfield      #159                // Field speed:D
       637: dconst_0
       638: dcmpg
       639: ifge          646
       642: iconst_1
       643: goto          647
       646: iconst_0
       647: istore        16
       649: iconst_0
       650: istore        17
       652: iload         17
       654: iload         6
       656: if_icmpge     1056
       659: iload         16
       661: ifeq          674
       664: iload         6
       666: iconst_1
       667: isub
       668: iload         17
       670: isub
       671: goto          676
       674: iload         17
       676: istore        18
       678: iload         18
       680: ifne          687
       683: dconst_0
       684: goto          710
       687: aload_0
       688: getfield      #195                // Field stress:[D
       691: iload         18
       693: iconst_1
       694: isub
       695: daload
       696: iload         16
       698: ifeq          706
       701: dload         13
       703: goto          708
       706: dload         11
       708: dneg
       709: dmul
       710: dstore        19
       712: iload         18
       714: aload_0
       715: getfield      #195                // Field stress:[D
       718: arraylength
       719: if_icmpne     726
       722: dconst_0
       723: goto          746
       726: aload_0
       727: getfield      #195                // Field stress:[D
       730: iload         18
       732: daload
       733: iload         16
       735: ifeq          743
       738: dload         11
       740: goto          745
       743: dload         13
       745: dmul
       746: dstore        21
       748: aload_0
       749: getfield      #177                // Field carriages:Ljava/util/List;
       752: iload         18
       754: invokeinterface #553,  2          // InterfaceMethod java/util/List.get:(I)Ljava/lang/Object;
       759: checkcast     #21                 // class com/simibubi/create/content/trains/entity/Carriage
       762: astore        23
       764: iload         18
       766: ifne          773
       769: aconst_null
       770: goto          792
       773: aload_0
       774: getfield      #177                // Field carriages:Ljava/util/List;
       777: iload         18
       779: iconst_1
       780: isub
       781: invokeinterface #553,  2          // InterfaceMethod java/util/List.get:(I)Ljava/lang/Object;
       786: checkcast     #21                 // class com/simibubi/create/content/trains/entity/Carriage
       789: invokevirtual #560                // Method com/simibubi/create/content/trains/entity/Carriage.getTrailingPoint:()Lcom/simibubi/create/content/trains/entity/TravellingPoint;
       792: astore        24
       794: iload         18
       796: iload         6
       798: iconst_1
       799: isub
       800: if_icmpne     807
       803: aconst_null
       804: goto          826
       807: aload_0
       808: getfield      #177                // Field carriages:Ljava/util/List;
       811: iload         18
       813: iconst_1
       814: iadd
       815: invokeinterface #553,  2          // InterfaceMethod java/util/List.get:(I)Ljava/lang/Object;
       820: checkcast     #21                 // class com/simibubi/create/content/trains/entity/Carriage
       823: invokevirtual #557                // Method com/simibubi/create/content/trains/entity/Carriage.getLeadingPoint:()Lcom/simibubi/create/content/trains/entity/TravellingPoint;
       826: astore        25
       828: aload_0
       829: getfield      #547                // Field derailed:Z
       832: ifeq          839
       835: dconst_0
       836: goto          844
       839: dload         19
       841: dload         21
       843: dadd
       844: dstore        26
       846: iload         18
       848: ifne          855
       851: iconst_1
       852: goto          856
       855: iconst_0
       856: istore        28
       858: iload         18
       860: iload         6
       862: iconst_1
       863: isub
       864: if_icmpne     871
       867: iconst_1
       868: goto          872
       871: iconst_0
       872: istore        29
       874: iload         28
       876: ifeq          892
       879: iload         29
       881: ifeq          888
       884: iconst_3
       885: goto          902
       888: iconst_0
       889: goto          902
       892: iload         29
       894: ifeq          901
       897: iconst_2
       898: goto          902
       901: iconst_1
       902: istore        30
       904: aload         23
       906: aload_1
       907: aload_0
       908: getfield      #175                // Field graph:Lcom/simibubi/create/content/trains/graph/TrackGraph;
       911: dload_3
       912: dload         26
       914: dadd
       915: aload         24
       917: aload         25
       919: iload         30
       921: invokevirtual #667                // Method com/simibubi/create/content/trains/entity/Carriage.travel:(Lnet/minecraft/world/level/Level;Lcom/simibubi/create/content/trains/graph/TrackGraph;DLcom/simibubi/create/content/trains/entity/TravellingPoint;Lcom/simibubi/create/content/trains/entity/TravellingPoint;I)D
       924: dstore        31
       926: iload         15
       928: aload         23
       930: getfield      #670                // Field com/simibubi/create/content/trains/entity/Carriage.blocked:Z
       933: ifne          944
       936: aload         23
       938: invokevirtual #673                // Method com/simibubi/create/content/trains/entity/Carriage.isOnIncompatibleTrack:()Z
       941: ifeq          948
       944: iconst_1
       945: goto          949
       948: iconst_0
       949: ior
       950: istore        15
       952: aload         23
       954: invokevirtual #676                // Method com/simibubi/create/content/trains/entity/Carriage.isOnTwoBogeys:()Z
       957: istore        33
       959: dload         8
       961: iload         33
       963: ifeq          981
       966: aload         23
       968: getfield      #679                // Field com/simibubi/create/content/trains/entity/Carriage.bogeySpacing:I
       971: i2d
       972: aload         23
       974: invokevirtual #682                // Method com/simibubi/create/content/trains/entity/Carriage.getAnchorDiff:()D
       977: dsub
       978: goto          982
       981: dconst_0
       982: invokestatic  #632                // Method java/lang/Math.max:(DD)D
       985: dstore        8
       987: dload         8
       989: aload         23
       991: invokevirtual #609                // Method com/simibubi/create/content/trains/entity/Carriage.leadingBogey:()Lcom/simibubi/create/content/trains/entity/CarriageBogey;
       994: invokevirtual #685                // Method com/simibubi/create/content/trains/entity/CarriageBogey.getStress:()D
       997: invokestatic  #632                // Method java/lang/Math.max:(DD)D
      1000: dstore        8
      1002: iload         33
      1004: ifeq          1022
      1007: dload         8
      1009: aload         23
      1011: invokevirtual #617                // Method com/simibubi/create/content/trains/entity/Carriage.trailingBogey:()Lcom/simibubi/create/content/trains/entity/CarriageBogey;
      1014: invokevirtual #685                // Method com/simibubi/create/content/trains/entity/CarriageBogey.getStress:()D
      1017: invokestatic  #632                // Method java/lang/Math.max:(DD)D
      1020: dstore        8
      1022: iload         17
      1024: ifne          1050
      1027: dload         31
      1029: dstore_3
      1030: aload_0
      1031: aload_1
      1032: aload         23
      1034: invokevirtual #688                // Method collideWithOtherTrains:(Lnet/minecraft/world/level/Level;Lcom/simibubi/create/content/trains/entity/Carriage;)V
      1037: aload_0
      1038: aconst_null
      1039: putfield      #690                // Field backwardsDriver:Lnet/minecraft/world/entity/player/Player;
      1042: aload_0
      1043: getfield      #175                // Field graph:Lcom/simibubi/create/content/trains/graph/TrackGraph;
      1046: ifnonnull     1050
      1049: return
      1050: iinc          17, 1
      1053: goto          652
      1056: iload         15
      1058: ifeq          1091
      1061: aload_0
      1062: dconst_0
      1063: putfield      #159                // Field speed:D
      1066: aload_0
      1067: getfield      #242                // Field navigation:Lcom/simibubi/create/content/trains/entity/Navigation;
      1070: invokevirtual #693                // Method com/simibubi/create/content/trains/entity/Navigation.cancelNavigation:()V
      1073: aload_0
      1074: getfield      #245                // Field runtime:Lcom/simibubi/create/content/trains/schedule/ScheduleRuntime;
      1077: aload_1
      1078: invokevirtual #541                // Method com/simibubi/create/content/trains/schedule/ScheduleRuntime.tick:(Lnet/minecraft/world/level/Level;)V
      1081: aload_0
      1082: getfield      #212                // Field status:Lcom/simibubi/create/content/trains/entity/TrainStatus;
      1085: invokevirtual #696                // Method com/simibubi/create/content/trains/entity/TrainStatus.endOfTrack:()V
      1088: goto          1151
      1091: dload         8
      1093: ldc2_w        #618                // double 4.0d
      1096: dcmpl
      1097: ifle          1135
      1100: aload_0
      1101: dconst_0
      1102: putfield      #159                // Field speed:D
      1105: aload_0
      1106: getfield      #242                // Field navigation:Lcom/simibubi/create/content/trains/entity/Navigation;
      1109: invokevirtual #693                // Method com/simibubi/create/content/trains/entity/Navigation.cancelNavigation:()V
      1112: aload_0
      1113: getfield      #245                // Field runtime:Lcom/simibubi/create/content/trains/schedule/ScheduleRuntime;
      1116: aload_1
      1117: invokevirtual #541                // Method com/simibubi/create/content/trains/schedule/ScheduleRuntime.tick:(Lnet/minecraft/world/level/Level;)V
      1120: aload_0
      1121: iconst_1
      1122: putfield      #547                // Field derailed:Z
      1125: aload_0
      1126: getfield      #212                // Field status:Lcom/simibubi/create/content/trains/entity/TrainStatus;
      1129: invokevirtual #699                // Method com/simibubi/create/content/trains/entity/TrainStatus.highStress:()V
      1132: goto          1151
      1135: aload_0
      1136: getfield      #159                // Field speed:D
      1139: dconst_0
      1140: dcmpl
      1141: ifeq          1151
      1144: aload_0
      1145: getfield      #212                // Field status:Lcom/simibubi/create/content/trains/entity/TrainStatus;
      1148: invokevirtual #702                // Method com/simibubi/create/content/trains/entity/TrainStatus.trackOK:()V
      1151: aload_0
      1152: aload_1
      1153: dload_3
      1154: invokevirtual #706                // Method updateNavigationTarget:(Lnet/minecraft/world/level/Level;D)V
      1157: return

  public com.simibubi.create.content.trains.entity.TravellingPoint$IEdgePointListener frontSignalListener();
    Code:
         0: aload_0
         1: invokedynamic #757,  0            // InvokeDynamic #3:test:(Lcom/simibubi/create/content/trains/entity/Train;)Lcom/simibubi/create/content/trains/entity/TravellingPoint$IEdgePointListener;
         6: areturn

  public void cancelStall();
    Code:
         0: aload_0
         1: aconst_null
         2: putfield      #163                // Field speedBeforeStall:Ljava/lang/Double;
         5: aload_0
         6: getfield      #177                // Field carriages:Ljava/util/List;
         9: invokedynamic #765,  0            // InvokeDynamic #4:accept:()Ljava/util/function/Consumer;
        14: invokeinterface #237,  2          // InterfaceMethod java/util/List.forEach:(Ljava/util/function/Consumer;)V
        19: return

  private boolean occupy(java.util.UUID, java.util.UUID);
    Code:
         0: aload_0
         1: getfield      #267                // Field reservedSignalBlocks:Ljava/util/Set;
         4: aload_1
         5: invokeinterface #769,  2          // InterfaceMethod java/util/Set.remove:(Ljava/lang/Object;)Z
        10: pop
        11: aload_2
        12: ifnull        47
        15: aload_0
        16: getfield      #262                // Field occupiedSignalBlocks:Ljava/util/Map;
        19: aload_1
        20: invokeinterface #772,  2          // InterfaceMethod java/util/Map.containsKey:(Ljava/lang/Object;)Z
        25: ifeq          47
        28: aload_2
        29: aload_0
        30: getfield      #262                // Field occupiedSignalBlocks:Ljava/util/Map;
        33: aload_1
        34: invokeinterface #494,  2          // InterfaceMethod java/util/Map.get:(Ljava/lang/Object;)Ljava/lang/Object;
        39: invokevirtual #773                // Method java/util/UUID.equals:(Ljava/lang/Object;)Z
        42: ifeq          47
        45: iconst_0
        46: ireturn
        47: aload_0
        48: getfield      #262                // Field occupiedSignalBlocks:Ljava/util/Map;
        51: aload_1
        52: aload_2
        53: invokeinterface #459,  3          // InterfaceMethod java/util/Map.put:(Ljava/lang/Object;Ljava/lang/Object;)Ljava/lang/Object;
        58: ifnonnull     65
        61: iconst_1
        62: goto          66
        65: iconst_0
        66: ireturn

  public com.simibubi.create.content.trains.entity.TravellingPoint$IEdgePointListener backSignalListener();
    Code:
         0: aload_0
         1: invokedynamic #781,  0            // InvokeDynamic #5:test:(Lcom/simibubi/create/content/trains/entity/Train;)Lcom/simibubi/create/content/trains/entity/TravellingPoint$IEdgePointListener;
         6: areturn

  private void updateNavigationTarget(net.minecraft.world.level.Level, double);
    Code:
         0: aload_0
         1: getfield      #242                // Field navigation:Lcom/simibubi/create/content/trains/entity/Navigation;
         4: getfield      #784                // Field com/simibubi/create/content/trains/entity/Navigation.destination:Lcom/simibubi/create/content/trains/station/GlobalStation;
         7: ifnonnull     11
        10: return
        11: aload_0
        12: getfield      #242                // Field navigation:Lcom/simibubi/create/content/trains/entity/Navigation;
        15: getfield      #787                // Field com/simibubi/create/content/trains/entity/Navigation.waitingForSignal:Lnet/createmod/catnip/data/Pair;
        18: astore        4
        20: aload_0
        21: getfield      #242                // Field navigation:Lcom/simibubi/create/content/trains/entity/Navigation;
        24: getfield      #655                // Field com/simibubi/create/content/trains/entity/Navigation.distanceToDestination:D
        27: ldc2_w        #788                // double 100.0d
        30: dcmpl
        31: ifle          56
        34: aload_0
        35: getfield      #242                // Field navigation:Lcom/simibubi/create/content/trains/entity/Navigation;
        38: getfield      #655                // Field com/simibubi/create/content/trains/entity/Navigation.distanceToDestination:D
        41: ldc2_w        #788                // double 100.0d
        44: drem
        45: ldc2_w        #790                // double 20.0d
        48: dcmpl
        49: ifle          56
        52: iconst_1
        53: goto          57
        56: iconst_0
        57: istore        5
        59: aload         4
        61: ifnull        86
        64: aload_0
        65: getfield      #242                // Field navigation:Lcom/simibubi/create/content/trains/entity/Navigation;
        68: getfield      #794                // Field com/simibubi/create/content/trains/entity/Navigation.distanceToSignal:D
        71: ldc2_w        #795                // double 50.0d
        74: drem
        75: ldc2_w        #656                // double 5.0d
        78: dcmpl
        79: ifle          86
        82: iconst_1
        83: goto          87
        86: iconst_0
        87: istore        6
        89: aload_0
        90: getfield      #242                // Field navigation:Lcom/simibubi/create/content/trains/entity/Navigation;
        93: getfield      #655                // Field com/simibubi/create/content/trains/entity/Navigation.distanceToDestination:D
        96: ldc2_w        #788                // double 100.0d
        99: dcmpg
       100: ifge          125
       103: aload_0
       104: getfield      #242                // Field navigation:Lcom/simibubi/create/content/trains/entity/Navigation;
       107: getfield      #655                // Field com/simibubi/create/content/trains/entity/Navigation.distanceToDestination:D
       110: ldc2_w        #795                // double 50.0d
       113: drem
       114: ldc2_w        #656                // double 5.0d
       117: dcmpl
       118: ifle          125
       121: iconst_1
       122: goto          126
       125: iconst_0
       126: istore        7
       128: aload_0
       129: getfield      #242                // Field navigation:Lcom/simibubi/create/content/trains/entity/Navigation;
       132: getfield      #799                // Field com/simibubi/create/content/trains/entity/Navigation.destinationBehindTrain:Z
       135: ifeq          143
       138: dload_2
       139: dneg
       140: goto          144
       143: dload_2
       144: dstore        8
       146: aload_0
       147: getfield      #245                // Field runtime:Lcom/simibubi/create/content/trains/schedule/ScheduleRuntime;
       150: getfield      #802                // Field com/simibubi/create/content/trains/schedule/ScheduleRuntime.paused:Z
       153: istore        10
       155: aload_0
       156: getfield      #242                // Field navigation:Lcom/simibubi/create/content/trains/entity/Navigation;
       159: dup
       160: getfield      #655                // Field com/simibubi/create/content/trains/entity/Navigation.distanceToDestination:D
       163: dload         8
       165: dsub
       166: putfield      #655                // Field com/simibubi/create/content/trains/entity/Navigation.distanceToDestination:D
       169: aload         4
       171: ifnull        216
       174: aload_0
       175: getfield      #242                // Field navigation:Lcom/simibubi/create/content/trains/entity/Navigation;
       178: dup
       179: getfield      #794                // Field com/simibubi/create/content/trains/entity/Navigation.distanceToSignal:D
       182: dload         8
       184: dsub
       185: putfield      #794                // Field com/simibubi/create/content/trains/entity/Navigation.distanceToSignal:D
       188: iload         6
       190: aload_0
       191: getfield      #242                // Field navigation:Lcom/simibubi/create/content/trains/entity/Navigation;
       194: getfield      #794                // Field com/simibubi/create/content/trains/entity/Navigation.distanceToSignal:D
       197: ldc2_w        #795                // double 50.0d
       200: drem
       201: ldc2_w        #656                // double 5.0d
       204: dcmpg
       205: ifge          212
       208: iconst_1
       209: goto          213
       212: iconst_0
       213: iand
       214: istore        6
       216: iload         5
       218: aload_0
       219: getfield      #242                // Field navigation:Lcom/simibubi/create/content/trains/entity/Navigation;
       222: getfield      #655                // Field com/simibubi/create/content/trains/entity/Navigation.distanceToDestination:D
       225: ldc2_w        #788                // double 100.0d
       228: drem
       229: ldc2_w        #790                // double 20.0d
       232: dcmpg
       233: ifgt          240
       236: iconst_1
       237: goto          241
       240: iconst_0
       241: iand
       242: istore        5
       244: iload         7
       246: aload_0
       247: getfield      #242                // Field navigation:Lcom/simibubi/create/content/trains/entity/Navigation;
       250: getfield      #655                // Field com/simibubi/create/content/trains/entity/Navigation.distanceToDestination:D
       253: ldc2_w        #795                // double 50.0d
       256: drem
       257: ldc2_w        #656                // double 5.0d
       260: dcmpg
       261: ifgt          268
       264: iconst_1
       265: goto          269
       268: iconst_0
       269: iand
       270: istore        7
       272: aload         4
       274: ifnull        355
       277: aload_0
       278: getfield      #242                // Field navigation:Lcom/simibubi/create/content/trains/entity/Navigation;
       281: getfield      #805                // Field com/simibubi/create/content/trains/entity/Navigation.ticksWaitingForSignal:I
       284: bipush        100
       286: irem
       287: bipush        50
       289: if_icmpne     355
       292: aload_0
       293: getfield      #175                // Field graph:Lcom/simibubi/create/content/trains/graph/TrackGraph;
       296: getstatic     #808                // Field com/simibubi/create/content/trains/graph/EdgePointType.SIGNAL:Lcom/simibubi/create/content/trains/graph/EdgePointType;
       299: aload         4
       301: invokevirtual #398                // Method net/createmod/catnip/data/Pair.getFirst:()Ljava/lang/Object;
       304: checkcast     #345                // class java/util/UUID
       307: invokevirtual #357                // Method com/simibubi/create/content/trains/graph/TrackGraph.getPoint:(Lcom/simibubi/create/content/trains/graph/EdgePointType;Ljava/util/UUID;)Lcom/simibubi/create/content/trains/signal/TrackEdgePoint;
       310: checkcast     #810                // class com/simibubi/create/content/trains/signal/SignalBoundary
       313: astore        11
       315: iload         5
       317: aload         11
       319: ifnull        351
       322: aload         11
       324: getfield      #814                // Field com/simibubi/create/content/trains/signal/SignalBoundary.types:Lnet/createmod/catnip/data/Couple;
       327: aload         4
       329: invokevirtual #390                // Method net/createmod/catnip/data/Pair.getSecond:()Ljava/lang/Object;
       332: checkcast     #392                // class java/lang/Boolean
       335: invokevirtual #395                // Method java/lang/Boolean.booleanValue:()Z
       338: invokevirtual #819                // Method net/createmod/catnip/data/Couple.get:(Z)Ljava/lang/Object;
       341: getstatic     #823                // Field com/simibubi/create/content/trains/signal/SignalBlock$SignalType.CROSS_SIGNAL:Lcom/simibubi/create/content/trains/signal/SignalBlock$SignalType;
       344: if_acmpne     351
       347: iconst_1
       348: goto          352
       351: iconst_0
       352: ior
       353: istore        5
       355: iload         6
       357: ifeq          368
       360: aload_0
       361: getfield      #242                // Field navigation:Lcom/simibubi/create/content/trains/entity/Navigation;
       364: aconst_null
       365: putfield      #787                // Field com/simibubi/create/content/trains/entity/Navigation.waitingForSignal:Lnet/createmod/catnip/data/Pair;
       368: iload         5
       370: ifne          379
       373: iload         7
       375: ifne          379
       378: return
       379: aload_0
       380: getfield      #267                // Field reservedSignalBlocks:Ljava/util/Set;
       383: invokeinterface #315,  1          // InterfaceMethod java/util/Set.isEmpty:()Z
       388: ifne          392
       391: return
       392: iload         10
       394: ifne          427
       397: iload         5
       399: ifeq          427
       402: aload_0
       403: getfield      #245                // Field runtime:Lcom/simibubi/create/content/trains/schedule/ScheduleRuntime;
       406: aload_1
       407: invokevirtual #827                // Method com/simibubi/create/content/trains/schedule/ScheduleRuntime.startCurrentInstruction:(Lnet/minecraft/world/level/Level;)Lcom/simibubi/create/content/trains/graph/DiscoveredPath;
       410: astore        11
       412: aload         11
       414: ifnull        427
       417: aload_0
       418: getfield      #242                // Field navigation:Lcom/simibubi/create/content/trains/entity/Navigation;
       421: aload         11
       423: invokevirtual #831                // Method com/simibubi/create/content/trains/entity/Navigation.startNavigation:(Lcom/simibubi/create/content/trains/graph/DiscoveredPath;)D
       426: pop2
       427: return

  private void tickDerailedSlowdown();
    Code:
         0: aload_0
         1: dup
         2: getfield      #159                // Field speed:D
         5: ldc2_w        #843                // double 3.0d
         8: ddiv
         9: putfield      #159                // Field speed:D
        12: aload_0
        13: getfield      #159                // Field speed:D
        16: dconst_0
        17: invokestatic  #848                // Method net/minecraft/util/Mth.equal:(DD)Z
        20: ifeq          28
        23: aload_0
        24: dconst_0
        25: putfield      #159                // Field speed:D
        28: return

  private void tickPassiveSlowdown();
    Code:
         0: aload_0
         1: getfield      #850                // Field manualTick:Z
         4: ifne          72
         7: aload_0
         8: getfield      #242                // Field navigation:Lcom/simibubi/create/content/trains/entity/Navigation;
        11: getfield      #784                // Field com/simibubi/create/content/trains/entity/Navigation.destination:Lcom/simibubi/create/content/trains/station/GlobalStation;
        14: ifnonnull     72
        17: aload_0
        18: getfield      #159                // Field speed:D
        21: dconst_0
        22: dcmpl
        23: ifeq          72
        26: aload_0
        27: invokevirtual #854                // Method acceleration:()F
        30: f2d
        31: dstore_1
        32: aload_0
        33: getfield      #159                // Field speed:D
        36: dconst_0
        37: dcmpl
        38: ifle          58
        41: aload_0
        42: aload_0
        43: getfield      #159                // Field speed:D
        46: dload_1
        47: dsub
        48: dconst_0
        49: invokestatic  #632                // Method java/lang/Math.max:(DD)D
        52: putfield      #159                // Field speed:D
        55: goto          72
        58: aload_0
        59: aload_0
        60: getfield      #159                // Field speed:D
        63: dload_1
        64: dadd
        65: dconst_0
        66: invokestatic  #857                // Method java/lang/Math.min:(DD)D
        69: putfield      #159                // Field speed:D
        72: aload_0
        73: iconst_0
        74: putfield      #850                // Field manualTick:Z
        77: return

  private void updateConductors();
    Code:
         0: aload_0
         1: getfield      #177                // Field carriages:Ljava/util/List;
         4: invokeinterface #324,  1          // InterfaceMethod java/util/List.iterator:()Ljava/util/Iterator;
         9: astore_1
        10: aload_1
        11: invokeinterface #329,  1          // InterfaceMethod java/util/Iterator.hasNext:()Z
        16: ifeq          36
        19: aload_1
        20: invokeinterface #333,  1          // InterfaceMethod java/util/Iterator.next:()Ljava/lang/Object;
        25: checkcast     #21                 // class com/simibubi/create/content/trains/entity/Carriage
        28: astore_2
        29: aload_2
        30: invokevirtual #858                // Method com/simibubi/create/content/trains/entity/Carriage.updateConductors:()V
        33: goto          10
        36: return

  public boolean hasForwardConductor();
    Code:
         0: aload_0
         1: getfield      #177                // Field carriages:Ljava/util/List;
         4: invokeinterface #324,  1          // InterfaceMethod java/util/List.iterator:()Ljava/util/Iterator;
         9: astore_1
        10: aload_1
        11: invokeinterface #329,  1          // InterfaceMethod java/util/Iterator.hasNext:()Z
        16: ifeq          50
        19: aload_1
        20: invokeinterface #333,  1          // InterfaceMethod java/util/Iterator.next:()Ljava/lang/Object;
        25: checkcast     #21                 // class com/simibubi/create/content/trains/entity/Carriage
        28: astore_2
        29: aload_2
        30: getfield      #862                // Field com/simibubi/create/content/trains/entity/Carriage.presentConductors:Lnet/createmod/catnip/data/Couple;
        33: invokevirtual #863                // Method net/createmod/catnip/data/Couple.getFirst:()Ljava/lang/Object;
        36: checkcast     #392                // class java/lang/Boolean
        39: invokevirtual #395                // Method java/lang/Boolean.booleanValue:()Z
        42: ifeq          47
        45: iconst_1
        46: ireturn
        47: goto          10
        50: iconst_0
        51: ireturn

  public boolean hasBackwardConductor();
    Code:
         0: aload_0
         1: getfield      #177                // Field carriages:Ljava/util/List;
         4: invokeinterface #324,  1          // InterfaceMethod java/util/List.iterator:()Ljava/util/Iterator;
         9: astore_1
        10: aload_1
        11: invokeinterface #329,  1          // InterfaceMethod java/util/Iterator.hasNext:()Z
        16: ifeq          50
        19: aload_1
        20: invokeinterface #333,  1          // InterfaceMethod java/util/Iterator.next:()Ljava/lang/Object;
        25: checkcast     #21                 // class com/simibubi/create/content/trains/entity/Carriage
        28: astore_2
        29: aload_2
        30: getfield      #862                // Field com/simibubi/create/content/trains/entity/Carriage.presentConductors:Lnet/createmod/catnip/data/Couple;
        33: invokevirtual #865                // Method net/createmod/catnip/data/Couple.getSecond:()Ljava/lang/Object;
        36: checkcast     #392                // class java/lang/Boolean
        39: invokevirtual #395                // Method java/lang/Boolean.booleanValue:()Z
        42: ifeq          47
        45: iconst_1
        46: ireturn
        47: goto          10
        50: iconst_0
        51: ireturn

  private void collideWithOtherTrains(net.minecraft.world.level.Level, com.simibubi.create.content.trains.entity.Carriage);
    Code:
         0: aload_0
         1: getfield      #547                // Field derailed:Z
         4: ifeq          8
         7: return
         8: aload_2
         9: invokevirtual #560                // Method com/simibubi/create/content/trains/entity/Carriage.getTrailingPoint:()Lcom/simibubi/create/content/trains/entity/TravellingPoint;
        12: astore_3
        13: aload_2
        14: invokevirtual #557                // Method com/simibubi/create/content/trains/entity/Carriage.getLeadingPoint:()Lcom/simibubi/create/content/trains/entity/TravellingPoint;
        17: astore        4
        19: aload         4
        21: getfield      #564                // Field com/simibubi/create/content/trains/entity/TravellingPoint.node1:Lcom/simibubi/create/content/trains/graph/TrackNode;
        24: ifnull        49
        27: aload_3
        28: getfield      #564                // Field com/simibubi/create/content/trains/entity/TravellingPoint.node1:Lcom/simibubi/create/content/trains/graph/TrackNode;
        31: ifnull        49
        34: aload         4
        36: getfield      #869                // Field com/simibubi/create/content/trains/entity/TravellingPoint.edge:Lcom/simibubi/create/content/trains/graph/TrackEdge;
        39: ifnull        49
        42: aload_3
        43: getfield      #869                // Field com/simibubi/create/content/trains/entity/TravellingPoint.edge:Lcom/simibubi/create/content/trains/graph/TrackEdge;
        46: ifnonnull     50
        49: return
        50: aload         4
        52: getfield      #564                // Field com/simibubi/create/content/trains/entity/TravellingPoint.node1:Lcom/simibubi/create/content/trains/graph/TrackNode;
        55: invokevirtual #570                // Method com/simibubi/create/content/trains/graph/TrackNode.getLocation:()Lcom/simibubi/create/content/trains/graph/TrackNodeLocation;
        58: getfield      #576                // Field com/simibubi/create/content/trains/graph/TrackNodeLocation.dimension:Lnet/minecraft/resources/ResourceKey;
        61: astore        5
        63: aload         5
        65: aload_3
        66: getfield      #564                // Field com/simibubi/create/content/trains/entity/TravellingPoint.node1:Lcom/simibubi/create/content/trains/graph/TrackNode;
        69: invokevirtual #570                // Method com/simibubi/create/content/trains/graph/TrackNode.getLocation:()Lcom/simibubi/create/content/trains/graph/TrackNodeLocation;
        72: getfield      #576                // Field com/simibubi/create/content/trains/graph/TrackNodeLocation.dimension:Lnet/minecraft/resources/ResourceKey;
        75: invokevirtual #588                // Method net/minecraft/resources/ResourceKey.equals:(Ljava/lang/Object;)Z
        78: ifne          82
        81: return
        82: aload_0
        83: getfield      #159                // Field speed:D
        86: dconst_0
        87: dcmpg
        88: ifge          95
        91: aload_3
        92: goto          97
        95: aload         4
        97: aload_0
        98: getfield      #175                // Field graph:Lcom/simibubi/create/content/trains/graph/TrackGraph;
       101: invokevirtual #873                // Method com/simibubi/create/content/trains/entity/TravellingPoint.getPosition:(Lcom/simibubi/create/content/trains/graph/TrackGraph;)Lnet/minecraft/world/phys/Vec3;
       104: astore        6
       106: aload_0
       107: getfield      #159                // Field speed:D
       110: dconst_0
       111: dcmpg
       112: ifge          120
       115: aload         4
       117: goto          121
       120: aload_3
       121: aload_0
       122: getfield      #175                // Field graph:Lcom/simibubi/create/content/trains/graph/TrackGraph;
       125: invokevirtual #873                // Method com/simibubi/create/content/trains/entity/TravellingPoint.getPosition:(Lcom/simibubi/create/content/trains/graph/TrackGraph;)Lnet/minecraft/world/phys/Vec3;
       128: astore        7
       130: aload_0
       131: aload_1
       132: aload         6
       134: aload         7
       136: aload         5
       138: invokevirtual #877                // Method findCollidingTrain:(Lnet/minecraft/world/level/Level;Lnet/minecraft/world/phys/Vec3;Lnet/minecraft/world/phys/Vec3;Lnet/minecraft/resources/ResourceKey;)Lnet/createmod/catnip/data/Pair;
       141: astore        8
       143: aload         8
       145: ifnonnull     149
       148: return
       149: aload         8
       151: invokevirtual #398                // Method net/createmod/catnip/data/Pair.getFirst:()Ljava/lang/Object;
       154: checkcast     #2                  // class com/simibubi/create/content/trains/entity/Train
       157: astore        9
       159: aload_0
       160: getfield      #159                // Field speed:D
       163: invokestatic  #628                // Method java/lang/Math.abs:(D)D
       166: aload         9
       168: getfield      #159                // Field speed:D
       171: invokestatic  #628                // Method java/lang/Math.abs:(D)D
       174: dadd
       175: dstore        10
       177: dload         10
       179: ldc2_w        #878                // double 0.20000000298023224d
       182: dcmpl
       183: ifle          233
       186: aload         8
       188: invokevirtual #390                // Method net/createmod/catnip/data/Pair.getSecond:()Ljava/lang/Object;
       191: checkcast     #601                // class net/minecraft/world/phys/Vec3
       194: astore        12
       196: aload_1
       197: aconst_null
       198: aload         12
       200: getfield      #882                // Field net/minecraft/world/phys/Vec3.x:D
       203: aload         12
       205: getfield      #885                // Field net/minecraft/world/phys/Vec3.y:D
       208: aload         12
       210: getfield      #888                // Field net/minecraft/world/phys/Vec3.z:D
       213: ldc2_w        #843                // double 3.0d
       216: dload         10
       218: dmul
       219: ldc2_w        #656                // double 5.0d
       222: invokestatic  #857                // Method java/lang/Math.min:(DD)D
       225: d2f
       226: getstatic     #891                // Field net/minecraft/world/level/Level$ExplosionInteraction.NONE:Lnet/minecraft/world/level/Level$ExplosionInteraction;
       229: invokevirtual #895                // Method net/minecraft/world/level/Level.explode:(Lnet/minecraft/world/entity/Entity;DDDFLnet/minecraft/world/level/Level$ExplosionInteraction;)Lnet/minecraft/world/level/Explosion;
       232: pop
       233: aload_0
       234: invokevirtual #898                // Method crash:()V
       237: aload         9
       239: invokevirtual #898                // Method crash:()V
       242: return

  public net.createmod.catnip.data.Pair<com.simibubi.create.content.trains.entity.Train, net.minecraft.world.phys.Vec3> findCollidingTrain(net.minecraft.world.level.Level, net.minecraft.world.phys.Vec3, net.minecraft.world.phys.Vec3, net.minecraft.resources.ResourceKey<net.minecraft.world.level.Level>);
    Code:
         0: aload_3
         1: aload_2
         2: invokevirtual #910                // Method net/minecraft/world/phys/Vec3.subtract:(Lnet/minecraft/world/phys/Vec3;)Lnet/minecraft/world/phys/Vec3;
         5: astore        5
         7: invokestatic  #916                // Method com/simibubi/create/infrastructure/config/AllConfigs.server:()Lcom/simibubi/create/infrastructure/config/CServer;
        10: getfield      #921                // Field com/simibubi/create/infrastructure/config/CServer.trains:Lcom/simibubi/create/infrastructure/config/CTrains;
        13: getfield      #927                // Field com/simibubi/create/infrastructure/config/CTrains.maxAssemblyLength:Lnet/createmod/catnip/config/ConfigBase$ConfigInt;
        16: invokevirtual #929                // Method net/createmod/catnip/config/ConfigBase$ConfigInt.get:()Ljava/lang/Object;
        19: checkcast     #400                // class java/lang/Integer
        22: invokevirtual #403                // Method java/lang/Integer.intValue:()I
        25: i2d
        26: ldc2_w        #930                // double 2.0d
        29: invokestatic  #934                // Method java/lang/Math.pow:(DD)D
        32: dstore        6
        34: getstatic     #483                // Field com/simibubi/create/Create.RAILWAYS:Lcom/simibubi/create/content/trains/GlobalRailwayManager;
        37: aload_1
        38: invokevirtual #938                // Method com/simibubi/create/content/trains/GlobalRailwayManager.sided:(Lnet/minecraft/world/level/LevelAccessor;)Lcom/simibubi/create/content/trains/GlobalRailwayManager;
        41: getfield      #940                // Field com/simibubi/create/content/trains/GlobalRailwayManager.trains:Ljava/util/Map;
        44: invokeinterface #944,  1          // InterfaceMethod java/util/Map.values:()Ljava/util/Collection;
        49: invokeinterface #491,  1          // InterfaceMethod java/util/Collection.iterator:()Ljava/util/Iterator;
        54: astore        8
        56: aload         8
        58: invokeinterface #329,  1          // InterfaceMethod java/util/Iterator.hasNext:()Z
        63: ifeq          614
        66: aload         8
        68: invokeinterface #333,  1          // InterfaceMethod java/util/Iterator.next:()Ljava/lang/Object;
        73: checkcast     #2                  // class com/simibubi/create/content/trains/entity/Train
        76: astore        9
        78: aload         9
        80: aload_0
        81: if_acmpne     87
        84: goto          56
        87: aload         9
        89: getfield      #175                // Field graph:Lcom/simibubi/create/content/trains/graph/TrackGraph;
        92: ifnull        110
        95: aload         9
        97: getfield      #175                // Field graph:Lcom/simibubi/create/content/trains/graph/TrackGraph;
       100: aload_0
       101: getfield      #175                // Field graph:Lcom/simibubi/create/content/trains/graph/TrackGraph;
       104: if_acmpeq     110
       107: goto          56
       110: aconst_null
       111: astore        10
       113: aload         9
       115: getfield      #177                // Field carriages:Ljava/util/List;
       118: invokeinterface #324,  1          // InterfaceMethod java/util/List.iterator:()Ljava/util/Iterator;
       123: astore        11
       125: aload         11
       127: invokeinterface #329,  1          // InterfaceMethod java/util/Iterator.hasNext:()Z
       132: ifeq          611
       135: aload         11
       137: invokeinterface #333,  1          // InterfaceMethod java/util/Iterator.next:()Ljava/lang/Object;
       142: checkcast     #21                 // class com/simibubi/create/content/trains/entity/Carriage
       145: astore        12
       147: getstatic     #582                // Field net/createmod/catnip/data/Iterate.trueAndFalse:[Z
       150: astore        13
       152: aload         13
       154: arraylength
       155: istore        14
       157: iconst_0
       158: istore        15
       160: iload         15
       162: iload         14
       164: if_icmpge     608
       167: aload         13
       169: iload         15
       171: baload
       172: istore        16
       174: iload         16
       176: ifeq          187
       179: aload         10
       181: ifnonnull     187
       184: goto          602
       187: aload         12
       189: invokevirtual #557                // Method com/simibubi/create/content/trains/entity/Carriage.getLeadingPoint:()Lcom/simibubi/create/content/trains/entity/TravellingPoint;
       192: astore        17
       194: aload         12
       196: invokevirtual #560                // Method com/simibubi/create/content/trains/entity/Carriage.getTrailingPoint:()Lcom/simibubi/create/content/trains/entity/TravellingPoint;
       199: astore        18
       201: aload         17
       203: getfield      #869                // Field com/simibubi/create/content/trains/entity/TravellingPoint.edge:Lcom/simibubi/create/content/trains/graph/TrackEdge;
       206: ifnull        602
       209: aload         18
       211: getfield      #869                // Field com/simibubi/create/content/trains/entity/TravellingPoint.edge:Lcom/simibubi/create/content/trains/graph/TrackEdge;
       214: ifnonnull     220
       217: goto          602
       220: aload         17
       222: getfield      #564                // Field com/simibubi/create/content/trains/entity/TravellingPoint.node1:Lcom/simibubi/create/content/trains/graph/TrackNode;
       225: invokevirtual #570                // Method com/simibubi/create/content/trains/graph/TrackNode.getLocation:()Lcom/simibubi/create/content/trains/graph/TrackNodeLocation;
       228: getfield      #576                // Field com/simibubi/create/content/trains/graph/TrackNodeLocation.dimension:Lnet/minecraft/resources/ResourceKey;
       231: astore        19
       233: aload         19
       235: aload         18
       237: getfield      #564                // Field com/simibubi/create/content/trains/entity/TravellingPoint.node1:Lcom/simibubi/create/content/trains/graph/TrackNode;
       240: invokevirtual #570                // Method com/simibubi/create/content/trains/graph/TrackNode.getLocation:()Lcom/simibubi/create/content/trains/graph/TrackNodeLocation;
       243: getfield      #576                // Field com/simibubi/create/content/trains/graph/TrackNodeLocation.dimension:Lnet/minecraft/resources/ResourceKey;
       246: invokevirtual #588                // Method net/minecraft/resources/ResourceKey.equals:(Ljava/lang/Object;)Z
       249: ifne          255
       252: goto          602
       255: aload         19
       257: aload         4
       259: invokevirtual #588                // Method net/minecraft/resources/ResourceKey.equals:(Ljava/lang/Object;)Z
       262: ifne          268
       265: goto          602
       268: aload         17
       270: aload         9
       272: getfield      #175                // Field graph:Lcom/simibubi/create/content/trains/graph/TrackGraph;
       275: invokevirtual #873                // Method com/simibubi/create/content/trains/entity/TravellingPoint.getPosition:(Lcom/simibubi/create/content/trains/graph/TrackGraph;)Lnet/minecraft/world/phys/Vec3;
       278: astore        20
       280: aload         18
       282: aload         9
       284: getfield      #175                // Field graph:Lcom/simibubi/create/content/trains/graph/TrackGraph;
       287: invokevirtual #873                // Method com/simibubi/create/content/trains/entity/TravellingPoint.getPosition:(Lcom/simibubi/create/content/trains/graph/TrackGraph;)Lnet/minecraft/world/phys/Vec3;
       290: astore        21
       292: aload         20
       294: aload_2
       295: invokevirtual #605                // Method net/minecraft/world/phys/Vec3.distanceToSqr:(Lnet/minecraft/world/phys/Vec3;)D
       298: aload         21
       300: aload_2
       301: invokevirtual #605                // Method net/minecraft/world/phys/Vec3.distanceToSqr:(Lnet/minecraft/world/phys/Vec3;)D
       304: invokestatic  #857                // Method java/lang/Math.min:(DD)D
       307: dload         6
       309: dcmpl
       310: ifle          316
       313: goto          56
       316: iload         16
       318: ifeq          329
       321: aload         20
       323: astore        21
       325: aload         10
       327: astore        20
       329: aload         21
       331: astore        10
       333: aload_3
       334: getfield      #885                // Field net/minecraft/world/phys/Vec3.y:D
       337: aload         21
       339: getfield      #885                // Field net/minecraft/world/phys/Vec3.y:D
       342: ldc2_w        #843                // double 3.0d
       345: dsub
       346: dcmpg
       347: iflt          367
       350: aload         21
       352: getfield      #885                // Field net/minecraft/world/phys/Vec3.y:D
       355: aload_3
       356: getfield      #885                // Field net/minecraft/world/phys/Vec3.y:D
       359: ldc2_w        #843                // double 3.0d
       362: dsub
       363: dcmpg
       364: ifge          404
       367: aload_2
       368: getfield      #885                // Field net/minecraft/world/phys/Vec3.y:D
       371: aload         20
       373: getfield      #885                // Field net/minecraft/world/phys/Vec3.y:D
       376: ldc2_w        #843                // double 3.0d
       379: dsub
       380: dcmpg
       381: iflt          602
       384: aload         20
       386: getfield      #885                // Field net/minecraft/world/phys/Vec3.y:D
       389: aload_2
       390: getfield      #885                // Field net/minecraft/world/phys/Vec3.y:D
       393: ldc2_w        #843                // double 3.0d
       396: dsub
       397: dcmpg
       398: ifge          404
       401: goto          602
       404: aload         21
       406: aload         20
       408: invokevirtual #910                // Method net/minecraft/world/phys/Vec3.subtract:(Lnet/minecraft/world/phys/Vec3;)Lnet/minecraft/world/phys/Vec3;
       411: astore        22
       413: aload         5
       415: invokevirtual #947                // Method net/minecraft/world/phys/Vec3.normalize:()Lnet/minecraft/world/phys/Vec3;
       418: astore        23
       420: aload         22
       422: invokevirtual #947                // Method net/minecraft/world/phys/Vec3.normalize:()Lnet/minecraft/world/phys/Vec3;
       425: astore        24
       427: aload_2
       428: aload         20
       430: aload         23
       432: aload         24
       434: getstatic     #951                // Field net/minecraft/core/Direction$Axis.Y:Lnet/minecraft/core/Direction$Axis;
       437: invokestatic  #957                // Method net/createmod/catnip/math/VecHelper.intersect:(Lnet/minecraft/world/phys/Vec3;Lnet/minecraft/world/phys/Vec3;Lnet/minecraft/world/phys/Vec3;Lnet/minecraft/world/phys/Vec3;Lnet/minecraft/core/Direction$Axis;)[D
       440: astore        25
       442: aload         25
       444: ifnonnull     527
       447: aload         20
       449: aload         24
       451: aload_2
       452: ldc2_w        #662                // double 0.125d
       455: invokestatic  #961                // Method net/createmod/catnip/math/VecHelper.intersectSphere:(Lnet/minecraft/world/phys/Vec3;Lnet/minecraft/world/phys/Vec3;Lnet/minecraft/world/phys/Vec3;D)Lnet/minecraft/world/phys/Vec3;
       458: astore        26
       460: aload         26
       462: ifnonnull     468
       465: goto          602
       468: aload         24
       470: aload         26
       472: aload         20
       474: invokevirtual #910                // Method net/minecraft/world/phys/Vec3.subtract:(Lnet/minecraft/world/phys/Vec3;)Lnet/minecraft/world/phys/Vec3;
       477: invokevirtual #947                // Method net/minecraft/world/phys/Vec3.normalize:()Lnet/minecraft/world/phys/Vec3;
       480: invokevirtual #965                // Method net/minecraft/world/phys/Vec3.dot:(Lnet/minecraft/world/phys/Vec3;)D
       483: dconst_1
       484: invokestatic  #848                // Method net/minecraft/util/Mth.equal:(DD)Z
       487: ifne          493
       490: goto          602
       493: iconst_2
       494: newarray       double
       496: astore        25
       498: aload         25
       500: iconst_0
       501: aload         26
       503: aload_2
       504: invokevirtual #967                // Method net/minecraft/world/phys/Vec3.distanceTo:(Lnet/minecraft/world/phys/Vec3;)D
       507: ldc2_w        #662                // double 0.125d
       510: dsub
       511: dastore
       512: aload         25
       514: iconst_1
       515: aload         26
       517: aload         20
       519: invokevirtual #967                // Method net/minecraft/world/phys/Vec3.distanceTo:(Lnet/minecraft/world/phys/Vec3;)D
       522: ldc2_w        #662                // double 0.125d
       525: dsub
       526: dastore
       527: aload         25
       529: iconst_0
       530: daload
       531: aload         5
       533: invokevirtual #970                // Method net/minecraft/world/phys/Vec3.length:()D
       536: dcmpl
       537: ifle          543
       540: goto          602
       543: aload         25
       545: iconst_1
       546: daload
       547: aload         22
       549: invokevirtual #970                // Method net/minecraft/world/phys/Vec3.length:()D
       552: dcmpl
       553: ifle          559
       556: goto          602
       559: aload         25
       561: iconst_0
       562: daload
       563: dconst_0
       564: dcmpg
       565: ifge          571
       568: goto          602
       571: aload         25
       573: iconst_1
       574: daload
       575: dconst_0
       576: dcmpg
       577: ifge          583
       580: goto          602
       583: aload         9
       585: aload_2
       586: aload         23
       588: aload         25
       590: iconst_0
       591: daload
       592: invokevirtual #974                // Method net/minecraft/world/phys/Vec3.scale:(D)Lnet/minecraft/world/phys/Vec3;
       595: invokevirtual #976                // Method net/minecraft/world/phys/Vec3.add:(Lnet/minecraft/world/phys/Vec3;)Lnet/minecraft/world/phys/Vec3;
       598: invokestatic  #455                // Method net/createmod/catnip/data/Pair.of:(Ljava/lang/Object;Ljava/lang/Object;)Lnet/createmod/catnip/data/Pair;
       601: areturn
       602: iinc          15, 1
       605: goto          160
       608: goto          125
       611: goto          56
       614: aconst_null
       615: areturn

  public void crash();
    Code:
         0: aload_0
         1: getfield      #242                // Field navigation:Lcom/simibubi/create/content/trains/entity/Navigation;
         4: invokevirtual #693                // Method com/simibubi/create/content/trains/entity/Navigation.cancelNavigation:()V
         7: aload_0
         8: getfield      #547                // Field derailed:Z
        11: ifeq          15
        14: return
        15: aload_0
        16: aload_0
        17: getfield      #159                // Field speed:D
        20: ldc2_w        #990                // double -0.5d
        23: ldc2_w        #660                // double 0.5d
        26: invokestatic  #652                // Method net/minecraft/util/Mth.clamp:(DDD)D
        29: dneg
        30: putfield      #159                // Field speed:D
        33: aload_0
        34: iconst_1
        35: putfield      #547                // Field derailed:Z
        38: aload_0
        39: aconst_null
        40: putfield      #175                // Field graph:Lcom/simibubi/create/content/trains/graph/TrackGraph;
        43: aload_0
        44: getfield      #212                // Field status:Lcom/simibubi/create/content/trains/entity/TrainStatus;
        47: invokevirtual #992                // Method com/simibubi/create/content/trains/entity/TrainStatus.crash:()V
        50: aload_0
        51: getfield      #177                // Field carriages:Ljava/util/List;
        54: invokeinterface #324,  1          // InterfaceMethod java/util/List.iterator:()Ljava/util/Iterator;
        59: astore_1
        60: aload_1
        61: invokeinterface #329,  1          // InterfaceMethod java/util/Iterator.hasNext:()Z
        66: ifeq          91
        69: aload_1
        70: invokeinterface #333,  1          // InterfaceMethod java/util/Iterator.next:()Ljava/lang/Object;
        75: checkcast     #21                 // class com/simibubi/create/content/trains/entity/Carriage
        78: astore_2
        79: aload_2
        80: invokedynamic #999,  0            // InvokeDynamic #6:accept:()Ljava/util/function/Consumer;
        85: invokevirtual #1002               // Method com/simibubi/create/content/trains/entity/Carriage.forEachPresentEntity:(Ljava/util/function/Consumer;)V
        88: goto          60
        91: aload_0
        92: getfield      #690                // Field backwardsDriver:Lnet/minecraft/world/entity/player/Player;
        95: ifnull        108
        98: getstatic     #1008               // Field com/simibubi/create/foundation/advancement/AllAdvancements.TRAIN_CRASH_BACKWARDS:Lcom/simibubi/create/foundation/advancement/CreateAdvancement;
       101: aload_0
       102: getfield      #690                // Field backwardsDriver:Lnet/minecraft/world/entity/player/Player;
       105: invokevirtual #1014               // Method com/simibubi/create/foundation/advancement/CreateAdvancement.awardTo:(Lnet/minecraft/world/entity/player/Player;)V
       108: return

  public boolean disassemble(net.minecraft.core.Direction, net.minecraft.core.BlockPos);
    Code:
         0: aload_0
         1: invokevirtual #1019               // Method canDisassemble:()Z
         4: ifne          9
         7: iconst_0
         8: ireturn
         9: iconst_1
        10: istore_3
        11: aload_0
        12: getfield      #1021               // Field currentlyBackwards:Z
        15: istore        4
        17: aconst_null
        18: astore        5
        20: iconst_0
        21: istore        6
        23: iload         6
        25: aload_0
        26: getfield      #177                // Field carriages:Ljava/util/List;
        29: invokeinterface #193,  1          // InterfaceMethod java/util/List.size:()I
        34: if_icmpge     346
        37: aload_0
        38: getfield      #177                // Field carriages:Ljava/util/List;
        41: iload         4
        43: ifeq          63
        46: aload_0
        47: getfield      #177                // Field carriages:Ljava/util/List;
        50: invokeinterface #193,  1          // InterfaceMethod java/util/List.size:()I
        55: iload         6
        57: isub
        58: iconst_1
        59: isub
        60: goto          65
        63: iload         6
        65: invokeinterface #553,  2          // InterfaceMethod java/util/List.get:(I)Ljava/lang/Object;
        70: checkcast     #21                 // class com/simibubi/create/content/trains/entity/Carriage
        73: astore        7
        75: aload         7
        77: invokevirtual #1027               // Method com/simibubi/create/content/trains/entity/Carriage.anyAvailableEntity:()Lcom/simibubi/create/content/trains/entity/CarriageContraptionEntity;
        80: astore        8
        82: aload         8
        84: ifnonnull     89
        87: iconst_0
        88: ireturn
        89: aload         8
        91: invokevirtual #1032               // Method com/simibubi/create/content/trains/entity/CarriageContraptionEntity.level:()Lnet/minecraft/world/level/Level;
        94: astore        5
        96: aload         8
        98: invokevirtual #1036               // Method com/simibubi/create/content/trains/entity/CarriageContraptionEntity.getContraption:()Lcom/simibubi/create/content/contraptions/Contraption;
       101: astore        10
       103: aload         10
       105: instanceof    #1038               // class com/simibubi/create/content/trains/entity/CarriageContraption
       108: ifeq          128
       111: aload         10
       113: checkcast     #1038               // class com/simibubi/create/content/trains/entity/CarriageContraption
       116: astore        9
       118: aload         9
       120: aload         7
       122: getfield      #337                // Field com/simibubi/create/content/trains/entity/Carriage.storage:Lcom/simibubi/create/content/contraptions/minecart/TrainCargoManager;
       125: invokevirtual #1042               // Method com/simibubi/create/content/trains/entity/CarriageContraption.returnStorageForDisassembly:(Lcom/simibubi/create/content/contraptions/MountedStorageManager;)V
       128: aload         8
       130: aload_2
       131: aload_1
       132: iload         4
       134: ifeq          147
       137: iload_3
       138: aload         7
       140: getfield      #679                // Field com/simibubi/create/content/trains/entity/Carriage.bogeySpacing:I
       143: iadd
       144: goto          148
       147: iload_3
       148: invokevirtual #1046               // Method net/minecraft/core/BlockPos.relative:(Lnet/minecraft/core/Direction;I)Lnet/minecraft/core/BlockPos;
       151: aload         7
       153: invokevirtual #609                // Method com/simibubi/create/content/trains/entity/Carriage.leadingBogey:()Lcom/simibubi/create/content/trains/entity/CarriageBogey;
       156: invokevirtual #614                // Method com/simibubi/create/content/trains/entity/CarriageBogey.isUpsideDown:()Z
       159: ifeq          166
       162: iconst_2
       163: goto          167
       166: iconst_0
       167: invokevirtual #1050               // Method net/minecraft/core/BlockPos.below:(I)Lnet/minecraft/core/BlockPos;
       170: invokestatic  #1054               // Method net/minecraft/world/phys/Vec3.atLowerCornerOf:(Lnet/minecraft/core/Vec3i;)Lnet/minecraft/world/phys/Vec3;
       173: invokevirtual #1058               // Method com/simibubi/create/content/trains/entity/CarriageContraptionEntity.setPos:(Lnet/minecraft/world/phys/Vec3;)V
       176: aload         8
       178: invokevirtual #1060               // Method com/simibubi/create/content/trains/entity/CarriageContraptionEntity.disassemble:()V
       181: aload         7
       183: getfield      #1063               // Field com/simibubi/create/content/trains/entity/Carriage.bogeys:Lnet/createmod/catnip/data/Couple;
       186: invokevirtual #1064               // Method net/createmod/catnip/data/Couple.iterator:()Ljava/util/Iterator;
       189: astore        9
       191: aload         9
       193: invokeinterface #329,  1          // InterfaceMethod java/util/Iterator.hasNext:()Z
       198: ifeq          276
       201: aload         9
       203: invokeinterface #333,  1          // InterfaceMethod java/util/Iterator.next:()Ljava/lang/Object;
       208: checkcast     #611                // class com/simibubi/create/content/trains/entity/CarriageBogey
       211: astore        10
       213: aload         10
       215: ifnonnull     221
       218: goto          191
       221: aload         10
       223: invokevirtual #1067               // Method com/simibubi/create/content/trains/entity/CarriageBogey.getAnchorPosition:()Lnet/minecraft/world/phys/Vec3;
       226: astore        11
       228: aload         11
       230: ifnonnull     236
       233: goto          191
       236: aload         5
       238: aload         11
       240: invokestatic  #1071               // Method net/minecraft/core/BlockPos.containing:(Lnet/minecraft/core/Position;)Lnet/minecraft/core/BlockPos;
       243: invokevirtual #1075               // Method net/minecraft/world/level/Level.getBlockEntity:(Lnet/minecraft/core/BlockPos;)Lnet/minecraft/world/level/block/entity/BlockEntity;
       246: astore        12
       248: aload         12
       250: instanceof    #1077               // class com/simibubi/create/content/trains/bogey/AbstractBogeyBlockEntity
       253: ifeq          191
       256: aload         12
       258: checkcast     #1077               // class com/simibubi/create/content/trains/bogey/AbstractBogeyBlockEntity
       261: astore        13
       263: aload         13
       265: aload         10
       267: getfield      #1081               // Field com/simibubi/create/content/trains/entity/CarriageBogey.bogeyData:Lnet/minecraft/nbt/CompoundTag;
       270: invokevirtual #1085               // Method com/simibubi/create/content/trains/bogey/AbstractBogeyBlockEntity.setBogeyData:(Lnet/minecraft/nbt/CompoundTag;)V
       273: goto          191
       276: iload_3
       277: aload         7
       279: getfield      #679                // Field com/simibubi/create/content/trains/entity/Carriage.bogeySpacing:I
       282: iadd
       283: istore_3
       284: iload         6
       286: aload_0
       287: getfield      #179                // Field carriageSpacing:Ljava/util/List;
       290: invokeinterface #193,  1          // InterfaceMethod java/util/List.size:()I
       295: if_icmpge     340
       298: iload_3
       299: aload_0
       300: getfield      #179                // Field carriageSpacing:Ljava/util/List;
       303: iload         4
       305: ifeq          325
       308: aload_0
       309: getfield      #179                // Field carriageSpacing:Ljava/util/List;
       312: invokeinterface #193,  1          // InterfaceMethod java/util/List.size:()I
       317: iload         6
       319: isub
       320: iconst_1
       321: isub
       322: goto          327
       325: iload         6
       327: invokeinterface #553,  2          // InterfaceMethod java/util/List.get:(I)Ljava/lang/Object;
       332: checkcast     #400                // class java/lang/Integer
       335: invokevirtual #403                // Method java/lang/Integer.intValue:()I
       338: iadd
       339: istore_3
       340: iinc          6, 1
       343: goto          23
       346: aload_0
       347: invokevirtual #533                // Method getCurrentStation:()Lcom/simibubi/create/content/trains/station/GlobalStation;
       350: astore        6
       352: aload         6
       354: ifnull        417
       357: aload         6
       359: aload_0
       360: invokevirtual #1088               // Method com/simibubi/create/content/trains/station/GlobalStation.cancelReservation:(Lcom/simibubi/create/content/trains/entity/Train;)V
       363: aload         6
       365: invokevirtual #1092               // Method com/simibubi/create/content/trains/station/GlobalStation.getBlockEntityPos:()Lnet/minecraft/core/BlockPos;
       368: astore        7
       370: aload         5
       372: aload         7
       374: invokevirtual #1075               // Method net/minecraft/world/level/Level.getBlockEntity:(Lnet/minecraft/core/BlockPos;)Lnet/minecraft/world/level/block/entity/BlockEntity;
       377: astore        9
       379: aload         9
       381: instanceof    #1094               // class com/simibubi/create/content/trains/station/StationBlockEntity
       384: ifeq          417
       387: aload         9
       389: checkcast     #1094               // class com/simibubi/create/content/trains/station/StationBlockEntity
       392: astore        8
       394: aload         8
       396: aload_0
       397: getfield      #205                // Field name:Lnet/minecraft/network/chat/Component;
       400: invokeinterface #1098,  1         // InterfaceMethod net/minecraft/network/chat/Component.copy:()Lnet/minecraft/network/chat/MutableComponent;
       405: putfield      #1101               // Field com/simibubi/create/content/trains/station/StationBlockEntity.lastDisassembledTrainName:Lnet/minecraft/network/chat/Component;
       408: aload         8
       410: aload_0
       411: getfield      #1103               // Field mapColorIndex:I
       414: putfield      #1106               // Field com/simibubi/create/content/trains/station/StationBlockEntity.lastDisassembledMapColorIndex:I
       417: getstatic     #483                // Field com/simibubi/create/Create.RAILWAYS:Lcom/simibubi/create/content/trains/GlobalRailwayManager;
       420: aload_0
       421: getfield      #171                // Field id:Ljava/util/UUID;
       424: invokevirtual #1110               // Method com/simibubi/create/content/trains/GlobalRailwayManager.removeTrain:(Ljava/util/UUID;)V
       427: invokestatic  #1116               // Method com/simibubi/create/AllPackets.getChannel:()Lnet/minecraftforge/network/simple/SimpleChannel;
       430: getstatic     #1120               // Field net/minecraftforge/network/PacketDistributor.ALL:Lnet/minecraftforge/network/PacketDistributor;
       433: invokevirtual #1124               // Method net/minecraftforge/network/PacketDistributor.noArg:()Lnet/minecraftforge/network/PacketDistributor$PacketTarget;
       436: new           #1126               // class com/simibubi/create/content/trains/entity/TrainPacket
       439: dup
       440: aload_0
       441: iconst_0
       442: invokespecial #1129               // Method com/simibubi/create/content/trains/entity/TrainPacket."<init>":(Lcom/simibubi/create/content/trains/entity/Train;Z)V
       445: invokevirtual #1135               // Method net/minecraftforge/network/simple/SimpleChannel.send:(Lnet/minecraftforge/network/PacketDistributor$PacketTarget;Ljava/lang/Object;)V
       448: iconst_1
       449: ireturn

  public boolean canDisassemble();
    Code:
         0: aload_0
         1: getfield      #177                // Field carriages:Ljava/util/List;
         4: invokeinterface #324,  1          // InterfaceMethod java/util/List.iterator:()Ljava/util/Iterator;
         9: astore_1
        10: aload_1
        11: invokeinterface #329,  1          // InterfaceMethod java/util/Iterator.hasNext:()Z
        16: ifeq          90
        19: aload_1
        20: invokeinterface #333,  1          // InterfaceMethod java/util/Iterator.next:()Ljava/lang/Object;
        25: checkcast     #21                 // class com/simibubi/create/content/trains/entity/Carriage
        28: astore_2
        29: aload_2
        30: invokevirtual #1158               // Method com/simibubi/create/content/trains/entity/Carriage.presentInMultipleDimensions:()Z
        33: ifeq          38
        36: iconst_0
        37: ireturn
        38: aload_2
        39: invokevirtual #1027               // Method com/simibubi/create/content/trains/entity/Carriage.anyAvailableEntity:()Lcom/simibubi/create/content/trains/entity/CarriageContraptionEntity;
        42: astore_3
        43: aload_3
        44: ifnonnull     49
        47: iconst_0
        48: ireturn
        49: aload_3
        50: getfield      #1161               // Field com/simibubi/create/content/trains/entity/CarriageContraptionEntity.pitch:F
        53: fconst_0
        54: invokestatic  #1164               // Method net/minecraft/util/Mth.equal:(FF)Z
        57: ifne          62
        60: iconst_0
        61: ireturn
        62: aload_3
        63: getfield      #1167               // Field com/simibubi/create/content/trains/entity/CarriageContraptionEntity.yaw:F
        66: ldc_w         #1168               // float 90.0f
        69: frem
        70: ldc_w         #1169               // float 360.0f
        73: fadd
        74: ldc_w         #1168               // float 90.0f
        77: frem
        78: fconst_0
        79: invokestatic  #1164               // Method net/minecraft/util/Mth.equal:(FF)Z
        82: ifne          87
        85: iconst_0
        86: ireturn
        87: goto          10
        90: iconst_1
        91: ireturn

  public boolean isTravellingOn(com.simibubi.create.content.trains.graph.TrackNode);
    Code:
         0: new           #1173               // class org/apache/commons/lang3/mutable/MutableBoolean
         3: dup
         4: iconst_0
         5: invokespecial #1176               // Method org/apache/commons/lang3/mutable/MutableBoolean."<init>":(Z)V
         8: astore_2
         9: aload_0
        10: aload_1
        11: aload_2
        12: invokedynamic #1186,  0           // InvokeDynamic #7:accept:(Lcom/simibubi/create/content/trains/graph/TrackNode;Lorg/apache/commons/lang3/mutable/MutableBoolean;)Ljava/util/function/Consumer;
        17: invokevirtual #1189               // Method forEachTravellingPoint:(Ljava/util/function/Consumer;)V
        20: aload_2
        21: invokevirtual #1190               // Method org/apache/commons/lang3/mutable/MutableBoolean.booleanValue:()Z
        24: ireturn

  public void detachFromTracks();
    Code:
         0: aload_0
         1: getfield      #250                // Field migratingPoints:Ljava/util/List;
         4: invokeinterface #1197,  1         // InterfaceMethod java/util/List.clear:()V
         9: aload_0
        10: getfield      #242                // Field navigation:Lcom/simibubi/create/content/trains/entity/Navigation;
        13: invokevirtual #693                // Method com/simibubi/create/content/trains/entity/Navigation.cancelNavigation:()V
        16: aload_0
        17: aload_0
        18: invokedynamic #1202,  0           // InvokeDynamic #8:accept:(Lcom/simibubi/create/content/trains/entity/Train;)Ljava/util/function/Consumer;
        23: invokevirtual #1189               // Method forEachTravellingPoint:(Ljava/util/function/Consumer;)V
        26: aload_0
        27: aconst_null
        28: putfield      #175                // Field graph:Lcom/simibubi/create/content/trains/graph/TrackGraph;
        31: return

  public void forEachTravellingPoint(java.util.function.Consumer<com.simibubi.create.content.trains.entity.TravellingPoint>);
    Code:
         0: aload_0
         1: getfield      #177                // Field carriages:Ljava/util/List;
         4: invokeinterface #324,  1          // InterfaceMethod java/util/List.iterator:()Ljava/util/Iterator;
         9: astore_2
        10: aload_2
        11: invokeinterface #329,  1          // InterfaceMethod java/util/Iterator.hasNext:()Z
        16: ifeq          81
        19: aload_2
        20: invokeinterface #333,  1          // InterfaceMethod java/util/Iterator.next:()Ljava/lang/Object;
        25: checkcast     #21                 // class com/simibubi/create/content/trains/entity/Carriage
        28: astore_3
        29: aload_3
        30: invokevirtual #609                // Method com/simibubi/create/content/trains/entity/Carriage.leadingBogey:()Lcom/simibubi/create/content/trains/entity/CarriageBogey;
        33: getfield      #1206               // Field com/simibubi/create/content/trains/entity/CarriageBogey.points:Lnet/createmod/catnip/data/Couple;
        36: aload_1
        37: dup
        38: invokestatic  #1211               // Method java/util/Objects.requireNonNull:(Ljava/lang/Object;)Ljava/lang/Object;
        41: pop
        42: invokedynamic #1219,  0           // InvokeDynamic #9:accept:(Ljava/util/function/Consumer;)Ljava/util/function/Consumer;
        47: invokevirtual #1220               // Method net/createmod/catnip/data/Couple.forEach:(Ljava/util/function/Consumer;)V
        50: aload_3
        51: invokevirtual #676                // Method com/simibubi/create/content/trains/entity/Carriage.isOnTwoBogeys:()Z
        54: ifeq          78
        57: aload_3
        58: invokevirtual #617                // Method com/simibubi/create/content/trains/entity/Carriage.trailingBogey:()Lcom/simibubi/create/content/trains/entity/CarriageBogey;
        61: getfield      #1206               // Field com/simibubi/create/content/trains/entity/CarriageBogey.points:Lnet/createmod/catnip/data/Couple;
        64: aload_1
        65: dup
        66: invokestatic  #1211               // Method java/util/Objects.requireNonNull:(Ljava/lang/Object;)Ljava/lang/Object;
        69: pop
        70: invokedynamic #1219,  0           // InvokeDynamic #9:accept:(Ljava/util/function/Consumer;)Ljava/util/function/Consumer;
        75: invokevirtual #1220               // Method net/createmod/catnip/data/Couple.forEach:(Ljava/util/function/Consumer;)V
        78: goto          10
        81: return

  public void forEachTravellingPointBackwards(java.util.function.BiConsumer<com.simibubi.create.content.trains.entity.TravellingPoint, java.lang.Double>);
    Code:
         0: dconst_0
         1: dstore_2
         2: iconst_0
         3: istore        4
         5: iload         4
         7: aload_0
         8: getfield      #177                // Field carriages:Ljava/util/List;
        11: invokeinterface #193,  1          // InterfaceMethod java/util/List.size:()I
        16: if_icmpge     230
        19: aload_0
        20: getfield      #177                // Field carriages:Ljava/util/List;
        23: invokeinterface #193,  1          // InterfaceMethod java/util/List.size:()I
        28: iload         4
        30: isub
        31: iconst_1
        32: isub
        33: istore        5
        35: aload_0
        36: getfield      #177                // Field carriages:Ljava/util/List;
        39: iload         5
        41: invokeinterface #553,  2          // InterfaceMethod java/util/List.get:(I)Ljava/lang/Object;
        46: checkcast     #21                 // class com/simibubi/create/content/trains/entity/Carriage
        49: astore        6
        51: aload         6
        53: invokevirtual #617                // Method com/simibubi/create/content/trains/entity/Carriage.trailingBogey:()Lcom/simibubi/create/content/trains/entity/CarriageBogey;
        56: astore        7
        58: aload         7
        60: getfield      #1231               // Field com/simibubi/create/content/trains/entity/CarriageBogey.type:Lcom/simibubi/create/content/trains/bogey/AbstractBogeyBlock;
        63: invokevirtual #1236               // Method com/simibubi/create/content/trains/bogey/AbstractBogeyBlock.getWheelPointSpacing:()D
        66: dstore        8
        68: aload_1
        69: aload         7
        71: invokevirtual #1239               // Method com/simibubi/create/content/trains/entity/CarriageBogey.trailing:()Lcom/simibubi/create/content/trains/entity/TravellingPoint;
        74: iload         4
        76: ifne          83
        79: dconst_0
        80: goto          110
        83: aload_0
        84: getfield      #179                // Field carriageSpacing:Ljava/util/List;
        87: iload         5
        89: invokeinterface #553,  2          // InterfaceMethod java/util/List.get:(I)Ljava/lang/Object;
        94: checkcast     #400                // class java/lang/Integer
        97: invokevirtual #403                // Method java/lang/Integer.intValue:()I
       100: i2d
       101: dload_2
       102: dsub
       103: dload         8
       105: ldc2_w        #930                // double 2.0d
       108: ddiv
       109: dsub
       110: invokestatic  #640                // Method java/lang/Double.valueOf:(D)Ljava/lang/Double;
       113: invokeinterface #1244,  3         // InterfaceMethod java/util/function/BiConsumer.accept:(Ljava/lang/Object;Ljava/lang/Object;)V
       118: aload_1
       119: aload         7
       121: invokevirtual #1247               // Method com/simibubi/create/content/trains/entity/CarriageBogey.leading:()Lcom/simibubi/create/content/trains/entity/TravellingPoint;
       124: dload         8
       126: invokestatic  #640                // Method java/lang/Double.valueOf:(D)Ljava/lang/Double;
       129: invokeinterface #1244,  3         // InterfaceMethod java/util/function/BiConsumer.accept:(Ljava/lang/Object;Ljava/lang/Object;)V
       134: dload         8
       136: ldc2_w        #930                // double 2.0d
       139: ddiv
       140: dstore_2
       141: aload         6
       143: invokevirtual #676                // Method com/simibubi/create/content/trains/entity/Carriage.isOnTwoBogeys:()Z
       146: ifne          152
       149: goto          224
       152: aload         6
       154: invokevirtual #609                // Method com/simibubi/create/content/trains/entity/Carriage.leadingBogey:()Lcom/simibubi/create/content/trains/entity/CarriageBogey;
       157: astore        10
       159: aload         6
       161: invokevirtual #609                // Method com/simibubi/create/content/trains/entity/Carriage.leadingBogey:()Lcom/simibubi/create/content/trains/entity/CarriageBogey;
       164: getfield      #1231               // Field com/simibubi/create/content/trains/entity/CarriageBogey.type:Lcom/simibubi/create/content/trains/bogey/AbstractBogeyBlock;
       167: invokevirtual #1236               // Method com/simibubi/create/content/trains/bogey/AbstractBogeyBlock.getWheelPointSpacing:()D
       170: dstore        11
       172: aload_1
       173: aload         10
       175: invokevirtual #1239               // Method com/simibubi/create/content/trains/entity/CarriageBogey.trailing:()Lcom/simibubi/create/content/trains/entity/TravellingPoint;
       178: aload         6
       180: getfield      #679                // Field com/simibubi/create/content/trains/entity/Carriage.bogeySpacing:I
       183: i2d
       184: dload_2
       185: dsub
       186: dload         11
       188: ldc2_w        #930                // double 2.0d
       191: ddiv
       192: dsub
       193: invokestatic  #640                // Method java/lang/Double.valueOf:(D)Ljava/lang/Double;
       196: invokeinterface #1244,  3         // InterfaceMethod java/util/function/BiConsumer.accept:(Ljava/lang/Object;Ljava/lang/Object;)V
       201: aload_1
       202: aload         7
       204: invokevirtual #1247               // Method com/simibubi/create/content/trains/entity/CarriageBogey.leading:()Lcom/simibubi/create/content/trains/entity/TravellingPoint;
       207: dload         11
       209: invokestatic  #640                // Method java/lang/Double.valueOf:(D)Ljava/lang/Double;
       212: invokeinterface #1244,  3         // InterfaceMethod java/util/function/BiConsumer.accept:(Ljava/lang/Object;Ljava/lang/Object;)V
       217: dload         11
       219: ldc2_w        #930                // double 2.0d
       222: ddiv
       223: dstore_2
       224: iinc          4, 1
       227: goto          5
       230: return

  public void reattachToTracks(net.minecraft.world.level.Level);
    Code:
         0: aload_0
         1: getfield      #1254               // Field migrationCooldown:I
         4: ifle          18
         7: aload_0
         8: dup
         9: getfield      #1254               // Field migrationCooldown:I
        12: iconst_1
        13: isub
        14: putfield      #1254               // Field migrationCooldown:I
        17: return
        18: new           #264                // class java/util/HashSet
        21: dup
        22: getstatic     #483                // Field com/simibubi/create/Create.RAILWAYS:Lcom/simibubi/create/content/trains/GlobalRailwayManager;
        25: getfield      #1257               // Field com/simibubi/create/content/trains/GlobalRailwayManager.trackNetworks:Ljava/util/Map;
        28: invokeinterface #1260,  1         // InterfaceMethod java/util/Map.entrySet:()Ljava/util/Set;
        33: invokespecial #1262               // Method java/util/HashSet."<init>":(Ljava/util/Collection;)V
        36: astore_2
        37: new           #259                // class java/util/HashMap
        40: dup
        41: invokespecial #260                // Method java/util/HashMap."<init>":()V
        44: astore_3
        45: aload_0
        46: getfield      #250                // Field migratingPoints:Ljava/util/List;
        49: invokeinterface #324,  1          // InterfaceMethod java/util/List.iterator:()Ljava/util/Iterator;
        54: astore        4
        56: aload         4
        58: invokeinterface #329,  1          // InterfaceMethod java/util/Iterator.hasNext:()Z
        63: ifeq          178
        66: aload         4
        68: invokeinterface #333,  1          // InterfaceMethod java/util/Iterator.next:()Ljava/lang/Object;
        73: checkcast     #1264               // class com/simibubi/create/content/trains/entity/TrainMigration
        76: astore        5
        78: aload_2
        79: invokeinterface #343,  1          // InterfaceMethod java/util/Set.iterator:()Ljava/util/Iterator;
        84: astore        6
        86: aload         6
        88: invokeinterface #329,  1          // InterfaceMethod java/util/Iterator.hasNext:()Z
        93: ifeq          175
        96: aload         6
        98: invokeinterface #333,  1          // InterfaceMethod java/util/Iterator.next:()Ljava/lang/Object;
       103: checkcast     #52                 // class java/util/Map$Entry
       106: astore        7
       108: aload         5
       110: aload         7
       112: invokeinterface #1267,  1         // InterfaceMethod java/util/Map$Entry.getValue:()Ljava/lang/Object;
       117: checkcast     #353                // class com/simibubi/create/content/trains/graph/TrackGraph
       120: invokevirtual #1271               // Method com/simibubi/create/content/trains/entity/TrainMigration.tryMigratingTo:(Lcom/simibubi/create/content/trains/graph/TrackGraph;)Lcom/simibubi/create/content/trains/graph/TrackGraphLocation;
       123: astore        8
       125: aload         8
       127: ifnonnull     140
       130: aload         6
       132: invokeinterface #499,  1          // InterfaceMethod java/util/Iterator.remove:()V
       137: goto          86
       140: aload_3
       141: aload         7
       143: invokeinterface #1276,  1         // InterfaceMethod java/util/Map$Entry.getKey:()Ljava/lang/Object;
       148: checkcast     #345                // class java/util/UUID
       151: invokedynamic #1283,  0           // InvokeDynamic #10:apply:()Ljava/util/function/Function;
       156: invokeinterface #385,  3          // InterfaceMethod java/util/Map.computeIfAbsent:(Ljava/lang/Object;Ljava/util/function/Function;)Ljava/lang/Object;
       161: checkcast     #189                // class java/util/List
       164: aload         8
       166: invokeinterface #1284,  2         // InterfaceMethod java/util/List.add:(Ljava/lang/Object;)Z
       171: pop
       172: goto          86
       175: goto          56
       178: aload_2
       179: invokeinterface #315,  1          // InterfaceMethod java/util/Set.isEmpty:()Z
       184: ifeq          206
       187: aload_0
       188: bipush        40
       190: putfield      #1254               // Field migrationCooldown:I
       193: aload_0
       194: getfield      #212                // Field status:Lcom/simibubi/create/content/trains/entity/TrainStatus;
       197: invokevirtual #1287               // Method com/simibubi/create/content/trains/entity/TrainStatus.failedMigration:()V
       200: aload_0
       201: iconst_1
       202: putfield      #547                // Field derailed:Z
       205: return
       206: aload_2
       207: invokeinterface #343,  1          // InterfaceMethod java/util/Set.iterator:()Ljava/util/Iterator;
       212: astore        4
       214: aload         4
       216: invokeinterface #329,  1          // InterfaceMethod java/util/Iterator.hasNext:()Z
       221: ifeq          368
       224: aload         4
       226: invokeinterface #333,  1          // InterfaceMethod java/util/Iterator.next:()Ljava/lang/Object;
       231: checkcast     #52                 // class java/util/Map$Entry
       234: astore        5
       236: aload_0
       237: aload         5
       239: invokeinterface #1267,  1         // InterfaceMethod java/util/Map$Entry.getValue:()Ljava/lang/Object;
       244: checkcast     #353                // class com/simibubi/create/content/trains/graph/TrackGraph
       247: putfield      #175                // Field graph:Lcom/simibubi/create/content/trains/graph/TrackGraph;
       250: aload_3
       251: aload         5
       253: invokeinterface #1276,  1         // InterfaceMethod java/util/Map$Entry.getKey:()Ljava/lang/Object;
       258: invokeinterface #494,  2          // InterfaceMethod java/util/Map.get:(Ljava/lang/Object;)Ljava/lang/Object;
       263: checkcast     #189                // class java/util/List
       266: astore        6
       268: aload_0
       269: aload         6
       271: invokedynamic #1295,  0           // InvokeDynamic #11:accept:(Ljava/util/List;)Ljava/util/function/Consumer;
       276: invokevirtual #1189               // Method forEachTravellingPoint:(Ljava/util/function/Consumer;)V
       279: aload_0
       280: getfield      #250                // Field migratingPoints:Ljava/util/List;
       283: invokeinterface #1197,  1         // InterfaceMethod java/util/List.clear:()V
       288: aload_0
       289: getfield      #547                // Field derailed:Z
       292: ifeq          302
       295: aload_0
       296: getfield      #212                // Field status:Lcom/simibubi/create/content/trains/entity/TrainStatus;
       299: invokevirtual #1298               // Method com/simibubi/create/content/trains/entity/TrainStatus.successfulMigration:()V
       302: aload_0
       303: iconst_0
       304: putfield      #547                // Field derailed:Z
       307: aload_0
       308: getfield      #245                // Field runtime:Lcom/simibubi/create/content/trains/schedule/ScheduleRuntime;
       311: invokevirtual #1302               // Method com/simibubi/create/content/trains/schedule/ScheduleRuntime.getSchedule:()Lcom/simibubi/create/content/trains/schedule/Schedule;
       314: ifnull        340
       317: aload_0
       318: getfield      #245                // Field runtime:Lcom/simibubi/create/content/trains/schedule/ScheduleRuntime;
       321: getfield      #1306               // Field com/simibubi/create/content/trains/schedule/ScheduleRuntime.state:Lcom/simibubi/create/content/trains/schedule/ScheduleRuntime$State;
       324: getstatic     #1309               // Field com/simibubi/create/content/trains/schedule/ScheduleRuntime$State.IN_TRANSIT:Lcom/simibubi/create/content/trains/schedule/ScheduleRuntime$State;
       327: if_acmpne     340
       330: aload_0
       331: getfield      #245                // Field runtime:Lcom/simibubi/create/content/trains/schedule/ScheduleRuntime;
       334: getstatic     #1312               // Field com/simibubi/create/content/trains/schedule/ScheduleRuntime$State.PRE_TRANSIT:Lcom/simibubi/create/content/trains/schedule/ScheduleRuntime$State;
       337: putfield      #1306               // Field com/simibubi/create/content/trains/schedule/ScheduleRuntime.state:Lcom/simibubi/create/content/trains/schedule/ScheduleRuntime$State;
       340: aload_0
       341: invokevirtual #533                // Method getCurrentStation:()Lcom/simibubi/create/content/trains/station/GlobalStation;
       344: astore        7
       346: aload         7
       348: ifnull        357
       351: aload         7
       353: aload_0
       354: invokevirtual #1315               // Method com/simibubi/create/content/trains/station/GlobalStation.reserveFor:(Lcom/simibubi/create/content/trains/entity/Train;)V
       357: aload_0
       358: iconst_1
       359: putfield      #309                // Field updateSignalBlocks:Z
       362: aload_0
       363: iconst_0
       364: putfield      #1254               // Field migrationCooldown:I
       367: return
       368: return

  public int getTotalLength();
    Code:
         0: iconst_0
         1: istore_1
         2: iconst_0
         3: istore_2
         4: iload_2
         5: aload_0
         6: getfield      #177                // Field carriages:Ljava/util/List;
         9: invokeinterface #193,  1          // InterfaceMethod java/util/List.size:()I
        14: if_icmpge     133
        17: aload_0
        18: getfield      #177                // Field carriages:Ljava/util/List;
        21: iload_2
        22: invokeinterface #553,  2          // InterfaceMethod java/util/List.get:(I)Ljava/lang/Object;
        27: checkcast     #21                 // class com/simibubi/create/content/trains/entity/Carriage
        30: astore_3
        31: iload_2
        32: ifne          54
        35: iload_1
        36: i2d
        37: aload_3
        38: invokevirtual #609                // Method com/simibubi/create/content/trains/entity/Carriage.leadingBogey:()Lcom/simibubi/create/content/trains/entity/CarriageBogey;
        41: getfield      #1231               // Field com/simibubi/create/content/trains/entity/CarriageBogey.type:Lcom/simibubi/create/content/trains/bogey/AbstractBogeyBlock;
        44: invokevirtual #1236               // Method com/simibubi/create/content/trains/bogey/AbstractBogeyBlock.getWheelPointSpacing:()D
        47: ldc2_w        #930                // double 2.0d
        50: ddiv
        51: dadd
        52: d2i
        53: istore_1
        54: iload_2
        55: aload_0
        56: getfield      #177                // Field carriages:Ljava/util/List;
        59: invokeinterface #193,  1          // InterfaceMethod java/util/List.size:()I
        64: iconst_1
        65: isub
        66: if_icmpne     88
        69: iload_1
        70: i2d
        71: aload_3
        72: invokevirtual #617                // Method com/simibubi/create/content/trains/entity/Carriage.trailingBogey:()Lcom/simibubi/create/content/trains/entity/CarriageBogey;
        75: getfield      #1231               // Field com/simibubi/create/content/trains/entity/CarriageBogey.type:Lcom/simibubi/create/content/trains/bogey/AbstractBogeyBlock;
        78: invokevirtual #1236               // Method com/simibubi/create/content/trains/bogey/AbstractBogeyBlock.getWheelPointSpacing:()D
        81: ldc2_w        #930                // double 2.0d
        84: ddiv
        85: dadd
        86: d2i
        87: istore_1
        88: iload_1
        89: aload_3
        90: getfield      #679                // Field com/simibubi/create/content/trains/entity/Carriage.bogeySpacing:I
        93: iadd
        94: istore_1
        95: iload_2
        96: aload_0
        97: getfield      #179                // Field carriageSpacing:Ljava/util/List;
       100: invokeinterface #193,  1          // InterfaceMethod java/util/List.size:()I
       105: if_icmpge     127
       108: iload_1
       109: aload_0
       110: getfield      #179                // Field carriageSpacing:Ljava/util/List;
       113: iload_2
       114: invokeinterface #553,  2          // InterfaceMethod java/util/List.get:(I)Ljava/lang/Object;
       119: checkcast     #400                // class java/lang/Integer
       122: invokevirtual #403                // Method java/lang/Integer.intValue:()I
       125: iadd
       126: istore_1
       127: iinc          2, 1
       130: goto          4
       133: iload_1
       134: ireturn

  public void leaveStation();
    Code:
         0: aload_0
         1: invokevirtual #533                // Method getCurrentStation:()Lcom/simibubi/create/content/trains/station/GlobalStation;
         4: astore_1
         5: aload_1
         6: ifnull        14
         9: aload_1
        10: aload_0
        11: invokevirtual #1333               // Method com/simibubi/create/content/trains/station/GlobalStation.trainDeparted:(Lcom/simibubi/create/content/trains/entity/Train;)V
        14: aload_0
        15: aconst_null
        16: putfield      #252                // Field currentStation:Ljava/util/UUID;
        19: return

  public void arriveAt(com.simibubi.create.content.trains.station.GlobalStation);
    Code:
         0: aload_0
         1: aload_1
         2: invokevirtual #1338               // Method setCurrentStation:(Lcom/simibubi/create/content/trains/station/GlobalStation;)V
         5: aload_0
         6: getfield      #267                // Field reservedSignalBlocks:Ljava/util/Set;
         9: invokeinterface #1339,  1         // InterfaceMethod java/util/Set.clear:()V
        14: aload_0
        15: getfield      #245                // Field runtime:Lcom/simibubi/create/content/trains/schedule/ScheduleRuntime;
        18: invokevirtual #1342               // Method com/simibubi/create/content/trains/schedule/ScheduleRuntime.destinationReached:()V
        21: aload_1
        22: invokevirtual #540                // Method com/simibubi/create/content/trains/station/GlobalStation.runMailTransfer:()V
        25: aload_0
        26: iconst_0
        27: putfield      #535                // Field ticksSinceLastMailTransfer:I
        30: return

  public void setCurrentStation(com.simibubi.create.content.trains.station.GlobalStation);
    Code:
         0: aload_0
         1: aload_1
         2: getfield      #1344               // Field com/simibubi/create/content/trains/station/GlobalStation.id:Ljava/util/UUID;
         5: putfield      #252                // Field currentStation:Ljava/util/UUID;
         8: return

  public com.simibubi.create.content.trains.station.GlobalStation getCurrentStation();
    Code:
         0: aload_0
         1: getfield      #252                // Field currentStation:Ljava/util/UUID;
         4: ifnonnull     9
         7: aconst_null
         8: areturn
         9: aload_0
        10: getfield      #175                // Field graph:Lcom/simibubi/create/content/trains/graph/TrackGraph;
        13: ifnonnull     18
        16: aconst_null
        17: areturn
        18: aload_0
        19: getfield      #175                // Field graph:Lcom/simibubi/create/content/trains/graph/TrackGraph;
        22: getstatic     #1347               // Field com/simibubi/create/content/trains/graph/EdgePointType.STATION:Lcom/simibubi/create/content/trains/graph/EdgePointType;
        25: aload_0
        26: getfield      #252                // Field currentStation:Ljava/util/UUID;
        29: invokevirtual #357                // Method com/simibubi/create/content/trains/graph/TrackGraph.getPoint:(Lcom/simibubi/create/content/trains/graph/EdgePointType;Ljava/util/UUID;)Lcom/simibubi/create/content/trains/signal/TrackEdgePoint;
        32: checkcast     #537                // class com/simibubi/create/content/trains/station/GlobalStation
        35: areturn

  public net.minecraft.world.entity.LivingEntity getOwner(net.minecraft.world.level.Level);
    Code:
         0: aload_1
         1: invokevirtual #1355               // Method net/minecraft/world/level/Level.getServer:()Lnet/minecraft/server/MinecraftServer;
         4: ifnonnull     9
         7: aconst_null
         8: areturn
         9: aload_0
        10: getfield      #173                // Field owner:Ljava/util/UUID;
        13: astore_2
        14: aload_2
        15: ifnonnull     22
        18: aconst_null
        19: goto          33
        22: aload_1
        23: invokevirtual #1355               // Method net/minecraft/world/level/Level.getServer:()Lnet/minecraft/server/MinecraftServer;
        26: invokevirtual #1361               // Method net/minecraft/server/MinecraftServer.getPlayerList:()Lnet/minecraft/server/players/PlayerList;
        29: aload_2
        30: invokevirtual #1367               // Method net/minecraft/server/players/PlayerList.getPlayer:(Ljava/util/UUID;)Lnet/minecraft/server/level/ServerPlayer;
        33: areturn
        34: astore_2
        35: aconst_null
        36: areturn
      Exception table:
         from    to  target type
             9    33    34   Class java/lang/IllegalArgumentException

  public void approachTargetSpeed(float);
    Code:
         0: aload_0
         1: getfield      #161                // Field targetSpeed:D
         4: dstore_2
         5: dload_2
         6: aload_0
         7: getfield      #159                // Field speed:D
        10: invokestatic  #848                // Method net/minecraft/util/Mth.equal:(DD)Z
        13: ifeq          17
        16: return
        17: aload_0
        18: getfield      #850                // Field manualTick:Z
        21: ifeq          28
        24: aload_0
        25: invokevirtual #1375               // Method leaveStation:()V
        28: aload_0
        29: invokevirtual #854                // Method acceleration:()F
        32: f2d
        33: dstore        4
        35: aload_0
        36: getfield      #159                // Field speed:D
        39: dload_2
        40: dcmpg
        41: ifge          65
        44: aload_0
        45: aload_0
        46: getfield      #159                // Field speed:D
        49: dload         4
        51: fload_1
        52: f2d
        53: dmul
        54: dadd
        55: dload_2
        56: invokestatic  #857                // Method java/lang/Math.min:(DD)D
        59: putfield      #159                // Field speed:D
        62: goto          92
        65: aload_0
        66: getfield      #159                // Field speed:D
        69: dload_2
        70: dcmpl
        71: ifle          92
        74: aload_0
        75: aload_0
        76: getfield      #159                // Field speed:D
        79: dload         4
        81: fload_1
        82: f2d
        83: dmul
        84: dsub
        85: dload_2
        86: invokestatic  #632                // Method java/lang/Math.max:(DD)D
        89: putfield      #159                // Field speed:D
        92: return

  public void collectInitiallyOccupiedSignalBlocks();
    Code:
         0: aload_0
         1: getfield      #177                // Field carriages:Ljava/util/List;
         4: aload_0
         5: getfield      #177                // Field carriages:Ljava/util/List;
         8: invokeinterface #193,  1          // InterfaceMethod java/util/List.size:()I
        13: iconst_1
        14: isub
        15: invokeinterface #553,  2          // InterfaceMethod java/util/List.get:(I)Ljava/lang/Object;
        20: checkcast     #21                 // class com/simibubi/create/content/trains/entity/Carriage
        23: invokevirtual #560                // Method com/simibubi/create/content/trains/entity/Carriage.getTrailingPoint:()Lcom/simibubi/create/content/trains/entity/TravellingPoint;
        26: astore_1
        27: aload_1
        28: getfield      #564                // Field com/simibubi/create/content/trains/entity/TravellingPoint.node1:Lcom/simibubi/create/content/trains/graph/TrackNode;
        31: astore_2
        32: aload_1
        33: getfield      #1380               // Field com/simibubi/create/content/trains/entity/TravellingPoint.node2:Lcom/simibubi/create/content/trains/graph/TrackNode;
        36: astore_3
        37: aload_1
        38: getfield      #869                // Field com/simibubi/create/content/trains/entity/TravellingPoint.edge:Lcom/simibubi/create/content/trains/graph/TrackEdge;
        41: astore        4
        43: aload         4
        45: ifnonnull     49
        48: return
        49: aload_1
        50: getfield      #1385               // Field com/simibubi/create/content/trains/entity/TravellingPoint.position:D
        53: dstore        5
        55: aload         4
        57: invokevirtual #1389               // Method com/simibubi/create/content/trains/graph/TrackEdge.getEdgeData:()Lcom/simibubi/create/content/trains/graph/EdgeData;
        60: astore        7
        62: aload_0
        63: getfield      #262                // Field occupiedSignalBlocks:Ljava/util/Map;
        66: invokeinterface #1390,  1         // InterfaceMethod java/util/Map.clear:()V
        71: aload_0
        72: getfield      #267                // Field reservedSignalBlocks:Ljava/util/Set;
        75: invokeinterface #1339,  1         // InterfaceMethod java/util/Set.clear:()V
        80: aload_0
        81: getfield      #269                // Field occupiedObservers:Ljava/util/Set;
        84: invokeinterface #1339,  1         // InterfaceMethod java/util/Set.clear:()V
        89: aload_0
        90: getfield      #271                // Field cachedObserverFiltering:Ljava/util/Map;
        93: invokeinterface #1390,  1         // InterfaceMethod java/util/Map.clear:()V
        98: new           #11                 // class com/simibubi/create/content/trains/entity/TravellingPoint
       101: dup
       102: aload_2
       103: aload_3
       104: aload         4
       106: dload         5
       108: iconst_0
       109: invokespecial #1393               // Method com/simibubi/create/content/trains/entity/TravellingPoint."<init>":(Lcom/simibubi/create/content/trains/graph/TrackNode;Lcom/simibubi/create/content/trains/graph/TrackNode;Lcom/simibubi/create/content/trains/graph/TrackEdge;DZ)V
       112: astore        8
       114: getstatic     #483                // Field com/simibubi/create/Create.RAILWAYS:Lcom/simibubi/create/content/trains/GlobalRailwayManager;
       117: getfield      #488                // Field com/simibubi/create/content/trains/GlobalRailwayManager.signalEdgeGroups:Ljava/util/Map;
       120: astore        9
       122: new           #1395               // class org/apache/commons/lang3/mutable/MutableObject
       125: dup
       126: aconst_null
       127: invokespecial #1397               // Method org/apache/commons/lang3/mutable/MutableObject."<init>":(Ljava/lang/Object;)V
       130: astore        10
       132: aload         7
       134: invokevirtual #1402               // Method com/simibubi/create/content/trains/graph/EdgeData.hasSignalBoundaries:()Z
       137: ifeq          305
       140: aload         7
       142: getstatic     #808                // Field com/simibubi/create/content/trains/graph/EdgePointType.SIGNAL:Lcom/simibubi/create/content/trains/graph/EdgePointType;
       145: dload         5
       147: invokevirtual #1405               // Method com/simibubi/create/content/trains/graph/EdgeData.next:(Lcom/simibubi/create/content/trains/graph/EdgePointType;D)Lcom/simibubi/create/content/trains/signal/TrackEdgePoint;
       150: checkcast     #810                // class com/simibubi/create/content/trains/signal/SignalBoundary
       153: astore        11
       155: aload         11
       157: ifnonnull     263
       160: dconst_0
       161: dstore        12
       163: aconst_null
       164: astore        14
       166: aload         7
       168: getstatic     #808                // Field com/simibubi/create/content/trains/graph/EdgePointType.SIGNAL:Lcom/simibubi/create/content/trains/graph/EdgePointType;
       171: dconst_0
       172: invokevirtual #1405               // Method com/simibubi/create/content/trains/graph/EdgeData.next:(Lcom/simibubi/create/content/trains/graph/EdgePointType;D)Lcom/simibubi/create/content/trains/signal/TrackEdgePoint;
       175: checkcast     #810                // class com/simibubi/create/content/trains/signal/SignalBoundary
       178: astore        15
       180: aload         15
       182: ifnull        216
       185: aload         15
       187: astore        14
       189: aload         15
       191: aload         4
       193: invokevirtual #1409               // Method com/simibubi/create/content/trains/signal/SignalBoundary.getLocationOn:(Lcom/simibubi/create/content/trains/graph/TrackEdge;)D
       196: dstore        12
       198: aload         7
       200: getstatic     #808                // Field com/simibubi/create/content/trains/graph/EdgePointType.SIGNAL:Lcom/simibubi/create/content/trains/graph/EdgePointType;
       203: dload         12
       205: invokevirtual #1405               // Method com/simibubi/create/content/trains/graph/EdgeData.next:(Lcom/simibubi/create/content/trains/graph/EdgePointType;D)Lcom/simibubi/create/content/trains/signal/TrackEdgePoint;
       208: checkcast     #810                // class com/simibubi/create/content/trains/signal/SignalBoundary
       211: astore        15
       213: goto          180
       216: aload         14
       218: ifnull        260
       221: aload         14
       223: aload_3
       224: invokevirtual #1413               // Method com/simibubi/create/content/trains/signal/SignalBoundary.getGroup:(Lcom/simibubi/create/content/trains/graph/TrackNode;)Ljava/util/UUID;
       227: astore        16
       229: getstatic     #483                // Field com/simibubi/create/Create.RAILWAYS:Lcom/simibubi/create/content/trains/GlobalRailwayManager;
       232: getfield      #488                // Field com/simibubi/create/content/trains/GlobalRailwayManager.signalEdgeGroups:Ljava/util/Map;
       235: aload         16
       237: invokeinterface #772,  2          // InterfaceMethod java/util/Map.containsKey:(Ljava/lang/Object;)Z
       242: ifeq          260
       245: aload_0
       246: aload         16
       248: aconst_null
       249: invokevirtual #1415               // Method occupy:(Ljava/util/UUID;Ljava/util/UUID;)Z
       252: pop
       253: aload         10
       255: aload         16
       257: invokevirtual #1418               // Method org/apache/commons/lang3/mutable/MutableObject.setValue:(Ljava/lang/Object;)V
       260: goto          302
       263: aload         11
       265: aload_2
       266: invokevirtual #1413               // Method com/simibubi/create/content/trains/signal/SignalBoundary.getGroup:(Lcom/simibubi/create/content/trains/graph/TrackNode;)Ljava/util/UUID;
       269: astore        12
       271: getstatic     #483                // Field com/simibubi/create/Create.RAILWAYS:Lcom/simibubi/create/content/trains/GlobalRailwayManager;
       274: getfield      #488                // Field com/simibubi/create/content/trains/GlobalRailwayManager.signalEdgeGroups:Ljava/util/Map;
       277: aload         12
       279: invokeinterface #772,  2          // InterfaceMethod java/util/Map.containsKey:(Ljava/lang/Object;)Z
       284: ifeq          302
       287: aload_0
       288: aload         12
       290: aconst_null
       291: invokevirtual #1415               // Method occupy:(Ljava/util/UUID;Ljava/util/UUID;)Z
       294: pop
       295: aload         10
       297: aload         12
       299: invokevirtual #1418               // Method org/apache/commons/lang3/mutable/MutableObject.setValue:(Ljava/lang/Object;)V
       302: goto          343
       305: aload         7
       307: aload_0
       308: getfield      #175                // Field graph:Lcom/simibubi/create/content/trains/graph/TrackGraph;
       311: invokevirtual #1422               // Method com/simibubi/create/content/trains/graph/EdgeData.getEffectiveEdgeGroupId:(Lcom/simibubi/create/content/trains/graph/TrackGraph;)Ljava/util/UUID;
       314: astore        11
       316: aload         9
       318: aload         11
       320: invokeinterface #772,  2          // InterfaceMethod java/util/Map.containsKey:(Ljava/lang/Object;)Z
       325: ifeq          343
       328: aload_0
       329: aload         11
       331: aconst_null
       332: invokevirtual #1415               // Method occupy:(Ljava/util/UUID;Ljava/util/UUID;)Z
       335: pop
       336: aload         10
       338: aload         11
       340: invokevirtual #1418               // Method org/apache/commons/lang3/mutable/MutableObject.setValue:(Ljava/lang/Object;)V
       343: aload_0
       344: aload_0
       345: aload         8
       347: aload         10
       349: invokedynamic #1433,  0           // InvokeDynamic #12:accept:(Lcom/simibubi/create/content/trains/entity/Train;Lcom/simibubi/create/content/trains/entity/TravellingPoint;Lorg/apache/commons/lang3/mutable/MutableObject;)Ljava/util/function/BiConsumer;
       354: invokevirtual #1435               // Method forEachTravellingPointBackwards:(Ljava/util/function/BiConsumer;)V
       357: return

  public boolean shouldCarriageSyncThisTick(long, int);
    Code:
         0: lload_1
         1: aload_0
         2: getfield      #285                // Field tickOffset:I
         5: i2l
         6: ladd
         7: iload_3
         8: i2l
         9: lrem
        10: lconst_0
        11: lcmp
        12: ifne          19
        15: iconst_1
        16: goto          20
        19: iconst_0
        20: ireturn

  public net.createmod.catnip.data.Couple<net.createmod.catnip.data.Couple<com.simibubi.create.content.trains.graph.TrackNode>> getEndpointEdges();
    Code:
         0: aload_0
         1: getfield      #177                // Field carriages:Ljava/util/List;
         4: iconst_0
         5: invokeinterface #553,  2          // InterfaceMethod java/util/List.get:(I)Ljava/lang/Object;
        10: checkcast     #21                 // class com/simibubi/create/content/trains/entity/Carriage
        13: invokevirtual #557                // Method com/simibubi/create/content/trains/entity/Carriage.getLeadingPoint:()Lcom/simibubi/create/content/trains/entity/TravellingPoint;
        16: aload_0
        17: getfield      #177                // Field carriages:Ljava/util/List;
        20: aload_0
        21: getfield      #177                // Field carriages:Ljava/util/List;
        24: invokeinterface #193,  1          // InterfaceMethod java/util/List.size:()I
        29: iconst_1
        30: isub
        31: invokeinterface #553,  2          // InterfaceMethod java/util/List.get:(I)Ljava/lang/Object;
        36: checkcast     #21                 // class com/simibubi/create/content/trains/entity/Carriage
        39: invokevirtual #560                // Method com/simibubi/create/content/trains/entity/Carriage.getTrailingPoint:()Lcom/simibubi/create/content/trains/entity/TravellingPoint;
        42: invokestatic  #1458               // Method net/createmod/catnip/data/Couple.create:(Ljava/lang/Object;Ljava/lang/Object;)Lnet/createmod/catnip/data/Couple;
        45: invokedynamic #1465,  0           // InvokeDynamic #13:apply:()Ljava/util/function/Function;
        50: invokevirtual #1469               // Method net/createmod/catnip/data/Couple.map:(Ljava/util/function/Function;)Lnet/createmod/catnip/data/Couple;
        53: areturn

  public int getNavigationPenalty();
    Code:
         0: aload_0
         1: getfield      #850                // Field manualTick:Z
         4: ifeq          11
         7: sipush        200
        10: ireturn
        11: aload_0
        12: getfield      #245                // Field runtime:Lcom/simibubi/create/content/trains/schedule/ScheduleRuntime;
        15: invokevirtual #1302               // Method com/simibubi/create/content/trains/schedule/ScheduleRuntime.getSchedule:()Lcom/simibubi/create/content/trains/schedule/Schedule;
        18: ifnull        31
        21: aload_0
        22: getfield      #245                // Field runtime:Lcom/simibubi/create/content/trains/schedule/ScheduleRuntime;
        25: getfield      #802                // Field com/simibubi/create/content/trains/schedule/ScheduleRuntime.paused:Z
        28: ifeq          35
        31: sipush        700
        34: ireturn
        35: aload_0
        36: getfield      #242                // Field navigation:Lcom/simibubi/create/content/trains/entity/Navigation;
        39: getfield      #787                // Field com/simibubi/create/content/trains/entity/Navigation.waitingForSignal:Lnet/createmod/catnip/data/Pair;
        42: ifnull        75
        45: aload_0
        46: getfield      #242                // Field navigation:Lcom/simibubi/create/content/trains/entity/Navigation;
        49: getfield      #805                // Field com/simibubi/create/content/trains/entity/Navigation.ticksWaitingForSignal:I
        52: ifle          75
        55: bipush        50
        57: aload_0
        58: getfield      #242                // Field navigation:Lcom/simibubi/create/content/trains/entity/Navigation;
        61: getfield      #805                // Field com/simibubi/create/content/trains/entity/Navigation.ticksWaitingForSignal:I
        64: bipush        20
        66: idiv
        67: sipush        1000
        70: invokestatic  #1473               // Method java/lang/Math.min:(II)I
        73: iadd
        74: ireturn
        75: aload_0
        76: getfield      #242                // Field navigation:Lcom/simibubi/create/content/trains/entity/Navigation;
        79: getfield      #784                // Field com/simibubi/create/content/trains/entity/Navigation.destination:Lcom/simibubi/create/content/trains/station/GlobalStation;
        82: ifnull        99
        85: aload_0
        86: getfield      #242                // Field navigation:Lcom/simibubi/create/content/trains/entity/Navigation;
        89: getfield      #655                // Field com/simibubi/create/content/trains/entity/Navigation.distanceToDestination:D
        92: ldc2_w        #795                // double 50.0d
        95: dcmpg
        96: iflt          113
        99: aload_0
       100: getfield      #242                // Field navigation:Lcom/simibubi/create/content/trains/entity/Navigation;
       103: getfield      #794                // Field com/simibubi/create/content/trains/entity/Navigation.distanceToSignal:D
       106: ldc2_w        #790                // double 20.0d
       109: dcmpg
       110: ifge          116
       113: bipush        50
       115: ireturn
       116: bipush        25
       118: ireturn

  public void burnFuel();
    Code:
         0: aload_0
         1: getfield      #1476               // Field fuelTicks:I
         4: ifle          18
         7: aload_0
         8: dup
         9: getfield      #1476               // Field fuelTicks:I
        12: iconst_1
        13: isub
        14: putfield      #1476               // Field fuelTicks:I
        17: return
        18: aload_0
        19: getfield      #159                // Field speed:D
        22: dconst_0
        23: dcmpg
        24: ifge          31
        27: iconst_1
        28: goto          32
        31: iconst_0
        32: istore_1
        33: aload_0
        34: getfield      #177                // Field carriages:Ljava/util/List;
        37: invokeinterface #193,  1          // InterfaceMethod java/util/List.size:()I
        42: istore_2
        43: iconst_0
        44: istore_3
        45: iload_3
        46: iload_2
        47: if_icmpge     210
        50: iload_1
        51: ifeq          62
        54: iload_2
        55: iconst_1
        56: isub
        57: iload_3
        58: isub
        59: goto          63
        62: iload_3
        63: istore        4
        65: aload_0
        66: getfield      #177                // Field carriages:Ljava/util/List;
        69: iload         4
        71: invokeinterface #553,  2          // InterfaceMethod java/util/List.get:(I)Ljava/lang/Object;
        76: checkcast     #21                 // class com/simibubi/create/content/trains/entity/Carriage
        79: astore        5
        81: aload         5
        83: getfield      #337                // Field com/simibubi/create/content/trains/entity/Carriage.storage:Lcom/simibubi/create/content/contraptions/minecart/TrainCargoManager;
        86: invokevirtual #1480               // Method com/simibubi/create/content/contraptions/minecart/TrainCargoManager.getFuelItems:()Lcom/simibubi/create/api/contraption/storage/item/MountedItemStorageWrapper;
        89: astore        6
        91: aload         6
        93: ifnonnull     99
        96: goto          204
        99: iconst_0
       100: istore        7
       102: iload         7
       104: aload         6
       106: invokeinterface #412,  1          // InterfaceMethod net/minecraftforge/items/IItemHandlerModifiable.getSlots:()I
       111: if_icmpge     204
       114: aload         6
       116: iload         7
       118: iconst_1
       119: iconst_1
       120: invokeinterface #416,  4          // InterfaceMethod net/minecraftforge/items/IItemHandlerModifiable.extractItem:(IIZ)Lnet/minecraft/world/item/ItemStack;
       125: astore        8
       127: aload         8
       129: aconst_null
       130: invokestatic  #1486               // Method net/minecraftforge/common/ForgeHooks.getBurnTime:(Lnet/minecraft/world/item/ItemStack;Lnet/minecraft/world/item/crafting/RecipeType;)I
       133: istore        9
       135: iload         9
       137: ifgt          143
       140: goto          198
       143: aload         6
       145: iload         7
       147: iconst_1
       148: iconst_0
       149: invokeinterface #416,  4          // InterfaceMethod net/minecraftforge/items/IItemHandlerModifiable.extractItem:(IIZ)Lnet/minecraft/world/item/ItemStack;
       154: astore        8
       156: aload_0
       157: dup
       158: getfield      #1476               // Field fuelTicks:I
       161: iload         9
       163: aload         8
       165: invokevirtual #1489               // Method net/minecraft/world/item/ItemStack.getCount:()I
       168: imul
       169: iadd
       170: putfield      #1476               // Field fuelTicks:I
       173: aload         8
       175: invokevirtual #1493               // Method net/minecraft/world/item/ItemStack.getCraftingRemainingItem:()Lnet/minecraft/world/item/ItemStack;
       178: astore        10
       180: aload         10
       182: invokevirtual #419                // Method net/minecraft/world/item/ItemStack.isEmpty:()Z
       185: ifne          197
       188: aload         6
       190: aload         10
       192: iconst_0
       193: invokestatic  #1499               // Method net/minecraftforge/items/ItemHandlerHelper.insertItemStacked:(Lnet/minecraftforge/items/IItemHandler;Lnet/minecraft/world/item/ItemStack;Z)Lnet/minecraft/world/item/ItemStack;
       196: pop
       197: return
       198: iinc          7, 1
       201: goto          102
       204: iinc          3, 1
       207: goto          45
       210: return

  public float maxSpeed();
    Code:
         0: aload_0
         1: getfield      #1476               // Field fuelTicks:I
         4: ifle          22
         7: invokestatic  #916                // Method com/simibubi/create/infrastructure/config/AllConfigs.server:()Lcom/simibubi/create/infrastructure/config/CServer;
        10: getfield      #921                // Field com/simibubi/create/infrastructure/config/CServer.trains:Lcom/simibubi/create/infrastructure/config/CTrains;
        13: getfield      #1508               // Field com/simibubi/create/infrastructure/config/CTrains.poweredTrainTopSpeed:Lnet/createmod/catnip/config/ConfigBase$ConfigFloat;
        16: invokevirtual #1511               // Method net/createmod/catnip/config/ConfigBase$ConfigFloat.getF:()F
        19: goto          34
        22: invokestatic  #916                // Method com/simibubi/create/infrastructure/config/AllConfigs.server:()Lcom/simibubi/create/infrastructure/config/CServer;
        25: getfield      #921                // Field com/simibubi/create/infrastructure/config/CServer.trains:Lcom/simibubi/create/infrastructure/config/CTrains;
        28: getfield      #1514               // Field com/simibubi/create/infrastructure/config/CTrains.trainTopSpeed:Lnet/createmod/catnip/config/ConfigBase$ConfigFloat;
        31: invokevirtual #1511               // Method net/createmod/catnip/config/ConfigBase$ConfigFloat.getF:()F
        34: ldc_w         #1515               // float 20.0f
        37: fdiv
        38: freturn

  public float maxTurnSpeed();
    Code:
         0: aload_0
         1: getfield      #1476               // Field fuelTicks:I
         4: ifle          22
         7: invokestatic  #916                // Method com/simibubi/create/infrastructure/config/AllConfigs.server:()Lcom/simibubi/create/infrastructure/config/CServer;
        10: getfield      #921                // Field com/simibubi/create/infrastructure/config/CServer.trains:Lcom/simibubi/create/infrastructure/config/CTrains;
        13: getfield      #1519               // Field com/simibubi/create/infrastructure/config/CTrains.poweredTrainTurningTopSpeed:Lnet/createmod/catnip/config/ConfigBase$ConfigFloat;
        16: invokevirtual #1511               // Method net/createmod/catnip/config/ConfigBase$ConfigFloat.getF:()F
        19: goto          34
        22: invokestatic  #916                // Method com/simibubi/create/infrastructure/config/AllConfigs.server:()Lcom/simibubi/create/infrastructure/config/CServer;
        25: getfield      #921                // Field com/simibubi/create/infrastructure/config/CServer.trains:Lcom/simibubi/create/infrastructure/config/CTrains;
        28: getfield      #1522               // Field com/simibubi/create/infrastructure/config/CTrains.trainTurningTopSpeed:Lnet/createmod/catnip/config/ConfigBase$ConfigFloat;
        31: invokevirtual #1511               // Method net/createmod/catnip/config/ConfigBase$ConfigFloat.getF:()F
        34: ldc_w         #1515               // float 20.0f
        37: fdiv
        38: freturn

  public float acceleration();
    Code:
         0: aload_0
         1: getfield      #1476               // Field fuelTicks:I
         4: ifle          22
         7: invokestatic  #916                // Method com/simibubi/create/infrastructure/config/AllConfigs.server:()Lcom/simibubi/create/infrastructure/config/CServer;
        10: getfield      #921                // Field com/simibubi/create/infrastructure/config/CServer.trains:Lcom/simibubi/create/infrastructure/config/CTrains;
        13: getfield      #1525               // Field com/simibubi/create/infrastructure/config/CTrains.poweredTrainAcceleration:Lnet/createmod/catnip/config/ConfigBase$ConfigFloat;
        16: invokevirtual #1511               // Method net/createmod/catnip/config/ConfigBase$ConfigFloat.getF:()F
        19: goto          34
        22: invokestatic  #916                // Method com/simibubi/create/infrastructure/config/AllConfigs.server:()Lcom/simibubi/create/infrastructure/config/CServer;
        25: getfield      #921                // Field com/simibubi/create/infrastructure/config/CServer.trains:Lcom/simibubi/create/infrastructure/config/CTrains;
        28: getfield      #1528               // Field com/simibubi/create/infrastructure/config/CTrains.trainAcceleration:Lnet/createmod/catnip/config/ConfigBase$ConfigFloat;
        31: invokevirtual #1511               // Method net/createmod/catnip/config/ConfigBase$ConfigFloat.getF:()F
        34: ldc_w         #1529               // float 400.0f
        37: fdiv
        38: freturn

  public net.minecraft.nbt.CompoundTag write(com.simibubi.create.content.trains.graph.DimensionPalette);
    Code:
         0: new           #1533               // class net/minecraft/nbt/CompoundTag
         3: dup
         4: invokespecial #1534               // Method net/minecraft/nbt/CompoundTag."<init>":()V
         7: astore_2
         8: aload_2
         9: ldc_w         #1536               // String Id
        12: aload_0
        13: getfield      #171                // Field id:Ljava/util/UUID;
        16: invokevirtual #1540               // Method net/minecraft/nbt/CompoundTag.putUUID:(Ljava/lang/String;Ljava/util/UUID;)V
        19: aload_0
        20: getfield      #173                // Field owner:Ljava/util/UUID;
        23: ifnull        37
        26: aload_2
        27: ldc_w         #1542               // String Owner
        30: aload_0
        31: getfield      #173                // Field owner:Ljava/util/UUID;
        34: invokevirtual #1540               // Method net/minecraft/nbt/CompoundTag.putUUID:(Ljava/lang/String;Ljava/util/UUID;)V
        37: aload_0
        38: getfield      #175                // Field graph:Lcom/simibubi/create/content/trains/graph/TrackGraph;
        41: ifnull        58
        44: aload_2
        45: ldc_w         #1544               // String Graph
        48: aload_0
        49: getfield      #175                // Field graph:Lcom/simibubi/create/content/trains/graph/TrackGraph;
        52: getfield      #1545               // Field com/simibubi/create/content/trains/graph/TrackGraph.id:Ljava/util/UUID;
        55: invokevirtual #1540               // Method net/minecraft/nbt/CompoundTag.putUUID:(Ljava/lang/String;Ljava/util/UUID;)V
        58: aload_2
        59: ldc_w         #1547               // String Carriages
        62: aload_0
        63: getfield      #177                // Field carriages:Ljava/util/List;
        66: aload_1
        67: invokedynamic #1557,  0           // InvokeDynamic #14:apply:(Lcom/simibubi/create/content/trains/graph/DimensionPalette;)Ljava/util/function/Function;
        72: invokestatic  #1563               // Method net/createmod/catnip/nbt/NBTHelper.writeCompoundList:(Ljava/lang/Iterable;Ljava/util/function/Function;)Lnet/minecraft/nbt/ListTag;
        75: invokevirtual #1566               // Method net/minecraft/nbt/CompoundTag.put:(Ljava/lang/String;Lnet/minecraft/nbt/Tag;)Lnet/minecraft/nbt/Tag;
        78: pop
        79: aload_2
        80: ldc_w         #1568               // String CarriageSpacing
        83: aload_0
        84: getfield      #179                // Field carriageSpacing:Ljava/util/List;
        87: invokevirtual #1572               // Method net/minecraft/nbt/CompoundTag.putIntArray:(Ljava/lang/String;Ljava/util/List;)V
        90: aload_2
        91: ldc_w         #1574               // String DoubleEnded
        94: aload_0
        95: getfield      #214                // Field doubleEnded:Z
        98: invokevirtual #1578               // Method net/minecraft/nbt/CompoundTag.putBoolean:(Ljava/lang/String;Z)V
       101: aload_2
       102: ldc_w         #1580               // String Speed
       105: aload_0
       106: getfield      #159                // Field speed:D
       109: invokevirtual #1584               // Method net/minecraft/nbt/CompoundTag.putDouble:(Ljava/lang/String;D)V
       112: aload_2
       113: ldc_w         #1586               // String Throttle
       116: aload_0
       117: getfield      #167                // Field throttle:D
       120: invokevirtual #1584               // Method net/minecraft/nbt/CompoundTag.putDouble:(Ljava/lang/String;D)V
       123: aload_0
       124: getfield      #163                // Field speedBeforeStall:Ljava/lang/Double;
       127: ifnull        144
       130: aload_2
       131: ldc_w         #1588               // String SpeedBeforeStall
       134: aload_0
       135: getfield      #163                // Field speedBeforeStall:Ljava/lang/Double;
       138: invokevirtual #644                // Method java/lang/Double.doubleValue:()D
       141: invokevirtual #1584               // Method net/minecraft/nbt/CompoundTag.putDouble:(Ljava/lang/String;D)V
       144: aload_2
       145: ldc_w         #1590               // String Fuel
       148: aload_0
       149: getfield      #1476               // Field fuelTicks:I
       152: invokevirtual #1594               // Method net/minecraft/nbt/CompoundTag.putInt:(Ljava/lang/String;I)V
       155: aload_2
       156: ldc_w         #1596               // String TargetSpeed
       159: aload_0
       160: getfield      #161                // Field targetSpeed:D
       163: invokevirtual #1584               // Method net/minecraft/nbt/CompoundTag.putDouble:(Ljava/lang/String;D)V
       166: aload_2
       167: ldc_w         #1598               // String IconType
       170: aload_0
       171: getfield      #187                // Field icon:Lcom/simibubi/create/content/trains/entity/TrainIconType;
       174: getfield      #1601               // Field com/simibubi/create/content/trains/entity/TrainIconType.id:Lnet/minecraft/resources/ResourceLocation;
       177: invokevirtual #1607               // Method net/minecraft/resources/ResourceLocation.toString:()Ljava/lang/String;
       180: invokevirtual #1611               // Method net/minecraft/nbt/CompoundTag.putString:(Ljava/lang/String;Ljava/lang/String;)V
       183: aload_2
       184: ldc_w         #1613               // String MapColorIndex
       187: aload_0
       188: getfield      #1103               // Field mapColorIndex:I
       191: invokevirtual #1594               // Method net/minecraft/nbt/CompoundTag.putInt:(Ljava/lang/String;I)V
       194: aload_2
       195: ldc_w         #1615               // String Name
       198: aload_0
       199: getfield      #205                // Field name:Lnet/minecraft/network/chat/Component;
       202: invokestatic  #1619               // Method net/minecraft/network/chat/Component$Serializer.toJson:(Lnet/minecraft/network/chat/Component;)Ljava/lang/String;
       205: invokevirtual #1611               // Method net/minecraft/nbt/CompoundTag.putString:(Ljava/lang/String;Ljava/lang/String;)V
       208: aload_0
       209: getfield      #252                // Field currentStation:Ljava/util/UUID;
       212: ifnull        226
       215: aload_2
       216: ldc_w         #1621               // String Station
       219: aload_0
       220: getfield      #252                // Field currentStation:Ljava/util/UUID;
       223: invokevirtual #1540               // Method net/minecraft/nbt/CompoundTag.putUUID:(Ljava/lang/String;Ljava/util/UUID;)V
       226: aload_2
       227: ldc_w         #1623               // String Backwards
       230: aload_0
       231: getfield      #1021               // Field currentlyBackwards:Z
       234: invokevirtual #1578               // Method net/minecraft/nbt/CompoundTag.putBoolean:(Ljava/lang/String;Z)V
       237: aload_2
       238: ldc_w         #1625               // String Derailed
       241: aload_0
       242: getfield      #547                // Field derailed:Z
       245: invokevirtual #1578               // Method net/minecraft/nbt/CompoundTag.putBoolean:(Ljava/lang/String;Z)V
       248: aload_2
       249: ldc_w         #1627               // String UpdateSignals
       252: aload_0
       253: getfield      #309                // Field updateSignalBlocks:Z
       256: invokevirtual #1578               // Method net/minecraft/nbt/CompoundTag.putBoolean:(Ljava/lang/String;Z)V
       259: aload_2
       260: ldc_w         #1629               // String SignalBlocks
       263: aload_0
       264: getfield      #262                // Field occupiedSignalBlocks:Ljava/util/Map;
       267: invokeinterface #1260,  1         // InterfaceMethod java/util/Map.entrySet:()Ljava/util/Set;
       272: invokedynamic #1636,  0           // InvokeDynamic #15:apply:()Ljava/util/function/Function;
       277: invokestatic  #1563               // Method net/createmod/catnip/nbt/NBTHelper.writeCompoundList:(Ljava/lang/Iterable;Ljava/util/function/Function;)Lnet/minecraft/nbt/ListTag;
       280: invokevirtual #1566               // Method net/minecraft/nbt/CompoundTag.put:(Ljava/lang/String;Lnet/minecraft/nbt/Tag;)Lnet/minecraft/nbt/Tag;
       283: pop
       284: aload_2
       285: ldc_w         #1638               // String ReservedSignalBlocks
       288: aload_0
       289: getfield      #267                // Field reservedSignalBlocks:Ljava/util/Set;
       292: invokedynamic #1645,  0           // InvokeDynamic #16:apply:()Ljava/util/function/Function;
       297: invokestatic  #1563               // Method net/createmod/catnip/nbt/NBTHelper.writeCompoundList:(Ljava/lang/Iterable;Ljava/util/function/Function;)Lnet/minecraft/nbt/ListTag;
       300: invokevirtual #1566               // Method net/minecraft/nbt/CompoundTag.put:(Ljava/lang/String;Lnet/minecraft/nbt/Tag;)Lnet/minecraft/nbt/Tag;
       303: pop
       304: aload_2
       305: ldc_w         #1647               // String OccupiedObservers
       308: aload_0
       309: getfield      #269                // Field occupiedObservers:Ljava/util/Set;
       312: invokedynamic #1652,  0           // InvokeDynamic #17:apply:()Ljava/util/function/Function;
       317: invokestatic  #1563               // Method net/createmod/catnip/nbt/NBTHelper.writeCompoundList:(Ljava/lang/Iterable;Ljava/util/function/Function;)Lnet/minecraft/nbt/ListTag;
       320: invokevirtual #1566               // Method net/minecraft/nbt/CompoundTag.put:(Ljava/lang/String;Lnet/minecraft/nbt/Tag;)Lnet/minecraft/nbt/Tag;
       323: pop
       324: aload_2
       325: ldc_w         #1654               // String MigratingPoints
       328: aload_0
       329: getfield      #250                // Field migratingPoints:Ljava/util/List;
       332: aload_1
       333: invokedynamic #1662,  0           // InvokeDynamic #18:apply:(Lcom/simibubi/create/content/trains/graph/DimensionPalette;)Ljava/util/function/Function;
       338: invokestatic  #1563               // Method net/createmod/catnip/nbt/NBTHelper.writeCompoundList:(Ljava/lang/Iterable;Ljava/util/function/Function;)Lnet/minecraft/nbt/ListTag;
       341: invokevirtual #1566               // Method net/minecraft/nbt/CompoundTag.put:(Ljava/lang/String;Lnet/minecraft/nbt/Tag;)Lnet/minecraft/nbt/Tag;
       344: pop
       345: aload_2
       346: ldc_w         #1664               // String Runtime
       349: aload_0
       350: getfield      #245                // Field runtime:Lcom/simibubi/create/content/trains/schedule/ScheduleRuntime;
       353: invokevirtual #1667               // Method com/simibubi/create/content/trains/schedule/ScheduleRuntime.write:()Lnet/minecraft/nbt/CompoundTag;
       356: invokevirtual #1566               // Method net/minecraft/nbt/CompoundTag.put:(Ljava/lang/String;Lnet/minecraft/nbt/Tag;)Lnet/minecraft/nbt/Tag;
       359: pop
       360: aload_2
       361: ldc_w         #1669               // String Navigation
       364: aload_0
       365: getfield      #242                // Field navigation:Lcom/simibubi/create/content/trains/entity/Navigation;
       368: aload_1
       369: invokevirtual #1671               // Method com/simibubi/create/content/trains/entity/Navigation.write:(Lcom/simibubi/create/content/trains/graph/DimensionPalette;)Lnet/minecraft/nbt/CompoundTag;
       372: invokevirtual #1566               // Method net/minecraft/nbt/CompoundTag.put:(Ljava/lang/String;Lnet/minecraft/nbt/Tag;)Lnet/minecraft/nbt/Tag;
       375: pop
       376: aload_2
       377: areturn

  public static com.simibubi.create.content.trains.entity.Train read(net.minecraft.nbt.CompoundTag, java.util.Map<java.util.UUID, com.simibubi.create.content.trains.graph.TrackGraph>, com.simibubi.create.content.trains.graph.DimensionPalette);
    Code:
         0: aload_0
         1: ldc_w         #1536               // String Id
         4: invokevirtual #1681               // Method net/minecraft/nbt/CompoundTag.getUUID:(Ljava/lang/String;)Ljava/util/UUID;
         7: astore_3
         8: aload_0
         9: ldc_w         #1542               // String Owner
        12: invokevirtual #1685               // Method net/minecraft/nbt/CompoundTag.contains:(Ljava/lang/String;)Z
        15: ifeq          28
        18: aload_0
        19: ldc_w         #1542               // String Owner
        22: invokevirtual #1681               // Method net/minecraft/nbt/CompoundTag.getUUID:(Ljava/lang/String;)Ljava/util/UUID;
        25: goto          29
        28: aconst_null
        29: astore        4
        31: aload_0
        32: ldc_w         #1544               // String Graph
        35: invokevirtual #1685               // Method net/minecraft/nbt/CompoundTag.contains:(Ljava/lang/String;)Z
        38: ifeq          51
        41: aload_0
        42: ldc_w         #1544               // String Graph
        45: invokevirtual #1681               // Method net/minecraft/nbt/CompoundTag.getUUID:(Ljava/lang/String;)Ljava/util/UUID;
        48: goto          52
        51: aconst_null
        52: astore        5
        54: aload         5
        56: ifnonnull     63
        59: aconst_null
        60: goto          74
        63: aload_1
        64: aload         5
        66: invokeinterface #494,  2          // InterfaceMethod java/util/Map.get:(Ljava/lang/Object;)Ljava/lang/Object;
        71: checkcast     #353                // class com/simibubi/create/content/trains/graph/TrackGraph
        74: astore        6
        76: new           #247                // class java/util/ArrayList
        79: dup
        80: invokespecial #248                // Method java/util/ArrayList."<init>":()V
        83: astore        7
        85: aload_0
        86: ldc_w         #1547               // String Carriages
        89: bipush        10
        91: invokevirtual #1689               // Method net/minecraft/nbt/CompoundTag.getList:(Ljava/lang/String;I)Lnet/minecraft/nbt/ListTag;
        94: aload         7
        96: aload         6
        98: aload_2
        99: invokedynamic #1698,  0           // InvokeDynamic #19:accept:(Ljava/util/List;Lcom/simibubi/create/content/trains/graph/TrackGraph;Lcom/simibubi/create/content/trains/graph/DimensionPalette;)Ljava/util/function/Consumer;
       104: invokestatic  #1702               // Method net/createmod/catnip/nbt/NBTHelper.iterateCompoundList:(Lnet/minecraft/nbt/ListTag;Ljava/util/function/Consumer;)V
       107: new           #247                // class java/util/ArrayList
       110: dup
       111: invokespecial #248                // Method java/util/ArrayList."<init>":()V
       114: astore        8
       116: aload_0
       117: ldc_w         #1568               // String CarriageSpacing
       120: invokevirtual #1706               // Method net/minecraft/nbt/CompoundTag.getIntArray:(Ljava/lang/String;)[I
       123: astore        9
       125: aload         9
       127: arraylength
       128: istore        10
       130: iconst_0
       131: istore        11
       133: iload         11
       135: iload         10
       137: if_icmpge     166
       140: aload         9
       142: iload         11
       144: iaload
       145: istore        12
       147: aload         8
       149: iload         12
       151: invokestatic  #448                // Method java/lang/Integer.valueOf:(I)Ljava/lang/Integer;
       154: invokeinterface #1284,  2         // InterfaceMethod java/util/List.add:(Ljava/lang/Object;)Z
       159: pop
       160: iinc          11, 1
       163: goto          133
       166: aload_0
       167: ldc_w         #1574               // String DoubleEnded
       170: invokevirtual #1713               // Method net/minecraft/nbt/CompoundTag.getBoolean:(Ljava/lang/String;)Z
       173: istore        9
       175: new           #2                  // class com/simibubi/create/content/trains/entity/Train
       178: dup
       179: aload_3
       180: aload         4
       182: aload         6
       184: aload         7
       186: aload         8
       188: iload         9
       190: invokespecial #1715               // Method "<init>":(Ljava/util/UUID;Ljava/util/UUID;Lcom/simibubi/create/content/trains/graph/TrackGraph;Ljava/util/List;Ljava/util/List;Z)V
       193: astore        10
       195: aload         10
       197: aload_0
       198: ldc_w         #1580               // String Speed
       201: invokevirtual #1719               // Method net/minecraft/nbt/CompoundTag.getDouble:(Ljava/lang/String;)D
       204: putfield      #159                // Field speed:D
       207: aload         10
       209: aload_0
       210: ldc_w         #1586               // String Throttle
       213: invokevirtual #1719               // Method net/minecraft/nbt/CompoundTag.getDouble:(Ljava/lang/String;)D
       216: putfield      #167                // Field throttle:D
       219: aload_0
       220: ldc_w         #1588               // String SpeedBeforeStall
       223: invokevirtual #1685               // Method net/minecraft/nbt/CompoundTag.contains:(Ljava/lang/String;)Z
       226: ifeq          244
       229: aload         10
       231: aload_0
       232: ldc_w         #1588               // String SpeedBeforeStall
       235: invokevirtual #1719               // Method net/minecraft/nbt/CompoundTag.getDouble:(Ljava/lang/String;)D
       238: invokestatic  #640                // Method java/lang/Double.valueOf:(D)Ljava/lang/Double;
       241: putfield      #163                // Field speedBeforeStall:Ljava/lang/Double;
       244: aload         10
       246: aload_0
       247: ldc_w         #1596               // String TargetSpeed
       250: invokevirtual #1719               // Method net/minecraft/nbt/CompoundTag.getDouble:(Ljava/lang/String;)D
       253: putfield      #161                // Field targetSpeed:D
       256: aload         10
       258: new           #1603               // class net/minecraft/resources/ResourceLocation
       261: dup
       262: aload_0
       263: ldc_w         #1598               // String IconType
       266: invokevirtual #1723               // Method net/minecraft/nbt/CompoundTag.getString:(Ljava/lang/String;)Ljava/lang/String;
       269: invokespecial #1726               // Method net/minecraft/resources/ResourceLocation."<init>":(Ljava/lang/String;)V
       272: invokestatic  #1730               // Method com/simibubi/create/content/trains/entity/TrainIconType.byId:(Lnet/minecraft/resources/ResourceLocation;)Lcom/simibubi/create/content/trains/entity/TrainIconType;
       275: putfield      #187                // Field icon:Lcom/simibubi/create/content/trains/entity/TrainIconType;
       278: aload         10
       280: aload_0
       281: ldc_w         #1613               // String MapColorIndex
       284: invokevirtual #1734               // Method net/minecraft/nbt/CompoundTag.getInt:(Ljava/lang/String;)I
       287: putfield      #1103               // Field mapColorIndex:I
       290: aload         10
       292: aload_0
       293: ldc_w         #1615               // String Name
       296: invokevirtual #1723               // Method net/minecraft/nbt/CompoundTag.getString:(Ljava/lang/String;)Ljava/lang/String;
       299: invokestatic  #1738               // Method net/minecraft/network/chat/Component$Serializer.fromJson:(Ljava/lang/String;)Lnet/minecraft/network/chat/MutableComponent;
       302: putfield      #205                // Field name:Lnet/minecraft/network/chat/Component;
       305: aload         10
       307: aload_0
       308: ldc_w         #1621               // String Station
       311: invokevirtual #1685               // Method net/minecraft/nbt/CompoundTag.contains:(Ljava/lang/String;)Z
       314: ifeq          327
       317: aload_0
       318: ldc_w         #1621               // String Station
       321: invokevirtual #1681               // Method net/minecraft/nbt/CompoundTag.getUUID:(Ljava/lang/String;)Ljava/util/UUID;
       324: goto          328
       327: aconst_null
       328: putfield      #252                // Field currentStation:Ljava/util/UUID;
       331: aload         10
       333: aload_0
       334: ldc_w         #1623               // String Backwards
       337: invokevirtual #1713               // Method net/minecraft/nbt/CompoundTag.getBoolean:(Ljava/lang/String;)Z
       340: putfield      #1021               // Field currentlyBackwards:Z
       343: aload         10
       345: aload_0
       346: ldc_w         #1625               // String Derailed
       349: invokevirtual #1713               // Method net/minecraft/nbt/CompoundTag.getBoolean:(Ljava/lang/String;)Z
       352: putfield      #547                // Field derailed:Z
       355: aload         10
       357: aload_0
       358: ldc_w         #1627               // String UpdateSignals
       361: invokevirtual #1713               // Method net/minecraft/nbt/CompoundTag.getBoolean:(Ljava/lang/String;)Z
       364: putfield      #309                // Field updateSignalBlocks:Z
       367: aload         10
       369: aload_0
       370: ldc_w         #1590               // String Fuel
       373: invokevirtual #1734               // Method net/minecraft/nbt/CompoundTag.getInt:(Ljava/lang/String;)I
       376: putfield      #1476               // Field fuelTicks:I
       379: aload_0
       380: ldc_w         #1629               // String SignalBlocks
       383: bipush        10
       385: invokevirtual #1689               // Method net/minecraft/nbt/CompoundTag.getList:(Ljava/lang/String;I)Lnet/minecraft/nbt/ListTag;
       388: aload         10
       390: invokedynamic #1744,  0           // InvokeDynamic #20:accept:(Lcom/simibubi/create/content/trains/entity/Train;)Ljava/util/function/Consumer;
       395: invokestatic  #1702               // Method net/createmod/catnip/nbt/NBTHelper.iterateCompoundList:(Lnet/minecraft/nbt/ListTag;Ljava/util/function/Consumer;)V
       398: aload_0
       399: ldc_w         #1638               // String ReservedSignalBlocks
       402: bipush        10
       404: invokevirtual #1689               // Method net/minecraft/nbt/CompoundTag.getList:(Ljava/lang/String;I)Lnet/minecraft/nbt/ListTag;
       407: aload         10
       409: invokedynamic #1749,  0           // InvokeDynamic #21:accept:(Lcom/simibubi/create/content/trains/entity/Train;)Ljava/util/function/Consumer;
       414: invokestatic  #1702               // Method net/createmod/catnip/nbt/NBTHelper.iterateCompoundList:(Lnet/minecraft/nbt/ListTag;Ljava/util/function/Consumer;)V
       417: aload_0
       418: ldc_w         #1647               // String OccupiedObservers
       421: bipush        10
       423: invokevirtual #1689               // Method net/minecraft/nbt/CompoundTag.getList:(Ljava/lang/String;I)Lnet/minecraft/nbt/ListTag;
       426: aload         10
       428: invokedynamic #1754,  0           // InvokeDynamic #22:accept:(Lcom/simibubi/create/content/trains/entity/Train;)Ljava/util/function/Consumer;
       433: invokestatic  #1702               // Method net/createmod/catnip/nbt/NBTHelper.iterateCompoundList:(Lnet/minecraft/nbt/ListTag;Ljava/util/function/Consumer;)V
       436: aload_0
       437: ldc_w         #1654               // String MigratingPoints
       440: bipush        10
       442: invokevirtual #1689               // Method net/minecraft/nbt/CompoundTag.getList:(Ljava/lang/String;I)Lnet/minecraft/nbt/ListTag;
       445: aload         10
       447: aload_2
       448: invokedynamic #1762,  0           // InvokeDynamic #23:accept:(Lcom/simibubi/create/content/trains/entity/Train;Lcom/simibubi/create/content/trains/graph/DimensionPalette;)Ljava/util/function/Consumer;
       453: invokestatic  #1702               // Method net/createmod/catnip/nbt/NBTHelper.iterateCompoundList:(Lnet/minecraft/nbt/ListTag;Ljava/util/function/Consumer;)V
       456: aload         10
       458: getfield      #245                // Field runtime:Lcom/simibubi/create/content/trains/schedule/ScheduleRuntime;
       461: aload_0
       462: ldc_w         #1664               // String Runtime
       465: invokevirtual #1766               // Method net/minecraft/nbt/CompoundTag.getCompound:(Ljava/lang/String;)Lnet/minecraft/nbt/CompoundTag;
       468: invokevirtual #1768               // Method com/simibubi/create/content/trains/schedule/ScheduleRuntime.read:(Lnet/minecraft/nbt/CompoundTag;)V
       471: aload         10
       473: getfield      #242                // Field navigation:Lcom/simibubi/create/content/trains/entity/Navigation;
       476: aload_0
       477: ldc_w         #1669               // String Navigation
       480: invokevirtual #1766               // Method net/minecraft/nbt/CompoundTag.getCompound:(Ljava/lang/String;)Lnet/minecraft/nbt/CompoundTag;
       483: aload         6
       485: aload_2
       486: invokevirtual #1771               // Method com/simibubi/create/content/trains/entity/Navigation.read:(Lnet/minecraft/nbt/CompoundTag;Lcom/simibubi/create/content/trains/graph/TrackGraph;Lcom/simibubi/create/content/trains/graph/DimensionPalette;)V
       489: aload         10
       491: invokevirtual #533                // Method getCurrentStation:()Lcom/simibubi/create/content/trains/station/GlobalStation;
       494: ifnull        507
       497: aload         10
       499: invokevirtual #533                // Method getCurrentStation:()Lcom/simibubi/create/content/trains/station/GlobalStation;
       502: aload         10
       504: invokevirtual #1315               // Method com/simibubi/create/content/trains/station/GlobalStation.reserveFor:(Lcom/simibubi/create/content/trains/entity/Train;)V
       507: aload         10
       509: areturn

  public int countPlayerPassengers();
    Code:
         0: new           #1776               // class java/util/concurrent/atomic/AtomicInteger
         3: dup
         4: invokespecial #1777               // Method java/util/concurrent/atomic/AtomicInteger."<init>":()V
         7: astore_1
         8: aload_0
         9: getfield      #177                // Field carriages:Ljava/util/List;
        12: invokeinterface #324,  1          // InterfaceMethod java/util/List.iterator:()Ljava/util/Iterator;
        17: astore_2
        18: aload_2
        19: invokeinterface #329,  1          // InterfaceMethod java/util/Iterator.hasNext:()Z
        24: ifeq          50
        27: aload_2
        28: invokeinterface #333,  1          // InterfaceMethod java/util/Iterator.next:()Ljava/lang/Object;
        33: checkcast     #21                 // class com/simibubi/create/content/trains/entity/Carriage
        36: astore_3
        37: aload_3
        38: aload_1
        39: invokedynamic #1785,  0           // InvokeDynamic #24:accept:(Ljava/util/concurrent/atomic/AtomicInteger;)Ljava/util/function/Consumer;
        44: invokevirtual #1002               // Method com/simibubi/create/content/trains/entity/Carriage.forEachPresentEntity:(Ljava/util/function/Consumer;)V
        47: goto          18
        50: aload_1
        51: invokevirtual #1786               // Method java/util/concurrent/atomic/AtomicInteger.intValue:()I
        54: ireturn

  public void determineHonk(net.minecraft.world.level.Level);
    Code:
         0: aload_0
         1: getfield      #1791               // Field lowHonk:Ljava/lang/Boolean;
         4: ifnull        8
         7: return
         8: aload_0
         9: getfield      #177                // Field carriages:Ljava/util/List;
        12: invokeinterface #324,  1          // InterfaceMethod java/util/List.iterator:()Ljava/util/Iterator;
        17: astore_2
        18: aload_2
        19: invokeinterface #329,  1          // InterfaceMethod java/util/Iterator.hasNext:()Z
        24: ifeq          140
        27: aload_2
        28: invokeinterface #333,  1          // InterfaceMethod java/util/Iterator.next:()Ljava/lang/Object;
        33: checkcast     #21                 // class com/simibubi/create/content/trains/entity/Carriage
        36: astore_3
        37: aload_3
        38: aload_1
        39: invokevirtual #1794               // Method net/minecraft/world/level/Level.dimension:()Lnet/minecraft/resources/ResourceKey;
        42: invokevirtual #592                // Method com/simibubi/create/content/trains/entity/Carriage.getDimensionalIfPresent:(Lnet/minecraft/resources/ResourceKey;)Lcom/simibubi/create/content/trains/entity/Carriage$DimensionalCarriageEntity;
        45: astore        4
        47: aload         4
        49: ifnonnull     53
        52: return
        53: aload         4
        55: getfield      #1797               // Field com/simibubi/create/content/trains/entity/Carriage$DimensionalCarriageEntity.entity:Ljava/lang/ref/WeakReference;
        58: invokevirtual #1800               // Method java/lang/ref/WeakReference.get:()Ljava/lang/Object;
        61: checkcast     #1029               // class com/simibubi/create/content/trains/entity/CarriageContraptionEntity
        64: astore        5
        66: aload         5
        68: ifnull        140
        71: aload         5
        73: invokevirtual #1036               // Method com/simibubi/create/content/trains/entity/CarriageContraptionEntity.getContraption:()Lcom/simibubi/create/content/contraptions/Contraption;
        76: astore        7
        78: aload         7
        80: instanceof    #1038               // class com/simibubi/create/content/trains/entity/CarriageContraption
        83: ifeq          140
        86: aload         7
        88: checkcast     #1038               // class com/simibubi/create/content/trains/entity/CarriageContraption
        91: astore        6
        93: aload         6
        95: getfield      #1804               // Field com/simibubi/create/content/trains/entity/CarriageContraption.soundQueue:Lcom/simibubi/create/content/trains/entity/ArrivalSoundQueue;
        98: aload         5
       100: invokevirtual #1810               // Method com/simibubi/create/content/trains/entity/ArrivalSoundQueue.getFirstWhistle:(Lcom/simibubi/create/content/trains/entity/CarriageContraptionEntity;)Lnet/createmod/catnip/data/Pair;
       103: astore        7
       105: aload         7
       107: ifnull        137
       110: aload_0
       111: aload         7
       113: invokevirtual #398                // Method net/createmod/catnip/data/Pair.getFirst:()Ljava/lang/Object;
       116: checkcast     #392                // class java/lang/Boolean
       119: putfield      #1791               // Field lowHonk:Ljava/lang/Boolean;
       122: aload_0
       123: aload         7
       125: invokevirtual #390                // Method net/createmod/catnip/data/Pair.getSecond:()Ljava/lang/Object;
       128: checkcast     #400                // class java/lang/Integer
       131: invokevirtual #403                // Method java/lang/Integer.intValue:()I
       134: putfield      #1812               // Field honkPitch:I
       137: goto          18
       140: return

  public float distanceToLocationSqr(net.minecraft.world.level.Level, net.minecraft.world.phys.Vec3);
    Code:
         0: ldc_w         #1817               // float 3.4028235E38f
         3: fstore_3
         4: aload_0
         5: getfield      #177                // Field carriages:Ljava/util/List;
         8: invokeinterface #324,  1          // InterfaceMethod java/util/List.iterator:()Ljava/util/Iterator;
        13: astore        4
        15: aload         4
        17: invokeinterface #329,  1          // InterfaceMethod java/util/Iterator.hasNext:()Z
        22: ifeq          82
        25: aload         4
        27: invokeinterface #333,  1          // InterfaceMethod java/util/Iterator.next:()Ljava/lang/Object;
        32: checkcast     #21                 // class com/simibubi/create/content/trains/entity/Carriage
        35: astore        5
        37: aload         5
        39: aload_1
        40: invokevirtual #1794               // Method net/minecraft/world/level/Level.dimension:()Lnet/minecraft/resources/ResourceKey;
        43: invokevirtual #592                // Method com/simibubi/create/content/trains/entity/Carriage.getDimensionalIfPresent:(Lnet/minecraft/resources/ResourceKey;)Lcom/simibubi/create/content/trains/entity/Carriage$DimensionalCarriageEntity;
        46: astore        6
        48: aload         6
        50: ifnull        15
        53: aload         6
        55: getfield      #1820               // Field com/simibubi/create/content/trains/entity/Carriage$DimensionalCarriageEntity.positionAnchor:Lnet/minecraft/world/phys/Vec3;
        58: ifnonnull     64
        61: goto          15
        64: fload_3
        65: aload         6
        67: getfield      #1820               // Field com/simibubi/create/content/trains/entity/Carriage$DimensionalCarriageEntity.positionAnchor:Lnet/minecraft/world/phys/Vec3;
        70: aload_2
        71: invokevirtual #605                // Method net/minecraft/world/phys/Vec3.distanceToSqr:(Lnet/minecraft/world/phys/Vec3;)D
        74: d2f
        75: invokestatic  #1823               // Method java/lang/Math.min:(FF)F
        78: fstore_3
        79: goto          15
        82: fload_3
        83: freturn

  public java.util.List<net.minecraft.resources.ResourceKey<net.minecraft.world.level.Level>> getPresentDimensions();
    Code:
         0: aload_0
         1: getfield      #177                // Field carriages:Ljava/util/List;
         4: invokeinterface #1832,  1         // InterfaceMethod java/util/List.stream:()Ljava/util/stream/Stream;
         9: invokedynamic #1839,  0           // InvokeDynamic #25:apply:()Ljava/util/function/Function;
        14: invokeinterface #1845,  2         // InterfaceMethod java/util/stream/Stream.flatMap:(Ljava/util/function/Function;)Ljava/util/stream/Stream;
        19: invokeinterface #1848,  1         // InterfaceMethod java/util/stream/Stream.distinct:()Ljava/util/stream/Stream;
        24: invokeinterface #1851,  1         // InterfaceMethod java/util/stream/Stream.toList:()Ljava/util/List;
        29: areturn

  public java.util.Optional<net.minecraft.core.BlockPos> getPositionInDimension(net.minecraft.resources.ResourceKey<net.minecraft.world.level.Level>);
    Code:
         0: aload_0
         1: getfield      #177                // Field carriages:Ljava/util/List;
         4: invokeinterface #1832,  1         // InterfaceMethod java/util/List.stream:()Ljava/util/stream/Stream;
         9: aload_1
        10: invokedynamic #1864,  0           // InvokeDynamic #26:apply:(Lnet/minecraft/resources/ResourceKey;)Ljava/util/function/Function;
        15: invokeinterface #1866,  2         // InterfaceMethod java/util/stream/Stream.map:(Ljava/util/function/Function;)Ljava/util/stream/Stream;
        20: invokedynamic #1878,  0           // InvokeDynamic #27:test:()Ljava/util/function/Predicate;
        25: invokeinterface #1881,  2         // InterfaceMethod java/util/stream/Stream.filter:(Ljava/util/function/Predicate;)Ljava/util/stream/Stream;
        30: invokedynamic #1886,  0           // InvokeDynamic #28:apply:()Ljava/util/function/Function;
        35: invokeinterface #1866,  2         // InterfaceMethod java/util/stream/Stream.map:(Ljava/util/function/Function;)Ljava/util/stream/Stream;
        40: invokeinterface #1890,  1         // InterfaceMethod java/util/stream/Stream.findFirst:()Ljava/util/Optional;
        45: areturn

  private static java.util.Optional lambda$getPositionInDimension$34(net.minecraft.resources.ResourceKey, com.simibubi.create.content.trains.entity.Carriage);
    Code:
         0: aload_1
         1: aload_0
         2: invokevirtual #1892               // Method com/simibubi/create/content/trains/entity/Carriage.getPositionInDimension:(Lnet/minecraft/resources/ResourceKey;)Ljava/util/Optional;
         5: areturn

  private static java.util.stream.Stream lambda$getPresentDimensions$33(com.simibubi.create.content.trains.entity.Carriage);
    Code:
         0: aload_0
         1: invokevirtual #1894               // Method com/simibubi/create/content/trains/entity/Carriage.getPresentDimensions:()Ljava/util/List;
         4: invokeinterface #1832,  1         // InterfaceMethod java/util/List.stream:()Ljava/util/stream/Stream;
         9: areturn

  private static void lambda$countPlayerPassengers$32(java.util.concurrent.atomic.AtomicInteger, com.simibubi.create.content.trains.entity.CarriageContraptionEntity);
    Code:
         0: aload_1
         1: invokevirtual #1898               // Method com/simibubi/create/content/trains/entity/CarriageContraptionEntity.getIndirectPassengers:()Ljava/lang/Iterable;
         4: aload_0
         5: invokedynamic #1906,  0           // InvokeDynamic #29:accept:(Ljava/util/concurrent/atomic/AtomicInteger;)Ljava/util/function/Consumer;
        10: invokeinterface #1909,  2         // InterfaceMethod java/lang/Iterable.forEach:(Ljava/util/function/Consumer;)V
        15: return

  private static void lambda$countPlayerPassengers$31(java.util.concurrent.atomic.AtomicInteger, net.minecraft.world.entity.Entity);
    Code:
         0: aload_1
         1: instanceof    #1912               // class net/minecraft/world/entity/player/Player
         4: ifeq          12
         7: aload_0
         8: invokevirtual #1915               // Method java/util/concurrent/atomic/AtomicInteger.incrementAndGet:()I
        11: pop
        12: return

  private static void lambda$read$30(com.simibubi.create.content.trains.entity.Train, com.simibubi.create.content.trains.graph.DimensionPalette, net.minecraft.nbt.CompoundTag);
    Code:
         0: aload_0
         1: getfield      #250                // Field migratingPoints:Ljava/util/List;
         4: aload_2
         5: aload_1
         6: invokestatic  #1920               // Method com/simibubi/create/content/trains/entity/TrainMigration.read:(Lnet/minecraft/nbt/CompoundTag;Lcom/simibubi/create/content/trains/graph/DimensionPalette;)Lcom/simibubi/create/content/trains/entity/TrainMigration;
         9: invokeinterface #1284,  2         // InterfaceMethod java/util/List.add:(Ljava/lang/Object;)Z
        14: pop
        15: return

  private static void lambda$read$29(com.simibubi.create.content.trains.entity.Train, net.minecraft.nbt.CompoundTag);
    Code:
         0: aload_0
         1: getfield      #269                // Field occupiedObservers:Ljava/util/Set;
         4: aload_1
         5: ldc_w         #1536               // String Id
         8: invokevirtual #1681               // Method net/minecraft/nbt/CompoundTag.getUUID:(Ljava/lang/String;)Ljava/util/UUID;
        11: invokeinterface #506,  2          // InterfaceMethod java/util/Set.add:(Ljava/lang/Object;)Z
        16: pop
        17: return

  private static void lambda$read$28(com.simibubi.create.content.trains.entity.Train, net.minecraft.nbt.CompoundTag);
    Code:
         0: aload_0
         1: getfield      #267                // Field reservedSignalBlocks:Ljava/util/Set;
         4: aload_1
         5: ldc_w         #1536               // String Id
         8: invokevirtual #1681               // Method net/minecraft/nbt/CompoundTag.getUUID:(Ljava/lang/String;)Ljava/util/UUID;
        11: invokeinterface #506,  2          // InterfaceMethod java/util/Set.add:(Ljava/lang/Object;)Z
        16: pop
        17: return

  private static void lambda$read$27(com.simibubi.create.content.trains.entity.Train, net.minecraft.nbt.CompoundTag);
    Code:
         0: aload_0
         1: getfield      #262                // Field occupiedSignalBlocks:Ljava/util/Map;
         4: aload_1
         5: ldc_w         #1536               // String Id
         8: invokevirtual #1681               // Method net/minecraft/nbt/CompoundTag.getUUID:(Ljava/lang/String;)Ljava/util/UUID;
        11: aload_1
        12: ldc_w         #1922               // String Boundary
        15: invokevirtual #1685               // Method net/minecraft/nbt/CompoundTag.contains:(Ljava/lang/String;)Z
        18: ifeq          31
        21: aload_1
        22: ldc_w         #1922               // String Boundary
        25: invokevirtual #1681               // Method net/minecraft/nbt/CompoundTag.getUUID:(Ljava/lang/String;)Ljava/util/UUID;
        28: goto          32
        31: aconst_null
        32: invokeinterface #459,  3          // InterfaceMethod java/util/Map.put:(Ljava/lang/Object;Ljava/lang/Object;)Ljava/lang/Object;
        37: pop
        38: return

  private static void lambda$read$26(java.util.List, com.simibubi.create.content.trains.graph.TrackGraph, com.simibubi.create.content.trains.graph.DimensionPalette, net.minecraft.nbt.CompoundTag);
    Code:
         0: aload_0
         1: aload_3
         2: aload_1
         3: aload_2
         4: invokestatic  #1925               // Method com/simibubi/create/content/trains/entity/Carriage.read:(Lnet/minecraft/nbt/CompoundTag;Lcom/simibubi/create/content/trains/graph/TrackGraph;Lcom/simibubi/create/content/trains/graph/DimensionPalette;)Lcom/simibubi/create/content/trains/entity/Carriage;
         7: invokeinterface #1284,  2         // InterfaceMethod java/util/List.add:(Ljava/lang/Object;)Z
        12: pop
        13: return

  private static net.minecraft.nbt.CompoundTag lambda$write$25(com.simibubi.create.content.trains.graph.DimensionPalette, com.simibubi.create.content.trains.entity.TrainMigration);
    Code:
         0: aload_1
         1: aload_0
         2: invokevirtual #1926               // Method com/simibubi/create/content/trains/entity/TrainMigration.write:(Lcom/simibubi/create/content/trains/graph/DimensionPalette;)Lnet/minecraft/nbt/CompoundTag;
         5: areturn

  private static net.minecraft.nbt.CompoundTag lambda$write$24(java.util.UUID);
    Code:
         0: new           #1533               // class net/minecraft/nbt/CompoundTag
         3: dup
         4: invokespecial #1534               // Method net/minecraft/nbt/CompoundTag."<init>":()V
         7: astore_1
         8: aload_1
         9: ldc_w         #1536               // String Id
        12: aload_0
        13: invokevirtual #1540               // Method net/minecraft/nbt/CompoundTag.putUUID:(Ljava/lang/String;Ljava/util/UUID;)V
        16: aload_1
        17: areturn

  private static net.minecraft.nbt.CompoundTag lambda$write$23(java.util.UUID);
    Code:
         0: new           #1533               // class net/minecraft/nbt/CompoundTag
         3: dup
         4: invokespecial #1534               // Method net/minecraft/nbt/CompoundTag."<init>":()V
         7: astore_1
         8: aload_1
         9: ldc_w         #1536               // String Id
        12: aload_0
        13: invokevirtual #1540               // Method net/minecraft/nbt/CompoundTag.putUUID:(Ljava/lang/String;Ljava/util/UUID;)V
        16: aload_1
        17: areturn

  private static net.minecraft.nbt.CompoundTag lambda$write$22(java.util.Map$Entry);
    Code:
         0: new           #1533               // class net/minecraft/nbt/CompoundTag
         3: dup
         4: invokespecial #1534               // Method net/minecraft/nbt/CompoundTag."<init>":()V
         7: astore_1
         8: aload_1
         9: ldc_w         #1536               // String Id
        12: aload_0
        13: invokeinterface #1276,  1         // InterfaceMethod java/util/Map$Entry.getKey:()Ljava/lang/Object;
        18: checkcast     #345                // class java/util/UUID
        21: invokevirtual #1540               // Method net/minecraft/nbt/CompoundTag.putUUID:(Ljava/lang/String;Ljava/util/UUID;)V
        24: aload_0
        25: invokeinterface #1267,  1         // InterfaceMethod java/util/Map$Entry.getValue:()Ljava/lang/Object;
        30: ifnull        49
        33: aload_1
        34: ldc_w         #1922               // String Boundary
        37: aload_0
        38: invokeinterface #1267,  1         // InterfaceMethod java/util/Map$Entry.getValue:()Ljava/lang/Object;
        43: checkcast     #345                // class java/util/UUID
        46: invokevirtual #1540               // Method net/minecraft/nbt/CompoundTag.putUUID:(Ljava/lang/String;Ljava/util/UUID;)V
        49: aload_1
        50: areturn

  private static net.minecraft.nbt.CompoundTag lambda$write$21(com.simibubi.create.content.trains.graph.DimensionPalette, com.simibubi.create.content.trains.entity.Carriage);
    Code:
         0: aload_1
         1: aload_0
         2: invokevirtual #1930               // Method com/simibubi/create/content/trains/entity/Carriage.write:(Lcom/simibubi/create/content/trains/graph/DimensionPalette;)Lnet/minecraft/nbt/CompoundTag;
         5: areturn

  private static net.createmod.catnip.data.Couple lambda$getEndpointEdges$20(com.simibubi.create.content.trains.entity.TravellingPoint);
    Code:
         0: aload_0
         1: getfield      #564                // Field com/simibubi/create/content/trains/entity/TravellingPoint.node1:Lcom/simibubi/create/content/trains/graph/TrackNode;
         4: aload_0
         5: getfield      #1380               // Field com/simibubi/create/content/trains/entity/TravellingPoint.node2:Lcom/simibubi/create/content/trains/graph/TrackNode;
         8: invokestatic  #1458               // Method net/createmod/catnip/data/Couple.create:(Ljava/lang/Object;Ljava/lang/Object;)Lnet/createmod/catnip/data/Couple;
        11: areturn

  private void lambda$collectInitiallyOccupiedSignalBlocks$19(com.simibubi.create.content.trains.entity.TravellingPoint, org.apache.commons.lang3.mutable.MutableObject, com.simibubi.create.content.trains.entity.TravellingPoint, java.lang.Double);
    Code:
         0: aload_1
         1: aload_0
         2: getfield      #175                // Field graph:Lcom/simibubi/create/content/trains/graph/TrackGraph;
         5: aload         4
         7: invokevirtual #644                // Method java/lang/Double.doubleValue:()D
        10: aload_1
        11: aload_3
        12: invokevirtual #1935               // Method com/simibubi/create/content/trains/entity/TravellingPoint.follow:(Lcom/simibubi/create/content/trains/entity/TravellingPoint;)Lcom/simibubi/create/content/trains/entity/TravellingPoint$ITrackSelector;
        15: aload_0
        16: aload_2
        17: invokedynamic #1943,  0           // InvokeDynamic #30:test:(Lcom/simibubi/create/content/trains/entity/Train;Lorg/apache/commons/lang3/mutable/MutableObject;)Lcom/simibubi/create/content/trains/entity/TravellingPoint$IEdgePointListener;
        22: aload_1
        23: invokevirtual #1947               // Method com/simibubi/create/content/trains/entity/TravellingPoint.ignoreTurns:()Lcom/simibubi/create/content/trains/entity/TravellingPoint$ITurnListener;
        26: invokevirtual #1950               // Method com/simibubi/create/content/trains/entity/TravellingPoint.travel:(Lcom/simibubi/create/content/trains/graph/TrackGraph;DLcom/simibubi/create/content/trains/entity/TravellingPoint$ITrackSelector;Lcom/simibubi/create/content/trains/entity/TravellingPoint$IEdgePointListener;Lcom/simibubi/create/content/trains/entity/TravellingPoint$ITurnListener;)D
        29: pop2
        30: return

  private boolean lambda$collectInitiallyOccupiedSignalBlocks$18(org.apache.commons.lang3.mutable.MutableObject, java.lang.Double, net.createmod.catnip.data.Pair);
    Code:
         0: aload_3
         1: invokevirtual #398                // Method net/createmod/catnip/data/Pair.getFirst:()Ljava/lang/Object;
         4: astore        5
         6: aload         5
         8: instanceof    #359                // class com/simibubi/create/content/trains/observer/TrackObserver
        11: ifeq          38
        14: aload         5
        16: checkcast     #359                // class com/simibubi/create/content/trains/observer/TrackObserver
        19: astore        4
        21: aload_0
        22: getfield      #269                // Field occupiedObservers:Ljava/util/Set;
        25: aload         4
        27: invokevirtual #1954               // Method com/simibubi/create/content/trains/observer/TrackObserver.getId:()Ljava/util/UUID;
        30: invokeinterface #506,  2          // InterfaceMethod java/util/Set.add:(Ljava/lang/Object;)Z
        35: pop
        36: iconst_0
        37: ireturn
        38: aload_3
        39: invokevirtual #398                // Method net/createmod/catnip/data/Pair.getFirst:()Ljava/lang/Object;
        42: astore        5
        44: aload         5
        46: instanceof    #810                // class com/simibubi/create/content/trains/signal/SignalBoundary
        49: ifeq          62
        52: aload         5
        54: checkcast     #810                // class com/simibubi/create/content/trains/signal/SignalBoundary
        57: astore        4
        59: goto          64
        62: iconst_0
        63: ireturn
        64: aload_3
        65: invokevirtual #390                // Method net/createmod/catnip/data/Pair.getSecond:()Ljava/lang/Object;
        68: checkcast     #816                // class net/createmod/catnip/data/Couple
        71: aload         4
        73: dup
        74: invokestatic  #1211               // Method java/util/Objects.requireNonNull:(Ljava/lang/Object;)Ljava/lang/Object;
        77: pop
        78: invokedynamic #1959,  0           // InvokeDynamic #31:apply:(Lcom/simibubi/create/content/trains/signal/SignalBoundary;)Ljava/util/function/Function;
        83: invokevirtual #1469               // Method net/createmod/catnip/data/Couple.map:(Ljava/util/function/Function;)Lnet/createmod/catnip/data/Couple;
        86: aload_0
        87: aload_1
        88: invokedynamic #1968,  0           // InvokeDynamic #32:accept:(Lcom/simibubi/create/content/trains/entity/Train;Lorg/apache/commons/lang3/mutable/MutableObject;)Ljava/util/function/Consumer;
        93: invokevirtual #1220               // Method net/createmod/catnip/data/Couple.forEach:(Ljava/util/function/Consumer;)V
        96: iconst_0
        97: ireturn

  private void lambda$collectInitiallyOccupiedSignalBlocks$17(org.apache.commons.lang3.mutable.MutableObject, java.util.UUID);
    Code:
         0: getstatic     #483                // Field com/simibubi/create/Create.RAILWAYS:Lcom/simibubi/create/content/trains/GlobalRailwayManager;
         3: getfield      #488                // Field com/simibubi/create/content/trains/GlobalRailwayManager.signalEdgeGroups:Ljava/util/Map;
         6: aload_2
         7: invokeinterface #772,  2          // InterfaceMethod java/util/Map.containsKey:(Ljava/lang/Object;)Z
        12: ifne          16
        15: return
        16: aload_2
        17: aload_1
        18: invokevirtual #1973               // Method org/apache/commons/lang3/mutable/MutableObject.getValue:()Ljava/lang/Object;
        21: invokevirtual #773                // Method java/util/UUID.equals:(Ljava/lang/Object;)Z
        24: ifeq          28
        27: return
        28: aload_0
        29: aload_2
        30: aconst_null
        31: invokevirtual #1415               // Method occupy:(Ljava/util/UUID;Ljava/util/UUID;)Z
        34: pop
        35: aload_1
        36: aload_2
        37: invokevirtual #1418               // Method org/apache/commons/lang3/mutable/MutableObject.setValue:(Ljava/lang/Object;)V
        40: return

  private static void lambda$reattachToTracks$16(java.util.List, com.simibubi.create.content.trains.entity.TravellingPoint);
    Code:
         0: aload_1
         1: aload_0
         2: invokevirtual #1977               // Method com/simibubi/create/content/trains/entity/TravellingPoint.migrateTo:(Ljava/util/List;)V
         5: return

  private static java.util.List lambda$reattachToTracks$15(java.util.UUID);
    Code:
         0: new           #247                // class java/util/ArrayList
         3: dup
         4: invokespecial #248                // Method java/util/ArrayList."<init>":()V
         7: areturn

  private void lambda$detachFromTracks$14(com.simibubi.create.content.trains.entity.TravellingPoint);
    Code:
         0: aload_0
         1: getfield      #250                // Field migratingPoints:Ljava/util/List;
         4: new           #1264               // class com/simibubi/create/content/trains/entity/TrainMigration
         7: dup
         8: aload_1
         9: invokespecial #1979               // Method com/simibubi/create/content/trains/entity/TrainMigration."<init>":(Lcom/simibubi/create/content/trains/entity/TravellingPoint;)V
        12: invokeinterface #1284,  2         // InterfaceMethod java/util/List.add:(Ljava/lang/Object;)Z
        17: pop
        18: return

  private static void lambda$isTravellingOn$13(com.simibubi.create.content.trains.graph.TrackNode, org.apache.commons.lang3.mutable.MutableBoolean, com.simibubi.create.content.trains.entity.TravellingPoint);
    Code:
         0: aload_2
         1: getfield      #564                // Field com/simibubi/create/content/trains/entity/TravellingPoint.node1:Lcom/simibubi/create/content/trains/graph/TrackNode;
         4: aload_0
         5: if_acmpeq     16
         8: aload_2
         9: getfield      #1380               // Field com/simibubi/create/content/trains/entity/TravellingPoint.node2:Lcom/simibubi/create/content/trains/graph/TrackNode;
        12: aload_0
        13: if_acmpne     20
        16: aload_1
        17: invokevirtual #1982               // Method org/apache/commons/lang3/mutable/MutableBoolean.setTrue:()V
        20: return

  private static void lambda$crash$12(com.simibubi.create.content.trains.entity.CarriageContraptionEntity);
    Code:
         0: aload_0
         1: invokevirtual #1898               // Method com/simibubi/create/content/trains/entity/CarriageContraptionEntity.getIndirectPassengers:()Ljava/lang/Iterable;
         4: aload_0
         5: invokedynamic #1990,  0           // InvokeDynamic #33:accept:(Lcom/simibubi/create/content/trains/entity/CarriageContraptionEntity;)Ljava/util/function/Consumer;
        10: invokeinterface #1909,  2         // InterfaceMethod java/lang/Iterable.forEach:(Ljava/util/function/Consumer;)V
        15: return

  private static void lambda$crash$11(com.simibubi.create.content.trains.entity.CarriageContraptionEntity, net.minecraft.world.entity.Entity);
    Code:
         0: aload_1
         1: instanceof    #1912               // class net/minecraft/world/entity/player/Player
         4: ifeq          15
         7: aload_1
         8: checkcast     #1912               // class net/minecraft/world/entity/player/Player
        11: astore_2
        12: goto          16
        15: return
        16: aload_0
        17: invokevirtual #1993               // Method com/simibubi/create/content/trains/entity/CarriageContraptionEntity.getControllingPlayer:()Ljava/util/Optional;
        20: astore_3
        21: aload_3
        22: invokevirtual #1872               // Method java/util/Optional.isPresent:()Z
        25: ifeq          46
        28: aload_3
        29: invokevirtual #1882               // Method java/util/Optional.get:()Ljava/lang/Object;
        32: checkcast     #345                // class java/util/UUID
        35: aload_2
        36: invokevirtual #1995               // Method net/minecraft/world/entity/player/Player.getUUID:()Ljava/util/UUID;
        39: invokevirtual #773                // Method java/util/UUID.equals:(Ljava/lang/Object;)Z
        42: ifeq          46
        45: return
        46: getstatic     #1998               // Field com/simibubi/create/foundation/advancement/AllAdvancements.TRAIN_CRASH:Lcom/simibubi/create/foundation/advancement/CreateAdvancement;
        49: aload_2
        50: invokevirtual #1014               // Method com/simibubi/create/foundation/advancement/CreateAdvancement.awardTo:(Lnet/minecraft/world/entity/player/Player;)V
        53: return

  private boolean lambda$backSignalListener$10(java.lang.Double, net.createmod.catnip.data.Pair);
    Code:
         0: aload_2
         1: invokevirtual #398                // Method net/createmod/catnip/data/Pair.getFirst:()Ljava/lang/Object;
         4: astore        4
         6: aload         4
         8: instanceof    #359                // class com/simibubi/create/content/trains/observer/TrackObserver
        11: ifeq          50
        14: aload         4
        16: checkcast     #359                // class com/simibubi/create/content/trains/observer/TrackObserver
        19: astore_3
        20: aload_0
        21: getfield      #269                // Field occupiedObservers:Ljava/util/Set;
        24: aload_3
        25: invokevirtual #1954               // Method com/simibubi/create/content/trains/observer/TrackObserver.getId:()Ljava/util/UUID;
        28: invokeinterface #769,  2          // InterfaceMethod java/util/Set.remove:(Ljava/lang/Object;)Z
        33: pop
        34: aload_0
        35: getfield      #271                // Field cachedObserverFiltering:Ljava/util/Map;
        38: aload_3
        39: invokevirtual #1954               // Method com/simibubi/create/content/trains/observer/TrackObserver.getId:()Ljava/util/UUID;
        42: invokeinterface #2003,  2         // InterfaceMethod java/util/Map.remove:(Ljava/lang/Object;)Ljava/lang/Object;
        47: pop
        48: iconst_0
        49: ireturn
        50: aload_2
        51: invokevirtual #398                // Method net/createmod/catnip/data/Pair.getFirst:()Ljava/lang/Object;
        54: astore        4
        56: aload         4
        58: instanceof    #810                // class com/simibubi/create/content/trains/signal/SignalBoundary
        61: ifeq          73
        64: aload         4
        66: checkcast     #810                // class com/simibubi/create/content/trains/signal/SignalBoundary
        69: astore_3
        70: goto          75
        73: iconst_0
        74: ireturn
        75: aload_3
        76: aload_2
        77: invokevirtual #390                // Method net/createmod/catnip/data/Pair.getSecond:()Ljava/lang/Object;
        80: checkcast     #816                // class net/createmod/catnip/data/Couple
        83: invokevirtual #863                // Method net/createmod/catnip/data/Couple.getFirst:()Ljava/lang/Object;
        86: checkcast     #566                // class com/simibubi/create/content/trains/graph/TrackNode
        89: invokevirtual #1413               // Method com/simibubi/create/content/trains/signal/SignalBoundary.getGroup:(Lcom/simibubi/create/content/trains/graph/TrackNode;)Ljava/util/UUID;
        92: astore        4
        94: aload_0
        95: getfield      #262                // Field occupiedSignalBlocks:Ljava/util/Map;
        98: aload         4
       100: invokeinterface #2003,  2         // InterfaceMethod java/util/Map.remove:(Ljava/lang/Object;)Ljava/lang/Object;
       105: pop
       106: iconst_0
       107: ireturn

  private static void lambda$cancelStall$9(com.simibubi.create.content.trains.entity.Carriage);
    Code:
         0: aload_0
         1: iconst_0
         2: putfield      #635                // Field com/simibubi/create/content/trains/entity/Carriage.stalled:Z
         5: aload_0
         6: invokedynamic #2010,  0           // InvokeDynamic #34:accept:()Ljava/util/function/Consumer;
        11: invokevirtual #1002               // Method com/simibubi/create/content/trains/entity/Carriage.forEachPresentEntity:(Ljava/util/function/Consumer;)V
        14: return

  private static void lambda$cancelStall$8(com.simibubi.create.content.trains.entity.CarriageContraptionEntity);
    Code:
         0: aload_0
         1: invokevirtual #1036               // Method com/simibubi/create/content/trains/entity/CarriageContraptionEntity.getContraption:()Lcom/simibubi/create/content/contraptions/Contraption;
         4: invokevirtual #2015               // Method com/simibubi/create/content/contraptions/Contraption.getActors:()Ljava/util/List;
         7: invokedynamic #2022,  0           // InvokeDynamic #35:accept:()Ljava/util/function/Consumer;
        12: invokeinterface #237,  2          // InterfaceMethod java/util/List.forEach:(Ljava/util/function/Consumer;)V
        17: return

  private static void lambda$cancelStall$7(org.apache.commons.lang3.tuple.MutablePair);
    Code:
         0: getstatic     #2029               // Field com/simibubi/create/api/behaviour/movement/MovementBehaviour.REGISTRY:Lcom/simibubi/create/api/registry/SimpleRegistry;
         3: aload_0
         4: invokevirtual #2032               // Method org/apache/commons/lang3/tuple/MutablePair.getKey:()Ljava/lang/Object;
         7: checkcast     #77                 // class net/minecraft/world/level/levelgen/structure/templatesystem/StructureTemplate$StructureBlockInfo
        10: invokevirtual #2035               // Method net/minecraft/world/level/levelgen/structure/templatesystem/StructureTemplate$StructureBlockInfo.state:()Lnet/minecraft/world/level/block/state/BlockState;
        13: invokeinterface #2040,  2         // InterfaceMethod com/simibubi/create/api/registry/SimpleRegistry.get:(Lnet/minecraft/world/level/block/state/StateHolder;)Ljava/lang/Object;
        18: checkcast     #2025               // class com/simibubi/create/api/behaviour/movement/MovementBehaviour
        21: astore_1
        22: aload_1
        23: ifnull        39
        26: aload_1
        27: aload_0
        28: invokevirtual #2041               // Method org/apache/commons/lang3/tuple/MutablePair.getValue:()Ljava/lang/Object;
        31: checkcast     #2043               // class com/simibubi/create/content/contraptions/behaviour/MovementContext
        34: invokeinterface #2046,  2         // InterfaceMethod com/simibubi/create/api/behaviour/movement/MovementBehaviour.cancelStall:(Lcom/simibubi/create/content/contraptions/behaviour/MovementContext;)V
        39: return

  private boolean lambda$frontSignalListener$6(java.lang.Double, net.createmod.catnip.data.Pair);
    Code:
         0: aload_2
         1: invokevirtual #398                // Method net/createmod/catnip/data/Pair.getFirst:()Ljava/lang/Object;
         4: astore        4
         6: aload         4
         8: instanceof    #537                // class com/simibubi/create/content/trains/station/GlobalStation
        11: ifeq          99
        14: aload         4
        16: checkcast     #537                // class com/simibubi/create/content/trains/station/GlobalStation
        19: astore_3
        20: aload_3
        21: aload_2
        22: invokevirtual #390                // Method net/createmod/catnip/data/Pair.getSecond:()Ljava/lang/Object;
        25: checkcast     #816                // class net/createmod/catnip/data/Couple
        28: invokevirtual #865                // Method net/createmod/catnip/data/Couple.getSecond:()Ljava/lang/Object;
        31: checkcast     #566                // class com/simibubi/create/content/trains/graph/TrackNode
        34: invokevirtual #2053               // Method com/simibubi/create/content/trains/station/GlobalStation.canApproachFrom:(Lcom/simibubi/create/content/trains/graph/TrackNode;)Z
        37: ifeq          51
        40: aload_0
        41: getfield      #242                // Field navigation:Lcom/simibubi/create/content/trains/entity/Navigation;
        44: getfield      #784                // Field com/simibubi/create/content/trains/entity/Navigation.destination:Lcom/simibubi/create/content/trains/station/GlobalStation;
        47: aload_3
        48: if_acmpeq     53
        51: iconst_0
        52: ireturn
        53: aload_0
        54: dconst_0
        55: putfield      #159                // Field speed:D
        58: aload_0
        59: getfield      #242                // Field navigation:Lcom/simibubi/create/content/trains/entity/Navigation;
        62: dconst_0
        63: putfield      #655                // Field com/simibubi/create/content/trains/entity/Navigation.distanceToDestination:D
        66: aload_0
        67: getfield      #242                // Field navigation:Lcom/simibubi/create/content/trains/entity/Navigation;
        70: getfield      #2056               // Field com/simibubi/create/content/trains/entity/Navigation.currentPath:Ljava/util/List;
        73: invokeinterface #1197,  1         // InterfaceMethod java/util/List.clear:()V
        78: aload_0
        79: aload_0
        80: getfield      #242                // Field navigation:Lcom/simibubi/create/content/trains/entity/Navigation;
        83: getfield      #784                // Field com/simibubi/create/content/trains/entity/Navigation.destination:Lcom/simibubi/create/content/trains/station/GlobalStation;
        86: invokevirtual #2058               // Method arriveAt:(Lcom/simibubi/create/content/trains/station/GlobalStation;)V
        89: aload_0
        90: getfield      #242                // Field navigation:Lcom/simibubi/create/content/trains/entity/Navigation;
        93: aconst_null
        94: putfield      #784                // Field com/simibubi/create/content/trains/entity/Navigation.destination:Lcom/simibubi/create/content/trains/station/GlobalStation;
        97: iconst_1
        98: ireturn
        99: aload_2
       100: invokevirtual #398                // Method net/createmod/catnip/data/Pair.getFirst:()Ljava/lang/Object;
       103: astore        4
       105: aload         4
       107: instanceof    #359                // class com/simibubi/create/content/trains/observer/TrackObserver
       110: ifeq          135
       113: aload         4
       115: checkcast     #359                // class com/simibubi/create/content/trains/observer/TrackObserver
       118: astore_3
       119: aload_0
       120: getfield      #269                // Field occupiedObservers:Ljava/util/Set;
       123: aload_3
       124: invokevirtual #1954               // Method com/simibubi/create/content/trains/observer/TrackObserver.getId:()Ljava/util/UUID;
       127: invokeinterface #506,  2          // InterfaceMethod java/util/Set.add:(Ljava/lang/Object;)Z
       132: pop
       133: iconst_0
       134: ireturn
       135: aload_2
       136: invokevirtual #398                // Method net/createmod/catnip/data/Pair.getFirst:()Ljava/lang/Object;
       139: astore        4
       141: aload         4
       143: instanceof    #810                // class com/simibubi/create/content/trains/signal/SignalBoundary
       146: ifeq          158
       149: aload         4
       151: checkcast     #810                // class com/simibubi/create/content/trains/signal/SignalBoundary
       154: astore_3
       155: goto          160
       158: iconst_0
       159: ireturn
       160: aload_0
       161: getfield      #242                // Field navigation:Lcom/simibubi/create/content/trains/entity/Navigation;
       164: getfield      #787                // Field com/simibubi/create/content/trains/entity/Navigation.waitingForSignal:Lnet/createmod/catnip/data/Pair;
       167: ifnull        208
       170: aload_0
       171: getfield      #242                // Field navigation:Lcom/simibubi/create/content/trains/entity/Navigation;
       174: getfield      #787                // Field com/simibubi/create/content/trains/entity/Navigation.waitingForSignal:Lnet/createmod/catnip/data/Pair;
       177: invokevirtual #398                // Method net/createmod/catnip/data/Pair.getFirst:()Ljava/lang/Object;
       180: checkcast     #345                // class java/util/UUID
       183: aload_3
       184: invokevirtual #2059               // Method com/simibubi/create/content/trains/signal/SignalBoundary.getId:()Ljava/util/UUID;
       187: invokevirtual #773                // Method java/util/UUID.equals:(Ljava/lang/Object;)Z
       190: ifeq          208
       193: aload_0
       194: dconst_0
       195: putfield      #159                // Field speed:D
       198: aload_0
       199: getfield      #242                // Field navigation:Lcom/simibubi/create/content/trains/entity/Navigation;
       202: dconst_0
       203: putfield      #794                // Field com/simibubi/create/content/trains/entity/Navigation.distanceToSignal:D
       206: iconst_1
       207: ireturn
       208: aload_3
       209: aload_2
       210: invokevirtual #390                // Method net/createmod/catnip/data/Pair.getSecond:()Ljava/lang/Object;
       213: checkcast     #816                // class net/createmod/catnip/data/Couple
       216: invokevirtual #865                // Method net/createmod/catnip/data/Couple.getSecond:()Ljava/lang/Object;
       219: checkcast     #566                // class com/simibubi/create/content/trains/graph/TrackNode
       222: invokevirtual #1413               // Method com/simibubi/create/content/trains/signal/SignalBoundary.getGroup:(Lcom/simibubi/create/content/trains/graph/TrackNode;)Ljava/util/UUID;
       225: astore        4
       227: getstatic     #483                // Field com/simibubi/create/Create.RAILWAYS:Lcom/simibubi/create/content/trains/GlobalRailwayManager;
       230: getfield      #488                // Field com/simibubi/create/content/trains/GlobalRailwayManager.signalEdgeGroups:Ljava/util/Map;
       233: aload         4
       235: invokeinterface #494,  2          // InterfaceMethod java/util/Map.get:(Ljava/lang/Object;)Ljava/lang/Object;
       240: checkcast     #496                // class com/simibubi/create/content/trains/signal/SignalEdgeGroup
       243: astore        5
       245: aload         5
       247: ifnonnull     252
       250: iconst_0
       251: ireturn
       252: aload_0
       253: getfield      #245                // Field runtime:Lcom/simibubi/create/content/trains/schedule/ScheduleRuntime;
       256: invokevirtual #1302               // Method com/simibubi/create/content/trains/schedule/ScheduleRuntime.getSchedule:()Lcom/simibubi/create/content/trains/schedule/Schedule;
       259: ifnull        272
       262: aload_0
       263: getfield      #245                // Field runtime:Lcom/simibubi/create/content/trains/schedule/ScheduleRuntime;
       266: getfield      #802                // Field com/simibubi/create/content/trains/schedule/ScheduleRuntime.paused:Z
       269: ifeq          295
       272: aload         5
       274: aload_0
       275: invokevirtual #2063               // Method com/simibubi/create/content/trains/signal/SignalEdgeGroup.isOccupiedUnless:(Lcom/simibubi/create/content/trains/entity/Train;)Z
       278: ifeq          295
       281: aload_0
       282: getfield      #177                // Field carriages:Ljava/util/List;
       285: invokedynamic #2068,  0           // InvokeDynamic #36:accept:()Ljava/util/function/Consumer;
       290: invokeinterface #237,  2          // InterfaceMethod java/util/List.forEach:(Ljava/util/function/Consumer;)V
       295: aload         5
       297: aload_3
       298: putfield      #2071               // Field com/simibubi/create/content/trains/signal/SignalEdgeGroup.reserved:Lcom/simibubi/create/content/trains/signal/SignalBoundary;
       301: aload_0
       302: aload         4
       304: aload_3
       305: getfield      #2072               // Field com/simibubi/create/content/trains/signal/SignalBoundary.id:Ljava/util/UUID;
       308: invokevirtual #1415               // Method occupy:(Ljava/util/UUID;Ljava/util/UUID;)Z
       311: pop
       312: iconst_0
       313: ireturn

  private static void lambda$frontSignalListener$5(com.simibubi.create.content.trains.entity.Carriage);
    Code:
         0: aload_0
         1: invokedynamic #2080,  0           // InvokeDynamic #37:accept:()Ljava/util/function/Consumer;
         6: invokevirtual #1002               // Method com/simibubi/create/content/trains/entity/Carriage.forEachPresentEntity:(Ljava/util/function/Consumer;)V
         9: return

  private static void lambda$frontSignalListener$4(com.simibubi.create.content.trains.entity.CarriageContraptionEntity);
    Code:
         0: aload_0
         1: invokevirtual #1993               // Method com/simibubi/create/content/trains/entity/CarriageContraptionEntity.getControllingPlayer:()Ljava/util/Optional;
         4: aload_0
         5: invokedynamic #2086,  0           // InvokeDynamic #38:accept:(Lcom/simibubi/create/content/trains/entity/CarriageContraptionEntity;)Ljava/util/function/Consumer;
        10: invokevirtual #2089               // Method java/util/Optional.ifPresent:(Ljava/util/function/Consumer;)V
        13: return

  private static void lambda$frontSignalListener$3(com.simibubi.create.content.trains.entity.CarriageContraptionEntity, java.util.UUID);
    Code:
         0: getstatic     #2092               // Field com/simibubi/create/foundation/advancement/AllAdvancements.RED_SIGNAL:Lcom/simibubi/create/foundation/advancement/CreateAdvancement;
         3: aload_0
         4: invokevirtual #1032               // Method com/simibubi/create/content/trains/entity/CarriageContraptionEntity.level:()Lnet/minecraft/world/level/Level;
         7: aload_1
         8: invokevirtual #2096               // Method net/minecraft/world/level/Level.getPlayerByUUID:(Ljava/util/UUID;)Lnet/minecraft/world/entity/player/Player;
        11: invokevirtual #1014               // Method com/simibubi/create/foundation/advancement/CreateAdvancement.awardTo:(Lnet/minecraft/world/entity/player/Player;)V
        14: return

  private static void lambda$tick$2(net.minecraft.world.level.Level, com.simibubi.create.content.trains.entity.Carriage);
    Code:
         0: aload_1
         1: aload_0
         2: invokevirtual #2099               // Method com/simibubi/create/content/trains/entity/Carriage.manageEntities:(Lnet/minecraft/world/level/Level;)V
         5: return

  private static net.createmod.catnip.data.Pair lambda$tickOccupiedObservers$1(java.util.UUID);
    Code:
         0: iconst_m1
         1: invokestatic  #448                // Method java/lang/Integer.valueOf:(I)Ljava/lang/Integer;
         4: iconst_0
         5: invokestatic  #451                // Method java/lang/Boolean.valueOf:(Z)Ljava/lang/Boolean;
         8: invokestatic  #455                // Method net/createmod/catnip/data/Pair.of:(Ljava/lang/Object;Ljava/lang/Object;)Lnet/createmod/catnip/data/Pair;
        11: areturn

  private void lambda$new$0(com.simibubi.create.content.trains.entity.Carriage);
    Code:
         0: aload_1
         1: aload_0
         2: invokevirtual #2103               // Method com/simibubi/create/content/trains/entity/Carriage.setTrain:(Lcom/simibubi/create/content/trains/entity/Train;)V
         5: return
}
